Workbook
Name DPS: #REF!
Name _AUG02: #REF!
Name perp_lev2: #REF!
Name kit: #REF!
Name TOOLBOX: #REF!
Name CF_begcash: #REF!
Name _8GG2_: #REF!
Name OPGRPRQ1: #REF!
Name IDP: #REF!
Name _4QTRFIN: #REF!
Name acq_cost_convert_low: #REF!
Name NewCo3ON: #REF!
Name SIDEntities: #REF!
Name LBOIPOExit1: #REF!
Name _Pg58: #REF!
Name Periods: #REF!
Name Procurementph: #REF!
Name fisher: #REF!
Name MENU: #REF!
Name Subrelated: #REF!
Name DownlodedOn: 'philips deals'!$F$4
Name codes: #REF!
Name CustRev: #REF!
Name WACC_sen: #REF!
Name Buys: #REF!
Name _GPQ3: #REF!
Name ManagementEBIT: #REF!
Name ccy: #REF!
Name IS_inctaxes: #REF!
Name CF_Other_CA: #REF!
Name _inv2: #REF!
Name PPDIAG2003: #REF!
Name FIGEADQ1: #REF!
Name page5: #REF!
Name LoanPmt: #REF!
Name actsummy: #REF!
Name FIGM95: #REF!
Name GPPFINQ3: #REF!
Name AsiaPL: #REF!
Name FINQ1: #REF!
Name CF_straightdebt: #REF!
Name MonthTable: #REF!
Name SmaxFOA: #REF!
Name terminal_year: #REF!
Name QAph: #REF!
Name FINOIQ4: #REF!
Name c_pageswitch: #REF!
Name CF_Inventory: #REF!
Name Graphs_2: #REF!
Name EuropePL: #REF!
Name BurnhamProdConph: #REF!
Name BkgsByProdline: #REF!
Name BS_AP: #REF!
Name _Pg32: #REF!
Name WDGRPRQ4: #REF!
Name BEGRSLQ1: #REF!
Name CF_deferredtaxes: #REF!
Name RF_International: #REF!
Name BkgsByProdline: #REF!
Name TOOL91: #REF!

Sheet JILL
G1: FITBIT BASE | H1: FIT STANDALONE CASE | L1: FIT STANDALONE + SYNERGY CASE
F2: 2017A | G2: 2018A | H2: 2019 1 | I2: 2020 | J2: 2021 | L2: 2019 | M2: 2020 | N2: 2021
B4: Net Revenue | F4: 24.9 | G4: 27.1 | H4: =14.5+17.3 -> 31.8 | I4: =45.2 -> 45.2 | J4: =60.1 -> 60.1 | L4: =14.5+19.3 -> 33.8 | M4: 59.73 | N4: 80.5
B5: Growth % | C5: 0.32 | D5: 0.4 | F5: 0.18757834 | G5: 0.088353414 | H5: =H4/G4-1 -> 0.17343173 | I5: =I4/H4-1 -> 0.42138365 | J5: =J4/I4-1 -> 0.32964602 | M5: =M4/L4-1 -> 0.76715976 | N5: =N4/M4-1 -> 0.34773146
B7: COGS | F7: 9.4435091 | G7: 10.942581 | H7: =5.41+7.41 -> 12.82 | I7: 16.43 | J7: 23.12 | L7: =5.4+8.2 -> 13.6 | M7: 22.06 | N7: 31.1
B8: % Revenue | C8: 0 | D8: 0 | F8: =F7/F4 -> 0.37925739 | G8: =G7/G4 -> 0.40378528 | H8: =H7/H4 -> 0.40314465 | I8: =I7/I4 -> 0.36349558 | J8: =J7/J4 -> 0.38469218 | L8: =L7/L4 -> 0.40236686 | M8: =M7/M4 -> 0.36932865 | N8: =N7/N4 -> 0.3863354
B10: GROSS PROFIT | F10: =F4-F7 -> 15.456491 | G10: =G4-G7 -> 16.157419 | H10: =H4-H7 -> 18.98 | I10: =I4-I7 -> 28.77 | J10: =J4-J7 -> 36.98 | L10: =L4-L7 -> 20.2 | M10: =M4-M7 -> 37.67 | N10: =N4-N7 -> 49.4
B11: % Margin | F11: =F10/F4 -> 0.62074261 | G11: =G10/G4 -> 0.59621472 | H11: =H10/H4 -> 0.59685535 | I11: =I10/I4 -> 0.63650442 | J11: =J10/J4 -> 0.61530782 | L11: =L10/L4 -> 0.59763314 | M11: =M10/M4 -> 0.63067135 | N11: =N10/N4 -> 0.6136646
B13: OPEX: | J13: ` | N13: `
B14: S&M | F14: 7.727007 | G14: 7.614628 | H14: =4+5.19 -> 9.19 | I14: =13 -> 13 | J14: =14.96 -> 14.96 | L14: =4+5.9 -> 9.9 | M14: 14.3 | N14: 16.4
A15: R&D | B15: G&A | F15: 7.308554 | G15: 6.992441 | H15: =0.12+0.12 -> 0.24 | I15: =0.24 -> 0.24 | J15: =0.24 -> 0.24 | L15: =0.1+1.6 -> 1.7 | M15: 3.4 | N15: 0.4
A16: G&A | B16: R&D | F16: 0.11225 | G16: 0.018178 | H16: =5.11+5.24 -> 10.35 | I16: =11.53 -> 11.53 | J16: =13.06 -> 13.06 | L16: =5.1+6.2 -> 11.3 | M16: 13.6 | N16: 15.1
B17: OPEX | F17: =SUM(F14:F16) -> 15.147811 | G17: =SUM(G14:G16) -> 14.625247 | H17: =SUM(H14:H16) -> 19.78 | I17: =SUM(I14:I16) -> 24.77 | J17: =SUM(J14:J16) -> 28.26 | L17: =SUM(L14:L16) -> 22.9 | M17: =SUM(M14:M16) -> 31.3 | N17: =SUM(N14:N16) -> 31.9
B18: % Revenue | F18: =F17/F4 -> 0.60834582 | G18: =G17/G4 -> 0.53967701 | H18: =H17/H4 -> 0.62201258 | I18: =I17/I4 -> 0.54800885 | J18: =J17/J4 -> 0.47021631 | L18: =L17/L4 -> 0.67751479 | M18: =M17/M4 -> 0.52402478 | N18: =N17/N4 -> 0.39627329
B20: OPEX % Revenue:
B21: S&M | C21: 0 | D21: 0 | F21: =F14/F$4 -> 0.31032157 | G21: =G14/G$4 -> 0.28098258 | H21: =H14/H$4 -> 0.28899371 | I21: =I14/I$4 -> 0.28761062 | J21: =I21+$C21 -> 0.28761062 | L21: =L14/L$4 -> 0.29289941 | M21: =M14/M$4 -> 0.23941068 | N21: =M21+$C21 -> 0.23941068
B22: G&A | C22: 0 | D22: 0 | F22: =F15/F$4 -> 0.29351622 | G22: =G15/G$4 -> 0.25802365 | H22: =H15/H$4 -> 0.0075471698 | I22: =I15/I$4 -> 0.0053097345 | J22: =I22+$C22 -> 0.0053097345 | L22: =L15/L$4 -> 0.050295858 | M22: =M15/M$4 -> 0.056922819 | N22: =M22+$C22 -> 0.056922819
B23: R&D | C23: 0 | D23: 0 | F23: =F16/F$4 -> 0.0045080321 | G23: =G16/G$4 -> 0.00067077491 | H23: =H16/H$4 -> 0.3254717 | I23: =I16/I$4 -> 0.2550885 | J23: =I23+$C23 -> 0.2550885 | L23: =L16/L$4 -> 0.33431953 | M23: =M16/M$4 -> 0.22769128 | N23: =M23+$C23 -> 0.22769128
B24: Total Opex % | F24: =SUM(F21:F23) -> 0.60834582 | G24: =SUM(G21:G23) -> 0.53967701 | H24: =SUM(H21:H23) -> 0.62201258 | I24: =SUM(I21:I23) -> 0.54800885 | J24: =SUM(J21:J23) -> 0.54800885 | L24: =SUM(L21:L23) -> 0.67751479 | M24: =SUM(M21:M23) -> 0.52402478 | N24: =SUM(N21:N23) -> 0.52402478
B26: EBIT | F26: =F10-F17 -> 0.30867991 | G26: =G10-G17 -> 1.532172 | H26: =H10-H17 -> -0.8 | I26: =I10-I17 -> 4 | J26: =J10-J17 -> 8.72 | L26: =L10-L17 -> -2.7 | M26: =M10-M17 -> 6.37 | N26: =N10-N17 -> 17.5
B27: % Margin | F27: =F26/F4 -> 0.012396784 | G27: =G26/G4 -> 0.056537712 | H27: =H26/H4 -> -0.025157233 | I27: =I26/I4 -> 0.088495575 | J27: =J26/J4 -> 0.14509151 | L27: =L26/L4 -> -0.079881657 | M27: =M26/M4 -> 0.10664658 | N27: =N26/N4 -> 0.2173913
B29: D&A | F29: 0.99483639 | G29: 2.2 | H29: =H35 -> 1.28 | I29: 1.3 | J29: 2.8 | L29: =0.3+0.4+0.32+0.32 -> 1.34 | M29: =2.1+0.32 -> 2.42 | N29: =3.9+0.32 -> 4.22
B30: % Revenue | C30: 0.05 | D30: =C30 -> 0.05 | F30: =F29/F4 -> 0.039953269 | G30: =G29/G4 -> 0.081180812 | H30: =H29/H4 -> 0.040251572 | I30: =I29/I4 -> 0.028761062 | J30: =J29/J4 -> 0.046589018 | L30: =L29/L4 -> 0.03964497 | M30: =M29/M4 -> 0.040515654 | N30: =N29/N4 -> 0.05242236
B32: EBITDA | F32: =F26+F29 -> 1.3035163 | G32: =G26+G29 -> 3.732172 | H32: =H26+H29 -> 0.48 | I32: =I26+I29 -> 5.3 | J32: =J26+J29 -> 11.52 | L32: =L26+L29 -> -1.36 | M32: =M26+M29 -> 8.79 | N32: =N26+N29 -> 21.72
B33: % Margin | F33: =F32/F4 -> 0.052350052 | G33: =G32/G4 -> 0.13771852 | H33: =H32/H4 -> 0.01509434 | I33: =I32/I4 -> 0.11725664 | J33: =J32/J4 -> 0.19168053 | L33: =L32/L4 -> -0.040236686 | M33: =M32/M4 -> 0.14716223 | N33: =N32/N4 -> 0.26981366
B35: Capex (HST) | F35: 0 | G35: 1 | H35: =(0.32*2)+(0.32*2) -> 1.28 | I35: =I29 -> 1.3 | J35: =J29 -> 2.8 | L35: =L29 -> 1.34 | M35: =M29 -> 2.42 | N35: =N29 -> 4.22
B36: % Revenue | C36: =C30 -> 0.05 | D36: =D30 -> 0.05 | F36: =F35/F4 -> 0 | G36: =G35/G4 -> 0.036900369 | H36: =H35/H4 -> 0.040251572 | I36: =I35/I4 -> 0.028761062 | J36: =J35/J4 -> 0.046589018 | L36: =L35/L4 -> 0.03964497 | M36: =M35/M4 -> 0.040515654 | N36: =N35/N4 -> 0.05242236
B38: NWC | C38: 0.15 | D38: 0.15 | G38: 1.452 | H38: 1.981 | I38: 2.156 | J38: 2.879 | L38: 2.359 | M38: 2.831 | N38: 3.927
B39: Change in NWC | H39: =H38-G38 -> 0.529 | I39: =I38-H38 -> 0.175 | J39: =J38-I38 -> 0.723 | M39: =M38-L38 -> 0.472 | N39: =N38-M38 -> 1.096
B40: % Sales | G40: =G38/G4 -> 0.053579336 | H40: =H38/H4 -> 0.062295597 | I40: =I38/I4 -> 0.047699115 | J40: =J38/J4 -> 0.047903494 | L40: =L38/L4 -> 0.069792899 | M40: =M38/M4 -> 0.047396618 | N40: =N38/N4 -> 0.048782609

Sheet Standalone Case
A1: STANDALONE CASE
F2: 2017A | G2: 2018A | H2: 2019 | I2: 2020 | J2: 2021 | K2: 2022 | L2: =K2+1 -> 2023 | M2: =L2+1 -> 2024 | N2: =M2+1 -> 2025 | O2: =N2+1 -> 2026 | P2: =O2+1 -> 2027 | Q2: =P2+1 -> 2028
B4: Net Revenue | F4: 23.20256 | G4: =JILL!G4 -> 27.1 | H4: =JILL!H4 -> 31.8 | I4: =JILL!I4 -> 45.2 | J4: =JILL!J4 -> 60.1 | K4: =J4*(1+K5) -> 73.6225 | L4: =K4*(1+L5) -> 86.506438 | M4: =L4*(1+M5) -> 99.482403 | N4: =M4*(1+N5) -> 111.9177 | O4: =N4*(1+O5) -> 123.10947 | P4: =O4*(1+P5) -> 132.34268 | Q4: =P4*(1+Q5) -> 138.95982
B5: Growth % | D5: 0.025 | F5: ='mgmt '!I25 -> 0.18757834 | G5: =G4/F4-1 -> 0.16797457 | H5: =H4/G4-1 -> 0.17343173 | I5: =I4/H4-1 -> 0.42138365 | J5: =J4/I4-1 -> 0.32964602 | K5: 0.225 | L5: 0.175 | M5: 0.15 | N5: =M5-$D$5 -> 0.125 | O5: =N5-$D$5 -> 0.1 | P5: =O5-$D$5 -> 0.075 | Q5: =P5-$D$5 -> 0.05
B7: COGS | F7: ='mgmt '!I48 -> 9.4435091 | G7: =JILL!G7 -> 10.942581 | H7: =JILL!H7 -> 12.82 | I7: =JILL!I7 -> 16.43 | J7: =JILL!J7 -> 23.12 | K7: =K4*K8 -> 28.322 | L7: =L4*L8 -> 33.27835 | M7: =M4*M8 -> 38.270103 | N7: =N4*N8 -> 43.053865 | O7: =O4*O8 -> 47.359252 | P7: =P4*P8 -> 50.911196 | Q7: =Q4*Q8 -> 53.456756
B8: % Revenue | C8: 0 | D8: 0 | F8: =F7/F4 -> 0.40700289 | G8: =G7/G4 -> 0.40378528 | H8: =H7/H4 -> 0.40314465 | I8: =I7/I4 -> 0.36349558 | J8: =J7/J4 -> 0.38469218 | K8: =J8+$C8 -> 0.38469218 | L8: =K8+$C8 -> 0.38469218 | M8: =L8+$D8 -> 0.38469218 | N8: =M8+$D8 -> 0.38469218 | O8: =N8+$D8 -> 0.38469218 | P8: =O8+$D8 -> 0.38469218 | Q8: =P8+$D8 -> 0.38469218
B10: GROSS PROFIT | F10: =F4-F7 -> 13.759051 | G10: =G4-G7 -> 16.157419 | H10: =H4-H7 -> 18.98 | I10: =I4-I7 -> 28.77 | J10: =J4-J7 -> 36.98 | K10: =K4-K7 -> 45.3005 | L10: =L4-L7 -> 53.228088 | M10: =M4-M7 -> 61.212301 | ... Q10: =Q4-Q7 -> 85.503063
B11: % Margin | F11: =F10/F4 -> 0.59299711 | G11: =G10/G4 -> 0.59621472 | H11: =H10/H4 -> 0.59685535 | I11: =I10/I4 -> 0.63650442 | J11: =J10/J4 -> 0.61530782 | K11: =K10/K4 -> 0.61530782 | L11: =L10/L4 -> 0.61530782 | M11: =M10/M4 -> 0.61530782 | ... Q11: =Q10/Q4 -> 0.61530782
B13: OPEX: | J13: `
B14: S&M | F14: ='mgmt '!I65+'mgmt '!I64 -> 7.727007 | G14: =JILL!G14 -> 7.614628 | H14: =JILL!H14 -> 9.19 | I14: =JILL!I14 -> 13 | J14: =JILL!J14 -> 14.96 | K14: =K$4*K21 -> 16.85355 | L14: =L$4*L21 -> 18.072792 | M14: =M$4*M21 -> 20.286299 | N14: =N$4*N21 -> 22.262498 | O14: =O$4*O21 -> 23.873201 | P14: =P$4*P21 -> 25.001977 | Q14: =Q$4*Q21 -> 25.557277
B15: R&D | F15: ='mgmt '!I63+'mgmt '!I66+'mgmt '!I67+'mgmt '!I69 -> 7.308554 | G15: =JILL!G15 -> 6.992441 | H15: =JILL!H15 -> 0.24 | I15: =JILL!I15 -> 0.24 | J15: =JILL!J15 -> 0.24 | K15: =K$4*K22 -> 7.36225 | L15: =L$4*L22 -> 8.6506438 | M15: =M$4*M22 -> 8.9534163 | N15: =N$4*N22 -> 8.9534163 | O15: =O$4*O22 -> 8.6176632 | P15: =P$4*P22 -> 7.9405611 | Q15: =Q$4*Q22 -> 6.9479909
B16: G&A | F16: ='mgmt '!I70-('Standalone Case'!F14+'Standalone Case'!F15) -> 0.11225 | G16: =JILL!G16 -> 0.018178 | H16: =JILL!H16 -> 10.35 | I16: =JILL!I16 -> 11.53 | J16: =JILL!J16 -> 13.06 | K16: =K$4*K23 -> 15.446331 | L16: =L$4*L23 -> 17.500641 | M16: =M$4*M23 -> 19.877031 | N16: =N$4*N23 -> 22.081866 | O16: =O$4*O23 -> 23.982279 | P16: =P$4*P23 -> 25.450093 | Q16: =Q$4*Q23 -> 26.375198
B17: OPEX | F17: =SUM(F14:F16) -> 15.147811 | G17: =SUM(G14:G16) -> 14.625247 | H17: =SUM(H14:H16) -> 19.78 | I17: =SUM(I14:I16) -> 24.77 | J17: =SUM(J14:J16) -> 28.26 | K17: =SUM(K14:K16) -> 39.662131 | L17: =SUM(L14:L16) -> 44.224077 | M17: =SUM(M14:M16) -> 49.116747 | ... Q17: =SUM(Q14:Q16) -> 58.880466
B18: % Revenue | F18: =F17/F4 -> 0.65285085 | G18: =G17/G4 -> 0.53967701 | H18: =H17/H4 -> 0.62201258 | I18: =I17/I4 -> 0.54800885 | J18: =J17/J4 -> 0.47021631 | K18: =K17/K4 -> 0.53872296 | L18: =L17/L4 -> 0.51122296 | M18: =M17/M4 -> 0.49372296 | ... Q18: =Q17/Q4 -> 0.42372296
B20: OPEX % Revenue:
B21: S&M | C21: -0.02 | D21: -0.005 | F21: =F14/F$4 -> 0.3330239 | G21: =G14/G$4 -> 0.28098258 | H21: =H14/H$4 -> 0.28899371 | I21: =I14/I$4 -> 0.28761062 | J21: =J14/J$4 -> 0.24891847 | K21: =J21+$C21 -> 0.22891847 | L21: =K21+$C21 -> 0.20891847 | M21: =L21+$D21 -> 0.20391847 | N21: =M21+$D21 -> 0.19891847 | O21: =N21+$D21 -> 0.19391847 | P21: =O21+$D21 -> 0.18891847 | Q21: =P21+$D21 -> 0.18391847
B22: R&D | D22: -0.01 | F22: =F15/F$4 -> 0.31498912 | G22: =G15/G$4 -> 0.25802365 | H22: =H15/H$4 -> 0.0075471698 | I22: =I15/I$4 -> 0.0053097345 | J22: =J15/J$4 -> 0.0039933444 | K22: 0.1 | L22: 0.1 | M22: =L22+$D22 -> 0.09 | N22: =M22+$D22 -> 0.08 | O22: =N22+$D22 -> 0.07 | P22: =O22+$D22 -> 0.06 | Q22: =P22+$D22 -> 0.05
B23: G&A | C23: -0.0075 | D23: -0.0025 | F23: =F16/F$4 -> 0.0048378282 | G23: =G16/G$4 -> 0.00067077491 | H23: =H16/H$4 -> 0.3254717 | I23: =I16/I$4 -> 0.2550885 | J23: =J16/J$4 -> 0.21730449 | K23: =J23+$C23 -> 0.20980449 | L23: =K23+$C23 -> 0.20230449 | M23: =L23+$D23 -> 0.19980449 | N23: =M23+$D23 -> 0.19730449 | O23: =N23+$D23 -> 0.19480449 | P23: =O23+$D23 -> 0.19230449 | Q23: =P23+$D23 -> 0.18980449
B24: Total Opex % | F24: =SUM(F21:F23) -> 0.65285085 | G24: =SUM(G21:G23) -> 0.53967701 | H24: =SUM(H21:H23) -> 0.62201258 | I24: =SUM(I21:I23) -> 0.54800885 | J24: =SUM(J21:J23) -> 0.47021631 | K24: =SUM(K21:K23) -> 0.53872296 | L24: =SUM(L21:L23) -> 0.51122296 | M24: =SUM(M21:M23) -> 0.49372296 | ... Q24: =SUM(Q21:Q23) -> 0.42372296
B26: EBIT | F26: =F10-F17 -> -1.3887601 | G26: =G10-G17 -> 1.532172 | H26: =H10-H17 -> -0.8 | I26: =I10-I17 -> 4 | J26: =J10-J17 -> 8.72 | K26: =K10-K17 -> 5.6383687 | L26: =L10-L17 -> 9.0040103 | M26: =M10-M17 -> 12.095554 | ... Q26: =Q10-Q17 -> 26.622597
B27: % Margin | F27: =F26/F4 -> -0.059853744 | G27: =G26/G4 -> 0.056537712 | H27: =H26/H4 -> -0.025157233 | I27: =I26/I4 -> 0.088495575 | J27: =J26/J4 -> 0.14509151 | K27: =K26/K4 -> 0.076584859 | L27: =L26/L4 -> 0.10408486 | M27: =M26/M4 -> 0.12158486 | ... Q27: =Q26/Q4 -> 0.19158486
B29: D&A | F29: ='mgmt '!I86 -> 0.99483639 | G29: =JILL!G29 -> 2.2 | H29: =JILL!H29 -> 1.28 | I29: =JILL!I29 -> 1.3 | J29: =JILL!J29 -> 2.8 | K29: =K4*K30 -> 3.681125 | L29: =L4*L30 -> 4.3253219 | M29: =M35 -> 5.670497 | N29: =N35 -> 6.043556 | O29: =O35 -> 6.2785832 | P29: =P35 -> 6.3524489 | Q29: =Q35 -> 6.2531918
B30: % Revenue | C30: 0.05 | D30: =D36 -> 0.003 | F30: =F29/F4 -> 0.042876148 | G30: =G29/G4 -> 0.081180812 | H30: =H29/H4 -> 0.040251572 | I30: =I29/I4 -> 0.028761062 | J30: =J29/J4 -> 0.046589018 | K30: =C30 -> 0.05 | L30: =K30 -> 0.05 | M30: =M29/M4 -> 0.057 | N30: =N29/N4 -> 0.054 | O30: =O29/O4 -> 0.051 | P30: =P29/P4 -> 0.048 | Q30: =Q29/Q4 -> 0.045
B32: EBITDA | F32: =F26+F29 -> -0.3939237 | G32: =G26+G29 -> 3.732172 | H32: =H26+H29 -> 0.48 | I32: =I26+I29 -> 5.3 | J32: =J26+J29 -> 11.52 | K32: =K26+K29 -> 9.3194937 | L32: =L26+L29 -> 13.329332 | M32: =M26+M29 -> 17.766051 | ... Q32: =Q26+Q29 -> 32.875789
B33: % Margin | F33: =F32/F4 -> -0.016977596 | G33: =G32/G4 -> 0.13771852 | H33: =H32/H4 -> 0.01509434 | I33: =I32/I4 -> 0.11725664 | J33: =J32/J4 -> 0.19168053 | K33: =K32/K4 -> 0.12658486 | L33: =L32/L4 -> 0.15408486 | M33: =M32/M4 -> 0.17858486 | ... Q33: =Q32/Q4 -> 0.23658486
B35: Capex (HST) | F35: 0 | G35: =JILL!G35 -> 1 | H35: =JILL!H35 -> 1.28 | I35: =JILL!I35 -> 1.3 | J35: =JILL!J35 -> 2.8 | K35: =K4*K36 -> 4.41735 | L35: =L4*L36 -> 5.1903863 | M35: =M4*M36 -> 5.670497 | N35: =N4*N36 -> 6.043556 | O35: =O4*O36 -> 6.2785832 | P35: =P4*P36 -> 6.3524489 | Q35: =Q4*Q36 -> 6.2531918
B36: % Revenue | C36: 0.06 | D36: 0.003 | F36: =F35/F4 -> 0 | G36: =G35/G4 -> 0.036900369 | H36: =H35/H4 -> 0.040251572 | I36: =I35/I4 -> 0.028761062 | J36: =J35/J4 -> 0.046589018 | K36: =C36 -> 0.06 | L36: =K36 -> 0.06 | M36: =L36-$D$36 -> 0.057 | N36: =M36-$D$36 -> 0.054 | O36: =N36-$D$36 -> 0.051 | P36: =O36-$D$36 -> 0.048 | Q36: =P36-$D$36 -> 0.045
A39: DCF
G40: PERIOD | H40: 1 | I40: 2 | J40: 3 | K40: 4 | L40: 5 | M40: =L40+1 -> 6 | N40: =M40+1 -> 7 | O40: =N40+1 -> 8 | P40: =O40+1 -> 9 | Q40: =P40+1 -> 10
B41: NWC | C41: 0.05 | D41: =C41 -> 0.05 | G41: =G4*$C$41 -> 1.355 | H41: =H4*$C$41 -> 1.59 | I41: =I4*$C$41 -> 2.26 | J41: =J4*$C$41 -> 3.005 | K41: =K4*$C$41 -> 3.681125 | L41: =L4*$C$41 -> 4.3253219 | M41: =M4*$D$41 -> 4.9741202 | N41: =N4*$D$41 -> 5.5958852 | O41: =O4*$D$41 -> 6.1554737 | P41: =P4*$D$41 -> 6.6171342 | Q41: =Q4*$D$41 -> 6.9479909
B42: Change in NWC | H42: =H41-G41 -> 0.235 | I42: =I41-H41 -> 0.67 | J42: =J41-I41 -> 0.745 | K42: =K41-J41 -> 0.676125 | L42: =L41-K41 -> 0.64419688 | M42: =M41-L41 -> 0.64879828 | N42: =N41-M41 -> 0.62176502 | O42: =O41-N41 -> 0.55958852 | ... Q42: =Q41-P41 -> 0.33085671
B44: EBIT | H44: =H26 -> -0.8 | I44: =I26 -> 4 | J44: =J26 -> 8.72 | K44: =K26 -> 5.6383687 | L44: =L26 -> 9.0040103 | M44: =M26 -> 12.095554 | N44: =N26 -> 15.566058 | O44: =O26 -> 19.27708 | ... Q44: =Q26 -> 26.622597
B45: - Taxes | C45: 0.2 | H45: 0 | I45: =-I44*$C$45 -> -0.8 | J45: =-J44*$C$45 -> -1.744 | K45: =-K44*$C$45 -> -1.1276738 | L45: =-L44*$C$45 -> -1.8008021 | M45: =-M44*$C$45 -> -2.4191108 | N45: =-N44*$C$45 -> -3.1132116 | O45: =-O44*$C$45 -> -3.8554159 | P45: =-P44*$C$45 -> -4.6077715 | Q45: =-Q44*$C$45 -> -5.3245194
B46: +NOL | C46: 1 | H46: =IF(-H45<=$C$46,-H45,($C$46)) -> 0 | I46: =IF(-I45<=$C$46,-I45,($C$46)) -> 0.8 | J46: =IF(-J45<=$C$46,-J45,($C$46)) -> 1 | K46: =IF(-K45<=$C$46,-K45,($C$46)) -> 1 | L46: =IF(-L45<=$C$46,-L45,($C$46)) -> 1 | M46: =IF(-M45<=$C$46,-M45,($C$46)) -> 1 | N46: =IF(-N45<=$C$46,-N45,($C$46)) -> 1 | O46: =IF(-O45<=$C$46,-O45,($C$46)) -> 1 | ... Q46: =IF(-Q45<=$C$46,-Q45,($C$46)) -> 1
B47: - Capex | H47: =-H35 -> -1.28 | I47: =-I35 -> -1.3 | J47: =-J35 -> -2.8 | K47: =-K35 -> -4.41735 | L47: =-L35 -> -5.1903863 | M47: =-M35 -> -5.670497 | N47: =-N35 -> -6.043556 | O47: =-O35 -> -6.2785832 | ... Q47: =-Q35 -> -6.2531918
B48: + D&A | H48: =H29 -> 1.28 | I48: =I29 -> 1.3 | J48: =J29 -> 2.8 | K48: =K29 -> 3.681125 | L48: =L29 -> 4.3253219 | M48: =M29 -> 5.670497 | N48: =N29 -> 6.043556 | O48: =O29 -> 6.2785832 | ... Q48: =Q29 -> 6.2531918
B49: +/- Changes in NWC | H49: =H42 -> 0.235 | I49: =I42 -> 0.67 | J49: =J42 -> 0.745 | K49: =K42 -> 0.676125 | L49: =L42 -> 0.64419688 | M49: =M42 -> 0.64879828 | N49: =N42 -> 0.62176502 | O49: =O42 -> 0.55958852 | ... Q49: =Q42 -> 0.33085671
B50: Free Cash Flow | H50: =SUM(H44:H49) -> -0.565 | I50: =SUM(I44:I49) -> 4.67 | J50: =SUM(J44:J49) -> 8.721 | K50: =SUM(K44:K49) -> 5.450595 | L50: =SUM(L44:L49) -> 7.9823407 | M50: =SUM(M44:M49) -> 11.325241 | N50: =SUM(N44:N49) -> 14.074611 | O50: =SUM(O44:O49) -> 16.981252 | ... Q50: =SUM(Q44:Q49) -> 22.628934
B52: Period # | H52: 1 | I52: =H52+1 -> 2 | J52: =I52+1 -> 3 | K52: =J52+1 -> 4 | L52: =K52+1 -> 5 | M52: =L52+1 -> 6 | N52: =M52+1 -> 7 | O52: =N52+1 -> 8 | P52: =O52+1 -> 9 | Q52: =P52+1 -> 10 | R52: TV
B53: Discount Factor | C53: 0.18 | H53: =1/((1+$C$53)^H52) -> 0.84745763 | I53: =1/((1+$C$53)^I52) -> 0.71818443 | J53: =1/((1+$C$53)^J52) -> 0.60863087 | K53: =1/((1+$C$53)^K52) -> 0.51578888 | L53: =1/((1+$C$53)^L52) -> 0.43710922 | M53: =1/((1+$C$53)^M52) -> 0.37043154 | N53: =1/((1+$C$53)^N52) -> 0.31392503 | O53: =1/((1+$C$53)^O52) -> 0.26603816 | ... Q53: =1/((1+$C$53)^Q52) -> 0.19106447 | R53: =Q53 -> 0.19106447
B54: TV Growth % | C54: 0.02
B56: PV | H56: =H50*H53 -> -0.47881356 | I56: =I50*I53 -> 3.3539213 | J56: =J50*J53 -> 5.3078698 | K56: =K50*K53 -> 2.8113563 | L56: =L50*L53 -> 3.4891547 | M56: =M50*M53 -> 4.1952266 | N56: =N50*N53 -> 4.4183728 | O56: =O50*O53 -> 4.5176611 | ... Q56: =Q50*Q53 -> 4.3235853 | R56: =((Q50*(1+C53))/(C53-C54))*Q53 -> 31.886442
Q57: % Total | R57: =R56/H58 -> 0.46679218
B58: NET PRESENT VALUE | H58: =SUM(H56:R56) -> 68.309717
B59: FCF (Ex TV) | H59: =SUM(H56:Q56) -> 36.423275
B60: Terminal Value | H60: =R56 -> 31.886442
B61: NOL's | H61: =SUM(H46:Q46) -> 8.8
G62: check | H62: =H58-SUM(H59+H60) -> 0
X64: Discount Rate %
X65: =H58 -> 68.309717 | Y65: =Z65-$Y$73 -> 0.17 | Z65: =AA65-$Y$73 -> 0.175 | AA65: 0.18 | AB65: =AA65+$Y$73 -> 0.185 | AC65: =AB65+$Y$73 -> 0.19
X66: =X67-$Y$74 -> 0.01 | Y66: 72.838274 | Z66: 69.525569 | AA66: 66.434043 | AB66: 63.544049 | AC66: 60.838134
X67: =X68-$Y$74 -> 0.015 | Y67: 73.948752 | Z67: 70.529467 | AA67: 67.343461 | AB67: 64.369482 | AC67: 61.588721
X68: 0.02 | Y68: 75.133261 | Z68: 71.598132 | AA68: 68.309717 | AB68: 65.244941 | AC68: 62.38346
X69: =X68+$Y$74 -> 0.025 | Y69: 76.39946 | Z69: 72.738041 | AA69: 69.338311 | AB69: 66.175117 | AC69: 63.226365
X70: =X69+$Y$74 -> 0.03 | Y70: 77.756102 | Z70: 73.956565 | AA70: 70.435479 | AB70: 67.165304 | AC70: 64.121952
X73: DR % | Y73: 0.005
X74: TGR % | Y74: 0.005
X76: DR % | Y76: =Y65 -> 0.17 | Z76: =Z65 -> 0.175 | AA76: =AA65 -> 0.18 | AB76: =AB65 -> 0.185 | AC76: =AC65 -> 0.19
Y77: =AVERAGE(Y66:Y70) -> 75.21517 | Z77: =AVERAGE(Z66:Z70) -> 71.669555 | AA77: =AVERAGE(AA66:AA70) -> 68.372202 | AB77: =AVERAGE(AB66:AB70) -> 65.299779 | AC77: =AVERAGE(AC66:AC70) -> 62.431726
Y78: YoY Change | Z78: =ABS(Z77-Y77) -> 3.5456149 | AA78: =ABS(AA77-Z77) -> 3.2973525 | AB78: =ABS(AB77-AA77) -> 3.0724236 | AC78: =ABS(AC77-AB77) -> 2.8680522
Y79: DR Med | Z79: =MEDIAN(Z78:AC78) -> 3.1848881
Y82: =X66 -> 0.01 | Z82: =X67 -> 0.015 | AA82: =X68 -> 0.02 | AB82: =X69 -> 0.025 | AC82: =X70 -> 0.03
X83: TGR % | Y83: =AVERAGE(Y66:AC66) -> 66.636014 | Z83: =AVERAGE(Y67:AC67) -> 67.555976 | AA83: =AVERAGE(Y68:AC68) -> 68.533902 | AB83: =AVERAGE(Y69:AC69) -> 69.575459 | AC83: =AVERAGE(Y70:AC70) -> 70.68708
Y84: YoY Change | Z84: =ABS(Z83-Y83) -> 0.91996242 | AA84: =ABS(AA83-Z83) -> 0.9779257 | AB84: =ABS(AB83-AA83) -> 1.0415569 | AC84: =ABS(AC83-AB83) -> 1.1116215
Y85: TBG Med | Z85: =MEDIAN(Z84:AC84) -> 1.0097413

Sheet SYNERGY CASE 
A1: SYNERGY BASE CASE
F2: 2017A | G2: 2018A | H2: 2019 | I2: 2020 | J2: 2021 | K2: 2022 | L2: =K2+1 -> 2023 | M2: =L2+1 -> 2024 | N2: =M2+1 -> 2025 | O2: =N2+1 -> 2026 | P2: =O2+1 -> 2027 | Q2: =P2+1 -> 2028
B4: Net Revenue | F4: 23.20256 | G4: =JILL!G4 -> 27.1 | H4: =JILL!L4 -> 33.8 | I4: =JILL!M4 -> 59.73 | J4: =JILL!N4 -> 80.5 | K4: =J4*(1+K5) -> 98.6125 | L4: =K4*(1+L5) -> 115.86969 | M4: =L4*(1+M5) -> 133.25014 | N4: =M4*(1+N5) -> 149.90641 | O4: =N4*(1+O5) -> 164.89705 | P4: =O4*(1+P5) -> 177.26433 | Q4: =P4*(1+Q5) -> 186.12754
B5: Growth % | D5: 0.025 | F5: ='mgmt '!I25 -> 0.18757834 | G5: =G4/F4-1 -> 0.16797457 | H5: =H4/G4-1 -> 0.24723247 | I5: =I4/H4-1 -> 0.76715976 | J5: =J4/I4-1 -> 0.34773146 | K5: 0.225 | L5: 0.175 | M5: 0.15 | N5: =M5-$D$5 -> 0.125 | O5: =N5-$D$5 -> 0.1 | P5: =O5-$D$5 -> 0.075 | Q5: =P5-$D$5 -> 0.05
B7: COGS | F7: ='mgmt '!I48 -> 9.4435091 | G7: =JILL!G7 -> 10.942581 | H7: =JILL!L7 -> 13.6 | I7: =JILL!M7 -> 22.06 | J7: =JILL!N7 -> 31.1 | K7: =K4*K8 -> 38.0975 | L7: =L4*L8 -> 44.764562 | M7: =M4*M8 -> 51.479247 | N7: =N4*N8 -> 57.914153 | O7: =O4*O8 -> 63.705568 | P7: =P4*P8 -> 68.483486 | Q7: =Q4*Q8 -> 71.90766
B8: % Revenue | C8: 0 | D8: 0 | F8: =F7/F4 -> 0.40700289 | G8: =G7/G4 -> 0.40378528 | H8: =H7/H4 -> 0.40236686 | I8: =I7/I4 -> 0.36932865 | J8: =J7/J4 -> 0.3863354 | K8: =J8+$C8 -> 0.3863354 | L8: =K8+$C8 -> 0.3863354 | M8: =L8+$D8 -> 0.3863354 | N8: =M8+$D8 -> 0.3863354 | O8: =N8+$D8 -> 0.3863354 | P8: =O8+$D8 -> 0.3863354 | Q8: =P8+$D8 -> 0.3863354
B10: GROSS PROFIT | F10: =F4-F7 -> 13.759051 | G10: =G4-G7 -> 16.157419 | H10: =H4-H7 -> 20.2 | I10: =I4-I7 -> 37.67 | J10: =J4-J7 -> 49.4 | K10: =K4-K7 -> 60.515 | L10: =L4-L7 -> 71.105125 | M10: =M4-M7 -> 81.770894 | ... Q10: =Q4-Q7 -> 114.21988
B11: % Margin | F11: =F10/F4 -> 0.59299711 | G11: =G10/G4 -> 0.59621472 | H11: =H10/H4 -> 0.59763314 | I11: =I10/I4 -> 0.63067135 | J11: =J10/J4 -> 0.6136646 | K11: =K10/K4 -> 0.6136646 | L11: =L10/L4 -> 0.6136646 | M11: =M10/M4 -> 0.6136646 | ... Q11: =Q10/Q4 -> 0.6136646
B13: OPEX: | J13: `
B14: S&M | F14: ='mgmt '!I65+'mgmt '!I64 -> 7.727007 | G14: =JILL!G14 -> 7.614628 | H14: =JILL!L14 -> 9.9 | I14: =JILL!M14 -> 14.3 | J14: =JILL!N14 -> 16.4 | K14: =K$4*K21 -> 18.11775 | L14: =L$4*L21 -> 18.970962 | M14: =M$4*M21 -> 21.150356 | N14: =N$4*N21 -> 23.044619 | O14: =O$4*O21 -> 24.524595 | P14: =P$4*P21 -> 25.477618 | Q14: =Q$4*Q21 -> 25.820861
B15: R&D | F15: ='mgmt '!I63+'mgmt '!I66+'mgmt '!I67+'mgmt '!I69 -> 7.308554 | G15: =JILL!G15 -> 6.992441 | H15: =JILL!L15 -> 1.7 | I15: =JILL!M15 -> 3.4 | J15: =JILL!N15 -> 0.4 | K15: =K$4*K22 -> 9.86125 | L15: =L$4*L22 -> 11.586969 | M15: =M$4*M22 -> 11.992513 | N15: =N$4*N22 -> 11.992513 | O15: =O$4*O22 -> 11.542793 | P15: =P$4*P22 -> 10.63586 | Q15: =Q$4*Q22 -> 9.3063772
B16: G&A | F16: ='mgmt '!I70-('SYNERGY CASE '!F14+'SYNERGY CASE '!F15) -> 0.11225 | G16: =JILL!G16 -> 0.018178 | H16: =JILL!L16 -> 11.3 | I16: =JILL!M16 -> 13.6 | J16: =JILL!N16 -> 15.1 | K16: =K$4*K23 -> 17.757906 | L16: =L$4*L23 -> 19.996517 | M16: =M$4*M23 -> 22.662869 | N16: =N$4*N23 -> 25.120962 | O16: =O$4*O23 -> 27.220816 | P16: =P$4*P23 -> 28.819216 | Q16: =Q$4*Q23 -> 29.794858
B17: OPEX | F17: =SUM(F14:F16) -> 15.147811 | G17: =SUM(G14:G16) -> 14.625247 | H17: =SUM(H14:H16) -> 22.9 | I17: =SUM(I14:I16) -> 31.3 | J17: =SUM(J14:J16) -> 31.9 | K17: =SUM(K14:K16) -> 45.736906 | L17: =SUM(L14:L16) -> 50.554448 | M17: =SUM(M14:M16) -> 55.805738 | ... Q17: =SUM(Q14:Q16) -> 64.922097
B18: % Revenue | F18: =F17/F4 -> 0.65285085 | G18: =G17/G4 -> 0.53967701 | H18: =H17/H4 -> 0.67751479 | I18: =I17/I4 -> 0.52402478 | J18: =J17/J4 -> 0.39627329 | K18: =K17/K4 -> 0.46380435 | L18: =L17/L4 -> 0.43630435 | M18: =M17/M4 -> 0.41880435 | ... Q18: =Q17/Q4 -> 0.34880435
B20: OPEX % Revenue:
B21: S&M | C21: -0.02 | D21: -0.005 | F21: =F14/F$4 -> 0.3330239 | G21: =G14/G$4 -> 0.28098258 | H21: =H14/H$4 -> 0.29289941 | I21: =I14/I$4 -> 0.23941068 | J21: =J14/J$4 -> 0.20372671 | K21: =J21+$C21 -> 0.18372671 | L21: =K21+$C21 -> 0.16372671 | M21: =L21+$D21 -> 0.15872671 | N21: =M21+$D21 -> 0.15372671 | O21: =N21+$D21 -> 0.14872671 | P21: =O21+$D21 -> 0.14372671 | Q21: =P21+$D21 -> 0.13872671
B22: R&D | D22: -0.01 | F22: =F15/F$4 -> 0.31498912 | G22: =G15/G$4 -> 0.25802365 | H22: =H15/H$4 -> 0.050295858 | I22: =I15/I$4 -> 0.056922819 | J22: =J15/J$4 -> 0.0049689441 | K22: 0.1 | L22: 0.1 | M22: =L22+$D22 -> 0.09 | N22: =M22+$D22 -> 0.08 | O22: =N22+$D22 -> 0.07 | P22: =O22+$D22 -> 0.06 | Q22: =P22+$D22 -> 0.05
B23: G&A | C23: -0.0075 | D23: -0.0025 | F23: =F16/F$4 -> 0.0048378282 | G23: =G16/G$4 -> 0.00067077491 | H23: =H16/H$4 -> 0.33431953 | I23: =I16/I$4 -> 0.22769128 | J23: =J16/J$4 -> 0.18757764 | K23: =J23+$C23 -> 0.18007764 | L23: =K23+$C23 -> 0.17257764 | M23: =L23+$D23 -> 0.17007764 | N23: =M23+$D23 -> 0.16757764 | O23: =N23+$D23 -> 0.16507764 | P23: =O23+$D23 -> 0.16257764 | Q23: =P23+$D23 -> 0.16007764
B24: Total Opex % | F24: =SUM(F21:F23) -> 0.65285085 | G24: =SUM(G21:G23) -> 0.53967701 | H24: =SUM(H21:H23) -> 0.67751479 | I24: =SUM(I21:I23) -> 0.52402478 | J24: =SUM(J21:J23) -> 0.39627329 | K24: =SUM(K21:K23) -> 0.46380435 | L24: =SUM(L21:L23) -> 0.43630435 | M24: =SUM(M21:M23) -> 0.41880435 | ... Q24: =SUM(Q21:Q23) -> 0.34880435
B26: EBIT | F26: =F10-F17 -> -1.3887601 | G26: =G10-G17 -> 1.532172 | H26: =H10-H17 -> -2.7 | I26: =I10-I17 -> 6.37 | J26: =J10-J17 -> 17.5 | K26: =K10-K17 -> 14.778094 | L26: =L10-L17 -> 20.550677 | M26: =M10-M17 -> 25.965156 | ... Q26: =Q10-Q17 -> 49.297788
B27: % Margin | F27: =F26/F4 -> -0.059853744 | G27: =G26/G4 -> 0.056537712 | H27: =H26/H4 -> -0.079881657 | I27: =I26/I4 -> 0.10664658 | J27: =J26/J4 -> 0.2173913 | K27: =K26/K4 -> 0.14986025 | L27: =L26/L4 -> 0.17736025 | M27: =M26/M4 -> 0.19486025 | ... Q27: =Q26/Q4 -> 0.26486025
B29: D&A | F29: ='mgmt '!I86 -> 0.99483639 | G29: =JILL!G29 -> 2.2 | H29: =JILL!H29 -> 1.28 | I29: =JILL!I29 -> 1.3 | J29: =JILL!J29 -> 2.8 | K29: =K4*K30 -> 4.930625 | L29: =L4*L30 -> 5.7934844 | M29: =M35 -> 7.595258 | N29: =N35 -> 8.094946 | O29: =O35 -> 8.4097495 | P29: =P35 -> 8.5086877 | Q29: =Q35 -> 8.3757395
B30: % Revenue | C30: 0.05 | D30: =D36 -> 0.003 | F30: =F29/F4 -> 0.042876148 | G30: =G29/G4 -> 0.081180812 | H30: =H29/H4 -> 0.037869822 | I30: =I29/I4 -> 0.021764607 | J30: =J29/J4 -> 0.034782609 | K30: =C30 -> 0.05 | L30: =K30 -> 0.05 | M30: =M29/M4 -> 0.057 | N30: =N29/N4 -> 0.054 | O30: =O29/O4 -> 0.051 | P30: =P29/P4 -> 0.048 | Q30: =Q29/Q4 -> 0.045
B32: EBITDA | F32: =F26+F29 -> -0.3939237 | G32: =G26+G29 -> 3.732172 | H32: =H26+H29 -> -1.42 | I32: =I26+I29 -> 7.67 | J32: =J26+J29 -> 20.3 | K32: =K26+K29 -> 19.708719 | L32: =L26+L29 -> 26.344161 | M32: =M26+M29 -> 33.560414 | ... Q32: =Q26+Q29 -> 57.673527
B33: % Margin | F33: =F32/F4 -> -0.016977596 | G33: =G32/G4 -> 0.13771852 | H33: =H32/H4 -> -0.042011834 | I33: =I32/I4 -> 0.12841118 | J33: =J32/J4 -> 0.25217391 | K33: =K32/K4 -> 0.19986025 | L33: =L32/L4 -> 0.22736025 | M33: =M32/M4 -> 0.25186025 | ... Q33: =Q32/Q4 -> 0.30986025
B35: Capex (HST) | F35: 0 | G35: =JILL!G35 -> 1 | H35: =JILL!H35 -> 1.28 | I35: =JILL!I35 -> 1.3 | J35: =JILL!J35 -> 2.8 | K35: =K4*K36 -> 5.91675 | L35: =L4*L36 -> 6.9521812 | M35: =M4*M36 -> 7.595258 | N35: =N4*N36 -> 8.094946 | O35: =O4*O36 -> 8.4097495 | P35: =P4*P36 -> 8.5086877 | Q35: =Q4*Q36 -> 8.3757395
B36: % Revenue | C36: 0.06 | D36: 0.003 | F36: =F35/F4 -> 0 | G36: =G35/G4 -> 0.036900369 | H36: =H35/H4 -> 0.037869822 | I36: =I35/I4 -> 0.021764607 | J36: =J35/J4 -> 0.034782609 | K36: =C36 -> 0.06 | L36: =K36 -> 0.06 | M36: =L36-$D$36 -> 0.057 | N36: =M36-$D$36 -> 0.054 | O36: =N36-$D$36 -> 0.051 | P36: =O36-$D$36 -> 0.048 | Q36: =P36-$D$36 -> 0.045
A39: DCF
G40: PERIOD | H40: 1 | I40: 2 | J40: 3 | K40: 4 | L40: 5 | M40: =L40+1 -> 6 | N40: =M40+1 -> 7 | O40: =N40+1 -> 8 | P40: =O40+1 -> 9 | Q40: =P40+1 -> 10
B41: NWC | C41: 0.05 | D41: =C41 -> 0.05 | G41: =G4*$C$41 -> 1.355 | H41: =H4*$C$41 -> 1.69 | I41: =I4*$C$41 -> 2.9865 | J41: =J4*$C$41 -> 4.025 | K41: =K4*$C$41 -> 4.930625 | L41: =L4*$C$41 -> 5.7934844 | M41: =M4*$D$41 -> 6.662507 | N41: =N4*$D$41 -> 7.4953204 | O41: =O4*$D$41 -> 8.2448525 | P41: =P4*$D$41 -> 8.8632164 | Q41: =Q4*$D$41 -> 9.3063772
B42: Change in NWC | H42: =H41-G41 -> 0.335 | I42: =I41-H41 -> 1.2965 | J42: =J41-I41 -> 1.0385 | K42: =K41-J41 -> 0.905625 | L42: =L41-K41 -> 0.86285937 | M42: =M41-L41 -> 0.86902266 | N42: =N41-M41 -> 0.83281338 | O42: =O41-N41 -> 0.74953204 | ... Q42: =Q41-P41 -> 0.44316082
B44: EBIT | H44: =H26 -> -2.7 | I44: =I26 -> 6.37 | J44: =J26 -> 17.5 | K44: =K26 -> 14.778094 | L44: =L26 -> 20.550677 | M44: =M26 -> 25.965156 | N44: =N26 -> 31.834162 | O44: =O26 -> 37.903277 | ... Q44: =Q26 -> 49.297788
B45: - Taxes | C45: 0.2 | H45: 0 | I45: =-I44*$C$45 -> -1.274 | J45: =-J44*$C$45 -> -3.5 | K45: =-K44*$C$45 -> -2.9556188 | L45: =-L44*$C$45 -> -4.1101353 | M45: =-M44*$C$45 -> -5.1930311 | N45: =-N44*$C$45 -> -6.3668324 | O45: =-O44*$C$45 -> -7.5806553 | P45: =-P44*$C$45 -> -8.7696296 | Q45: =-Q44*$C$45 -> -9.8595575
B46: +NOL | C46: 1 | H46: =IF(-H45<=$C$46,-H45,($C$46)) -> 0 | I46: =IF(-I45<=$C$46,-I45,($C$46)) -> 1 | J46: =IF(-J45<=$C$46,-J45,($C$46)) -> 1 | K46: =IF(-K45<=$C$46,-K45,($C$46)) -> 1 | L46: =IF(-L45<=$C$46,-L45,($C$46)) -> 1 | M46: =IF(-M45<=$C$46,-M45,($C$46)) -> 1 | N46: =IF(-N45<=$C$46,-N45,($C$46)) -> 1 | O46: =IF(-O45<=$C$46,-O45,($C$46)) -> 1 | ... Q46: =IF(-Q45<=$C$46,-Q45,($C$46)) -> 1
B47: - Capex | H47: =-H35 -> -1.28 | I47: =-I35 -> -1.3 | J47: =-J35 -> -2.8 | K47: =-K35 -> -5.91675 | L47: =-L35 -> -6.9521812 | M47: =-M35 -> -7.595258 | N47: =-N35 -> -8.094946 | O47: =-O35 -> -8.4097495 | ... Q47: =-Q35 -> -8.3757395
B48: + D&A | H48: =H29 -> 1.28 | I48: =I29 -> 1.3 | J48: =J29 -> 2.8 | K48: =K29 -> 4.930625 | L48: =L29 -> 5.7934844 | M48: =M29 -> 7.595258 | N48: =N29 -> 8.094946 | O48: =O29 -> 8.4097495 | ... Q48: =Q29 -> 8.3757395
B49: +/- Changes in NWC | H49: =H42 -> 0.335 | I49: =I42 -> 1.2965 | J49: =J42 -> 1.0385 | K49: =K42 -> 0.905625 | L49: =L42 -> 0.86285937 | M49: =M42 -> 0.86902266 | N49: =N42 -> 0.83281338 | O49: =O42 -> 0.74953204 | ... Q49: =Q42 -> 0.44316082
B50: Free Cash Flow | H50: =SUM(H44:H49) -> -2.365 | I50: =SUM(I44:I49) -> 7.3925 | J50: =SUM(J44:J49) -> 16.0385 | K50: =SUM(K44:K49) -> 12.741975 | L50: =SUM(L44:L49) -> 17.144704 | M50: =SUM(M44:M49) -> 22.641147 | N50: =SUM(N44:N49) -> 27.300143 | O50: =SUM(O44:O49) -> 32.072153 | ... Q50: =SUM(Q44:Q49) -> 40.881391
B52: Period # | H52: 1 | I52: =H52+1 -> 2 | J52: =I52+1 -> 3 | K52: =J52+1 -> 4 | L52: =K52+1 -> 5 | M52: =L52+1 -> 6 | N52: =M52+1 -> 7 | O52: =N52+1 -> 8 | P52: =O52+1 -> 9 | Q52: =P52+1 -> 10 | R52: TV
B53: Discount Factor | C53: 0.18 | H53: =1/((1+$C$53)^H52) -> 0.84745763 | I53: =1/((1+$C$53)^I52) -> 0.71818443 | J53: =1/((1+$C$53)^J52) -> 0.60863087 | K53: =1/((1+$C$53)^K52) -> 0.51578888 | L53: =1/((1+$C$53)^L52) -> 0.43710922 | M53: =1/((1+$C$53)^M52) -> 0.37043154 | N53: =1/((1+$C$53)^N52) -> 0.31392503 | O53: =1/((1+$C$53)^O52) -> 0.26603816 | ... Q53: =1/((1+$C$53)^Q52) -> 0.19106447 | R53: =Q53 -> 0.19106447
B54: TV Growth % | C54: 0.02
B56: PV | H56: =H50*H53 -> -2.0042373 | I56: =I50*I53 -> 5.3091784 | J56: =J50*J53 -> 9.7615263 | K56: =K50*K53 -> 6.572169 | L56: =L50*L53 -> 7.494108 | M56: =M50*M53 -> 8.386995 | N56: =N50*N53 -> 8.5701983 | O56: =O50*O53 -> 8.5324168 | ... Q56: =Q50*Q53 -> 7.8109812 | R56: =((Q50*(1+C53))/(C53-C54))*Q53 -> 57.605986
Q57: % Total | R57: =R56/H58 -> 0.45605798
B58: NET PRESENT VALUE | H58: =SUM(H56:R56) -> 126.31286
B59: FCF (Ex TV) | H59: =SUM(H56:Q56) -> 68.70687
B60: Terminal Value | H60: =R56 -> 57.605986
B61: NOL's | H61: =SUM(H46:Q46) -> 9
G62: check | H62: =H58-SUM(H59+H60) -> 0
X64: Discount Rate %
X65: =H58 -> 126.31286 | Y65: =Z65-$Y$73 -> 0.17 | Z65: =AA65-$Y$73 -> 0.175 | AA65: 0.18 | AB65: =AA65+$Y$73 -> 0.185 | AC65: =AB65+$Y$73 -> 0.19
X66: =X67-$Y$74 -> 0.01 | Y66: 134.69761 | Z66: 128.60957 | AA66: 122.92427 | AB66: 117.6061 | AC66: 112.62344
X67: =X68-$Y$74 -> 0.015 | Y67: 136.7038 | Z67: 130.42321 | AA67: 124.56722 | AB67: 119.09733 | AC67: 113.97945
X68: 0.02 | Y68: 138.84373 | Z68: 132.35386 | AA68: 126.31286 | AB68: 120.67893 | AC68: 115.41522
X69: =X68+$Y$74 -> 0.025 | Y69: 141.13124 | Z69: 134.41322 | AA69: 128.17111 | AB69: 122.35939 | AC69: 116.93801
X70: =X69+$Y$74 -> 0.03 | Y70: 143.58215 | Z70: 136.6146 | AA70: 130.15326 | AB70: 124.14826 | AC70: 118.55598
X73: DR % | Y73: 0.005
X74: TGR % | Y74: 0.005
X76: DR % | Y76: =Y65 -> 0.17 | Z76: =Z65 -> 0.175 | AA76: =AA65 -> 0.18 | AB76: =AB65 -> 0.185 | AC76: =AC65 -> 0.19
Y77: =AVERAGE(Y66:Y70) -> 138.99171 | Z77: =AVERAGE(Z66:Z70) -> 132.48289 | AA77: =AVERAGE(AA66:AA70) -> 126.42574 | AB77: =AVERAGE(AB66:AB70) -> 120.778 | AC77: =AVERAGE(AC66:AC70) -> 115.50242
Y78: YoY Change | Z78: =ABS(Z77-Y77) -> 6.5088172 | AA78: =ABS(AA77-Z77) -> 6.0571471 | AB78: =ABS(AB77-AA77) -> 5.6477416 | AC78: =ABS(AC77-AB77) -> 5.2755808
Y79: DR Med | Z79: =MEDIAN(Z78:AC78) -> 5.8524443
Y82: =X66 -> 0.01 | Z82: =X67 -> 0.015 | AA82: =X68 -> 0.02 | AB82: =X69 -> 0.025 | AC82: =X70 -> 0.03
X83: TGR % | Y83: =AVERAGE(Y66:AC66) -> 123.2922 | Z83: =AVERAGE(Y67:AC67) -> 124.9542 | AA83: =AVERAGE(Y68:AC68) -> 126.72092 | AB83: =AVERAGE(Y69:AC69) -> 128.60259 | AC83: =AVERAGE(Y70:AC70) -> 130.61085
Y84: YoY Change | Z84: =ABS(Z83-Y83) -> 1.6620024 | AA84: =ABS(AA83-Z83) -> 1.7667187 | AB84: =ABS(AB83-AA83) -> 1.8816747 | AC84: =ABS(AC83-AB83) -> 2.0082534
Y85: TBG Med | Z85: =MEDIAN(Z84:AC84) -> 1.8241967

Sheet BENCHMARKS
B1: Conditional Formatting: | L1: Low | M1: High | N1: Check Mark
K2: Revenue | L2: 20000 | M2: 60000
A4: COMPARABLE PUBLIC COMP BENCHMARK FINANCIAL ANALYSIS
A5: $ in thousands (source: PitchBook retrieved April 2019)
S6: 3 YR CAGR
J7: =K7-1 -> 2011 | K7: =L7-1 -> 2012 | L7: =M7-1 -> 2013 | M7: =N7-1 -> 2014 | N7: =O7-1 -> 2015 | O7: =P7-1 -> 2016 | P7: =Q7-1 -> 2017 | Q7: 2018 | S7: 2015 -2018
A8: 1. REVENUE
B9: 1. REVENUE
B10: BioTelemetry | J10: ='BIO - Income Statement (2)'!U12 -> 119022 | K10: ='BIO - Income Statement (2)'!V12 -> 111494 | L10: ='BIO - Income Statement (2)'!W12 -> 129501 | M10: ='BIO - Income Statement (2)'!X12 -> 166578 | N10: ='BIO - Income Statement (2)'!Y12 -> 178513 | O10: ='BIO - Income Statement (2)'!Z12 -> 198229 | P10: ='BIO - Income Statement (2)'!AA12 -> 273175 | Q10: ='BIO - Income Statement (2)'!AB12 -> 389373 | S10: =(Q10/N10)^(1/3)-1 -> 0.29687662
B11: Inogen | J11: ='inogen P&L'!M12 -> 30099 | K11: ='inogen P&L'!N12 -> 48576 | L11: ='inogen P&L'!O12 -> 75443 | M11: ='inogen P&L'!P12 -> 112537 | N11: ='inogen P&L'!Q12 -> 159005 | O11: ='inogen P&L'!R12 -> 202829 | P11: ='inogen P&L'!S12 -> 249438 | Q11: ='inogen P&L'!T12 -> 358111 | S11: =(Q11/N11)^(1/3)-1 -> 0.31079757
B12: iRhythm | M12: ='irhy - P&L'!M12 -> 21749 | N12: ='irhy - P&L'!N12 -> 36140 | O12: ='irhy - P&L'!O12 -> 64072 | P12: ='irhy - P&L'!P12 -> 98509 | Q12: ='irhy - P&L'!Q12 -> 147293 | S12: =(Q12/N12)^(1/3)-1 -> 0.59734228
B14: 1.A REVENUE GROWTH:
B15: BioTelemetry | K15: =K10/J10-1 -> -0.063248811 | L15: =L10/K10-1 -> 0.16150645 | M15: =M10/L10-1 -> 0.28630667 | N15: =N10/M10-1 -> 0.071648117 | O15: =O10/N10-1 -> 0.11044574 | P15: =P10/O10-1 -> 0.37807788 | Q15: =Q10/P10-1 -> 0.42536103
B16: Inogen | K16: =K11/J11-1 -> 0.61387422 | L16: =L11/K11-1 -> 0.55309206 | M16: =M11/L11-1 -> 0.49168246 | N16: =N11/M11-1 -> 0.41291309 | O16: =O11/N11-1 -> 0.27561397 | P16: =P11/O11-1 -> 0.22979456 | Q16: =Q11/P11-1 -> 0.43567139
B17: iRhythm | K17: NA | L17: NA | M17: NA | N17: =N12/M12-1 -> 0.66168559 | O17: =O12/N12-1 -> 0.77288323 | P17: =P12/O12-1 -> 0.53747347 | Q17: =Q12/P12-1 -> 0.49522379
C19: 1.B REVENUE GROWTH ANALYTICS:
C20: 75th Percentile | K20: =PERCENTILE(K15:K17, 0.75) -> 0.44459346 | L20: =PERCENTILE(L15:L17, 0.75) -> 0.45519566 | M20: =PERCENTILE(M15:M17, 0.75) -> 0.44033851 | N20: =PERCENTILE(N15:N17, 0.75) -> 0.53729934 | O20: =PERCENTILE(O15:O17, 0.75) -> 0.5242486 | P20: =PERCENTILE(P15:P17, 0.75) -> 0.45777567 | Q20: =PERCENTILE(Q15:Q17, 0.75) -> 0.46544759 | S20: =PERCENTILE(S10:S12, 0.75) -> 0.45406992
C21: Median | K21: =MEDIAN(K15:K17) -> 0.2753127 | L21: =MEDIAN(L15:L17) -> 0.35729926 | M21: =MEDIAN(M15:M17) -> 0.38899457 | N21: =MEDIAN(N15:N17) -> 0.41291309 | O21: =MEDIAN(O15:O17) -> 0.27561397 | P21: =MEDIAN(P15:P17) -> 0.37807788 | Q21: =MEDIAN(Q15:Q17) -> 0.43567139 | S21: =MEDIAN(S10:S12) -> 0.31079757
C22: 25th Percentile | K22: =PERCENTILE(K15:K17, 0.25) -> 0.10603195 | L22: =PERCENTILE(L15:L17, 0.25) -> 0.25940285 | M22: =PERCENTILE(M15:M17, 0.25) -> 0.33765062 | N22: =PERCENTILE(N15:N17, 0.25) -> 0.2422806 | O22: =PERCENTILE(O15:O17, 0.25) -> 0.19302986 | P22: =PERCENTILE(P15:P17, 0.25) -> 0.30393622 | Q22: =PERCENTILE(Q15:Q17, 0.25) -> 0.43051621 | S22: =PERCENTILE(S10:S12, 0.25) -> 0.30383709
B24: Revenue Growth YoY Change %
B25: BioTelemetry | L25: =L15-K15 -> 0.22475526 | M25: =M15-L15 -> 0.12480022 | N25: =N15-M15 -> -0.21465855 | O25: =O15-N15 -> 0.038797621 | P25: =P15-O15 -> 0.26763214 | Q25: =Q15-P15 -> 0.047283153
B26: Inogen | L26: =L16-K16 -> -0.060782153 | M26: =M16-L16 -> -0.0614096 | N26: =N16-M16 -> -0.078769376 | O26: =O16-N16 -> -0.13729911 | P26: =P16-O16 -> -0.045819418 | Q26: =Q16-P16 -> 0.20587683
B27: iRhythm | M27: NA | N27: NM | O27: =O17-N17 -> 0.11119764 | P27: =P17-O17 -> -0.23540976 | Q27: =Q17-P17 -> -0.042249681
B29: COGS:
B30: BioTelemetry | J30: ='BIO - Income Statement (2)'!U15 -> 49076 | K30: ='BIO - Income Statement (2)'!V15 -> 45593 | L30: ='BIO - Income Statement (2)'!W15 -> 50431 | M30: ='BIO - Income Statement (2)'!X15 -> 73114 | N30: ='BIO - Income Statement (2)'!Y15 -> 71956 | O30: ='BIO - Income Statement (2)'!Z15 -> 78882 | P30: ='BIO - Income Statement (2)'!AA15 -> 114406 | Q30: ='BIO - Income Statement (2)'!AB15 -> 148986 | S30: =(Q30/M30)^(1/3)-1 -> 0.26779287
B31: Inogen | K31: ='inogen P&L'!N18 -> 24627 | L31: ='inogen P&L'!O18 -> 36452 | M31: ='inogen P&L'!P18 -> 57020 | N31: ='inogen P&L'!Q18 -> 82747 | O31: ='inogen P&L'!R18 -> 105519 | P31: ='inogen P&L'!S18 -> 128201 | Q31: ='inogen P&L'!T18 -> 179531 | S31: =(Q31/M31)^(1/3)-1 -> 0.4656741
B32: iRhythm | M32: ='irhy - P&L'!M14 -> 10591 | N32: ='irhy - P&L'!N14 -> 14700 | O32: ='irhy - P&L'!O14 -> 20883 | P32: ='irhy - P&L'!P14 -> 27708 | Q32: ='irhy - P&L'!Q14 -> 38579 | S32: =(Q32/M32)^(1/3)-1 -> 0.53864347
B34: Gross Profit:
B35: BioTelemetry | J35: =J10-J30 -> 69946 | K35: =K10-K30 -> 65901 | L35: =L10-L30 -> 79070 | M35: =M10-M30 -> 93464 | N35: =N10-N30 -> 106557 | O35: =O10-O30 -> 119347 | P35: =P10-P30 -> 158769 | Q35: =Q10-Q30 -> 240387
B36: Inogen | J36: ='Inogen - Key Metrics'!L12 | K36: =K11-K31 -> 23949 | L36: =L11-L31 -> 38991 | M36: =M11-M31 -> 55517 | N36: =N11-N31 -> 76258 | O36: =O11-O31 -> 97310 | P36: =P11-P31 -> 121237 | Q36: =Q11-Q31 -> 178580
B37: iRhythm | M37: =M12-M32 -> 11158 | N37: =N12-N32 -> 21440 | O37: =O12-O32 -> 43189 | P37: =P12-P32 -> 70801 | Q37: =Q12-Q32 -> 108714
B39: Gross Margin %:
B40: BioTelemetry | J40: =J35/J10 -> 0.58767287 | K40: =K35/K10 -> 0.59107217 | L40: =L35/L10 -> 0.61057444 | M40: =M35/M10 -> 0.5610825 | N40: =N35/N10 -> 0.59691451 | O40: =O35/O10 -> 0.6020663 | P40: =P35/P10 -> 0.58119887 | Q40: =Q35/Q10 -> 0.61736946
B41: Inogen | K41: =K36/K11 -> 0.49302125 | L41: =L36/L11 -> 0.51682727 | M41: =M36/M11 -> 0.4933222 | N41: =N36/N11 -> 0.47959498 | O41: =O36/O11 -> 0.47976374 | P41: =P36/P11 -> 0.48604062 | Q41: =Q36/Q11 -> 0.4986722
B42: iRhythm | M42: =M37/M12 -> 0.51303508 | N42: =N37/N12 -> 0.59324848 | O42: =O37/O12 -> 0.6740698 | P42: =P37/P12 -> 0.71872621 | Q42: =Q37/Q12 -> 0.73807988
B44: 75th Percentile | K44: =PERCENTILE(K40:K42, 0.75) -> 0.56655944 | L44: =PERCENTILE(L40:L42, 0.75) -> 0.58713765 | M44: =PERCENTILE(M40:M42, 0.75) -> 0.53705879 | N44: =PERCENTILE(N40:N42, 0.75) -> 0.59508149 | O44: =PERCENTILE(O40:O42, 0.75) -> 0.63806805 | P44: =PERCENTILE(P40:P42, 0.75) -> 0.64996254 | Q44: =PERCENTILE(Q40:Q42, 0.75) -> 0.67772467
B45: Median | K45: =MEDIAN(K40:K42) -> 0.54204671 | L45: =MEDIAN(L40:L42) -> 0.56370085 | M45: =MEDIAN(M40:M42) -> 0.51303508 | N45: =MEDIAN(N40:N42) -> 0.59324848 | O45: =MEDIAN(O40:O42) -> 0.6020663 | P45: =MEDIAN(P40:P42) -> 0.58119887 | Q45: =MEDIAN(Q40:Q42) -> 0.61736946
B46: 25th Percentile | K46: =PERCENTILE(K40:K42, 0.25) -> 0.51753398 | L46: =PERCENTILE(L40:L42, 0.25) -> 0.54026406 | M46: =PERCENTILE(M40:M42, 0.25) -> 0.50317864 | N46: =PERCENTILE(N40:N42, 0.25) -> 0.53642173 | O46: =PERCENTILE(O40:O42, 0.25) -> 0.54091502 | P46: =PERCENTILE(P40:P42, 0.25) -> 0.53361974 | Q46: =PERCENTILE(Q40:Q42, 0.25) -> 0.55802083
B48: OPEX:
B50: S&M:
B51: BioTelemetry | K51: ='BIO - Income Statement (2)'!V22 -> 25604 | L51: ='BIO - Income Statement (2)'!W22 -> 26275 | M51: ='BIO - Income Statement (2)'!X22 -> 28805 | N51: ='BIO - Income Statement (2)'!Y22 -> 27936 | O51: ='BIO - Income Statement (2)'!Z22 -> 28636 | P51: ='BIO - Income Statement (2)'!AA22 -> 35322 | Q51: ='BIO - Income Statement (2)'!AB22 -> 42849 | S51: =(Q51/M51)^(1/3)-1 -> 0.14153948
B52: Inogen | K52: ='inogen P&L'!N23 -> 12569 | L52: ='inogen P&L'!O23 -> 18375 | M52: ='inogen P&L'!P23 -> 24087 | N52: ='inogen P&L'!Q23 -> 31369 | O52: ='inogen P&L'!R23 -> 37540 | P52: ='inogen P&L'!S23 -> 50758 | Q52: ='inogen P&L'!T23 -> 95641 | S52: =(Q52/M52)^(1/3)-1 -> 0.58350874
B53: iRhythm | S53: =(Q53/M53)^(1/3)-1 -> #DIV/0!
B55: G&A: | S55: =(Q55/M55)^(1/3)-1 -> #DIV/0!
B56: BioTelemetry | K56: ='BIO - Income Statement (2)'!V19+'BIO - Income Statement (2)'!V20+'BIO - Income Statement (2)'!V21 -> 36692 | L56: ='BIO - Income Statement (2)'!W19+'BIO - Income Statement (2)'!W20+'BIO - Income Statement (2)'!W21 -> 44551 | M56: ='BIO - Income Statement (2)'!X19+'BIO - Income Statement (2)'!X20+'BIO - Income Statement (2)'!X21 -> 52229 | N56: ='BIO - Income Statement (2)'!Y20 -> 47882 | O56: ='BIO - Income Statement (2)'!Z20 -> 55877 | P56: ='BIO - Income Statement (2)'!AA20 -> 82983 | Q56: ='BIO - Income Statement (2)'!AB20 -> 109736 | S56: =(Q56/M56)^(1/3)-1 -> 0.28079357
B57: Inogen | K57: ='inogen P&L'!N22 -> 8289 | L57: ='inogen P&L'!O22 -> 13754 | M57: ='inogen P&L'!P22 -> 17942 | N57: ='inogen P&L'!Q22 -> 25658 | O57: ='inogen P&L'!R22 -> 31793 | P57: ='inogen P&L'!S22 -> 37576 | Q57: ='inogen P&L'!T22 -> 38018 | S57: =(Q57/M57)^(1/3)-1 -> 0.28441727
B58: iRhythm
B60: R&D:
B61: BioTelemetry | K61: ='BIO - Income Statement (2)'!V24 -> 4664 | L61: ='BIO - Income Statement (2)'!W24 -> 7338 | M61: ='BIO - Income Statement (2)'!X24 -> 7396 | N61: ='BIO - Income Statement (2)'!Y24 -> 7111 | O61: ='BIO - Income Statement (2)'!Z24 -> 8355 | P61: ='BIO - Income Statement (2)'!AA24 -> 11101 | Q61: ='BIO - Income Statement (2)'!AB24 -> 11206 | S61: =(Q61/M61)^(1/3)-1 -> 0.14855352
B62: Inogen | K62: ='inogen P&L'!N25 -> 2262 | L62: ='inogen P&L'!O25 -> 2398 | M62: ='inogen P&L'!P25 -> 2977 | N62: ='inogen P&L'!Q25 -> 4180 | O62: ='inogen P&L'!R25 -> 5113 | P62: ='inogen P&L'!S25 -> 5313 | Q62: ='inogen P&L'!T25 -> 7029 | S62: =(Q62/M62)^(1/3)-1 -> 0.3315932
B63: iRhythm | M63: ='irhy - P&L'!M18 -> 5698 | N63: ='irhy - P&L'!N18 -> 6349 | O63: ='irhy - P&L'!O18 -> 7150 | P63: ='irhy - P&L'!P18 -> 13335 | Q63: ='irhy - P&L'!Q18 -> 20750 | S63: =(Q63/M63)^(1/3)-1 -> 0.53850372
B65: S&M % Revenue
B66: BioTelemetry | K66: =K51/K10 -> 0.22964464 | L66: =L51/L10 -> 0.20289419 | M66: =M51/M10 -> 0.17292199 | N66: =N51/N10 -> 0.1564928 | O66: =O51/O10 -> 0.14445919 | P66: =P51/P10 -> 0.12930173 | Q66: =Q51/Q10 -> 0.11004615
B67: Inogen | K67: NM | L67: =L52/L11 -> 0.24356136 | M67: =M52/M11 -> 0.21403627 | N67: =N52/N11 -> 0.1972831 | O67: =O52/O11 -> 0.18508201 | P67: =P52/P11 -> 0.20348944 | Q67: =Q52/Q11 -> 0.26707082
B68: iRhythm | K68: NA | L68: =K68 -> NA | M68: =L68 -> NA | N68: =M68 -> NA | O68: =N68 -> NA | P68: =O68 -> NA | Q68: =P68 -> NA
B70: 75th Percentile | K70: =PERCENTILE(K66:K68, 0.75) -> 0.22964464 | L70: =PERCENTILE(L66:L68, 0.75) -> 0.23339457 | M70: =PERCENTILE(M66:M68, 0.75) -> 0.2037577 | N70: =PERCENTILE(N66:N68, 0.75) -> 0.18708553 | O70: =PERCENTILE(O66:O68, 0.75) -> 0.17492631 | P70: =PERCENTILE(P66:P68, 0.75) -> 0.18494252 | Q70: =PERCENTILE(Q66:Q68, 0.75) -> 0.22781466
B71: Median | K71: =MEDIAN(K66:K68) -> 0.22964464 | L71: =MEDIAN(L66:L68) -> 0.22322778 | M71: =MEDIAN(M66:M68) -> 0.19347913 | N71: =MEDIAN(N66:N68) -> 0.17688795 | O71: =MEDIAN(O66:O68) -> 0.1647706 | P71: =MEDIAN(P66:P68) -> 0.16639559 | Q71: =MEDIAN(Q66:Q68) -> 0.18855849
B72: 25th Percentile | K72: =PERCENTILE(K66:K68, 0.25) -> 0.22964464 | L72: =PERCENTILE(L66:L68, 0.25) -> 0.21306098 | M72: =PERCENTILE(M66:M68, 0.25) -> 0.18320056 | N72: =PERCENTILE(N66:N68, 0.25) -> 0.16669038 | O72: =PERCENTILE(O66:O68, 0.25) -> 0.15461489 | P72: =PERCENTILE(P66:P68, 0.25) -> 0.14784866 | Q72: =PERCENTILE(Q66:Q68, 0.25) -> 0.14930232
B74: G&A % Revenue
B75: BioTelemetry | J75: =J56/J38 -> #DIV/0! | K75: =K56/K10 -> 0.32909394 | L75: =L56/L10 -> 0.34402051 | M75: =M56/M10 -> 0.3135408 | N75: =N56/N10 -> 0.26822696 | O75: =O56/O10 -> 0.28188106 | P75: =P56/P10 -> 0.30377231 | Q75: =Q56/Q10 -> 0.28182745
B76: Inogen | K76: =K57/K11 -> 0.17063982 | L76: =L57/L11 -> 0.18230982 | M76: =M57/M11 -> 0.15943201 | N76: =N57/N11 -> 0.16136599 | O76: =O57/O11 -> 0.1567478 | P76: =P57/P11 -> 0.15064264 | Q76: =Q57/Q11 -> 0.10616261
B77: iRhythm | K77: NA | L77: =K77 -> NA | M77: =L77 -> NA | N77: =M77 -> NA | O77: =N77 -> NA | P77: =O77 -> NA | Q77: =P77 -> NA
B79: 75th Percentile | K79: =PERCENTILE(K75:K77, 0.75) -> 0.28948041 | L79: =PERCENTILE(L75:L77, 0.75) -> 0.30359284 | M79: =PERCENTILE(M75:M77, 0.75) -> 0.2750136 | N79: =PERCENTILE(N75:N77, 0.75) -> 0.24151172 | O79: =PERCENTILE(O75:O77, 0.75) -> 0.25059774 | P79: =PERCENTILE(P75:P77, 0.75) -> 0.26548989 | Q79: =PERCENTILE(Q75:Q77, 0.75) -> 0.23791124
B80: Median | K80: =MEDIAN(K75:K77) -> 0.24986688 | L80: =MEDIAN(L75:L77) -> 0.26316517 | M80: =MEDIAN(M75:M77) -> 0.23648641 | N80: =MEDIAN(N75:N77) -> 0.21479648 | O80: =MEDIAN(O75:O77) -> 0.21931443 | P80: =MEDIAN(P75:P77) -> 0.22720748 | Q80: =MEDIAN(Q75:Q77) -> 0.19399503
B81: 25th Percentile | K81: =PERCENTILE(K75:K77, 0.25) -> 0.21025335 | L81: =PERCENTILE(L75:L77, 0.25) -> 0.22273749 | M81: =PERCENTILE(M75:M77, 0.25) -> 0.19795921 | N81: =PERCENTILE(N75:N77, 0.25) -> 0.18808124 | O81: =PERCENTILE(O75:O77, 0.25) -> 0.18803112 | P81: =PERCENTILE(P75:P77, 0.25) -> 0.18892506 | Q81: =PERCENTILE(Q75:Q77, 0.25) -> 0.15007882
B83: R&D % Revenue
B84: BioTelemetry | J84: =J61/J47 -> #DIV/0! | K84: =K61/K10 -> 0.041831847 | L84: =L61/L10 -> 0.056663655 | M84: =M61/M10 -> 0.044399621 | N84: =N61/N10 -> 0.039834634 | O84: =O61/O10 -> 0.042148223 | P84: =P61/P10 -> 0.040636954 | Q84: =Q61/Q10 -> 0.028779602
B85: Inogen | K85: =K62/K11 -> 0.046566206 | L85: =L62/L11 -> 0.031785586 | M85: =M62/M11 -> 0.026453522 | N85: =N62/N11 -> 0.026288481 | O85: =O62/O11 -> 0.025208427 | P85: =P62/P11 -> 0.021299882 | Q85: =Q62/Q11 -> 0.019627992
B86: iRhythm | K86: NA | L86: =K86 -> NA | M86: =L86 -> NA | N86: =M86 -> NA | O86: =N86 -> NA | P86: =O86 -> NA | Q86: =P86 -> NA
B88: 75th Percentile | K88: =PERCENTILE(K84:K86, 0.75) -> 0.045382616 | L88: =PERCENTILE(L84:L86, 0.75) -> 0.050444138 | M88: =PERCENTILE(M84:M86, 0.75) -> 0.039913096 | N88: =PERCENTILE(N84:N86, 0.75) -> 0.036448096 | O88: =PERCENTILE(O84:O86, 0.75) -> 0.037913274 | P88: =PERCENTILE(P84:P86, 0.75) -> 0.035802686 | Q88: =PERCENTILE(Q84:Q86, 0.75) -> 0.0264917
B89: Median | K89: =MEDIAN(K84:K86) -> 0.044199026 | L89: =MEDIAN(L84:L86) -> 0.044224621 | M89: =MEDIAN(M84:M86) -> 0.035426571 | N89: =MEDIAN(N84:N86) -> 0.033061558 | O89: =MEDIAN(O84:O86) -> 0.033678325 | P89: =MEDIAN(P84:P86) -> 0.030968418 | Q89: =MEDIAN(Q84:Q86) -> 0.024203797
B90: 25th Percentile | K90: =PERCENTILE(K84:K86, 0.25) -> 0.043015437 | L90: =PERCENTILE(L84:L86, 0.25) -> 0.038005104 | M90: =PERCENTILE(M84:M86, 0.25) -> 0.030940047 | N90: =PERCENTILE(N84:N86, 0.25) -> 0.02967502 | O90: =PERCENTILE(O84:O86, 0.25) -> 0.029443376 | P90: =PERCENTILE(P84:P86, 0.25) -> 0.02613415 | Q90: =PERCENTILE(Q84:Q86, 0.25) -> 0.021915895
B92: OPEX % Revenue
B93: BioTelemetry | J93: =J66/J51 -> #DIV/0! | K93: =K66+K75+K84 -> 0.60057043 | L93: =L66+L75+L84 -> 0.60357835 | M93: =M66+M75+M84 -> 0.53086242 | N93: =N66+N75+N84 -> 0.4645544 | O93: =O66+O75+O84 -> 0.46848847 | P93: =P66+P75+P84 -> 0.47371099 | Q93: =Q66+Q75+Q84 -> 0.4206532
B94: Inogen | K94: =K95 -> NA | L94: =L67+L76+L85 -> 0.45765677 | M94: =M67+M76+M85 -> 0.3999218 | N94: =N67+N76+N85 -> 0.38493758 | O94: =O67+O76+O85 -> 0.36703824 | P94: =P67+P76+P85 -> 0.37543197 | Q94: =Q67+Q76+Q85 -> 0.39286143
B95: iRhythm | K95: NA | L95: NA | M95: NA | N95: =M95 -> NA | O95: =N95 -> NA | P95: =O95 -> NA | Q95: =P95 -> NA
B97: 75th Percentile | K97: NM | L97: =PERCENTILE(L93:L95, 0.75) -> 0.56709796 | M97: =PERCENTILE(M93:M95, 0.75) -> 0.49812726 | N97: =PERCENTILE(N93:N95, 0.75) -> 0.4446502 | O97: =PERCENTILE(O93:O95, 0.75) -> 0.44312591 | P97: =PERCENTILE(P93:P95, 0.75) -> 0.44914124 | Q97: =PERCENTILE(Q93:Q95, 0.75) -> 0.41370526
B98: Median | K98: =K97 -> NM | L98: =MEDIAN(L93:L95) -> 0.53061756 | M98: =MEDIAN(M93:M95) -> 0.46539211 | N98: =MEDIAN(N93:N95) -> 0.42474599 | O98: =MEDIAN(O93:O95) -> 0.41776335 | P98: =MEDIAN(P93:P95) -> 0.42457148 | Q98: =MEDIAN(Q93:Q95) -> 0.40675732
B99: 25th Percentile | K99: =K98 -> NM | L99: =PERCENTILE(L93:L95, 0.25) -> 0.49413717 | M99: =PERCENTILE(M93:M95, 0.25) -> 0.43265696 | N99: =PERCENTILE(N93:N95, 0.25) -> 0.40484179 | O99: =PERCENTILE(O93:O95, 0.25) -> 0.3924008 | P99: =PERCENTILE(P93:P95, 0.25) -> 0.40000173 | Q99: =PERCENTILE(Q93:Q95, 0.25) -> 0.39980937
B102: OPEX (CALCULATED);
B103: BioTelemetry | K103: =K51+K56+K61 -> 66960 | L103: =L51+L56+L61 -> 78164 | M103: =M51+M56+M61 -> 88430 | N103: =N51+N56+N61 -> 82929 | O103: =O51+O56+O61 -> 92868 | P103: =P51+P56+P61 -> 129406 | Q103: =Q51+Q56+Q61 -> 163791
B104: Inogen | K104: =K52+K57+K62 -> 23120 | L104: =L52+L57+L62 -> 34527 | M104: =M52+M57+M62 -> 45006 | N104: =N52+N57+N62 -> 61207 | O104: =O52+O57+O62 -> 74446 | P104: =P52+P57+P62 -> 93647 | Q104: =Q52+Q57+Q62 -> 140688
B105: iRhythm | K105: =K53+K58+K63 -> 0 | L105: =L53+L58+L63 -> 0 | M105: =M53+M58+M63 -> 5698 | N105: =N53+N58+N63 -> 6349 | O105: =O53+O58+O63 -> 7150 | P105: =P53+P58+P63 -> 13335 | Q105: =Q53+Q58+Q63 -> 20750
B109: EBIT (NORMALIZED):
B110: BioTelemetry | K110: ='BIO - Income Statement (2)'!V85 -> -13107 | L110: ='BIO - Income Statement (2)'!W85 -> -6881 | M110: ='BIO - Income Statement (2)'!X85 -> -4110 | N110: ='BIO - Income Statement (2)'!Y85 -> 9430 | O110: ='BIO - Income Statement (2)'!Z85 -> 27818 | P110: ='BIO - Income Statement (2)'!AA85 -> 22086 | Q110: ='BIO - Income Statement (2)'!AB85 -> 73401
B111: Inogen | K111: ='inogen P&L'!N80 -> 1102 | L111: ='inogen P&L'!O80 -> 4981 | M111: ='inogen P&L'!P80 -> 12320 | N111: ='inogen P&L'!Q80 -> 15861 | O111: ='inogen P&L'!R80 -> 23465 | P111: ='inogen P&L'!S80 -> 29963 | Q111: ='inogen P&L'!T80 -> 37940
B112: iRhythm
B114: EBIT (Normalized) % Margin:
B115: BioTelemetry | J115: =J95/J68 -> #DIV/0! | K115: =K110/K10 -> -0.1175579 | L115: =L110/L10 -> -0.053134725 | M115: =M110/M10 -> -0.024673126 | N115: =N110/N10 -> 0.052825284 | O115: =O110/O10 -> 0.14033265 | P115: =P110/P10 -> 0.080849272 | Q115: =Q110/Q10 -> 0.18851076
B116: Inogen | K116: =K111/K11 -> 0.0226861 | L116: =L111/L11 -> 0.066023355 | M116: =M111/M11 -> 0.10947511 | N116: =N111/N11 -> 0.09975158 | O116: =O111/O11 -> 0.11568858 | P116: =P111/P11 -> 0.12012203 | Q116: =Q111/Q11 -> 0.1059448
B117: iRhythm | M117: =M112/M12 -> 0 | N117: =N112/N12 -> 0 | O117: =O112/O12 -> 0 | P117: =P112/P12 -> 0 | Q117: =Q112/Q12 -> 0
B119: 75th Percentile | K119: =PERCENTILE(K115:K117, 0.75) -> -0.012374899 | L119: =PERCENTILE(L115:L117, 0.75) -> 0.036233835 | M119: =PERCENTILE(M115:M117, 0.75) -> 0.054737553 | N119: =PERCENTILE(N115:N117, 0.75) -> 0.076288432 | O119: =PERCENTILE(O115:O117, 0.75) -> 0.12801062 | P119: =PERCENTILE(P115:P117, 0.75) -> 0.10048565 | Q119: =PERCENTILE(Q115:Q117, 0.75) -> 0.14722778
B120: Median | K120: =MEDIAN(K115:K117) -> -0.047435898 | L120: =MEDIAN(L115:L117) -> 0.0064443153 | M120: =MEDIAN(M115:M117) -> 0 | N120: =MEDIAN(N115:N117) -> 0.052825284 | O120: =MEDIAN(O115:O117) -> 0.11568858 | P120: =MEDIAN(P115:P117) -> 0.080849272 | Q120: =MEDIAN(Q115:Q117) -> 0.1059448
B121: 25th Percentile | K121: =PERCENTILE(K115:K117, 0.25) -> -0.082496897 | L121: =PERCENTILE(L115:L117, 0.25) -> -0.023345205 | M121: =PERCENTILE(M115:M117, 0.25) -> -0.012336563 | N121: =PERCENTILE(N115:N117, 0.25) -> 0.026412642 | O121: =PERCENTILE(O115:O117, 0.25) -> 0.057844292 | P121: =PERCENTILE(P115:P117, 0.25) -> 0.040424636 | Q121: =PERCENTILE(Q115:Q117, 0.25) -> 0.052972402
B124: EBIT (CALCULATED):
B125: BioTelemetry | K125: =K35-K103 -> -1059 | L125: =L35-L103 -> 906 | M125: =M35-M103 -> 5034 | N125: =N35-N103 -> 23628 | O125: =O35-O103 -> 26479 | P125: =P35-P103 -> 29363 | Q125: =Q35-Q103 -> 76596
B126: Inogen | K126: =K36-K104 -> 829 | L126: =L36-L104 -> 4464 | M126: =M36-M104 -> 10511 | N126: =N36-N104 -> 15051 | O126: =O36-O104 -> 22864 | P126: =P36-P104 -> 27590 | Q126: =Q36-Q104 -> 37892
B127: iRhythm | K127: =K37-K105 -> 0 | L127: =L37-L105 -> 0 | M127: =M37-M105 -> 5460 | N127: =N37-N105 -> 15091 | O127: =O37-O105 -> 36039 | P127: =P37-P105 -> 57466 | Q127: =Q37-Q105 -> 87964
B129: EBIT (Calculated) % Margin:
B130: BioTelemetry | J130: =J110/J91 -> #DIV/0! | K130: =K125/K10 -> -0.009498269 | L130: =L125/L10 -> 0.006996085 | M130: =M125/M10 -> 0.030220077 | N130: =N125/N10 -> 0.13236011 | O130: =O125/O10 -> 0.13357783 | P130: =P125/P10 -> 0.10748787 | Q130: =Q125/Q10 -> 0.19671626
...

Sheet Synergy Base Case - old
A1: SYNERGY BASE CASE
F2: 2017A | G2: 2018A | H2: 2019 | I2: 2020 | J2: 2021 | K2: 2022 | L2: =K2+1 -> 2023 | M2: =L2+1 -> 2024 | N2: =M2+1 -> 2025 | O2: =N2+1 -> 2026 | P2: =O2+1 -> 2027 | Q2: =P2+1 -> 2028
B4: Net Revenue | F4: 23.20256 | G4: ='Standalone Case'!G4 -> 27.1 | H4: =JILL!L4 -> 33.8 | I4: =JILL!M4 -> 59.73 | J4: =JILL!N4 -> 80.5 | K4: =J4*(1+K5) -> 96.6 | L4: =K4*(1+L5) -> 115.92 | M4: =L4*(1+M5) -> 127.512 | N4: =M4*(1+N5) -> 140.2632 | O4: =N4*(1+O5) -> 154.28952 | P4: =O4*(1+P5) -> 169.71847 | Q4: =P4*(1+Q5) -> 186.69032
B5: Growth % | C5: 0.2 | D5: 0.1 | F5: ='mgmt '!I25 -> 0.18757834 | G5: =G4/F4-1 -> 0.16797457 | H5: =H4/G4-1 -> 0.24723247 | I5: =I4/H4-1 -> 0.76715976 | J5: =J4/I4-1 -> 0.34773146 | K5: =C5 -> 0.2 | L5: =K5 -> 0.2 | M5: =D5 -> 0.1 | N5: =M5 -> 0.1 | O5: =N5 -> 0.1 | P5: =O5 -> 0.1 | Q5: =P5 -> 0.1
B7: COGS | C7: YoY Improvement | F7: ='mgmt '!I48 -> 9.4435091 | G7: ='Standalone Case'!G7 -> 10.942581 | H7: =JILL!L7 -> 13.6 | I7: =JILL!M7 -> 22.06 | J7: =JILL!N7 -> 31.1 | K7: =K4*K8 -> 37.32 | L7: =L4*L8 -> 44.784 | M7: =M4*M8 -> 49.2624 | N7: =N4*N8 -> 54.18864 | O7: =O4*O8 -> 59.607504 | P7: =P4*P8 -> 65.568254 | Q7: =Q4*Q8 -> 72.12508
B8: % Revenue | C8: 0 | D8: 0 | F8: =F7/F4 -> 0.40700289 | G8: =G7/G4 -> 0.40378528 | H8: =H7/H4 -> 0.40236686 | I8: =I7/I4 -> 0.36932865 | J8: =J7/J4 -> 0.3863354 | K8: =J8+$C8 -> 0.3863354 | L8: =K8+$C8 -> 0.3863354 | M8: =L8+$D8 -> 0.3863354 | N8: =M8+$D8 -> 0.3863354 | O8: =N8+$D8 -> 0.3863354 | P8: =O8+$D8 -> 0.3863354 | Q8: =P8+$D8 -> 0.3863354
B10: GROSS PROFIT | F10: =F4-F7 -> 13.759051 | G10: =G4-G7 -> 16.157419 | H10: =H4-H7 -> 20.2 | I10: =I4-I7 -> 37.67 | J10: =J4-J7 -> 49.4 | K10: =K4-K7 -> 59.28 | L10: =L4-L7 -> 71.136 | M10: =M4-M7 -> 78.2496 | ... Q10: =Q4-Q7 -> 114.56524
B11: % Margin | F11: =F10/F4 -> 0.59299711 | G11: =G10/G4 -> 0.59621472 | H11: =H10/H4 -> 0.59763314 | I11: =I10/I4 -> 0.63067135 | J11: =J10/J4 -> 0.6136646 | K11: =K10/K4 -> 0.6136646 | L11: =L10/L4 -> 0.6136646 | M11: =M10/M4 -> 0.6136646 | ... Q11: =Q10/Q4 -> 0.6136646
B13: OPEX: | J13: `
B14: S&M | F14: ='mgmt '!I65+'mgmt '!I64 -> 7.727007 | G14: ='Standalone Case'!G14 -> 7.614628 | H14: =JILL!L14 -> 9.9 | I14: =JILL!M14 -> 14.3 | J14: =JILL!N14 -> 16.4 | K14: =K$4*K21 -> 19.68 | L14: =L$4*L21 -> 23.616 | M14: =M$4*M21 -> 25.9776 | N14: =N$4*N21 -> 28.57536 | O14: =O$4*O21 -> 31.432896 | P14: =P$4*P21 -> 34.576186 | Q14: =Q$4*Q21 -> 38.033804
B15: R&D | F15: ='mgmt '!I63+'mgmt '!I66+'mgmt '!I67+'mgmt '!I69 -> 7.308554 | G15: ='Standalone Case'!G15 -> 6.992441 | H15: =JILL!L15 -> 1.7 | I15: =JILL!M15 -> 3.4 | J15: =JILL!N15 -> 0.4 | K15: =K$4*K22 -> 0.48 | L15: =L$4*L22 -> 0.576 | M15: =M$4*M22 -> 0.6336 | N15: =N$4*N22 -> 0.69696 | O15: =O$4*O22 -> 0.766656 | P15: =P$4*P22 -> 0.8433216 | Q15: =Q$4*Q22 -> 0.92765376
B16: G&A | F16: ='mgmt '!I70-('Synergy Base Case - old'!F14+'Synergy Base Case - old'!F15) -> 0.11225 | G16: ='Standalone Case'!G16 -> 0.018178 | H16: =JILL!L16 -> 11.3 | I16: =JILL!M16 -> 13.6 | J16: =JILL!N16 -> 15.1 | K16: =K$4*K23 -> 18.12 | L16: =L$4*L23 -> 21.744 | M16: =M$4*M23 -> 23.9184 | N16: =N$4*N23 -> 26.31024 | O16: =O$4*O23 -> 28.941264 | P16: =P$4*P23 -> 31.83539 | Q16: =Q$4*Q23 -> 35.018929
B17: OPEX | F17: =SUM(F14:F16) -> 15.147811 | G17: =SUM(G14:G16) -> 14.625247 | H17: =SUM(H14:H16) -> 22.9 | I17: =SUM(I14:I16) -> 31.3 | J17: =SUM(J14:J16) -> 31.9 | K17: =SUM(K14:K16) -> 38.28 | L17: =SUM(L14:L16) -> 45.936 | M17: =SUM(M14:M16) -> 50.5296 | ... Q17: =SUM(Q14:Q16) -> 73.980387
B18: % Revenue | F18: =F17/F4 -> 0.65285085 | G18: =G17/G4 -> 0.53967701 | H18: =H17/H4 -> 0.67751479 | I18: =I17/I4 -> 0.52402478 | J18: =J17/J4 -> 0.39627329 | K18: =K17/K4 -> 0.39627329 | L18: =L17/L4 -> 0.39627329 | M18: =M17/M4 -> 0.39627329 | ... Q18: =Q17/Q4 -> 0.39627329
B20: OPEX % Revenue: | C20: YoY Improvement
B21: S&M | C21: 0 | D21: 0 | F21: =F14/F$4 -> 0.3330239 | G21: =G14/G$4 -> 0.28098258 | H21: =H14/H$4 -> 0.29289941 | I21: =I14/I$4 -> 0.23941068 | J21: =J14/J$4 -> 0.20372671 | K21: =J21+$C21 -> 0.20372671 | L21: =K21+$C21 -> 0.20372671 | M21: =L21+$D21 -> 0.20372671 | N21: =M21+$D21 -> 0.20372671 | O21: =N21+$D21 -> 0.20372671 | P21: =O21+$D21 -> 0.20372671 | Q21: =P21+$D21 -> 0.20372671
B22: R&D | C22: 0 | D22: 0 | F22: =F15/F$4 -> 0.31498912 | G22: =G15/G$4 -> 0.25802365 | H22: =H15/H$4 -> 0.050295858 | I22: =I15/I$4 -> 0.056922819 | J22: =J15/J$4 -> 0.0049689441 | K22: =J22+$C22 -> 0.0049689441 | L22: =K22+$C22 -> 0.0049689441 | M22: =L22+$D22 -> 0.0049689441 | N22: =M22+$D22 -> 0.0049689441 | O22: =N22+$D22 -> 0.0049689441 | P22: =O22+$D22 -> 0.0049689441 | Q22: =P22+$D22 -> 0.0049689441
B23: G&A | C23: 0 | D23: 0 | F23: =F16/F$4 -> 0.0048378282 | G23: =G16/G$4 -> 0.00067077491 | H23: =H16/H$4 -> 0.33431953 | I23: =I16/I$4 -> 0.22769128 | J23: =J16/J$4 -> 0.18757764 | K23: =J23+$C23 -> 0.18757764 | L23: =K23+$C23 -> 0.18757764 | M23: =L23+$D23 -> 0.18757764 | N23: =M23+$D23 -> 0.18757764 | O23: =N23+$D23 -> 0.18757764 | P23: =O23+$D23 -> 0.18757764 | Q23: =P23+$D23 -> 0.18757764
B24: Total Opex % | G24: =SUM(G21:G23) -> 0.53967701 | H24: =SUM(H21:H23) -> 0.67751479 | I24: =SUM(I21:I23) -> 0.52402478 | J24: =SUM(J21:J23) -> 0.39627329
F25: =F10-F17 -> -1.3887601
B26: EBIT | F26: =F25/F4 -> -0.059853744 | G26: =G10-G17 -> 1.532172 | H26: =H10-H17 -> -2.7 | I26: =I10-I17 -> 6.37 | J26: =J10-J17 -> 17.5 | K26: =K10-K17 -> 21 | L26: =L10-L17 -> 25.2 | M26: =M10-M17 -> 27.72 | N26: =N10-N17 -> 30.492 | ... Q26: =Q10-Q17 -> 40.584852
B27: % Margin | G27: =G26/G4 -> 0.056537712 | H27: =H26/H4 -> -0.079881657 | I27: =I26/I4 -> 0.10664658 | J27: =J26/J4 -> 0.2173913 | K27: =K26/K4 -> 0.2173913 | L27: =L26/L4 -> 0.2173913 | M27: =M26/M4 -> 0.2173913 | N27: =N26/N4 -> 0.2173913 | ... Q27: =Q26/Q4 -> 0.2173913
B29: D&A | F29: ='mgmt '!I86 -> 0.99483639 | G29: ='Standalone Case'!G29 -> 2.2 | H29: =JILL!H29 -> 1.28 | I29: =JILL!I29 -> 1.3 | J29: =JILL!J29 -> 2.8 | K29: =K4*K30 -> 5.064 | L29: =L4*L30 -> 6.0768 | M29: =M4*M30 -> 6.68448 | N29: =N4*N30 -> 7.352928 | O29: =O4*O30 -> 8.0882208 | P29: =P4*P30 -> 8.8970429 | Q29: =Q4*Q30 -> 9.7867472
B30: % Revenue | C30: =C36 -> 0.05242236 | D30: =C30 -> 0.05242236 | F30: =F29/F4 -> 0.042876148 | G30: =G29/G4 -> 0.081180812 | H30: =H29/H4 -> 0.037869822 | I30: =I29/I4 -> 0.021764607 | J30: =J29/J4 -> 0.034782609 | K30: =C30 -> 0.05242236 | L30: =K30 -> 0.05242236 | M30: =D30 -> 0.05242236 | N30: =M30 -> 0.05242236 | O30: =N30 -> 0.05242236 | P30: =O30 -> 0.05242236 | Q30: =P30 -> 0.05242236
B32: EBITDA | F32: =F25+F29 -> -0.3939237 | G32: =G26+G29 -> 3.732172 | H32: =H26+H29 -> -1.42 | I32: =I26+I29 -> 7.67 | J32: =J26+J29 -> 20.3 | K32: =K26+K29 -> 26.064 | L32: =L26+L29 -> 31.2768 | M32: =M26+M29 -> 34.40448 | N32: =N26+N29 -> 37.844928 | ... Q32: =Q26+Q29 -> 50.371599
B33: % Margin | F33: =F32/F4 -> -0.016977596 | G33: =G32/G4 -> 0.13771852 | H33: =H32/H4 -> -0.042011834 | I33: =I32/I4 -> 0.12841118 | J33: =J32/J4 -> 0.25217391 | K33: =K32/K4 -> 0.26981366 | L33: =L32/L4 -> 0.26981366 | M33: =M32/M4 -> 0.26981366 | ... Q33: =Q32/Q4 -> 0.26981366
B35: Capex (HST) | F35: 0 | G35: =JILL!G35 -> 1 | H35: =JILL!L29 -> 1.34 | I35: =JILL!M29 -> 2.42 | J35: =JILL!N29 -> 4.22 | K35: =K4*K36 -> 5.064 | L35: =L4*L36 -> 6.0768 | M35: =M4*M36 -> 6.68448 | N35: =N4*N36 -> 7.352928 | O35: =O4*O36 -> 8.0882208 | P35: =P4*P36 -> 8.8970429 | Q35: =Q4*Q36 -> 9.7867472
B36: % Revenue | C36: =J36 -> 0.05242236 | D36: =C36 -> 0.05242236 | F36: =F35/F4 -> 0 | G36: =G35/G4 -> 0.036900369 | H36: =H35/H4 -> 0.03964497 | I36: =I35/I4 -> 0.040515654 | J36: =J35/J4 -> 0.05242236 | K36: =C36 -> 0.05242236 | L36: =K36 -> 0.05242236 | M36: =D36 -> 0.05242236 | N36: =M36 -> 0.05242236 | O36: =N36 -> 0.05242236 | P36: =O36 -> 0.05242236 | Q36: =P36 -> 0.05242236
A39: DCF
G40: PERIOD | H40: 1 | I40: 2 | J40: 3 | K40: 4 | L40: 5 | M40: =L40+1 -> 6 | N40: =M40+1 -> 7 | O40: =N40+1 -> 8 | P40: =O40+1 -> 9 | Q40: =P40+1 -> 10
B41: NWC | C41: 0.15 | G41: =G4*$C$41 -> 4.065 | H41: =H4*$C$41 -> 5.07 | I41: =I4*$C$41 -> 8.9595 | J41: =J4*$C$41 -> 12.075 | K41: =K4*$C$41 -> 14.49 | L41: =L4*$C$41 -> 17.388 | M41: =M4*$C$41 -> 19.1268 | N41: =N4*$C$41 -> 21.03948 | ... Q41: =Q4*$C$41 -> 28.003548
B42: Change in NWC | H42: =H41-G41 -> 1.005 | I42: =I41-H41 -> 3.8895 | J42: =J41-I41 -> 3.1155 | K42: =K41-J41 -> 2.415 | L42: =L41-K41 -> 2.898 | M42: =M41-L41 -> 1.7388 | N42: =N41-M41 -> 1.91268 | O42: =O41-N41 -> 2.103948 | ... Q42: =Q41-P41 -> 2.5457771
B44: EBIT | H44: =H26 -> -2.7 | I44: =I26 -> 6.37 | J44: =J26 -> 17.5 | K44: =K26 -> 21 | L44: =L26 -> 25.2 | M44: =M26 -> 27.72 | N44: =N26 -> 30.492 | O44: =O26 -> 33.5412 | ... Q44: =Q26 -> 40.584852
B45: - Taxes | C45: 0.2 | H45: =H44*$C$45 -> -0.54 | I45: =-I44*$C$45 -> -1.274 | J45: =-J44*$C$45 -> -3.5 | K45: =-K44*$C$45 -> -4.2 | L45: =-L44*$C$45 -> -5.04 | M45: =-M44*$C$45 -> -5.544 | N45: =-N44*$C$45 -> -6.0984 | O45: =-O44*$C$45 -> -6.70824 | P45: =-P44*$C$45 -> -7.379064 | Q45: =-Q44*$C$45 -> -8.1169704
B46: +NOL | C46: 1 | H46: =IF(-H45<=$C$46,-H45,($C$46)) -> 0.54 | I46: =IF(-I45<=$C$46,-I45,($C$46)) -> 1 | J46: =IF(-J45<=$C$46,-J45,($C$46)) -> 1 | K46: =IF(-K45<=$C$46,-K45,($C$46)) -> 1 | L46: =IF(-L45<=$C$46,-L45,($C$46)) -> 1 | M46: =IF(-M45<=$C$46,-M45,($C$46)) -> 1 | N46: =IF(-N45<=$C$46,-N45,($C$46)) -> 1 | O46: =IF(-O45<=$C$46,-O45,($C$46)) -> 1 | ... Q46: =IF(-Q45<=$C$46,-Q45,($C$46)) -> 1
B47: - Capex | H47: =-H35 -> -1.34 | I47: =-I35 -> -2.42 | J47: =-J35 -> -4.22 | K47: =-K35 -> -5.064 | L47: =-L35 -> -6.0768 | M47: =-M35 -> -6.68448 | N47: =-N35 -> -7.352928 | O47: =-O35 -> -8.0882208 | ... Q47: =-Q35 -> -9.7867472
B48: + D&A | H48: =H29 -> 1.28 | I48: =I29 -> 1.3 | J48: =J29 -> 2.8 | K48: =K29 -> 5.064 | L48: =L29 -> 6.0768 | M48: =M29 -> 6.68448 | N48: =N29 -> 7.352928 | O48: =O29 -> 8.0882208 | ... Q48: =Q29 -> 9.7867472
B49: +/- Changes in NWC | H49: =H42 -> 1.005 | I49: =I42 -> 3.8895 | J49: =J42 -> 3.1155 | K49: =K42 -> 2.415 | L49: =L42 -> 2.898 | M49: =M42 -> 1.7388 | N49: =N42 -> 1.91268 | O49: =O42 -> 2.103948 | ... Q49: =Q42 -> 2.5457771
B50: Free Cash Flow | H50: =SUM(H44:H49) -> -1.755 | I50: =SUM(I44:I49) -> 8.8655 | J50: =SUM(J44:J49) -> 16.6955 | K50: =SUM(K44:K49) -> 20.215 | L50: =SUM(L44:L49) -> 24.058 | M50: =SUM(M44:M49) -> 24.9148 | N50: =SUM(N44:N49) -> 27.30628 | O50: =SUM(O44:O49) -> 29.936908 | ... Q50: =SUM(Q44:Q49) -> 36.013659
B52: Period # | H52: 1 | I52: =H52+1 -> 2 | J52: =I52+1 -> 3 | K52: =J52+1 -> 4 | L52: =K52+1 -> 5 | M52: =L52+1 -> 6 | N52: =M52+1 -> 7 | O52: =N52+1 -> 8 | P52: =O52+1 -> 9 | Q52: =P52+1 -> 10 | R52: TV
B53: Discount Factor | C53: 0.18 | H53: =1/((1+$C$53)^H52) -> 0.84745763 | I53: =1/((1+$C$53)^I52) -> 0.71818443 | J53: =1/((1+$C$53)^J52) -> 0.60863087 | K53: =1/((1+$C$53)^K52) -> 0.51578888 | L53: =1/((1+$C$53)^L52) -> 0.43710922 | M53: =1/((1+$C$53)^M52) -> 0.37043154 | N53: =1/((1+$C$53)^N52) -> 0.31392503 | O53: =1/((1+$C$53)^O52) -> 0.26603816 | ... Q53: =1/((1+$C$53)^Q52) -> 0.19106447 | R53: =Q53 -> 0.19106447
B54: TV Growth % | C54: 0.03
B56: PV | H56: =H50*H53 -> -1.4872881 | I56: =I50*I53 -> 6.3670641 | J56: =J50*J53 -> 10.161397 | K56: =K50*K53 -> 10.426672 | L56: =L50*L53 -> 10.515974 | M56: =M50*M53 -> 9.2292277 | N56: =N50*N53 -> 8.5721249 | O56: =O50*O53 -> 7.96436 | ... Q56: =Q50*Q53 -> 6.8809305 | R56: =((Q50*(1+C53))/(C53-C54))*Q53 -> 54.129987
Q57: % Total | R57: =R56/H58 -> 0.4158653
B58: NET PRESENT VALUE | H58: =SUM(H56:R56) -> 130.16231
B59: FCF (Ex TV) | H59: =SUM(H56:Q56) -> 76.032319
B60: Terminal Value | H60: =R56 -> 54.129987
B61: NOL's | H61: =SUM(H46:Q46) -> 9.54
G62: check | H62: =H58-SUM(H59+H60) -> 0
X64: Discount Rate %
X65: =H58 -> 130.16231 | Y65: =Z65-$Y$73 -> 0.17 | Z65: =AA65-$Y$73 -> 0.175 | AA65: 0.18 | AB65: =AA65+$Y$73 -> 0.185 | AC65: =AB65+$Y$73 -> 0.19
X66: =X67-$Y$74 -> 0.02 | Y66: 138.42032 | Z66: 132.39818 | AA66: 126.77918 | AB66: 121.52627 | AC66: 116.60674
X67: =X68-$Y$74 -> 0.025 | Y67: 140.43546 | Z67: 134.21233 | AA67: 128.41618 | AB67: 123.00663 | AC67: 117.94822
X68: 0.03 | Y68: 142.59454 | Z68: 136.1516 | AA68: 130.16231 | AB68: 124.5825 | AC68: 119.37353
X69: =X68+$Y$74 -> 0.035 | Y69: 144.91355 | Z69: 138.22938 | AA69: 132.02886 | AB69: 126.26343 | AC69: 120.8908
X70: =X69+$Y$74 -> 0.04 | Y70: 147.41095 | Z70: 140.46107 | AA70: 134.02873 | AB70: 128.06029 | AC70: 122.50922
X73: DR % | Y73: 0.005
X74: TGR % | Y74: 0.005
X76: DR % | Y76: =Y65 -> 0.17 | Z76: =Z65 -> 0.175 | AA76: =AA65 -> 0.18 | AB76: =AB65 -> 0.185 | AC76: =AC65 -> 0.19
Y77: =AVERAGE(Y66:Y70) -> 142.75497 | Z77: =AVERAGE(Z66:Z70) -> 136.29051 | AA77: =AVERAGE(AA66:AA70) -> 130.28305 | AB77: =AVERAGE(AB66:AB70) -> 124.68783 | AC77: =AVERAGE(AC66:AC70) -> 119.4657
Y78: YoY Change | Z78: =ABS(Z77-Y77) -> 6.4644536 | AA78: =ABS(AA77-Z77) -> 6.0074616 | AB78: =ABS(AB77-AA77) -> 5.5952254 | AC78: =ABS(AC77-AB77) -> 5.2221221
Y79: DR Med | Z79: =MEDIAN(Z78:AC78) -> 5.8013435
Y82: =X66 -> 0.02 | Z82: =X67 -> 0.025 | AA82: =X68 -> 0.03 | AB82: =X69 -> 0.035 | AC82: =X70 -> 0.04
X83: TGR % | Y83: =AVERAGE(Y66:AC66) -> 127.14614 | Z83: =AVERAGE(Y67:AC67) -> 128.80376 | AA83: =AVERAGE(Y68:AC68) -> 130.5729 | AB83: =AVERAGE(Y69:AC69) -> 132.4652 | AC83: =AVERAGE(Y70:AC70) -> 134.49405
Y84: YoY Change | Z84: =ABS(Z83-Y83) -> 1.6576244 | AA84: =ABS(AA83-Z83) -> 1.7691314 | AB84: =ABS(AB83-AA83) -> 1.8923088 | AC84: =ABS(AC83-AB83) -> 2.0288484
Y85: TBG Med | Z85: =MEDIAN(Z84:AC84) -> 1.8307201

Sheet DEAL COMPS
A2: DEAL COMPS
A4: ($ in millions)
I5: Purchsae | Q5: PP /
A6: Announced | C6: Acquirer | E6: Target | G6: Target Description | I6: Price (PP) | K6: LTM Revenue | M6: Gross Profit | O6: =U6 -> EBITDA | Q6: Revenue | S6: Gross Profit | U6: EBITDA
A8: April 2017 | C8: BioTelemetry | E8: LifeWatch | G8: Provider of remote cardiac monitoring diagnostic services for healthcare professionals. | I8: 239 | K8: 114 | M8: =K8*49% -> 55.86 | O8: =I8*5% -> 11.95 | Q8: =$I8/K8 -> 2.0964912 | S8: =$I8/M8 -> 4.2785535 | U8: =$I8/O8 -> 20
A9: Sept 2014 | C9: Preventice | E9: eCardio Diagnostics | G9: Provider of ambulatory cardiac monitoring products and services for arrhythmia diagnosis | I9: 150 | K9: 50 | M9: =I9*56% -> 84 | O9: =I9*14% -> 21 | Q9: =$I9/K9 -> 3 | S9: =$I9/M9 -> 1.7857143 | U9: =$I9/O9 -> 7.1428571
A10: Aug 2013 | C10: Medtronic | E10: Cardiocom | G10: Manufacturer and distributor of health monitoring products for multiple chronic diseases | I10: 200 | K10: 37 | M10: NA | O10: NA | Q10: =$I10/K10 -> 5.4054054 | S10: =M10 -> NA | U10: =O10 -> NA
A11: Aug 2012 | C11: Linde | E11: Lincare | G11: Supplier of durable / home medical equipment such as hospital beds, wheelchairs, CPAP, pulsox, etc. | I11: 3600 | K11: 1963.961 | M11: 1327.185 | O11: 470.071 | Q11: =$I11/K11 -> 1.8330303 | S11: =$I11/M11 -> 2.7125081 | U11: =$I11/O11 -> 7.6584176
I14: 75th Percentile | Q14: =PERCENTILE(Q8:Q11, 0.75) -> 3.6013514 | S14: =PERCENTILE(S8:S11, 0.75) -> 3.4955308 | U14: =PERCENTILE(U8:U11, 0.75) -> 13.829209
I15: Median | Q15: =MEDIAN(Q8:Q11) -> 2.5482456 | S15: =MEDIAN(S8:S11) -> 2.7125081 | U15: =MEDIAN(U8:U11) -> 7.6584176
I16: 25th Percentile | Q16: =PERCENTILE(Q8:Q11, 0.25) -> 2.030626 | S16: =PERCENTILE(S8:S11, 0.25) -> 2.2491112 | U16: =PERCENTILE(U8:U11, 0.25) -> 7.4006374
E19: Nola (2018A) | K19: ='Standalone Case'!G4 -> 27.1 | M19: =#REF! -> #REF! | O19: NM
A21: Sources: PitchBook, Company Financials, Piper Jaffery, Public Filings & Internal Company Estimates.
A26: Nov 2017 | C26: Altus Capital | E26: MGC Diagnostics | I26: 62.1 | K26: 40.464 | M26: 19.852 | O26: 0.593 | Q26: =$I26/K26 -> 1.5346975 | S26: =$I26/M26 -> 3.1281483 | U26: =$I26/O26 -> 104.72175

Sheet Pub Comps
C1: PUB COMPS
A3: 43531 | C3: ($ in millions)
G4: Share | K4: Revenue | O4: Revenue Growth % | S4: GM % | U4: EBITDA | Y4: EBITDA % | AD4: EV/Revenue | AH4: EV/EBITDA
A5: ID | B5: Category | E5: Company | G5: Price | I5: EV | K5: 2018A | L5: 2019E | M5: 2020E | O5: 2018A-2019E | Q5: 2019E-2020E | S5: 2018A | U5: 2018A | V5: 2019E | W5: 2020E | Y5: 2018A | Z5: 2019E | AA5: 2020E | AD5: 2018A | AF5: 2019E | AH5: =AD5 -> 2018A | AJ5: =AF5 -> 2019E
A6: =A51 | B6: Diagnostics | C6: DIAGNOSTICS | E6: BioTelemetry | G6: 67.19 | I6: 2358.3805 | K6: 389.373 | L6: 440.9 | M6: 485.8 | O6: =L6/K6-1 -> 0.13233326 | Q6: =M6/L6-1 -> 0.10183715 | S6: 0.63098746 | U6: 91.101 | V6: 127.864 | W6: 143.297 | Y6: =U6/K6 -> 0.23396846 | Z6: =V6/L6 -> 0.2900068 | AA6: =W6/M6 -> 0.29497118 | AD6: =$I6/K6 -> 6.0568671 | AF6: =$I6/L6 -> 5.3490145 | AH6: =$I6/U6 -> 25.887537 | AJ6: =$I6/V6 -> 18.444445
A7: =A49 | B7: Diagnostics | E7: Inogen | G7: 97.23 | I7: 1880.7132 | K7: 358.111 | L7: 435 | M7: 519.848 | O7: =L7/K7-1 -> 0.21470717 | Q7: =M7/L7-1 -> 0.19505287 | S7: 0.48604062 | U7: 48.491 | V7: 70.208 | W7: 85.4 | Y7: =U7/K7 -> 0.13540774 | Z7: =V7/L7 -> 0.1613977 | AA7: =W7/M7 -> 0.16427879 | AD7: =$I7/K7 -> 5.2517606 | AF7: =$I7/L7 -> 4.3234787 | AH7: =$I7/U7 -> 38.78479 | AJ7: =$I7/V7 -> 26.787734
A8: =A48 | B8: Diagnostics | E8: iRhythm | G8: 89.89 | I8: 2155.5855 | K8: 147.293 | L8: 205.4 | M8: 268.073 | O8: =L8/K8-1 -> 0.3944994 | Q8: =M8/L8-1 -> 0.30512658 | S8: 0.71872621 | U8: -42.852 | V8: -36.722 | W8: 12 | Y8: NM | Z8: NM | AA8: =W8/M8 -> 0.044763926 | AD8: =$I8/K8 -> 14.634677 | AF8: =$I8/M8 -> 8.0410392 | AH8: NM | AJ8: NM
A9: =A50 | B9: Sleep | C9: SLEEP | E9: Fisher & Paykel | G9: 10.188263 | I9: 5828.5847 | K9: 688.77114 | L9: 742.527 | M9: 822.245 | O9: =L9/K9-1 -> 0.078046043 | Q9: =M9/L9-1 -> 0.10736041 | S9: 0.65039919 | U9: 224.59152 | V9: 234.377 | W9: 277.335 | Y9: =U9/K9 -> 0.32607569 | Z9: =V9/L9 -> 0.31564778 | AA9: =W9/M9 -> 0.33728998 | AD9: =$I9/K9 -> 8.4622952 | AF9: =$I9/L9 -> 7.8496602 | AH9: =$I9/U9 -> 25.951935 | AJ9: =$I9/V9 -> 24.868416
A10: =A47 | B10: Sleep | E10: Itamar Medical | G10: 0.35788383 | I10: 106.79799 | K10: 20.701 | L10: NA | M10: NA | O10: NA | Q10: NA | S10: 0.72998915 | U10: -0.28 | V10: NA | W10: NA | Y10: NM | Z10: NA | AA10: NA | AD10: =$I10/K10 -> 5.1590738 | AF10: NM | AH10: NM | AJ10: NM
A11: =A46 | B11: Sleep | E11: ResMed | G11: 100.49 | I11: 15448.228 | K11: 2340.196 | L11: 2601 | M11: 2881 | O11: =L11/K11-1 -> 0.11144537 | Q11: =M11/L11-1 -> 0.1076509 | S11: 0.58146973 | U11: 653.249 | V11: 775.189 | W11: 860.071 | Y11: =U11/K11 -> 0.27914286 | Z11: =V11/L11 -> 0.29803499 | AA11: =W11/M11 -> 0.29853211 | AD11: =$I11/K11 -> 6.6012539 | AF11: =$I11/L11 -> 5.9393418 | AH11: =$I11/U11 -> 23.648299 | AJ11: =$I11/V11 -> 19.928337
V14: 75th Percentile | Y14: =PERCENTILE(Y6:Y11, 0.75) -> 0.29087607 | Z14: =PERCENTILE(Z6:Z11, 0.75) -> 0.30243819 | AA14: =PERCENTILE(AA6:AA11, 0.75) -> 0.29853211 | AD14: =PERCENTILE(AD6:AD11, 0.75) -> 7.9970348 | AF14: =PERCENTILE(AF6:AF11, 0.75) -> 7.8496602 | AH14: =PERCENTILE(AH6:AH11, 0.75) -> 29.160149 | AJ14: =PERCENTILE(AJ6:AJ11, 0.75) -> 25.348245
V15: Median | Y15: =MEDIAN(Y6:Y11) -> 0.25655566 | Z15: =MEDIAN(Z6:Z11) -> 0.2940209 | AA15: =MEDIAN(AA6:AA11) -> 0.29497118 | AD15: =MEDIAN(AD6:AD11) -> 6.3290605 | AF15: =MEDIAN(AF6:AF11) -> 5.9393418 | AH15: =MEDIAN(AH6:AH11) -> 25.919736 | AJ15: =MEDIAN(AJ6:AJ11) -> 22.398377
V16: 25th Percentile | Y16: =PERCENTILE(Y6:Y11, 0.25) -> 0.20932828 | Z16: =PERCENTILE(Z6:Z11, 0.25) -> 0.25785453 | AA16: =PERCENTILE(AA6:AA11, 0.25) -> 0.16427879 | AD16: =PERCENTILE(AD6:AD11, 0.25) -> 5.4530372 | AF16: =PERCENTILE(AF6:AF11, 0.25) -> 5.3490145 | AH16: =PERCENTILE(AH6:AH11, 0.25) -> 25.327728 | AJ16: =PERCENTILE(AJ6:AJ11, 0.25) -> 19.557364
E19: Standalone Case | K19: ='Standalone Case'!G4 -> 27.1 | L19: ='Standalone Case'!H4 -> 31.8 | M19: ='Standalone Case'!I4 -> 45.2 | O19: =L19/K19-1 -> 0.17343173 | Q19: =M19/L19-1 -> 0.42138365 | S19: ='Standalone Case'!G11 -> 0.59621472 | U19: ='Standalone Case'!G32 -> 3.732172 | V19: ='Standalone Case'!H32 -> 0.48 | W19: ='Standalone Case'!I32 -> 5.3 | Y19: =U19/K19 -> 0.13771852 | Z19: =V19/L19 -> 0.01509434 | AA19: =W19/M19 -> 0.11725664
E20: Synergy Base Case | K20: =K19 -> 27.1 | L20: ='SYNERGY CASE '!H4 -> 33.8 | M20: ='SYNERGY CASE '!I4 -> 59.73 | O20: =L20/K20-1 -> 0.24723247 | Q20: =M20/L20-1 -> 0.76715976 | S20: =S19 -> 0.59621472 | U20: =U19 -> 3.732172 | V20: ='SYNERGY CASE '!H32 -> -1.42 | W20: ='SYNERGY CASE '!I32 -> 7.67 | Y20: =U20/K20 -> 0.13771852 | Z20: =V20/L20 -> -0.042011834 | AA20: =W20/M20 -> 0.12841118
E22: Sources: PitchBook, Company Financials, Piper Jaffery, Public Filings & Internal Company Estimates. Enterprise Value calculation based off stock closing price of [March 9, 2019]

Sheet FOOTBALL FIELD
D1: THINKCELL | S1: IMPLIED DCF
H3: CHECK | K3: Discount Rate %
A4: DCF | C4: Standalone Case | D4: =U4 -> 65.244941 | E4: =T4-U4 -> 3.0647751 | F4: =S4-T4 -> 3.2884153 | H4: =SUM(D4:F4)-S4 -> 0 | K4: ='Standalone Case'!Z65 -> 0.175 | L4: ='Standalone Case'!AA65 -> 0.18 | M4: ='Standalone Case'!AB65 -> 0.185 | S4: ='Standalone Case'!Z68 -> 71.598132 | T4: ='Standalone Case'!AA68 -> 68.309717 | U4: ='Standalone Case'!AB68 -> 65.244941
A5: DCF | C5: Synergy Base Case | D5: =U5 -> 124.5825 | E5: =T5-U5 -> 5.5798016 | F5: =S5-T5 -> 5.9892907 | H5: =SUM(D5:F5)-S5 -> 0 | K5: =K4 -> 0.175 | L5: =L4 -> 0.18 | M5: =M4 -> 0.185 | S5: ='Synergy Base Case - old'!Z68 -> 136.1516 | T5: ='Synergy Base Case - old'!AA68 -> 130.16231 | U5: ='Synergy Base Case - old'!AB68 -> 124.5825
K7: 0.25 | L7: Median | M7: 0.75 | O7: Nola Revenue:
A8: Deal Comps | C8: =O8 -> 2018 (Actual) | D8: =S8 -> 55.029964 | E8: =T8-S8 -> 14.027492 | F8: =U8-T8 -> 28.539165 | H8: =SUM(D8:F8)-U8 -> 0 | K8: ='DEAL COMPS'!Q16 -> 2.030626 | L8: ='DEAL COMPS'!Q15 -> 2.5482456 | M8: ='DEAL COMPS'!Q14 -> 3.6013514 | O8: 2018 (Actual) | P8: =I27 -> 27.1 | S8: =$K$8*$P$8 -> 55.029964 | T8: =L$8*$P$8 -> 69.057456 | U8: =M$8*$P$8 -> 97.596622
K10: 0.25 | L10: Median | M10: 0.75 | O10: Nola Revenue by Case: | R10: Pub Discount
A11: Pub Comps | C11: 2018A Revenue | D11: =S11 -> 110.83298 | E11: =T11-S11 -> 60.684557 | F11: =U11-T11 -> 45.202105 | H11: =SUM(D11:F11)-U11 -> 0 | K11: ='Pub Comps'!AD16 -> 5.4530372 | L11: ='Pub Comps'!AD15 -> 6.3290605 | M11: ='Pub Comps'!AD14 -> 7.9970348 | O11: 2018 (Actual) | P11: =I27 -> 27.1 | R11: 0.25 | S11: =($K$11*$P$11)*(1-$R$11) -> 110.83298 | T11: =L$11*$P$11 -> 171.51754 | U11: =M$11*$P$11 -> 216.71964
A12: Pub Comps | C12: 2019E Standalone Case | D12: =S12 -> 170.09866 | E12: =T12-S12 -> 18.772406 | F12: =U12-T12 -> 60.748128 | H12: =SUM(D12:F12)-U12 -> 0 | K12: ='Pub Comps'!AF16 -> 5.3490145 | L12: ='Pub Comps'!AF15 -> 5.9393418 | M12: ='Pub Comps'!AF14 -> 7.8496602 | O12: 2019E (Standalone) | P12: =J27 -> 31.8 | S12: =K$12*$P$12 -> 170.09866 | T12: =L$12*$P$12 -> 188.87107 | U12: =M$12*$P$12 -> 249.6192
A13: Pub Comps | C13: 2019E Synergy Base Case | D13: =S13 -> 180.79669 | E13: =T13-S13 -> 19.95306 | F13: =U13-T13 -> 64.568764 | H13: =SUM(D13:F13)-U13 -> 0 | K13: =K12 -> 5.3490145 | L13: =L12 -> 5.9393418 | M13: =M12 -> 7.8496602 | O13: 2019E (Synergy Base) | P13: =J28 -> 33.8 | S13: =K$13*$P$13 -> 180.79669 | T13: =L$13*$P$13 -> 200.74975 | U13: =M$13*$P$13 -> 265.31852
A15: Pub Comps (25% discount) | C15: 2018A Revenue | D15: =S15 -> 83.124736 | E15: =T15-S15 -> 45.513418 | F15: =U15-T15 -> 33.901579 | S15: =S11*(1-R$11) -> 83.124736 | T15: =T11*(1-$R$11) -> 128.63815 | U15: =U11*(1-$R$11) -> 162.53973
A16: Pub Comps (25% discount) | C16: 2019E Standalone Case | D16: =S16 -> 127.574 | E16: =T16-S16 -> 14.079304 | F16: =U16-T16 -> 45.561096 | S16: =S12*(1-R$11) -> 127.574 | T16: =T12*(1-$R$11) -> 141.6533 | U16: =U12*(1-$R$11) -> 187.2144
A17: Pub Comps (25% discount) | C17: 2019E Synergy Base Case | D17: =S17 -> 135.59752 | E17: =T17-S17 -> 14.964795 | F17: =U17-T17 -> 48.426573 | S17: =S13*(1-R$11) -> 135.59752 | T17: =T13*(1-$R$11) -> 150.56231 | U17: =U13*(1-$R$11) -> 198.98889
K22: Notes: DCF analysis based on midpoint of 17.5 - 19.5% discount rate and 3.0% terminal value growth rate over ten-year horizon; M&A deal comps and public trading comparable multiple data sources include Pitchbook, Factset, Piper Jaffery and internal management estimates as of March 2019.
I25: Nola Base Revenue
C26: Nola Revenue: | I26: 2018A | J26: 2019E
C27: Standalone Case | I27: ='Standalone Case'!G4 -> 27.1 | J27: ='Standalone Case'!H4 -> 31.8
C28: Synergy Case | I28: =I27 -> 27.1 | J28: ='Synergy Base Case - old'!H4 -> 33.8
M36: ]

Sheet bio - Cash Flow
M2: 2012 | N2: 2013 | O2: 2014 | P2: 2015 | Q2: 2016 | R2: 2017 | S2: 2018 | T2: 2011 | U2: 2010 | V2: 2009 | W2: 2008 | X2: 2007 | Y2: 2006 | Z2: 2005 | AA2: 2004
C3: Cash Flow (Fiscal Year)
C4: Downloaded On: 10-Mar-2019 | D4: Summary Stats
C5: Company: BioTelemetry (NAS: BEAT) | D5: Median | E5: Mean | F5: Min | G5: Max | H5: 25th pctile | I5: 75th pctile | J5: Std. Dev | K5: Coefficient of Variation | M5: FY 2012 | N5: FY 2013 | O5: FY 2014 | P5: FY 2015 | Q5: FY 2016 | R5: FY 2017 | S5: FY 2018 | T5: FY 2011 | U5: FY 2010 | V5: FY 2009 | W5: FY 2008 | X5: FY 2007 | Y5: FY 2006 | Z5: FY 2005 | AA5: FY 2004 | AB5: FY 2003
C6: Amounts in Thousands, USD (except Ratios, Multiples & per share items)
O8: Filed: 22-Feb-2017 | S8: Filed: 22-Feb-2019 | U8: Filed: 31-Dec-2010 | V8: Filed: 31-Dec-2009 | W8: Filed: 31-Dec-2008 | X8: Filed: 31-Dec-2007
O9: View 10-K | S9: View 10-K | U9: View 10-K | V9: View 10-K | W9: View 10-K | X9: View 10-K
A10: 1 | C10: Cash Flow from Operating Activities, Indirect
A11: 1 | C11: Net Cash Flow from Continuing Operating Activities, Indirect
A12: 1 | C12: Cash Generated from Operating Activities
A13: 1 | C13: Income/(Loss) before Non-Cash Adjustment | D13: -7644.732 | E13: -3405.6717 | F13: -61422 | G13: 53437 | H13: -17143 | I13: 7428 | J13: 28628.701 | K13: -8.4061835 | M13: -12202 | N13: -7319 | O13: -9793 | P13: 7428 | Q13: 53437 | R13: -17143 | S13: 41874 | T13: -61422 | U13: -19860 | V13: -20476 | W13: 9205 | X13: -358 | Y13: -7644.732
A14: 1 | C14: Adjustments for Non-Cash Items
A15: 1 | C15: Depreciation, Amortization and Depletion, Non-Cash Adjustment | D15: 12132 | E15: 13905.407 | F15: 2656.291 | G15: 40168 | H15: 9378 | I15: 12550 | J15: 9950.2155 | K15: 0.71556449 | M15: 9378 | N15: 12318 | O15: 12550 | P15: 12488 | Q15: 14269 | R15: 28561 | S15: 40168 | T15: 12132 | U15: 12071 | V15: 10937 | W15: 8693 | X15: 4549 | Y15: 2656.291
A16: 1 | C16: Depreciation and Amortization, Non-Cash Adjustment | D16: 12132 | E16: 13905.407 | F16: 2656.291 | G16: 40168 | H16: 9378 | I16: 12550 | J16: 9950.2155 | K16: 0.71556449 | M16: 9378 | N16: 12318 | O16: 12550 | P16: 12488 | Q16: 14269 | R16: 28561 | S16: 40168 | T16: 12132 | U16: 12071 | V16: 10937 | W16: 8693 | X16: 4549 | Y16: 2656.291
A17: 1 | C17: Depreciation, Non-Cash Adjustment | D17: 10015.5 | E17: 10985.667 | F17: 3750 | G17: 22963 | H17: 8652.75 | I17: 11108.75 | J17: 5048.7968 | K17: 0.45958038 | M17: 8037 | N17: 9978 | O17: 8858 | P17: 8987 | Q17: 10547 | R17: 18337 | S17: 22963 | T17: 10913 | U17: 11696 | V17: 10053 | W17: 7709 | X17: 3750
A18: 1 | C18: Amortization, Non-Cash Adjustment | D18: 1840.5 | E18: 3857.1667 | F18: 375 | G18: 17205 | H18: 959 | I18: 3699.5 | J18: 4982.1419 | K18: 1.2916584 | M18: 1341 | N18: 2340 | O18: 3692 | P18: 3501 | Q18: 3722 | R18: 10224 | S18: 17205 | T18: 1219 | U18: 375 | V18: 884 | W18: 984 | X18: 799
A19: 1 | C19: Total Depreciation and Amortization, Non-Cash Adjustment | D19: 12132 | E19: 13905.407 | F19: 2656.291 | G19: 40168 | H19: 9378 | I19: 12550 | J19: 9950.2155 | K19: 0.71556449 | M19: 9378 | N19: 12318 | O19: 12550 | P19: 12488 | Q19: 14269 | R19: 28561 | S19: 40168 | T19: 12132 | U19: 12071 | V19: 10937 | W19: 8693 | X19: 4549 | Y19: 2656.291
A20: 1 | C20: Total Depreciation, Amortization and Depletion, Non-Cash Adjustment | D20: 12132 | E20: 13905.407 | F20: 2656.291 | G20: 40168 | H20: 9378 | I20: 12550 | J20: 9950.2155 | K20: 0.71556449 | M20: 9378 | N20: 12318 | O20: 12550 | P20: 12488 | Q20: 14269 | R20: 28561 | S20: 40168 | T20: 12132 | U20: 12071 | V20: 10937 | W20: 8693 | X20: 4549 | Y20: 2656.291
A21: 1 | C21: Amortization of Securities, Non-Cash Adjustment | D21: 344.5 | E21: 377.25 | F21: 259 | G21: 561 | H21: 265.75 | I21: 456 | J21: 143.29079 | K21: 0.37982979 | M21: 268 | P21: 259 | T21: 561 | U21: 421
A22: 1 | C22: Stock-Based Compensation, Non-Cash Adjustment | D22: 4021.5 | E22: 5685.75 | F22: 779 | G22: 16625 | H22: 3658.25 | I22: 6796.5 | J22: 4100.7224 | K22: 0.72122806 | M22: 3747 | N22: 3303 | O22: 4037 | P22: 4952 | Q22: 6502 | R22: 7680 | S22: 9261 | T22: 4006 | U22: 3945 | V22: 16625 | W22: 3392 | X22: 779
A23: 1 | C23: Taxes, Non-Cash Adjustment | D23: 0 | E23: -5050.2857 | F23: -38141 | G23: 6050 | H23: -1663.5 | I23: 33 | J23: 14827.526 | K23: -2.9359777 | M23: -1033 | N23: 53 | Q23: -38141 | R23: 6050 | S23: -2294 | T23: 13 | U23: 0
A24: 1 | C24: Interest and Finance (Income)/Expenses, Non-Cash Adjustment | D24: 678 | E24: 712.66667 | F24: 217 | G24: 1243 | H24: 447.5 | I24: 960.5 | J24: 513.87774 | K24: 0.72106325 | Q24: 217 | R24: 678 | S24: 1243
A25: 1 | C25: Other Provisions, Non-Cash Adjustment | D25: 11912 | E25: 11680.8 | F25: 7787 | G25: 18578 | H25: 8047 | I25: 12080 | J25: 4363.2088 | K25: 0.37353681 | M25: 11912 | N25: 7787 | P25: 8047 | T25: 12080 | U25: 18578
A26: 1 | C26: Irregular (Income)/Loss, Non-Cash Adjustment | D26: 615 | E26: 10724.4 | F26: 0 | G26: 45999 | H26: 254.25 | I26: 19149.25 | J26: 15983.176 | K26: 1.4903562 | M26: 0 | O26: 203 | Q26: 9931 | R26: 27201 | S26: 22222 | T26: 45999 | U26: 807 | V26: 408 | W26: 423 | X26: 50
A27: 1 | C27: (Gain)/Loss on Disposals, Non-Cash Adjustment | D27: 415.5 | E27: 422 | F27: 50 | G27: 807 | H27: 318.5 | I27: 519 | J27: 309.19573 | K27: 0.73269131 | U27: 807 | V27: 408 | W27: 423 | X27: 50
A28: 1 | C28: (Gain)/Loss on Disposal/Sale of Fixed Assets, Non-Cash Adjustment | D28: 415.5 | E28: 422 | F28: 50 | G28: 807 | H28: 318.5 | I28: 519 | J28: 309.19573 | K28: 0.73269131 | U28: 807 | V28: 408 | W28: 423 | X28: 50
A29: 1 | C29: Total (Gain)/Loss on Disposals, Non-Cash Adjustment | D29: 415.5 | E29: 422 | F29: 50 | G29: 807 | H29: 318.5 | I29: 519 | J29: 309.19573 | K29: 0.73269131 | U29: 807 | V29: 408 | W29: 423 | X29: 50
A30: 1 | C30: Impairment/Write Off/Write Down of Capital Assets Loss/Reversal, Non-Cash Adjustment | D30: 22999.5 | E30: 22999.5 | F30: 0 | G30: 45999 | H30: 11499.75 | I30: 34499.25 | J30: 32526.205 | K30: 1.4142136 | T30: 45999 | U30: 0
A31: 1 | C31: Impairment/Write Off/Write Down of Other Assets, Non-Cash Adjustment | D31: 22222 | E31: 19603.667 | F31: 9931 | G31: 26658 | H31: 16076.5 | I31: 24440 | J31: 8665.442 | K31: 0.44203169 | Q31: 9931 | R31: 26658 | S31: 22222
A32: 1 | C32: (Gain)/Loss on Extinguishment of Debt, Non-Cash Adjustment | D32: 0 | E32: 149.2 | F32: 0 | G32: 543 | H32: 0 | I32: 203 | J32: 237.04156 | K32: 1.5887504 | M32: 0 | O32: 203 | Q32: 0 | R32: 543 | S32: 0
A33: 1 | C33: Total Irregular (Income)/Loss, Non-Cash Adjustment | D33: 615 | E33: 10724.4 | F33: 0 | G33: 45999 | H33: 254.25 | I33: 19149.25 | J33: 15983.176 | K33: 1.4903562 | M33: 0 | O33: 203 | Q33: 9931 | R33: 27201 | S33: 22222 | T33: 45999 | U33: 807 | V33: 408 | W33: 423 | X33: 50
A34: 1 | C34: Other Operating (Gain)/Loss, Non-Cash Adjustment | D34: 14.471 | E34: 14.471 | F34: 14.471 | G34: 14.471 | H34: 14.471 | I34: 14.471 | Y34: 14.471
A35: 1 | C35: Other Non-Cash Items | D35: 231 | E35: 4030.086 | F35: -3977 | G35: 19982 | H35: -303 | I35: 9204 | J35: 6988.2916 | K35: 1.7340304 | M35: -198 | N35: -215 | O35: 9702 | P35: 231 | Q35: 457 | R35: -3977 | S35: -446 | T35: -303 | U35: -340 | V35: 19982 | W35: 13339 | X35: 9204 | Y35: 4955.118
A36: 1 | C36: Total Adjustments for Non-Cash Items | D36: 25977 | E36: 33488.298 | F36: -6765 | G36: 74488 | H36: 23246 | I36: 47952 | J36: 24684.766 | K36: 0.73711616 | M36: 24074 | N36: 23246 | O36: 26492 | P36: 25977 | Q36: -6765 | R36: 66193 | S36: 70154 | T36: 74488 | U36: 35482 | V36: 47952 | W36: 25847 | X36: 14582 | Y36: 7625.88
A37: 1 | C37: Changes in Operating Capital | D37: -8036 | E37: -14097.221 | F37: -39282 | G37: -2893.877 | H37: -20104 | I37: -5389 | J37: 10959.463 | K37: -0.77742008 | M37: -6129 | N37: -4668 | O37: -5389 | P37: -19055 | Q37: -7821 | R37: -25268 | S37: -39282 | T37: -8036 | U37: -5260 | V37: -20104 | W37: -24744 | X37: -14614 | Y37: -2893.877
A38: 1 | C38: Change in Inventories | D38: 0 | E38: -298.33333 | F38: -1991 | G38: 665 | H38: -753 | I38: 299 | J38: 828.867 | K38: -2.7783251 | M38: -885 | N38: 340 | O38: 299 | P38: 188 | Q38: -753 | R38: 665 | S38: -1991 | T38: -548 | U38: 0
A39: 1 | C39: Change in Trade and Other Receivables | D39: -8707 | E39: -13074.579 | F39: -35742 | G39: -3062 | H39: -15455 | I39: -5554.522 | J39: 10312.838 | K39: -0.7887702 | M39: -3635 | N39: -4597 | O39: -12795 | P39: -7677 | Q39: -8707 | R39: -15455 | S39: -35742 | T39: -6653 | U39: -3062 | V39: -21436 | W39: -29687 | X39: -14969 | Y39: -5554.522
A40: 1 | C40: Change in Trade/Accounts Receivable | D40: -7165 | E40: -11489.625 | F40: -29733 | G40: -3062 | H40: -16702 | I40: -4356.5 | J40: 9732.986 | K40: -0.84711085 | M40: -3635 | N40: -4597 | P40: -7677 | T40: -6653 | U40: -3062 | V40: -21436 | W40: -29733 | X40: -15124
A41: 1 | C41: Change in Other Receivables | D41: 100.5 | E41: 100.5 | F41: 46 | G41: 155 | H41: 73.25 | I41: 127.75 | J41: 77.074639 | K41: 0.76691183 | W41: 46 | X41: 155
A42: 1 | C42: Total Change in Trade and Other Receivables | D42: -8707 | E42: -13074.579 | F42: -35742 | G42: -3062 | H42: -15455 | I42: -5554.522 | J42: 10312.838 | K42: -0.7887702 | M42: -3635 | N42: -4597 | O42: -12795 | P42: -7677 | Q42: -8707 | R42: -15455 | S42: -35742 | T42: -6653 | U42: -3062 | V42: -21436 | W42: -29687 | X42: -14969 | Y42: -5554.522
A43: 1 | C43: Change in Prepayments and Deposits | D43: -3 | E43: 249.49215 | F43: -1759 | G43: 3661 | H43: -694 | I43: 223 | J43: 1613.0812 | K43: 6.4654586 | M43: 691 | N43: -637 | O43: -128 | P43: -3 | Q43: -1050 | R43: -694 | S43: 3517 | T43: 3661 | U43: 0 | V43: -1759 | W43: -772 | X43: 223 | Y43: 194.398
A44: 1 | C44: Change in Other Current Assets | D44: -196.357 | E44: -196.357 | F44: -196.357 | G44: -196.357 | H44: -196.357 | I44: -196.357 | Y44: -196.357
A45: 1 | C45: Change in Payables and Accrued Expenses | D45: 226 | E45: -1075.0375 | F45: -9784 | G45: 3679 | H45: -4496 | I45: 2302 | J45: 4022.6748 | K45: -3.7418927 | M45: -2300 | N45: 226 | O45: 835 | P45: -5163 | Q45: 2689 | R45: -9784 | S45: -5066 | T45: -4496 | U45: -155 | V45: 2954 | W45: 3679 | X45: 2302 | Y45: 303.513
A46: 1 | C46: Change in Trade and Other Payables | D46: 299.5 | E46: -233.33333 | F46: -8320 | G46: 3760 | H46: -1644.75 | I46: 2563 | J46: 3619.7984 | K46: -15.513422 | M46: 552 | N46: 2369 | O46: 47 | P46: -4699 | Q46: 3145 | R46: -8320 | S46: 3760 | T46: -3033 | U46: -1182 | V46: 3322 | W46: -134 | X46: 1373
A47: 1 | C47: Change in Trade/Accounts Payable | D47: 299.5 | E47: -233.33333 | F47: -8320 | G47: 3760 | H47: -1644.75 | I47: 2563 | J47: 3619.7984 | K47: -15.513422 | M47: 552 | N47: 2369 | O47: 47 | P47: -4699 | Q47: 3145 | R47: -8320 | S47: 3760 | T47: -3033 | U47: -1182 | V47: 3322 | W47: -134 | X47: 1373
A48: 1 | C48: Total Change in Trade and Other Payables | D48: 299.5 | E48: -233.33333 | F48: -8320 | G48: 3760 | H48: -1644.75 | I48: 2563 | J48: 3619.7984 | K48: -15.513422 | M48: 552 | N48: 2369 | O48: 47 | P48: -4699 | Q48: 3145 | R48: -8320 | S48: 3760 | T48: -3033 | U48: -1182 | V48: 3322 | W48: -134 | X48: 1373
A49: 1 | C49: Change in Accrued Expenses | D49: -460 | E49: -956.58333 | F49: -8826 | G49: 3813 | H49: -1633.75 | I49: 823.25 | J49: 3038.6003 | K49: -3.176514 | M49: -2852 | N49: -2143 | O49: 788 | P49: -464 | Q49: -456 | R49: -1464 | S49: -8826 | T49: -1463 | U49: 1027 | V49: -368 | W49: 3813 | X49: 929
A50: 1 | C50: Total Change in Payables and Accrued Expenses | D50: 226 | E50: -1075.0375 | F50: -9784 | G50: 3679 | H50: -4496 | I50: 2302 | J50: 4022.6748 | K50: -3.7418927 | M50: -2300 | N50: 226 | O50: 835 | P50: -5163 | Q50: 2689 | R50: -9784 | S50: -5066 | T50: -4496 | U50: -155 | V50: 2954 | W50: 3679 | X50: 2302 | Y50: 303.513
A51: 1 | C51: Change in Other Current Liabilities | D51: 2427.991 | E51: 2427.991 | F51: 2427.991 | G51: 2427.991 | H51: 2427.991 | I51: 2427.991 | Y51: 2427.991
A52: 1 | C52: Change in Other Operating Capital | D52: -68.9 | E52: -301.27143 | F52: -6400 | G52: 6400 | H52: -2106.5 | I52: 1086.5 | J52: 3965.1862 | K52: -13.161508 | O52: 6400 | P52: -6400 | U52: -2043 | V52: 137 | W52: 2036 | X52: -2170 | Y52: -68.9
A53: 1 | C53: Total Changes in Operating Capital | D53: -8036 | E53: -14097.221 | F53: -39282 | G53: -2893.877 | H53: -20104 | I53: -5389 | J53: 10959.463 | K53: -0.77742008 | M53: -6129 | N53: -4668 | O53: -5389 | P53: -19055 | Q53: -7821 | R53: -25268 | S53: -39282 | T53: -8036 | U53: -5260 | V53: -20104 | W53: -24744 | X53: -14614 | Y53: -2893.877
A54: 1 | C54: Total Cash Generated from Operating Activities | D54: 10362 | E54: 15985.405 | F54: -2912.729 | G54: 72746 | H54: 5743 | I54: 14350 | J54: 20084.255 | K54: 1.256412 | M54: 5743 | N54: 11259 | O54: 11310 | P54: 14350 | Q54: 38851 | R54: 23782 | S54: 72746 | T54: 5030 | U54: 10362 | V54: 7372 | W54: 10308 | X54: -390 | Y54: -2912.729
A55: 1 | C55: Taxes Refund/(Paid), Indirect | D55: -2499 | E55: -2499 | F55: -2499 | G55: -2499 | H55: -2499 | I55: -2499 | O55: -2499
A56: 1 | C56: Other Operating Cash Flow | D56: 342.5 | E56: 342.5 | F56: 153 | G56: 532 | H56: 247.75 | I56: 437.25 | J56: 267.99347 | K56: 0.78246269 | V56: 532 | X56: 153
A57: 1 | C57: Total Net Cash Flow from Continuing Operating Activities, Indirect | D57: 10308 | E57: 15845.867 | F57: -2912.729 | G57: 72746 | H57: 5743 | I57: 14350 | J57: 20116.366 | K57: 1.2695024 | M57: 5743 | N57: 11259 | O57: 8811 | P57: 14350 | Q57: 38851 | R57: 23782 | S57: 72746 | T57: 5030 | U57: 10362 | V57: 7904 | W57: 10308 | X57: -237 | Y57: -2912.729
A58: 1 | C58: Total Cash Flow from Operating Activities, Indirect | D58: 10308 | E58: 15845.867 | F58: -2912.729 | G58: 72746 | H58: 5743 | I58: 14350 | J58: 20116.366 | K58: 1.2695024 | M58: 5743 | N58: 11259 | O58: 8811 | P58: 14350 | Q58: 38851 | R58: 23782 | S58: 72746 | T58: 5030 | U58: 10362 | V58: 7904 | W58: 10308 | X58: -237 | Y58: -2912.729
A59: 1 | C59: Cash Flow from Investing Activities
A60: 1 | C60: Cash Flow from Continuing Investing Activities
A61: 1 | C61: (Purchase)/Sale and Disposal of Property, Plant and Equipment, Net | D61: -11804 | E61: -11127.128 | F61: -24637 | G61: -913.666 | H61: -13600 | I61: -5962 | J61: 6490.9409 | K61: -0.58334377 | M61: -5962 | N61: -8169 | O61: -12781 | P61: -13600 | Q61: -10899 | R61: -13697 | S61: -24637 | T61: -3954 | U61: -5247 | V61: -19938 | W61: -11804 | X61: -13051 | Y61: -913.666
A62: 1 | C62: Purchase of Property, Plant and Equipment | D62: -11804 | E62: -11127.128 | F62: -24637 | G62: -913.666 | H62: -13600 | I62: -5962 | J62: 6490.9409 | K62: -0.58334377 | M62: -5962 | N62: -8169 | O62: -12781 | P62: -13600 | Q62: -10899 | R62: -13697 | S62: -24637 | T62: -3954 | U62: -5247 | V62: -19938 | W62: -11804 | X62: -13051 | Y62: -913.666
A63: 1 | C63: Total (Purchase)/Sale and Disposal of Property, Plant and Equipment, Net | D63: -11804 | E63: -11127.128 | F63: -24637 | G63: -913.666 | H63: -13600 | I63: -5962 | J63: 6490.9409 | K63: -0.58334377 | M63: -5962 | N63: -8169 | O63: -12781 | P63: -13600 | Q63: -10899 | R63: -13697 | S63: -24637 | T63: -3954 | U63: -5247 | V63: -19938 | W63: -11804 | X63: -13051 | Y63: -913.666
A64: 1 | C64: (Purchase)/Sale of Business, Net | D64: -11976 | E64: -29304.9 | F64: -161479 | G64: 0 | H64: -27358.75 | I64: -4021.5 | J64: 48699.389 | K64: -1.6618173 | M64: -28155 | O64: -14100 | Q64: -24970 | R64: -161479 | S64: -3750 | T64: 0 | U64: -9852 | V64: 0 | W64: -4836 | X64: -45907
A65: 1 | C65: Purchase/Acquisition of Business | D65: -11976 | E65: -29304.9 | F65: -161479 | G65: 0 | H65: -27358.75 | I65: -4021.5 | J65: 48699.389 | K65: -1.6618173 | M65: -28155 | O65: -14100 | Q65: -24970 | R65: -161479 | S65: -3750 | T65: 0 | U65: -9852 | V65: 0 | W65: -4836 | X65: -45907
A66: 1 | C66: Total (Purchase)/Sale of Business, Net | D66: -11976 | E66: -29304.9 | F66: -161479 | G66: 0 | H66: -27358.75 | I66: -4021.5 | J66: 48699.389 | K66: -1.6618173 | M66: -28155 | O66: -14100 | Q66: -24970 | R66: -161479 | S66: -3750 | T66: 0 | U66: -9852 | V66: 0 | W66: -4836 | X66: -45907
A67: 1 | C67: (Purchase)/Sale of Equity Investments | D67: -464 | E67: -488.66667 | F67: -690 | G67: -312 | H67: -577 | I67: -388 | J67: 190.2034 | K67: -0.38922933 | Q67: -312 | R67: -690 | S67: -464
A68: 1 | C68: Purchase of Joint Venture/Associate | D68: -464 | E68: -488.66667 | F68: -690 | G68: -312 | H68: -577 | I68: -388 | J68: 190.2034 | K68: -0.38922933 | Q68: -312 | R68: -690 | S68: -464
A69: 1 | C69: Total (Purchase)/Sale of Equity Investments | D69: -464 | E69: -488.66667 | F69: -690 | G69: -312 | H69: -577 | I69: -388 | J69: 190.2034 | K69: -0.38922933 | Q69: -312 | R69: -690 | S69: -464
A70: 1 | C70: (Purchase)/Sale of Investments, Net | D70: 0 | E70: -367.42857 | F70: -27192 | G70: 27701 | H70: -1540.5 | I70: 0 | J70: 15867.404 | K70: -43.185002 | M70: 27701 | O70: 0 | Q70: 0 | R70: -1322 | S70: 0 | T70: -1759 | U70: -27192
A71: 1 | C71: Purchase of Investments | D71: -1322 | E71: -14265.143 | F71: -49657 | G71: 0 | H71: -24438.5 | I71: 0 | J71: 20616.582 | K71: -1.4452419 | M71: -11935 | O71: 0 | Q71: 0 | R71: -1322 | S71: 0 | T71: -49657 | U71: -36942
A72: 1 | C72: Sale of Investments | D72: 39636 | E72: 32428 | F72: 9750 | G72: 47898 | H72: 24693 | I72: 43767 | J72: 20069.477 | K72: 0.61889347 | M72: 39636 | T72: 47898 | U72: 9750
A73: 1 | C73: Total (Purchase)/Sale of Investments, Net | D73: 0 | E73: -367.42857 | F73: -27192 | G73: 27701 | H73: -1540.5 | I73: 0 | J73: 15867.404 | K73: -43.185002 | M73: 27701 | O73: 0 | Q73: 0 | R73: -1322 | S73: 0 | T73: -1759 | U73: -27192
A74: 1 | C74: Total Cash Flow from Continuing Investing Activities | D74: -19938 | E74: -33979.974 | F74: -177188 | G74: -913.666 | H74: -36181 | I74: -8169 | J74: 46110.95 | K74: -1.3570037 | M74: -6416 | N74: -8169 | O74: -26881 | P74: -13600 | Q74: -36181 | R74: -177188 | S74: -28851 | T74: -5713 | U74: -42291 | V74: -19938 | W74: -16640 | X74: -58958 | Y74: -913.666
A75: 1 | C75: Total Cash Flow from Investing Activities | D75: -19938 | E75: -33979.974 | F75: -177188 | G75: -913.666 | H75: -36181 | I75: -8169 | J75: 46110.95 | K75: -1.3570037 | M75: -6416 | N75: -8169 | O75: -26881 | P75: -13600 | Q75: -36181 | R75: -177188 | S75: -28851 | T75: -5713 | U75: -42291 | V75: -19938 | W75: -16640 | X75: -58958 | Y75: -913.666
A76: 1 | C76: Cash Flow from Financing Activities
A77: 1 | C77: Cash Flow from Continuing Financing Activities
A78: 1 | C78: Issuance of/(Payments for) Common Stock, Net | D78: 68 | E78: 9351.356 | F78: 10 | G78: 46475 | H78: 36 | I78: 167.78 | J78: 20752.834 | K78: 2.2192326 | U78: 10 | V78: 36 | W78: 46475 | X78: 68 | Y78: 167.78
A79: 1 | C79: Proceeds from Issuance of Common Stock | D79: 68 | E79: 9351.392 | F79: 10 | G79: 46475 | H79: 36 | I79: 167.96 | J79: 20752.814 | K79: 2.2192219 | U79: 10 | V79: 36 | W79: 46475 | X79: 68 | Y79: 167.96
A80: 1 | C80: Payments for Common Stock | D80: -1 | E80: -1 | F80: -1 | G80: -1 | H80: -1 | I80: -1 | Y80: -1
A81: 1 | C81: Total Issuance of/(Payments for) Common Stock, Net | D81: 68 | E81: 9351.356 | F81: 10 | G81: 46475 | H81: 36 | I81: 167.78 | J81: 20752.834 | K81: 2.2192326 | U81: 10 | V81: 36 | W81: 46475 | X81: 68 | Y81: 167.78
A82: 1 | C82: Issuance of/(Payments for) Preferred Stock, Net | D82: 0 | E82: 34039 | F82: 0 | G82: 102117 | H82: 0 | I82: 51058.5 | J82: 58957.277 | K82: 1.7320508 | V82: 0 | W82: 0 | X82: 102117
A83: 1 | C83: Proceeds from Issuance of Preferred Stock | D83: 0 | E83: 34039 | F83: 0 | G83: 102117 | H83: 0 | I83: 51058.5 | J83: 58957.277 | K83: 1.7320508 | V83: 0 | W83: 0 | X83: 102117
A84: 1 | C84: Total Issuance of/(Payments for) Preferred Stock, Net | D84: 0 | E84: 34039 | F84: 0 | G84: 102117 | H84: 0 | I84: 51058.5 | J84: 58957.277 | K84: 1.7320508 | V84: 0 | W84: 0 | X84: 102117
A85: 1 | C85: Issuance of/(Payments for) Debt, Net | D85: -36 | E85: 16299.833 | F85: -29178 | G85: 176160 | H85: -1772 | I85: 3976.5005 | J85: 57253.492 | K85: 3.5125201 | M85: 0 | O85: 15404 | P85: -938 | Q85: 1562 | R85: 176160 | S85: -2050 | V85: -72 | W85: -2671 | X85: -29178 | Y85: 4781.334
A86: 1 | C86: Issuance of/(Repayments for) Long Term Debt, Net | D86: -72 | E86: 17579.667 | F86: -29178 | G86: 176160 | H86: -2050 | I86: 1562 | J86: 60574.586 | K86: 3.4457187 | M86: 0 | O86: 15404 | P86: -938 | Q86: 1562 | R86: 176160 | S86: -2050 | V86: -72 | W86: -2671 | X86: -29178
A87: 1 | C87: Proceeds from Issuance of Long Term Debt | D87: 436.5 | E87: 32776.375 | F87: 0 | G87: 205000 | H87: 0 | I87: 21334.5 | J87: 71105.285 | K87: 2.1694066 | M87: 0 | O87: 41838 | Q87: 14500 | R87: 205000 | S87: 0 | V87: 0 | W87: 500 | X87: 373
A88: 1 | C88: Repayments for Long Term Debt | D88: -3171 | E88: -11554.889 | F88: -29551 | G88: 0 | H88: -26434 | I88: -938 | J88: 13156.078 | K88: -1.1385724 | M88: 0 | O88: -26434 | P88: -938 | Q88: -12938 | R88: -28840 | S88: -2050 | V88: -72 | W88: -3171 | X88: -29551
A89: 1 | C89: Total Issuance of/(Repayments for) Long Term Debt, Net | D89: -72 | E89: 17579.667 | F89: -29178 | G89: 176160 | H89: -2050 | I89: 1562 | J89: 60574.586 | K89: 3.4457187 | M89: 0 | O89: 15404 | P89: -938 | Q89: 1562 | R89: 176160 | S89: -2050 | V89: -72 | W89: -2671 | X89: -29178
A90: 1 | C90: Total Issuance of/(Repayments for) Debt, Net | D90: -36 | E90: 16299.833 | F90: -29178 | G90: 176160 | H90: -1772 | I90: 3976.5005 | J90: 57253.492 | K90: 3.5125201 | M90: 0 | O90: 15404 | P90: -938 | Q90: 1562 | R90: 176160 | S90: -2050 | V90: -72 | W90: -2671 | X90: -29178 | Y90: 4781.334
A91: 1 | C91: Issuance of/(Repayments for) Lease Financing | D91: -400.5 | E91: -1002.125 | F91: -3740 | G91: 0 | H91: -1112.5 | I91: -63 | J91: 1452.6169 | K91: -1.4495366 | M91: 0 | N91: -84 | O91: -529 | P91: -480 | Q91: -321 | R91: -2863 | S91: -3740 | T91: 0
A92: 1 | C92: Repayments for Lease Financing | D92: -400.5 | E92: -1002.125 | F92: -3740 | G92: 0 | H92: -1112.5 | I92: -63 | J92: 1452.6169 | K92: -1.4495366 | M92: 0 | N92: -84 | O92: -529 | P92: -480 | Q92: -321 | R92: -2863 | S92: -3740 | T92: 0
A93: 1 | C93: Total Issuance of/(Repayments for) Lease Financing | D93: -400.5 | E93: -1002.125 | F93: -3740 | G93: 0 | H93: -1112.5 | I93: -63 | J93: 1452.6169 | K93: -1.4495366 | M93: 0 | N93: -84 | O93: -529 | P93: -480 | Q93: -321 | R93: -2863 | S93: -3740 | T93: 0
A94: 1 | C94: Net Movement in Non-Controlling/Minority Interest | D94: -2885 | E94: -2550 | F94: -4765 | G94: 0 | H94: -3825 | I94: -1442.5 | J94: 2400.099 | K94: -0.94121528 | Q94: 0 | R94: -4765 | S94: -2885
A95: 1 | C95: Issue and Financing Costs | D95: 0 | E95: -2071 | F95: -6213 | G95: 0 | H95: -3106.5 | I95: 0 | J95: 3587.0772 | K95: -1.7320508 | Q95: 0 | R95: -6213 | S95: 0
A96: 1 | C96: Debt Issuance Costs | D96: 0 | E96: -2071 | F96: -6213 | G96: 0 | H96: -3106.5 | I96: 0 | J96: 3587.0772 | K96: -1.7320508 | Q96: 0 | R96: -6213 | S96: 0
A97: 1 | C97: Total Issue and Financing Costs | D97: 0 | E97: -2071 | F97: -6213 | G97: 0 | H97: -3106.5 | I97: 0 | J97: 3587.0772 | K97: -1.7320508 | Q97: 0 | R97: -6213 | S97: 0
A98: 1 | C98: Proceeds from Issuance/Exercising of Stock Options/Warrants | D98: 1472 | E98: 2855.3636 | F98: 0 | G98: 12186 | H98: 865.5 | I98: 2795 | J98: 3519.1583 | K98: 1.2324729 | M98: 440 | O98: 1400 | P98: 1222 | Q98: 2519 | R98: 6071 | S98: 12186 | T98: 509 | U98: 1472 | V98: 3051 | W98: 2539 | X98: 0
A99: 1 | C99: Other Financing Cash Flow | D99: -349 | E99: -865.01389 | F99: -2910 | G99: 847 | H99: -1933 | I99: 69 | J99: 1340.5021 | K99: -1.5496885 | N99: 847 | O99: -349 | P99: -1575 | Q99: -2333 | R99: -1933 | S99: -2910 | W99: 69 | X99: 370 | Y99: 28.875
A100: 1 | C100: Total Cash Flow from Continuing Financing Activities | D100: 1482 | E100: 24124.307 | F100: -1771 | G100: 166457 | H100: 601 | I100: 15926 | J100: 48284.483 | K100: 2.0014869 | M100: 440 | N100: 763 | O100: 15926 | P100: -1771 | Q100: 1427 | R100: 166457 | S100: 601 | T100: 509 | U100: 1482 | V100: 3015 | W100: 46412 | X100: 73377 | Y100: 4977.989
A101: 1 | C101: Total Cash Flow from Financing Activities | D101: 1482 | E101: 24124.307 | F101: -1771 | G101: 166457 | H101: 601 | I101: 15926 | J101: 48284.483 | K101: 2.0014869 | M101: 440 | N101: 763 | O101: 15926 | P101: -1771 | Q101: 1427 | R101: 166457 | S101: 601 | T101: 509 | U101: 1482 | V101: 3015 | W101: 46412 | X101: 73377 | Y101: 4977.989
A102: 1 | C102: Cash and Cash Equivalents, End of Period
...

Sheet NOLs

Sheet BIO - Income Statement (2)
C3: Income Statement (Fiscal Year)
C4: Downloaded On: 10-Mar-2019 | D4: Summary Stats
C5: Company: BioTelemetry (NAS: BEAT) | D5: Median | E5: Mean | F5: Min | G5: Max | H5: 25th pctile | I5: 75th pctile | J5: Std. Dev | K5: Coefficient of Variation | M5: =HYPERLINK("https://my.pitchbook.com?c=41533-84", "FY 2003") -> FY 2003 | N5: =HYPERLINK("https://my.pitchbook.com?c=41533-84", "FY 2004") -> FY 2004 | O5: =HYPERLINK("https://my.pitchbook.com?c=41533-84", "FY 2005") -> FY 2005 | P5: =HYPERLINK("https://my.pitchbook.com?c=41533-84", "FY 2006") -> FY 2006 | Q5: =HYPERLINK("https://my.pitchbook.com?c=41533-84", "FY 2007") -> FY 2007 | R5: =HYPERLINK("https://my.pitchbook.com?c=41533-84", "FY 2008") -> FY 2008 | S5: =HYPERLINK("https://my.pitchbook.com?c=41533-84", "FY 2009") -> FY 2009 | T5: =HYPERLINK("https://my.pitchbook.com?c=41533-84", "FY 2010") -> FY 2010 | U5: =HYPERLINK("https://my.pitchbook.com?c=41533-84", "FY 2011") -> FY 2011 | V5: =HYPERLINK("https://my.pitchbook.com?c=41533-84", "FY 2012") -> FY 2012 | W5: =HYPERLINK("https://my.pitchbook.com?c=41533-84", "FY 2013") -> FY 2013 | X5: =HYPERLINK("https://my.pitchbook.com?c=41533-84", "FY 2014") -> FY 2014 | Y5: =HYPERLINK("https://my.pitchbook.com?c=41533-84", "FY 2015") -> FY 2015 | Z5: =HYPERLINK("https://my.pitchbook.com?c=41533-84", "FY 2016") -> FY 2016 | AA5: =HYPERLINK("https://my.pitchbook.com?c=41533-84", "FY 2017") -> FY 2017 | AB5: =HYPERLINK("https://my.pitchbook.com?c=41533-84", "FY 2018") -> FY 2018
C6: Amounts in Thousands, USD (except Ratios, Multiples & per share items)
M8: Filed: 31-Dec-2003 | N8: Filed: 31-Dec-2004 | O8: Filed: 31-Dec-2005 | P8: Filed: 31-Dec-2006 | Q8: Filed: 31-Dec-2007 | R8: Filed: 31-Dec-2008 | S8: Filed: 31-Dec-2009 | T8: Filed: 31-Dec-2010 | U8: Filed: 31-Dec-2011 | V8: Filed: 31-Dec-2012 | W8: Filed: 22-Feb-2016 | X8: Filed: 22-Feb-2017 | Y8: Filed: 27-Feb-2018 | Z8: Filed: 22-Feb-2019 | AA8: Filed: 22-Feb-2019 | AB8: Filed: 22-Feb-2019
Q9: =HYPERLINK("https://my.pitchbook.com/profile/41533-84/company/financials?reportId=19728931553&financialGroup=INCOME_STATEMENT&period=ANN&exchangeId=NAS&exchangeSymbol=BEAT", "View 10-K") -> View 10-K | R9: =HYPERLINK("https://my.pitchbook.com/profile/41533-84/company/financials?reportId=19728931617&financialGroup=INCOME_STATEMENT&period=ANN&exchangeId=NAS&exchangeSymbol=BEAT", "View 10-K") -> View 10-K | S9: =HYPERLINK("https://my.pitchbook.com/profile/41533-84/company/financials?reportId=19728931681&financialGroup=INCOME_STATEMENT&period=ANN&exchangeId=NAS&exchangeSymbol=BEAT", "View 10-K") -> View 10-K | T9: =HYPERLINK("https://my.pitchbook.com/profile/41533-84/company/financials?reportId=19728931745&financialGroup=INCOME_STATEMENT&period=ANN&exchangeId=NAS&exchangeSymbol=BEAT", "View 10-K") -> View 10-K | U9: =HYPERLINK("https://my.pitchbook.com/profile/41533-84/company/financials?reportId=19728931809&financialGroup=INCOME_STATEMENT&period=ANN&exchangeId=NAS&exchangeSymbol=BEAT", "View 10-K") -> View 10-K | V9: =HYPERLINK("https://my.pitchbook.com/profile/41533-84/company/financials?reportId=19728931873&financialGroup=INCOME_STATEMENT&period=ANN&exchangeId=NAS&exchangeSymbol=BEAT", "View 10-K") -> View 10-K | W9: =HYPERLINK("https://my.pitchbook.com/profile/41533-84/company/financials?reportId=19728931937&financialGroup=INCOME_STATEMENT&period=ANN&exchangeId=NAS&exchangeSymbol=BEAT", "View 10-K") -> View 10-K | X9: =HYPERLINK("https://my.pitchbook.com/profile/41533-84/company/financials?reportId=19728932001&financialGroup=INCOME_STATEMENT&period=ANN&exchangeId=NAS&exchangeSymbol=BEAT", "View 10-K") -> View 10-K | Y9: =HYPERLINK("https://my.pitchbook.com/profile/41533-84/company/financials?reportId=19728932065&financialGroup=INCOME_STATEMENT&period=ANN&exchangeId=NAS&exchangeSymbol=BEAT", "View 10-K") -> View 10-K | Z9: =HYPERLINK("https://my.pitchbook.com/profile/41533-84/company/financials?reportId=19728932129&financialGroup=INCOME_STATEMENT&period=ANN&exchangeId=NAS&exchangeSymbol=BEAT", "View 10-K") -> View 10-K | AA9: =HYPERLINK("https://my.pitchbook.com/profile/41533-84/company/financials?reportId=19728932193&financialGroup=INCOME_STATEMENT&period=ANN&exchangeId=NAS&exchangeSymbol=BEAT", "View 10-K") -> View 10-K | AB9: =HYPERLINK("https://my.pitchbook.com/profile/41533-84/company/financials?reportId=19728932257&financialGroup=INCOME_STATEMENT&period=ANN&exchangeId=NAS&exchangeSymbol=BEAT", "View 10-K") -> View 10-K
A10: 1 | C10: =IF(SUBTOTAL(109,A11)=A11,"Gross Profit","Gross Profit") -> Gross Profit | D10: =IF(COUNT(M10:AB10)>0,MEDIAN(M10:AB10),"") -> 2010.5 | E10: =IF(COUNT(M10:AB10)>0,AVERAGE(M10:AB10),"") -> 2010.5 | F10: =IF(COUNT(M10:AB10)>0,MIN(M10:AB10),"") -> 2003 | G10: =IF(COUNT(M10:AB10)>0,MAX(M10:AB10),"") -> 2018 | H10: =IF(COUNT(M10:AB10)>0,QUARTILE(M10:AB10,1),"") -> 2006.75 | I10: =IF(COUNT(M10:AB10)>0,QUARTILE(M10:AB10,3),"") -> 2014.25 | J10: =IF(COUNT(M10:AB10)>1,STDEV(M10:AB10),"") -> 4.7609523 | K10: =IF(COUNT(M10:AB10)>1,STDEV(M10:AB10)/AVERAGE(M10:AB10),"") -> 0.0023680439 | M10: 2003 | N10: 2004 | O10: 2005 | P10: 2006 | Q10: 2007 | R10: 2008 | S10: 2009 | T10: 2010 | U10: 2011 | V10: 2012 | W10: 2013 | X10: 2014 | Y10: 2015 | Z10: 2016 | AA10: 2017 | AB10: 2018
A11: 1 | C11: =IF(SUBTOTAL(109,A12)=A12," Revenue"," Total Revenue") -> Revenue | D11: =IF(COUNT(M11:AB11)>0,MEDIAN(M11:AB11),"") -> #VALUE! | E11: =IF(COUNT(M11:AB11)>0,AVERAGE(M11:AB11),"") -> #VALUE! | F11: =IF(COUNT(M11:AB11)>0,MIN(M11:AB11),"") -> #VALUE! | G11: =IF(COUNT(M11:AB11)>0,MAX(M11:AB11),"") -> #VALUE! | H11: =IF(COUNT(M11:AB11)>0,QUARTILE(M11:AB11,1),"") -> #VALUE! | I11: =IF(COUNT(M11:AB11)>0,QUARTILE(M11:AB11,3),"") -> #VALUE! | J11: =IF(COUNT(M11:AB11)>1,STDEV(M11:AB11),"") | K11: =IF(COUNT(M11:AB11)>1,STDEV(M11:AB11)/AVERAGE(M11:AB11),"") | M11: =IF(SUBTOTAL(109,#REF!)=#REF!,"",7923) -> #VALUE! | N11: =IF(SUBTOTAL(109,#REF!)=#REF!,"",22231) -> #VALUE! | O11: =IF(SUBTOTAL(109,#REF!)=#REF!,"",30937.728) -> #VALUE! | P11: =IF(SUBTOTAL(109,#REF!)=#REF!,"",33922.801) -> #VALUE! | Q11: =IF(SUBTOTAL(109,#REF!)=#REF!,"",72992) -> #VALUE! | R11: =IF(SUBTOTAL(109,#REF!)=#REF!,"",120454) -> #VALUE! | S11: =IF(SUBTOTAL(109,#REF!)=#REF!,"",140621) -> #VALUE! | T11: =IF(SUBTOTAL(109,#REF!)=#REF!,"",119924) -> #VALUE! | U11: =IF(SUBTOTAL(109,B12)=B12,"",119022) | V11: =IF(SUBTOTAL(109,D12)=D12,"",111494) | W11: =IF(SUBTOTAL(109,F12)=F12,"",129501) | X11: =IF(SUBTOTAL(109,H12)=H12,"",166578) | Y11: =IF(SUBTOTAL(109,J12)=J12,"",178513) | Z11: =IF(SUBTOTAL(109,L12)=L12,"",208332) -> 208332 | AA11: =IF(SUBTOTAL(109,N12)=N12,"",286776) | AB11: =IF(SUBTOTAL(109,P12)=P12,"",399472)
A12: 1 | C12: =" Business Revenue" -> Business Revenue | D12: =IF(COUNT(M12:AB12)>0,MEDIAN(M12:AB12),"") -> 120189 | E12: =IF(COUNT(M12:AB12)>0,AVERAGE(M12:AB12),"") -> 132180.66 | F12: =IF(COUNT(M12:AB12)>0,MIN(M12:AB12),"") -> 7923 | G12: =IF(COUNT(M12:AB12)>0,MAX(M12:AB12),"") -> 389373 | H12: =IF(COUNT(M12:AB12)>0,QUARTILE(M12:AB12,1),"") -> 63224.7 | I12: =IF(COUNT(M12:AB12)>0,QUARTILE(M12:AB12,3),"") -> 169561.75 | J12: =IF(COUNT(M12:AB12)>1,STDEV(M12:AB12),"") -> 98530.445 | K12: =IF(COUNT(M12:AB12)>1,STDEV(M12:AB12)/AVERAGE(M12:AB12),"") -> 0.74542256 | M12: 7923 | N12: 22231 | O12: 30937.728 | P12: 33922.801 | Q12: 72992 | R12: 120454 | S12: 140621 | T12: 119924 | U12: 119022 | V12: 111494 | W12: 129501 | X12: 166578 | Y12: 178513 | Z12: 198229 | AA12: 273175 | AB12: 389373
A13: 1 | C13: =" Other Revenue" -> Other Revenue | D13: =IF(COUNT(M13:AB13)>0,MEDIAN(M13:AB13),"") -> 10103 | E13: =IF(COUNT(M13:AB13)>0,AVERAGE(M13:AB13),"") -> 11267.667 | F13: =IF(COUNT(M13:AB13)>0,MIN(M13:AB13),"") -> 10099 | G13: =IF(COUNT(M13:AB13)>0,MAX(M13:AB13),"") -> 13601 | H13: =IF(COUNT(M13:AB13)>0,QUARTILE(M13:AB13,1),"") -> 10101 | I13: =IF(COUNT(M13:AB13)>0,QUARTILE(M13:AB13,3),"") -> 11852 | J13: =IF(COUNT(M13:AB13)>1,STDEV(M13:AB13),"") -> 2020.7269 | K13: =IF(COUNT(M13:AB13)>1,STDEV(M13:AB13)/AVERAGE(M13:AB13),"") -> 0.17933854 | Z13: 10103 | AA13: 13601 | AB13: 10099
A14: 1 | C14: =" Total Revenue" -> Total Revenue | D14: =IF(COUNT(M14:AB14)>0,MEDIAN(M14:AB14),"") -> 120189 | E14: =IF(COUNT(M14:AB14)>0,AVERAGE(M14:AB14),"") -> 134293.35 | F14: =IF(COUNT(M14:AB14)>0,MIN(M14:AB14),"") -> 7923 | G14: =IF(COUNT(M14:AB14)>0,MAX(M14:AB14),"") -> 399472 | H14: =IF(COUNT(M14:AB14)>0,QUARTILE(M14:AB14,1),"") -> 63224.7 | I14: =IF(COUNT(M14:AB14)>0,QUARTILE(M14:AB14,3),"") -> 169561.75 | J14: =IF(COUNT(M14:AB14)>1,STDEV(M14:AB14),"") -> 102080.37 | K14: =IF(COUNT(M14:AB14)>1,STDEV(M14:AB14)/AVERAGE(M14:AB14),"") -> 0.76012978 | M14: 7923 | N14: 22231 | O14: 30937.728 | P14: 33922.801 | Q14: 72992 | R14: 120454 | S14: 140621 | T14: 119924 | U14: 119022 | V14: 111494 | W14: 129501 | X14: 166578 | Y14: 178513 | Z14: 208332 | AA14: 286776 | AB14: 399472
A15: 1 | C15: =" Cost of Revenue" -> Cost of Revenue | D15: =IF(COUNT(M15:AB15)>0,MEDIAN(M15:AB15),"") -> 48688 | E15: =IF(COUNT(M15:AB15)>0,AVERAGE(M15:AB15),"") -> 55293.267 | F15: =IF(COUNT(M15:AB15)>0,MIN(M15:AB15),"") -> 5664 | G15: =IF(COUNT(M15:AB15)>0,MAX(M15:AB15),"") -> 148986 | H15: =IF(COUNT(M15:AB15)>0,QUARTILE(M15:AB15,1),"") -> 32719.5 | I15: =IF(COUNT(M15:AB15)>0,QUARTILE(M15:AB15,3),"") -> 72535 | J15: =IF(COUNT(M15:AB15)>1,STDEV(M15:AB15),"") -> 38315.963 | K15: =IF(COUNT(M15:AB15)>1,STDEV(M15:AB15)/AVERAGE(M15:AB15),"") -> 0.69295893 | M15: 5664 | N15: 16971 | P15: 12700.998 | Q15: 25526 | R15: 39913 | S15: 48688 | T15: 47492 | U15: 49076 | V15: 45593 | W15: 50431 | X15: 73114 | Y15: 71956 | Z15: 78882 | AA15: 114406 | AB15: 148986
A16: 1 | C16: =" Total Gross Profit" -> Total Gross Profit | D16: =IF(COUNT(M16:AB16)>0,MEDIAN(M16:AB16),"") -> 79070 | E16: =IF(COUNT(M16:AB16)>0,AVERAGE(M16:AB16),"") -> 85890.454 | F16: =IF(COUNT(M16:AB16)>0,MIN(M16:AB16),"") -> 2259 | G16: =IF(COUNT(M16:AB16)>0,MAX(M16:AB16),"") -> 250486 | H16: =IF(COUNT(M16:AB16)>0,QUARTILE(M16:AB16,1),"") -> 56683.5 | I16: =IF(COUNT(M16:AB16)>0,QUARTILE(M16:AB16,3),"") -> 100010.5 | J16: =IF(COUNT(M16:AB16)>1,STDEV(M16:AB16),"") -> 63837.321 | K16: =IF(COUNT(M16:AB16)>1,STDEV(M16:AB16)/AVERAGE(M16:AB16),"") -> 0.74324116 | M16: 2259 | N16: 5260 | P16: 21221.803 | Q16: 47466 | R16: 80541 | S16: 91933 | T16: 72432 | U16: 69946 | V16: 65901 | W16: 79070 | X16: 93464 | Y16: 106557 | Z16: 129450 | AA16: 172370 | AB16: 250486
A17: 1 | C17: =IF(SUBTOTAL(109,A18)=A18,"Operating (Income)/Expenses","Operating (Income)/Expenses") -> Operating (Income)/Expenses | D17: =IF(COUNT(M17:AB17)>0,MEDIAN(M17:AB17),"") -> #VALUE! | E17: =IF(COUNT(M17:AB17)>0,AVERAGE(M17:AB17),"") -> #VALUE! | F17: =IF(COUNT(M17:AB17)>0,MIN(M17:AB17),"") -> #VALUE! | G17: =IF(COUNT(M17:AB17)>0,MAX(M17:AB17),"") -> #VALUE! | H17: =IF(COUNT(M17:AB17)>0,QUARTILE(M17:AB17,1),"") -> #VALUE! | I17: =IF(COUNT(M17:AB17)>0,QUARTILE(M17:AB17,3),"") -> #VALUE! | J17: =IF(COUNT(M17:AB17)>1,STDEV(M17:AB17),"") | K17: =IF(COUNT(M17:AB17)>1,STDEV(M17:AB17)/AVERAGE(M17:AB17),"") | M17: =IF(SUBTOTAL(109,#REF!)=#REF!,"",14985) -> #VALUE! | N17: =IF(SUBTOTAL(109,#REF!)=#REF!,"",25359) -> #VALUE! | O17: =IF(SUBTOTAL(109,#REF!)=#REF!,"","") -> #VALUE! | P17: =IF(SUBTOTAL(109,#REF!)=#REF!,"",25709.719) -> #VALUE! | Q17: =IF(SUBTOTAL(109,#REF!)=#REF!,"",47224) -> #VALUE! | R17: =IF(SUBTOTAL(109,#REF!)=#REF!,"",65970) -> #VALUE! | S17: =IF(SUBTOTAL(109,#REF!)=#REF!,"",99601) -> #VALUE! | T17: =IF(SUBTOTAL(109,#REF!)=#REF!,"",87470) -> #VALUE! | U17: =IF(SUBTOTAL(109,B18)=B18,"",80610) | V17: =IF(SUBTOTAL(109,D18)=D18,"",78872) -> #VALUE! | W17: =IF(SUBTOTAL(109,F18)=F18,"",85951) -> #VALUE! | X17: =IF(SUBTOTAL(109,H18)=H18,"",97777) -> #VALUE! | Y17: =IF(SUBTOTAL(109,J18)=J18,"",90976) -> #VALUE! | Z17: =IF(SUBTOTAL(109,L18)=L18,"",101507) -> 101507 | AA17: =IF(SUBTOTAL(109,N18)=N18,"",160842) -> #VALUE! | AB17: =IF(SUBTOTAL(109,P18)=P18,"",178450) -> #VALUE!
A18: 1 | C18: =IF(SUBTOTAL(109,A19)=A19," Selling, General and Administrative Expenses"," Selling, General and Administrative Expenses") -> Selling, General and Administrative Expenses | D18: =IF(COUNT(M18:AB18)>0,MEDIAN(M18:AB18),"") -> #VALUE! | E18: =IF(COUNT(M18:AB18)>0,AVERAGE(M18:AB18),"") -> #VALUE! | F18: =IF(COUNT(M18:AB18)>0,MIN(M18:AB18),"") -> #VALUE! | G18: =IF(COUNT(M18:AB18)>0,MAX(M18:AB18),"") -> #VALUE! | H18: =IF(COUNT(M18:AB18)>0,QUARTILE(M18:AB18,1),"") -> #VALUE! | I18: =IF(COUNT(M18:AB18)>0,QUARTILE(M18:AB18,3),"") -> #VALUE! | J18: =IF(COUNT(M18:AB18)>1,STDEV(M18:AB18),"") -> #VALUE! | K18: =IF(COUNT(M18:AB18)>1,STDEV(M18:AB18)/AVERAGE(M18:AB18),"") -> #VALUE! | M18: =IF(SUBTOTAL(109,#REF!)=#REF!,"",3527) -> #VALUE! | N18: =IF(SUBTOTAL(109,#REF!)=#REF!,"",7695) -> #VALUE! | O18: =IF(SUBTOTAL(109,#REF!)=#REF!,"","") -> #VALUE! | P18: =IF(SUBTOTAL(109,#REF!)=#REF!,"",22078.9) -> #VALUE! | Q18: =IF(SUBTOTAL(109,#REF!)=#REF!,"",15968) -> #VALUE! | R18: =IF(SUBTOTAL(109,#REF!)=#REF!,"",48718) -> #VALUE! | S18: =IF(SUBTOTAL(109,#REF!)=#REF!,"",73809) -> #VALUE! | T18: =IF(SUBTOTAL(109,#REF!)=#REF!,"",63995) -> #VALUE! | U18: =IF(SUBTOTAL(109,B19)=B19,"",62832) | V18: =IF(SUBTOTAL(109,D19)=D19,"",62296) | W18: =IF(SUBTOTAL(109,F19)=F19,"",70826) | X18: =IF(SUBTOTAL(109,H19)=H19,"",81034) | Y18: =IF(SUBTOTAL(109,J19)=J19,"",75818) | Z18: =IF(SUBTOTAL(109,L19)=L19,"",84513) -> 84513 | AA18: =IF(SUBTOTAL(109,N19)=N19,"",118305) -> 118305 | AB18: =IF(SUBTOTAL(109,P19)=P19,"",152585) -> 152585
A19: 1 | C19: =" Staff Costs" -> Staff Costs | D19: =IF(COUNT(M19:AB19)>0,MEDIAN(M19:AB19),"") -> 1490 | E19: =IF(COUNT(M19:AB19)>0,AVERAGE(M19:AB19),"") -> 1546 | F19: =IF(COUNT(M19:AB19)>0,MIN(M19:AB19),"") -> 1410 | G19: =IF(COUNT(M19:AB19)>0,MAX(M19:AB19),"") -> 1738 | H19: =IF(COUNT(M19:AB19)>0,QUARTILE(M19:AB19,1),"") -> 1450 | I19: =IF(COUNT(M19:AB19)>0,QUARTILE(M19:AB19,3),"") -> 1614 | J19: =IF(COUNT(M19:AB19)>1,STDEV(M19:AB19),"") -> 171.02047 | K19: =IF(COUNT(M19:AB19)>1,STDEV(M19:AB19)/AVERAGE(M19:AB19),"") -> 0.11062126 | V19: 1490 | W19: 1410 | X19: 1738
A20: 1 | C20: =" General and Administrative Expenses" -> General and Administrative Expenses | D20: =IF(COUNT(M20:AB20)>0,MEDIAN(M20:AB20),"") -> 39153 | E20: =IF(COUNT(M20:AB20)>0,AVERAGE(M20:AB20),"") -> 49932.818 | F20: =IF(COUNT(M20:AB20)>0,MIN(M20:AB20),"") -> 27607 | G20: =IF(COUNT(M20:AB20)>0,MAX(M20:AB20),"") -> 109736 | H20: =IF(COUNT(M20:AB20)>0,QUARTILE(M20:AB20,1),"") -> 34834 | I20: =IF(COUNT(M20:AB20)>0,QUARTILE(M20:AB20,3),"") -> 51879.5 | J20: =IF(COUNT(M20:AB20)>1,STDEV(M20:AB20),"") -> 24964.885 | K20: =IF(COUNT(M20:AB20)>1,STDEV(M20:AB20)/AVERAGE(M20:AB20),"") -> 0.49996948 | R20: 27607 | S20: 39153 | T20: 34657 | U20: 35011 | V20: 33422 | W20: 37133 | X20: 45800 | Y20: 47882 | Z20: 55877 | AA20: 82983 | AB20: 109736
A21: 1 | C21: =" Legal, Accounting, Auditing and Consulting Fees" -> Legal, Accounting, Auditing and Consulting Fees | D21: =IF(COUNT(M21:AB21)>0,MEDIAN(M21:AB21),"") -> 4691 | E21: =IF(COUNT(M21:AB21)>0,AVERAGE(M21:AB21),"") -> 4159.6667 | F21: =IF(COUNT(M21:AB21)>0,MIN(M21:AB21),"") -> 1780 | G21: =IF(COUNT(M21:AB21)>0,MAX(M21:AB21),"") -> 6008 | H21: =IF(COUNT(M21:AB21)>0,QUARTILE(M21:AB21,1),"") -> 3235.5 | I21: =IF(COUNT(M21:AB21)>0,QUARTILE(M21:AB21,3),"") -> 5349.5 | J21: =IF(COUNT(M21:AB21)>1,STDEV(M21:AB21),"") -> 2163.5 | K21: =IF(COUNT(M21:AB21)>1,STDEV(M21:AB21)/AVERAGE(M21:AB21),"") -> 0.5201138 | V21: 1780 | W21: 6008 | X21: 4691
A22: 1 | C22: =" Selling and Marketing Expenses" -> Selling and Marketing Expenses | D22: =IF(COUNT(M22:AB22)>0,MEDIAN(M22:AB22),"") -> 27878.5 | E22: =IF(COUNT(M22:AB22)>0,AVERAGE(M22:AB22),"") -> 25395.929 | F22: =IF(COUNT(M22:AB22)>0,MIN(M22:AB22),"") -> 3527 | G22: =IF(COUNT(M22:AB22)>0,MAX(M22:AB22),"") -> 42849 | H22: =IF(COUNT(M22:AB22)>0,QUARTILE(M22:AB22,1),"") -> 22234.25 | I22: =IF(COUNT(M22:AB22)>0,QUARTILE(M22:AB22,3),"") -> 29204.75 | J22: =IF(COUNT(M22:AB22)>1,STDEV(M22:AB22),"") -> 10519.263 | K22: =IF(COUNT(M22:AB22)>1,STDEV(M22:AB22)/AVERAGE(M22:AB22),"") -> 0.41421061 | M22: 3527 | N22: 7695 | Q22: 15968 | R22: 21111 | S22: 34656 | T22: 29338 | U22: 27821 | V22: 25604 | W22: 26275 | X22: 28805 | Y22: 27936 | Z22: 28636 | AA22: 35322 | AB22: 42849
A23: 1 | C23: =" Total Selling, General and Administrative Expenses" -> Total Selling, General and Administrative Expenses | D23: =IF(COUNT(M23:AB23)>0,MEDIAN(M23:AB23),"") -> 63995 | E23: =IF(COUNT(M23:AB23)>0,AVERAGE(M23:AB23),"") -> 62933.327 | F23: =IF(COUNT(M23:AB23)>0,MIN(M23:AB23),"") -> 3527 | G23: =IF(COUNT(M23:AB23)>0,MAX(M23:AB23),"") -> 152585 | H23: =IF(COUNT(M23:AB23)>0,QUARTILE(M23:AB23,1),"") -> 35398.45 | I23: =IF(COUNT(M23:AB23)>0,QUARTILE(M23:AB23,3),"") -> 78426 | J23: =IF(COUNT(M23:AB23)>1,STDEV(M23:AB23),"") -> 40445.89 | K23: =IF(COUNT(M23:AB23)>1,STDEV(M23:AB23)/AVERAGE(M23:AB23),"") -> 0.64267841 | M23: 3527 | N23: 7695 | P23: 22078.9 | Q23: 15968 | R23: 48718 | S23: 73809 | T23: 63995 | U23: 62832 | V23: 62296 | W23: 70826 | X23: 81034 | Y23: 75818 | Z23: 84513 | AA23: 118305 | AB23: 152585
A24: 1 | C24: =" Research and Development Expenses" -> Research and Development Expenses | D24: =IF(COUNT(M24:AB24)>0,MEDIAN(M24:AB24),"") -> 5698 | E24: =IF(COUNT(M24:AB24)>0,AVERAGE(M24:AB24),"") -> 6122.5213 | F24: =IF(COUNT(M24:AB24)>0,MIN(M24:AB24),"") -> 2412 | G24: =IF(COUNT(M24:AB24)>0,MAX(M24:AB24),"") -> 11206 | H24: =IF(COUNT(M24:AB24)>0,QUARTILE(M24:AB24,1),"") -> 4218.5 | I24: =IF(COUNT(M24:AB24)>0,QUARTILE(M24:AB24,3),"") -> 7367 | J24: =IF(COUNT(M24:AB24)>1,STDEV(M24:AB24),"") -> 2624.0075 | K24: =IF(COUNT(M24:AB24)>1,STDEV(M24:AB24)/AVERAGE(M24:AB24),"") -> 0.42858282 | M24: 4438 | N24: 2412 | P24: 3630.819 | Q24: 3782 | R24: 3999 | S24: 5810 | T24: 4897 | U24: 5698 | V24: 4664 | W24: 7338 | X24: 7396 | Y24: 7111 | Z24: 8355 | AA24: 11101 | AB24: 11206
A25: 1 | C25: =IF(SUBTOTAL(109,A26)=A26," Provision Expense/Write-Back"," Provision Expense/Write-Back") -> Provision Expense/Write-Back | D25: =IF(COUNT(M25:AB25)>0,MEDIAN(M25:AB25),"") | E25: =IF(COUNT(M25:AB25)>0,AVERAGE(M25:AB25),"") | F25: =IF(COUNT(M25:AB25)>0,MIN(M25:AB25),"") | G25: =IF(COUNT(M25:AB25)>0,MAX(M25:AB25),"") | H25: =IF(COUNT(M25:AB25)>0,QUARTILE(M25:AB25,1),"") | I25: =IF(COUNT(M25:AB25)>0,QUARTILE(M25:AB25,3),"") | J25: =IF(COUNT(M25:AB25)>1,STDEV(M25:AB25),"") | K25: =IF(COUNT(M25:AB25)>1,STDEV(M25:AB25)/AVERAGE(M25:AB25),"") | M25: =IF(SUBTOTAL(109,#REF!)=#REF!,"","") -> #VALUE! | N25: =IF(SUBTOTAL(109,#REF!)=#REF!,"","") -> #VALUE! | O25: =IF(SUBTOTAL(109,#REF!)=#REF!,"","") -> #VALUE! | P25: =IF(SUBTOTAL(109,#REF!)=#REF!,"","") -> #VALUE! | Q25: =IF(SUBTOTAL(109,#REF!)=#REF!,"","") -> #VALUE! | R25: =IF(SUBTOTAL(109,#REF!)=#REF!,"",13253) -> #VALUE! | S25: =IF(SUBTOTAL(109,#REF!)=#REF!,"",19982) -> #VALUE! | T25: =IF(SUBTOTAL(109,#REF!)=#REF!,"",18578) -> #VALUE! | U25: =IF(SUBTOTAL(109,B26)=B26,"",12080) | V25: =IF(SUBTOTAL(109,D26)=D26,"",11912) | W25: =IF(SUBTOTAL(109,F26)=F26,"",7787) | X25: =IF(SUBTOTAL(109,H26)=H26,"",9347) | Y25: =IF(SUBTOTAL(109,J26)=J26,"",8047) | Z25: =IF(SUBTOTAL(109,L26)=L26,"","") | AA25: =IF(SUBTOTAL(109,N26)=N26,"","") | AB25: =IF(SUBTOTAL(109,P26)=P26,"","")
A26: 1 | C26: =" Provision for Doubtful Accounts" -> Provision for Doubtful Accounts | D26: =IF(COUNT(M26:AB26)>0,MEDIAN(M26:AB26),"") -> 11996 | E26: =IF(COUNT(M26:AB26)>0,AVERAGE(M26:AB26),"") -> 12623.25 | F26: =IF(COUNT(M26:AB26)>0,MIN(M26:AB26),"") -> 7787 | G26: =IF(COUNT(M26:AB26)>0,MAX(M26:AB26),"") -> 19982 | H26: =IF(COUNT(M26:AB26)>0,QUARTILE(M26:AB26,1),"") -> 9022 | I26: =IF(COUNT(M26:AB26)>0,QUARTILE(M26:AB26,3),"") -> 14584.25 | J26: =IF(COUNT(M26:AB26)>1,STDEV(M26:AB26),"") -> 4564.9757 | K26: =IF(COUNT(M26:AB26)>1,STDEV(M26:AB26)/AVERAGE(M26:AB26),"") -> 0.36163236 | R26: 13253 | S26: 19982 | T26: 18578 | U26: 12080 | V26: 11912 | W26: 7787 | X26: 9347 | Y26: 8047
A27: 1 | C27: =" Total Provision Expense/Write-Back" -> Total Provision Expense/Write-Back | D27: =IF(COUNT(M27:AB27)>0,MEDIAN(M27:AB27),"") -> 11996 | E27: =IF(COUNT(M27:AB27)>0,AVERAGE(M27:AB27),"") -> 12623.25 | F27: =IF(COUNT(M27:AB27)>0,MIN(M27:AB27),"") -> 7787 | G27: =IF(COUNT(M27:AB27)>0,MAX(M27:AB27),"") -> 19982 | H27: =IF(COUNT(M27:AB27)>0,QUARTILE(M27:AB27,1),"") -> 9022 | I27: =IF(COUNT(M27:AB27)>0,QUARTILE(M27:AB27,3),"") -> 14584.25 | J27: =IF(COUNT(M27:AB27)>1,STDEV(M27:AB27),"") -> 4564.9757 | K27: =IF(COUNT(M27:AB27)>1,STDEV(M27:AB27)/AVERAGE(M27:AB27),"") -> 0.36163236 | R27: 13253 | S27: 19982 | T27: 18578 | U27: 12080 | V27: 11912 | W27: 7787 | X27: 9347 | Y27: 8047
A28: 1 | C28: =IF(SUBTOTAL(109,A29)=A29," Other (Income)/Expense, Operating"," Other (Income)/Expense, Operating") -> Other (Income)/Expense, Operating | D28: =IF(COUNT(M28:AB28)>0,MEDIAN(M28:AB28),"") -> #VALUE! | E28: =IF(COUNT(M28:AB28)>0,AVERAGE(M28:AB28),"") -> #VALUE! | F28: =IF(COUNT(M28:AB28)>0,MIN(M28:AB28),"") -> #VALUE! | G28: =IF(COUNT(M28:AB28)>0,MAX(M28:AB28),"") -> #VALUE! | H28: =IF(COUNT(M28:AB28)>0,QUARTILE(M28:AB28,1),"") -> #VALUE! | I28: =IF(COUNT(M28:AB28)>0,QUARTILE(M28:AB28,3),"") -> #VALUE! | J28: =IF(COUNT(M28:AB28)>1,STDEV(M28:AB28),"") -> #VALUE! | K28: =IF(COUNT(M28:AB28)>1,STDEV(M28:AB28)/AVERAGE(M28:AB28),"") -> #VALUE! | M28: =IF(SUBTOTAL(109,#REF!)=#REF!,"",7020) -> #VALUE! | N28: =IF(SUBTOTAL(109,#REF!)=#REF!,"",15252) -> #VALUE! | O28: =IF(SUBTOTAL(109,#REF!)=#REF!,"","") -> #VALUE! | P28: =IF(SUBTOTAL(109,#REF!)=#REF!,"","") -> #VALUE! | Q28: =IF(SUBTOTAL(109,#REF!)=#REF!,"",27474) -> #VALUE! | R28: =IF(SUBTOTAL(109,#REF!)=#REF!,"","") -> #VALUE! | S28: =IF(SUBTOTAL(109,#REF!)=#REF!,"","") -> #VALUE! | T28: =IF(SUBTOTAL(109,#REF!)=#REF!,"","") -> #VALUE! | U28: =IF(SUBTOTAL(109,B29)=B29,"","") | V28: =IF(SUBTOTAL(109,D29)=D29,"","") | W28: =IF(SUBTOTAL(109,F29)=F29,"","") | X28: =IF(SUBTOTAL(109,H29)=H29,"","") | Y28: =IF(SUBTOTAL(109,J29)=J29,"","") | Z28: =IF(SUBTOTAL(109,L29)=L29,"",8639) -> 8639 | AA28: =IF(SUBTOTAL(109,N29)=N29,"",31436) -> 31436 | AB28: =IF(SUBTOTAL(109,P29)=P29,"",14659) -> 14659
A29: 1 | C29: =" Other Expenses, Operating" -> Other Expenses, Operating | D29: =IF(COUNT(M29:AB29)>0,MEDIAN(M29:AB29),"") -> 14659 | E29: =IF(COUNT(M29:AB29)>0,AVERAGE(M29:AB29),"") -> 18244.667 | F29: =IF(COUNT(M29:AB29)>0,MIN(M29:AB29),"") -> 8639 | G29: =IF(COUNT(M29:AB29)>0,MAX(M29:AB29),"") -> 31436 | H29: =IF(COUNT(M29:AB29)>0,QUARTILE(M29:AB29,1),"") -> 11649 | I29: =IF(COUNT(M29:AB29)>0,QUARTILE(M29:AB29,3),"") -> 23047.5 | J29: =IF(COUNT(M29:AB29)>1,STDEV(M29:AB29),"") -> 11813.914 | K29: =IF(COUNT(M29:AB29)>1,STDEV(M29:AB29)/AVERAGE(M29:AB29),"") -> 0.64752697 | Z29: 8639 | AA29: 31436 | AB29: 14659
A30: 1 | C30: =" Total Other (Income)/Expense, Operating" -> Total Other (Income)/Expense, Operating | D30: =IF(COUNT(M30:AB30)>0,MEDIAN(M30:AB30),"") -> 14955.5 | E30: =IF(COUNT(M30:AB30)>0,AVERAGE(M30:AB30),"") -> 17413.333 | F30: =IF(COUNT(M30:AB30)>0,MIN(M30:AB30),"") -> 7020 | G30: =IF(COUNT(M30:AB30)>0,MAX(M30:AB30),"") -> 31436 | H30: =IF(COUNT(M30:AB30)>0,QUARTILE(M30:AB30,1),"") -> 10144 | I30: =IF(COUNT(M30:AB30)>0,QUARTILE(M30:AB30,3),"") -> 24418.5 | J30: =IF(COUNT(M30:AB30)>1,STDEV(M30:AB30),"") -> 9951.0825 | K30: =IF(COUNT(M30:AB30)>1,STDEV(M30:AB30)/AVERAGE(M30:AB30),"") -> 0.57146339 | M30: 7020 | N30: 15252 | Q30: 27474 | Z30: 8639 | AA30: 31436 | AB30: 14659
A31: 1 | C31: =" Total Operating (Income)/Expenses" -> Total Operating (Income)/Expenses | D31: =IF(COUNT(M31:AB31)>0,MEDIAN(M31:AB31),"") -> 85951 | E31: =IF(COUNT(M31:AB31)>0,AVERAGE(M31:AB31),"") -> 82753.581 | F31: =IF(COUNT(M31:AB31)>0,MIN(M31:AB31),"") -> 14985 | G31: =IF(COUNT(M31:AB31)>0,MAX(M31:AB31),"") -> 178450 | H31: =IF(COUNT(M31:AB31)>0,QUARTILE(M31:AB31,1),"") -> 56597 | I31: =IF(COUNT(M31:AB31)>0,QUARTILE(M31:AB31,3),"") -> 98689 | J31: =IF(COUNT(M31:AB31)>1,STDEV(M31:AB31),"") -> 45451.177 | K31: =IF(COUNT(M31:AB31)>1,STDEV(M31:AB31)/AVERAGE(M31:AB31),"") -> 0.54923517 | M31: 14985 | N31: 25359 | P31: 25709.719 | Q31: 47224 | R31: 65970 | S31: 99601 | T31: 87470 | U31: 80610 | V31: 78872 | W31: 85951 | X31: 97777 | Y31: 90976 | Z31: 101507 | AA31: 160842 | AB31: 178450
A32: 1 | C32: ="Total Operating Profit/(Loss)" -> Total Operating Profit/(Loss) | D32: =IF(COUNT(M32:AB32)>0,MEDIAN(M32:AB32),"") -> -4400.458 | E32: =IF(COUNT(M32:AB32)>0,AVERAGE(M32:AB32),"") -> 4874.4258 | F32: =IF(COUNT(M32:AB32)>0,MIN(M32:AB32),"") -> -20099 | G32: =IF(COUNT(M32:AB32)>0,MAX(M32:AB32),"") -> 72036 | H32: =IF(COUNT(M32:AB32)>0,QUARTILE(M32:AB32,1),"") -> -11179.5 | I32: =IF(COUNT(M32:AB32)>0,QUARTILE(M32:AB32,3),"") -> 14823.5 | J32: =IF(COUNT(M32:AB32)>1,STDEV(M32:AB32),"") -> 23599.342 | K32: =IF(COUNT(M32:AB32)>1,STDEV(M32:AB32)/AVERAGE(M32:AB32),"") -> 4.8414609 | M32: -12726 | N32: -20099 | O32: 30937.728 | P32: -4487.916 | Q32: 242 | R32: 14571 | S32: -7668 | T32: -15038 | U32: -10664 | V32: -12971 | W32: -6881 | X32: -4313 | Y32: 15581 | Z32: 27943 | AA32: 11528 | AB32: 72036
A33: 1 | C33: =IF(SUBTOTAL(109,A34)=A34,"Non-Operating Income/(Expenses)","Non-Operating Income/(Expenses), Total") -> Non-Operating Income/(Expenses), Total | D33: =IF(COUNT(M33:AB33)>0,MEDIAN(M33:AB33),"") -> #VALUE! | E33: =IF(COUNT(M33:AB33)>0,AVERAGE(M33:AB33),"") -> #VALUE! | F33: =IF(COUNT(M33:AB33)>0,MIN(M33:AB33),"") -> #VALUE! | G33: =IF(COUNT(M33:AB33)>0,MAX(M33:AB33),"") -> #VALUE! | H33: =IF(COUNT(M33:AB33)>0,QUARTILE(M33:AB33,1),"") -> #VALUE! | I33: =IF(COUNT(M33:AB33)>0,QUARTILE(M33:AB33,3),"") -> #VALUE! | J33: =IF(COUNT(M33:AB33)>1,STDEV(M33:AB33),"") -> #VALUE! | K33: =IF(COUNT(M33:AB33)>1,STDEV(M33:AB33)/AVERAGE(M33:AB33),"") -> #VALUE! | M33: =IF(SUBTOTAL(109,#REF!)=#REF!,"",0) -> #VALUE! | N33: =IF(SUBTOTAL(109,#REF!)=#REF!,"",0) -> #VALUE! | O33: =IF(SUBTOTAL(109,#REF!)=#REF!,"","") -> #VALUE! | P33: =IF(SUBTOTAL(109,#REF!)=#REF!,"","") -> #VALUE! | Q33: =IF(SUBTOTAL(109,#REF!)=#REF!,"",-600) -> #VALUE! | R33: =IF(SUBTOTAL(109,#REF!)=#REF!,"",-3883) -> #VALUE! | S33: =IF(SUBTOTAL(109,#REF!)=#REF!,"",-12803) -> #VALUE! | T33: =IF(SUBTOTAL(109,#REF!)=#REF!,"",-4560) -> #VALUE! | U33: =IF(SUBTOTAL(109,B34)=B34,"",-50514) | V33: =IF(SUBTOTAL(109,D34)=D34,"",-136) -> #VALUE! | W33: =IF(SUBTOTAL(109,F34)=F34,"",-223) -> #VALUE! | X33: =IF(SUBTOTAL(109,H34)=H34,"",-7793) -> #VALUE! | Y33: =IF(SUBTOTAL(109,J34)=J34,"",-7685) -> -7685 | Z33: =IF(SUBTOTAL(109,L34)=L34,"",-12173) -> -12173 | AA33: =IF(SUBTOTAL(109,N34)=N34,"",-21924) -> #VALUE! | AB33: =IF(SUBTOTAL(109,P34)=P34,"",-30532) -> #VALUE!
A34: 1 | C34: =IF(SUBTOTAL(109,A35)=A35," Net Finance (Income)/Expense"," Total Net Finance (Income)/Expense") -> Total Net Finance (Income)/Expense | D34: =IF(COUNT(M34:AB34)>0,MEDIAN(M34:AB34),"") -> #VALUE! | E34: =IF(COUNT(M34:AB34)>0,AVERAGE(M34:AB34),"") -> #VALUE! | F34: =IF(COUNT(M34:AB34)>0,MIN(M34:AB34),"") -> #VALUE! | G34: =IF(COUNT(M34:AB34)>0,MAX(M34:AB34),"") -> #VALUE! | H34: =IF(COUNT(M34:AB34)>0,QUARTILE(M34:AB34,1),"") -> #VALUE! | I34: =IF(COUNT(M34:AB34)>0,QUARTILE(M34:AB34,3),"") -> #VALUE! | J34: =IF(COUNT(M34:AB34)>1,STDEV(M34:AB34),"") | K34: =IF(COUNT(M34:AB34)>1,STDEV(M34:AB34)/AVERAGE(M34:AB34),"") | M34: =IF(SUBTOTAL(109,#REF!)=#REF!,"","") -> #VALUE! | N34: =IF(SUBTOTAL(109,#REF!)=#REF!,"","") -> #VALUE! | O34: =IF(SUBTOTAL(109,#REF!)=#REF!,"","") -> #VALUE! | P34: =IF(SUBTOTAL(109,#REF!)=#REF!,"","") -> #VALUE! | Q34: =IF(SUBTOTAL(109,#REF!)=#REF!,"",600) -> #VALUE! | R34: =IF(SUBTOTAL(109,#REF!)=#REF!,"",-997) -> #VALUE! | S34: =IF(SUBTOTAL(109,#REF!)=#REF!,"",-178) -> #VALUE! | T34: =IF(SUBTOTAL(109,#REF!)=#REF!,"",-94) -> #VALUE! | U34: =IF(SUBTOTAL(109,B35)=B35,"","") | V34: =IF(SUBTOTAL(109,D35)=D35,"","") -> #VALUE! | W34: =IF(SUBTOTAL(109,F35)=F35,"",223) -> #VALUE! | X34: =IF(SUBTOTAL(109,H35)=H35,"",7793) -> #VALUE! | Y34: =IF(SUBTOTAL(109,J35)=J35,"",1534) -> #VALUE! | Z34: =IF(SUBTOTAL(109,L35)=L35,"",1830) -> 1830 | AA34: =IF(SUBTOTAL(109,N35)=N35,"",4897) -> #VALUE! | AB34: =IF(SUBTOTAL(109,P35)=P35,"",9429) -> #VALUE!
A35: 1 | C35: =IF(SUBTOTAL(109,A36)=A36," Net Interest (Income)/Expense"," Net Interest (Income)/Expense") -> Net Interest (Income)/Expense | D35: =IF(COUNT(M35:AB35)>0,MEDIAN(M35:AB35),"") -> #VALUE! | E35: =IF(COUNT(M35:AB35)>0,AVERAGE(M35:AB35),"") -> #VALUE! | F35: =IF(COUNT(M35:AB35)>0,MIN(M35:AB35),"") -> #VALUE! | G35: =IF(COUNT(M35:AB35)>0,MAX(M35:AB35),"") -> #VALUE! | H35: =IF(COUNT(M35:AB35)>0,QUARTILE(M35:AB35,1),"") -> #VALUE! | I35: =IF(COUNT(M35:AB35)>0,QUARTILE(M35:AB35,3),"") -> #VALUE! | J35: =IF(COUNT(M35:AB35)>1,STDEV(M35:AB35),"") -> #VALUE! | K35: =IF(COUNT(M35:AB35)>1,STDEV(M35:AB35)/AVERAGE(M35:AB35),"") -> #VALUE! | M35: =IF(SUBTOTAL(109,#REF!)=#REF!,"","") -> #VALUE! | N35: =IF(SUBTOTAL(109,#REF!)=#REF!,"","") -> #VALUE! | O35: =IF(SUBTOTAL(109,#REF!)=#REF!,"","") -> #VALUE! | P35: =IF(SUBTOTAL(109,#REF!)=#REF!,"","") -> #VALUE! | Q35: =IF(SUBTOTAL(109,#REF!)=#REF!,"",600) -> #VALUE! | R35: =IF(SUBTOTAL(109,#REF!)=#REF!,"",-997) -> #VALUE! | S35: =IF(SUBTOTAL(109,#REF!)=#REF!,"",-178) -> #VALUE! | T35: =IF(SUBTOTAL(109,#REF!)=#REF!,"",-94) -> #VALUE! | U35: =IF(SUBTOTAL(109,B36)=B36,"","") | V35: =IF(SUBTOTAL(109,D36)=D36,"","") | W35: =IF(SUBTOTAL(109,F36)=F36,"",223) -> 223 | X35: =IF(SUBTOTAL(109,H36)=H36,"",7793) -> 7793 | Y35: =IF(SUBTOTAL(109,J36)=J36,"",1534) -> 1534 | Z35: =IF(SUBTOTAL(109,L36)=L36,"",1830) -> 1830 | AA35: =IF(SUBTOTAL(109,N36)=N36,"",4897) -> 4897 | AB35: =IF(SUBTOTAL(109,P36)=P36,"",9429) -> 9429
A36: 1 | C36: =" Interest Expense Net of Capitalized Interest" -> Interest Expense Net of Capitalized Interest | D36: =IF(COUNT(M36:AB36)>0,MEDIAN(M36:AB36),"") -> 1682 | E36: =IF(COUNT(M36:AB36)>0,AVERAGE(M36:AB36),"") -> 2512 | F36: =IF(COUNT(M36:AB36)>0,MIN(M36:AB36),"") -> 3 | G36: =IF(COUNT(M36:AB36)>0,MAX(M36:AB36),"") -> 9429 | H36: =IF(COUNT(M36:AB36)>0,QUARTILE(M36:AB36,1),"") -> 130.5 | I36: =IF(COUNT(M36:AB36)>0,QUARTILE(M36:AB36,3),"") -> 2890 | J36: =IF(COUNT(M36:AB36)>1,STDEV(M36:AB36),"") -> 3230.8656 | K36: =IF(COUNT(M36:AB36)>1,STDEV(M36:AB36)/AVERAGE(M36:AB36),"") -> 1.2861726 | Q36: 2221 | R36: 170 | S36: 12 | T36: 3 | Y36: 1534 | Z36: 1830 | AA36: 4897 | AB36: 9429
A37: 1 | C37: =" Interest Income" -> Interest Income | D37: =IF(COUNT(M37:AB37)>0,MEDIAN(M37:AB37),"") -> 678.5 | E37: =IF(COUNT(M37:AB37)>0,AVERAGE(M37:AB37),"") -> 768.75 | F37: =IF(COUNT(M37:AB37)>0,MIN(M37:AB37),"") -> 97 | G37: =IF(COUNT(M37:AB37)>0,MAX(M37:AB37),"") -> 1621 | H37: =IF(COUNT(M37:AB37)>0,QUARTILE(M37:AB37,1),"") -> 166.75 | I37: =IF(COUNT(M37:AB37)>0,QUARTILE(M37:AB37,3),"") -> 1280.5 | J37: =IF(COUNT(M37:AB37)>1,STDEV(M37:AB37),"") -> 746.35397 | K37: =IF(COUNT(M37:AB37)>1,STDEV(M37:AB37)/AVERAGE(M37:AB37),"") -> 0.97086695 | Q37: 1621 | R37: 1167 | S37: 190 | T37: 97
A38: 1 | C38: =" Total Net Interest (Income)/Expense" -> Total Net Interest (Income)/Expense | D38: =IF(COUNT(M38:AB38)>0,MEDIAN(M38:AB38),"") -> 1067 | E38: =IF(COUNT(M38:AB38)>0,AVERAGE(M38:AB38),"") -> 2503.7 | F38: =IF(COUNT(M38:AB38)>0,MIN(M38:AB38),"") -> -997 | G38: =IF(COUNT(M38:AB38)>0,MAX(M38:AB38),"") -> 9429 | H38: =IF(COUNT(M38:AB38)>0,QUARTILE(M38:AB38,1),"") -> -14.75 | I38: =IF(COUNT(M38:AB38)>0,QUARTILE(M38:AB38,3),"") -> 4130.25 | J38: =IF(COUNT(M38:AB38)>1,STDEV(M38:AB38),"") -> 3622.1337 | K38: =IF(COUNT(M38:AB38)>1,STDEV(M38:AB38)/AVERAGE(M38:AB38),"") -> 1.4467124 | Q38: 600 | R38: -997 | S38: -178 | T38: -94 | W38: 223 | X38: 7793 | Y38: 1534 | Z38: 1830 | AA38: 4897 | AB38: 9429
A39: 1 | C39: =" Total Net Finance (Income)/Expense" -> Total Net Finance (Income)/Expense | D39: =IF(COUNT(M39:AB39)>0,MEDIAN(M39:AB39),"") -> 1067 | E39: =IF(COUNT(M39:AB39)>0,AVERAGE(M39:AB39),"") -> 2503.7 | F39: =IF(COUNT(M39:AB39)>0,MIN(M39:AB39),"") -> -997 | G39: =IF(COUNT(M39:AB39)>0,MAX(M39:AB39),"") -> 9429 | H39: =IF(COUNT(M39:AB39)>0,QUARTILE(M39:AB39,1),"") -> -14.75 | I39: =IF(COUNT(M39:AB39)>0,QUARTILE(M39:AB39,3),"") -> 4130.25 | J39: =IF(COUNT(M39:AB39)>1,STDEV(M39:AB39),"") -> 3622.1337 | K39: =IF(COUNT(M39:AB39)>1,STDEV(M39:AB39)/AVERAGE(M39:AB39),"") -> 1.4467124 | Q39: 600 | R39: -997 | S39: -178 | T39: -94 | W39: 223 | X39: 7793 | Y39: 1534 | Z39: 1830 | AA39: 4897 | AB39: 9429
A40: 1 | C40: =IF(SUBTOTAL(109,A41)=A41," Net Investment Income"," Net Investment Income") -> Net Investment Income | D40: =IF(COUNT(M40:AB40)>0,MEDIAN(M40:AB40),"") -> #VALUE! | E40: =IF(COUNT(M40:AB40)>0,AVERAGE(M40:AB40),"") -> #VALUE! | F40: =IF(COUNT(M40:AB40)>0,MIN(M40:AB40),"") -> #VALUE! | G40: =IF(COUNT(M40:AB40)>0,MAX(M40:AB40),"") -> #VALUE! | H40: =IF(COUNT(M40:AB40)>0,QUARTILE(M40:AB40,1),"") -> #VALUE! | I40: =IF(COUNT(M40:AB40)>0,QUARTILE(M40:AB40,3),"") -> #VALUE! | J40: =IF(COUNT(M40:AB40)>1,STDEV(M40:AB40),"") -> #VALUE! | K40: =IF(COUNT(M40:AB40)>1,STDEV(M40:AB40)/AVERAGE(M40:AB40),"") -> #VALUE! | M40: =IF(SUBTOTAL(109,#REF!)=#REF!,"","") -> #VALUE! | N40: =IF(SUBTOTAL(109,#REF!)=#REF!,"","") -> #VALUE! | O40: =IF(SUBTOTAL(109,#REF!)=#REF!,"","") -> #VALUE! | P40: =IF(SUBTOTAL(109,#REF!)=#REF!,"","") -> #VALUE! | Q40: =IF(SUBTOTAL(109,#REF!)=#REF!,"","") -> #VALUE! | R40: =IF(SUBTOTAL(109,#REF!)=#REF!,"","") -> #VALUE! | S40: =IF(SUBTOTAL(109,#REF!)=#REF!,"","") -> #VALUE! | T40: =IF(SUBTOTAL(109,#REF!)=#REF!,"","") -> #VALUE! | U40: =IF(SUBTOTAL(109,B41)=B41,"","") | V40: =IF(SUBTOTAL(109,D41)=D41,"","") | W40: =IF(SUBTOTAL(109,F41)=F41,"","") | X40: =IF(SUBTOTAL(109,H41)=H41,"","") | Y40: =IF(SUBTOTAL(109,J41)=J41,"","") | Z40: =IF(SUBTOTAL(109,L41)=L41,"",-287) -> -287 | AA40: =IF(SUBTOTAL(109,N41)=N41,"",-384) -> -384 | AB40: =IF(SUBTOTAL(109,P41)=P41,"",-246) -> -246
A41: 1 | C41: =" Gain/(Loss) on Investments and Other Financial Instruments" -> Gain/(Loss) on Investments and Other Financial Instruments | D41: =IF(COUNT(M41:AB41)>0,MEDIAN(M41:AB41),"") -> -287 | E41: =IF(COUNT(M41:AB41)>0,AVERAGE(M41:AB41),"") -> -305.66667 | F41: =IF(COUNT(M41:AB41)>0,MIN(M41:AB41),"") -> -384 | G41: =IF(COUNT(M41:AB41)>0,MAX(M41:AB41),"") -> -246 | H41: =IF(COUNT(M41:AB41)>0,QUARTILE(M41:AB41,1),"") -> -335.5 | I41: =IF(COUNT(M41:AB41)>0,QUARTILE(M41:AB41,3),"") -> -266.5 | J41: =IF(COUNT(M41:AB41)>1,STDEV(M41:AB41),"") -> 70.868423 | K41: =IF(COUNT(M41:AB41)>1,STDEV(M41:AB41)/AVERAGE(M41:AB41),"") -> -0.23184871 | Z41: -287 | AA41: -384 | AB41: -246
A42: 1 | C42: =" Total Net Investment Income" -> Total Net Investment Income | D42: =IF(COUNT(M42:AB42)>0,MEDIAN(M42:AB42),"") -> -287 | E42: =IF(COUNT(M42:AB42)>0,AVERAGE(M42:AB42),"") -> -305.66667 | F42: =IF(COUNT(M42:AB42)>0,MIN(M42:AB42),"") -> -384 | G42: =IF(COUNT(M42:AB42)>0,MAX(M42:AB42),"") -> -246 | H42: =IF(COUNT(M42:AB42)>0,QUARTILE(M42:AB42,1),"") -> -335.5 | I42: =IF(COUNT(M42:AB42)>0,QUARTILE(M42:AB42,3),"") -> -266.5 | J42: =IF(COUNT(M42:AB42)>1,STDEV(M42:AB42),"") -> 70.868423 | K42: =IF(COUNT(M42:AB42)>1,STDEV(M42:AB42)/AVERAGE(M42:AB42),"") -> -0.23184871 | Z42: -287 | AA42: -384 | AB42: -246
A43: 1 | C43: =IF(SUBTOTAL(109,A44)=A44," Irregular (Income)/Expenses"," Irregular (Income)/Expenses") -> Irregular (Income)/Expenses | D43: =IF(COUNT(M43:AB43)>0,MEDIAN(M43:AB43),"") -> #VALUE! | E43: =IF(COUNT(M43:AB43)>0,AVERAGE(M43:AB43),"") -> #VALUE! | F43: =IF(COUNT(M43:AB43)>0,MIN(M43:AB43),"") -> #VALUE! | G43: =IF(COUNT(M43:AB43)>0,MAX(M43:AB43),"") -> #VALUE! | H43: =IF(COUNT(M43:AB43)>0,QUARTILE(M43:AB43,1),"") -> #VALUE! | I43: =IF(COUNT(M43:AB43)>0,QUARTILE(M43:AB43,3),"") -> #VALUE! | J43: =IF(COUNT(M43:AB43)>1,STDEV(M43:AB43),"") -> #VALUE! | K43: =IF(COUNT(M43:AB43)>1,STDEV(M43:AB43)/AVERAGE(M43:AB43),"") -> #VALUE! | M43: =IF(SUBTOTAL(109,#REF!)=#REF!,"",0) -> #VALUE! | N43: =IF(SUBTOTAL(109,#REF!)=#REF!,"",0) -> #VALUE! | O43: =IF(SUBTOTAL(109,#REF!)=#REF!,"","") -> #VALUE! | P43: =IF(SUBTOTAL(109,#REF!)=#REF!,"","") -> #VALUE! | Q43: =IF(SUBTOTAL(109,#REF!)=#REF!,"",0) -> #VALUE! | R43: =IF(SUBTOTAL(109,#REF!)=#REF!,"",4880) -> #VALUE! | S43: =IF(SUBTOTAL(109,#REF!)=#REF!,"",12981) -> #VALUE! | T43: =IF(SUBTOTAL(109,#REF!)=#REF!,"",4654) -> #VALUE! | U43: =IF(SUBTOTAL(109,B44)=B44,"",50514) | V43: =IF(SUBTOTAL(109,D44)=D44,"",136) | W43: =IF(SUBTOTAL(109,F44)=F44,"","") | X43: =IF(SUBTOTAL(109,H44)=H44,"",0) | Y43: =IF(SUBTOTAL(109,J44)=J44,"",6151) -> 6151 | Z43: =IF(SUBTOTAL(109,L44)=L44,"",9931) -> 9931 | AA43: =IF(SUBTOTAL(109,N44)=N44,"",13834) -> 13834 | AB43: =IF(SUBTOTAL(109,P44)=P44,"",22222) -> 22222
A44: 1 | C44: =" Impairment/Write Off/Write Down of Capital Assets" -> Impairment/Write Off/Write Down of Capital Assets | D44: =IF(COUNT(M44:AB44)>0,MEDIAN(M44:AB44),"") -> 0 | E44: =IF(COUNT(M44:AB44)>0,AVERAGE(M44:AB44),"") -> 11499.75 | F44: =IF(COUNT(M44:AB44)>0,MIN(M44:AB44),"") -> 0 | G44: =IF(COUNT(M44:AB44)>0,MAX(M44:AB44),"") -> 45999 | H44: =IF(COUNT(M44:AB44)>0,QUARTILE(M44:AB44,1),"") -> 0 | I44: =IF(COUNT(M44:AB44)>0,QUARTILE(M44:AB44,3),"") -> 11499.75 | J44: =IF(COUNT(M44:AB44)>1,STDEV(M44:AB44),"") -> 22999.5 | K44: =IF(COUNT(M44:AB44)>1,STDEV(M44:AB44)/AVERAGE(M44:AB44),"") -> 2 | R44: 0 | S44: 0 | T44: 0 | U44: 45999
A45: 1 | C45: =" Impairment/Write Off/Write Down of Other Assets" -> Impairment/Write Off/Write Down of Other Assets | D45: =IF(COUNT(M45:AB45)>0,MEDIAN(M45:AB45),"") -> 13291 | E45: =IF(COUNT(M45:AB45)>0,AVERAGE(M45:AB45),"") -> 15148 | F45: =IF(COUNT(M45:AB45)>0,MIN(M45:AB45),"") -> 9931 | G45: =IF(COUNT(M45:AB45)>0,MAX(M45:AB45),"") -> 22222 | H45: =IF(COUNT(M45:AB45)>0,QUARTILE(M45:AB45,1),"") -> 11611 | I45: =IF(COUNT(M45:AB45)>0,QUARTILE(M45:AB45,3),"") -> 17756.5 | J45: =IF(COUNT(M45:AB45)>1,STDEV(M45:AB45),"") -> 6352.441 | K45: =IF(COUNT(M45:AB45)>1,STDEV(M45:AB45)/AVERAGE(M45:AB45),"") -> 0.4193584 | Z45: 9931 | AA45: 13291 | AB45: 22222
A46: 1 | C46: =" (Gain)/Loss on Extinguishment of Debt" -> (Gain)/Loss on Extinguishment of Debt | D46: =IF(COUNT(M46:AB46)>0,MEDIAN(M46:AB46),"") -> 0 | E46: =IF(COUNT(M46:AB46)>0,AVERAGE(M46:AB46),"") -> 181 | F46: =IF(COUNT(M46:AB46)>0,MIN(M46:AB46),"") -> 0 | G46: =IF(COUNT(M46:AB46)>0,MAX(M46:AB46),"") -> 543 | H46: =IF(COUNT(M46:AB46)>0,QUARTILE(M46:AB46,1),"") -> 0 | I46: =IF(COUNT(M46:AB46)>0,QUARTILE(M46:AB46,3),"") -> 271.5 | J46: =IF(COUNT(M46:AB46)>1,STDEV(M46:AB46),"") -> 313.5012 | K46: =IF(COUNT(M46:AB46)>1,STDEV(M46:AB46)/AVERAGE(M46:AB46),"") -> 1.7320508 | Z46: 0 | AA46: 543 | AB46: 0
A47: 1 | C47: =" Restructuring and Reorganization (Income)/Expense" -> Restructuring and Reorganization (Income)/Expense | D47: =IF(COUNT(M47:AB47)>0,MEDIAN(M47:AB47),"") -> 4659 | E47: =IF(COUNT(M47:AB47)>0,AVERAGE(M47:AB47),"") -> 5434.8 | F47: =IF(COUNT(M47:AB47)>0,MIN(M47:AB47),"") -> 0 | G47: =IF(COUNT(M47:AB47)>0,MAX(M47:AB47),"") -> 12981 | H47: =IF(COUNT(M47:AB47)>0,QUARTILE(M47:AB47,1),"") -> 4654 | I47: =IF(COUNT(M47:AB47)>0,QUARTILE(M47:AB47,3),"") -> 4880 | J47: =IF(COUNT(M47:AB47)>1,STDEV(M47:AB47),"") -> 4690.4558 | K47: =IF(COUNT(M47:AB47)>1,STDEV(M47:AB47)/AVERAGE(M47:AB47),"") -> 0.86304111 | Q47: 0 | R47: 4880 | S47: 12981 | T47: 4654 | U47: 4659
A48: 1 | C48: =" Other Irregular Income/(Expenses)" -> Other Irregular Income/(Expenses) | D48: =IF(COUNT(M48:AB48)>0,MEDIAN(M48:AB48),"") -> -144 | E48: =IF(COUNT(M48:AB48)>0,AVERAGE(M48:AB48),"") -> -144 | F48: =IF(COUNT(M48:AB48)>0,MIN(M48:AB48),"") -> -144 | G48: =IF(COUNT(M48:AB48)>0,MAX(M48:AB48),"") -> -144 | H48: =IF(COUNT(M48:AB48)>0,QUARTILE(M48:AB48,1),"") -> -144 | I48: =IF(COUNT(M48:AB48)>0,QUARTILE(M48:AB48,3),"") -> -144 | J48: =IF(COUNT(M48:AB48)>1,STDEV(M48:AB48),"") | K48: =IF(COUNT(M48:AB48)>1,STDEV(M48:AB48)/AVERAGE(M48:AB48),"") | U48: -144
A49: 1 | C49: =" Total Irregular (Income)/Expenses" -> Total Irregular (Income)/Expenses | D49: =IF(COUNT(M49:AB49)>0,MEDIAN(M49:AB49),"") -> 4880 | E49: =IF(COUNT(M49:AB49)>0,AVERAGE(M49:AB49),"") -> 9638.6923 | F49: =IF(COUNT(M49:AB49)>0,MIN(M49:AB49),"") -> 0 | G49: =IF(COUNT(M49:AB49)>0,MAX(M49:AB49),"") -> 50514 | H49: =IF(COUNT(M49:AB49)>0,QUARTILE(M49:AB49,1),"") -> 0 | I49: =IF(COUNT(M49:AB49)>0,QUARTILE(M49:AB49,3),"") -> 12981 | J49: =IF(COUNT(M49:AB49)>1,STDEV(M49:AB49),"") -> 14081.792 | K49: =IF(COUNT(M49:AB49)>1,STDEV(M49:AB49)/AVERAGE(M49:AB49),"") -> 1.460965 | M49: 0 | N49: 0 | Q49: 0 | R49: 4880 | S49: 12981 | T49: 4654 | U49: 50514 | V49: 136 | X49: 0 | Y49: 6151 | Z49: 9931 | AA49: 13834 | AB49: 22222
A50: 1 | C50: =" Other Income/(Expense), Non-Operating" -> Other Income/(Expense), Non-Operating | D50: =IF(COUNT(M50:AB50)>0,MEDIAN(M50:AB50),"") -> -125 | E50: =IF(COUNT(M50:AB50)>0,AVERAGE(M50:AB50),"") -> -523 | F50: =IF(COUNT(M50:AB50)>0,MIN(M50:AB50),"") -> -2809 | G50: =IF(COUNT(M50:AB50)>0,MAX(M50:AB50),"") -> 1365 | H50: =IF(COUNT(M50:AB50)>0,QUARTILE(M50:AB50,1),"") -> -1467 | I50: =IF(COUNT(M50:AB50)>0,QUARTILE(M50:AB50,3),"") -> 620 | J50: =IF(COUNT(M50:AB50)>1,STDEV(M50:AB50),"") -> 2115.2711 | K50: =IF(COUNT(M50:AB50)>1,STDEV(M50:AB50)/AVERAGE(M50:AB50),"") -> -4.0444955 | Z50: -125 | AA50: -2809 | AB50: 1365
A51: 1 | C51: =" Total Non-Operating Income/(Expenses), Total" -> Total Non-Operating Income/(Expenses), Total | D51: =IF(COUNT(M51:AB51)>0,MEDIAN(M51:AB51),"") -> -6122.5 | E51: =IF(COUNT(M51:AB51)>0,AVERAGE(M51:AB51),"") -> -10916.143 | F51: =IF(COUNT(M51:AB51)>0,MIN(M51:AB51),"") -> -50514 | G51: =IF(COUNT(M51:AB51)>0,MAX(M51:AB51),"") -> 0 | H51: =IF(COUNT(M51:AB51)>0,QUARTILE(M51:AB51,1),"") -> -12645.5 | I51: =IF(COUNT(M51:AB51)>0,QUARTILE(M51:AB51,3),"") -> -317.25 | J51: =IF(COUNT(M51:AB51)>1,STDEV(M51:AB51),"") -> 14582.516 | K51: =IF(COUNT(M51:AB51)>1,STDEV(M51:AB51)/AVERAGE(M51:AB51),"") -> -1.335867 | M51: 0 | N51: 0 | Q51: -600 | R51: -3883 | S51: -12803 | T51: -4560 | U51: -50514 | V51: -136 | W51: -223 | X51: -7793 | Y51: -7685 | Z51: -12173 | AA51: -21924 | AB51: -30532
A52: 1 | C52: ="Pretax Income" -> Pretax Income | D52: =IF(COUNT(M52:AB52)>0,MEDIAN(M52:AB52),"") -> -8750 | E52: =IF(COUNT(M52:AB52)>0,AVERAGE(M52:AB52),"") -> -5705 | F52: =IF(COUNT(M52:AB52)>0,MIN(M52:AB52),"") -> -61178 | G52: =IF(COUNT(M52:AB52)>0,MAX(M52:AB52),"") -> 41504 | H52: =IF(COUNT(M52:AB52)>0,QUARTILE(M52:AB52,1),"") -> -14729.75 | I52: =IF(COUNT(M52:AB52)>0,QUARTILE(M52:AB52,3),"") -> 8594 | J52: =IF(COUNT(M52:AB52)>1,STDEV(M52:AB52),"") -> 24827.042 | K52: =IF(COUNT(M52:AB52)>1,STDEV(M52:AB52)/AVERAGE(M52:AB52),"") -> -4.3518041 | Q52: -358 | R52: 10688 | S52: -20471 | T52: -19598 | U52: -61178 | V52: -13107 | W52: -7104 | X52: -12106 | Y52: 7896 | Z52: 15770 | AA52: -10396 | AB52: 41504
A53: 1 | C53: ="Provision for Income Tax" -> Provision for Income Tax | D53: =IF(COUNT(M53:AB53)>0,MEDIAN(M53:AB53),"") -> 110 | E53: =IF(COUNT(M53:AB53)>0,AVERAGE(M53:AB53),"") -> -2652.5833 | F53: =IF(COUNT(M53:AB53)>0,MIN(M53:AB53),"") -> -37667 | G53: =IF(COUNT(M53:AB53)>0,MAX(M53:AB53),"") -> 6747 | H53: =IF(COUNT(M53:AB53)>0,QUARTILE(M53:AB53,1),"") -> -503.75 | I53: =IF(COUNT(M53:AB53)>0,QUARTILE(M53:AB53,3),"") -> 313.5 | J53: =IF(COUNT(M53:AB53)>1,STDEV(M53:AB53),"") -> 11236.261 | K53: =IF(COUNT(M53:AB53)>1,STDEV(M53:AB53)/AVERAGE(M53:AB53),"") -> -4.2359691 | Q53: 0 | R53: 1483 | S53: 5 | T53: 262 | U53: 244 | V53: -905 | W53: 215 | X53: -2313 | Y53: 468 | Z53: -37667 | AA53: 6747 | AB53: -370
A54: 1 | C54: ="Net Income from Continuing Operations" -> Net Income from Continuing Operations | D54: =IF(COUNT(M54:AB54)>0,MEDIAN(M54:AB54),"") -> -10628.129 | E54: =IF(COUNT(M54:AB54)>0,AVERAGE(M54:AB54),"") -> -5585.2493 | F54: =IF(COUNT(M54:AB54)>0,MIN(M54:AB54),"") -> -61422 | G54: =IF(COUNT(M54:AB54)>0,MAX(M54:AB54),"") -> 53437 | H54: =IF(COUNT(M54:AB54)>0,QUARTILE(M54:AB54,1),"") -> -17822.25 | I54: =IF(COUNT(M54:AB54)>0,QUARTILE(M54:AB54,3),"") -> 1588.5 | J54: =IF(COUNT(M54:AB54)>1,STDEV(M54:AB54),"") -> 26099.627 | K54: =IF(COUNT(M54:AB54)>1,STDEV(M54:AB54)/AVERAGE(M54:AB54),"") -> -4.6729564 | M54: -12680 | N54: -20947 | O54: -11463.257 | P54: -7644.732 | Q54: -358 | R54: 9205 | S54: -20476 | T54: -19860 | U54: -61422 | V54: -12202 | W54: -7319 | X54: -9793 | Y54: 7428 | Z54: 53437 | AA54: -17143 | AB54: 41874
A55: 1 | C55: ="Net Income after Extraordinary Items and Discontinued Operations" -> Net Income after Extraordinary Items and Discontinued Operations | D55: =IF(COUNT(M55:AB55)>0,MEDIAN(M55:AB55),"") -> -9793 | E55: =IF(COUNT(M55:AB55)>0,AVERAGE(M55:AB55),"") -> -3297.3636 | F55: =IF(COUNT(M55:AB55)>0,MIN(M55:AB55),"") -> -61422 | G55: =IF(COUNT(M55:AB55)>0,MAX(M55:AB55),"") -> 53437 | H55: =IF(COUNT(M55:AB55)>0,QUARTILE(M55:AB55,1),"") -> -18501.5 | I55: =IF(COUNT(M55:AB55)>0,QUARTILE(M55:AB55,3),"") -> 8316.5 | J55: =IF(COUNT(M55:AB55)>1,STDEV(M55:AB55),"") -> 31317.477 | K55: =IF(COUNT(M55:AB55)>1,STDEV(M55:AB55)/AVERAGE(M55:AB55),"") -> -9.4977322 | R55: 9205 | S55: -20476 | T55: -19860 | U55: -61422 | V55: -12202 | W55: -7319 | X55: -9793 | Y55: 7428 | Z55: 53437 | AA55: -17143 | AB55: 41874
A56: 1 | C56: ="Non-Controlling/Minority Interests" -> Non-Controlling/Minority Interests | D56: =IF(COUNT(M56:AB56)>0,MEDIAN(M56:AB56),"") -> -946 | E56: =IF(COUNT(M56:AB56)>0,AVERAGE(M56:AB56),"") -> -711 | F56: =IF(COUNT(M56:AB56)>0,MIN(M56:AB56),"") -> -1187 | G56: =IF(COUNT(M56:AB56)>0,MAX(M56:AB56),"") -> 0 | H56: =IF(COUNT(M56:AB56)>0,QUARTILE(M56:AB56,1),"") -> -1066.5 | I56: =IF(COUNT(M56:AB56)>0,QUARTILE(M56:AB56,3),"") -> -473 | J56: =IF(COUNT(M56:AB56)>1,STDEV(M56:AB56),"") -> 627.4241 | K56: =IF(COUNT(M56:AB56)>1,STDEV(M56:AB56)/AVERAGE(M56:AB56),"") -> -0.88245302 | Z56: 0 | AA56: -1187 | AB56: -946
A57: 1 | C57: ="Net Income after Non-Controlling/Minority Interests" -> Net Income after Non-Controlling/Minority Interests | D57: =IF(COUNT(M57:AB57)>0,MEDIAN(M57:AB57),"") -> -10628.129 | E57: =IF(COUNT(M57:AB57)>0,AVERAGE(M57:AB57),"") -> -5451.9368 | F57: =IF(COUNT(M57:AB57)>0,MIN(M57:AB57),"") -> -61422 | G57: =IF(COUNT(M57:AB57)>0,MAX(M57:AB57),"") -> 53437 | H57: =IF(COUNT(M57:AB57)>0,QUARTILE(M57:AB57,1),"") -> -16932 | I57: =IF(COUNT(M57:AB57)>0,QUARTILE(M57:AB57,3),"") -> 1588.5 | J57: =IF(COUNT(M57:AB57)>1,STDEV(M57:AB57),"") -> 26181.714 | K57: =IF(COUNT(M57:AB57)>1,STDEV(M57:AB57)/AVERAGE(M57:AB57),"") -> -4.8022775 | M57: -12680 | N57: -20947 | O57: -11463.257 | P57: -7644.732 | Q57: -358 | R57: 9205 | S57: -20476 | T57: -19860 | U57: -61422 | V57: -12202 | W57: -7319 | X57: -9793 | Y57: 7428 | Z57: 53437 | AA57: -15956 | AB57: 42820
A58: 1 | C58: ="Preferred/Other Stock Distribution" -> Preferred/Other Stock Distribution | D58: =IF(COUNT(M58:AB58)>0,MEDIAN(M58:AB58),"") -> 1298.5 | E58: =IF(COUNT(M58:AB58)>0,AVERAGE(M58:AB58),"") -> 2735.75 | F58: =IF(COUNT(M58:AB58)>0,MIN(M58:AB58),"") -> 0 | G58: =IF(COUNT(M58:AB58)>0,MAX(M58:AB58),"") -> 8346 | H58: =IF(COUNT(M58:AB58)>0,QUARTILE(M58:AB58,1),"") -> 0 | I58: =IF(COUNT(M58:AB58)>0,QUARTILE(M58:AB58,3),"") -> 4034.25 | J58: =IF(COUNT(M58:AB58)>1,STDEV(M58:AB58),"") -> 3935.4294 | K58: =IF(COUNT(M58:AB58)>1,STDEV(M58:AB58)/AVERAGE(M58:AB58),"") -> 1.4385194 | Q58: 8346 | R58: 2597 | S58: 0 | T58: 0
A59: 1 | C59: ="Net Income Available to Common Stockholders" -> Net Income Available to Common Stockholders | D59: =IF(COUNT(M59:AB59)>0,MEDIAN(M59:AB59),"") -> -10628.129 | E59: =IF(COUNT(M59:AB59)>0,AVERAGE(M59:AB59),"") -> -6135.8743 | F59: =IF(COUNT(M59:AB59)>0,MIN(M59:AB59),"") -> -61422 | G59: =IF(COUNT(M59:AB59)>0,MAX(M59:AB59),"") -> 53437 | H59: =IF(COUNT(M59:AB59)>0,QUARTILE(M59:AB59,1),"") -> -16932 | I59: =IF(COUNT(M59:AB59)>0,QUARTILE(M59:AB59,3),"") -> -3837.25 | J59: =IF(COUNT(M59:AB59)>1,STDEV(M59:AB59),"") -> 26064.013 | K59: =IF(COUNT(M59:AB59)>1,STDEV(M59:AB59)/AVERAGE(M59:AB59),"") -> -4.2478075 | M59: -12680 | N59: -20947 | O59: -11463.257 | P59: -7644.732 | Q59: -8704 | R59: 6608 | S59: -20476 | T59: -19860 | U59: -61422 | V59: -12202 | W59: -7319 | X59: -9793 | Y59: 7428 | Z59: 53437 | AA59: -15956 | AB59: 42820
A60: 1 | C60: ="Diluted Net Income Available to Common Stockholders" -> Diluted Net Income Available to Common Stockholders | D60: =IF(COUNT(M60:AB60)>0,MEDIAN(M60:AB60),"") -> -10628.129 | E60: =IF(COUNT(M60:AB60)>0,AVERAGE(M60:AB60),"") -> -6135.8743 | F60: =IF(COUNT(M60:AB60)>0,MIN(M60:AB60),"") -> -61422 | G60: =IF(COUNT(M60:AB60)>0,MAX(M60:AB60),"") -> 53437 | H60: =IF(COUNT(M60:AB60)>0,QUARTILE(M60:AB60,1),"") -> -16932 | I60: =IF(COUNT(M60:AB60)>0,QUARTILE(M60:AB60,3),"") -> -3837.25 | J60: =IF(COUNT(M60:AB60)>1,STDEV(M60:AB60),"") -> 26064.013 | K60: =IF(COUNT(M60:AB60)>1,STDEV(M60:AB60)/AVERAGE(M60:AB60),"") -> -4.2478075 | M60: -12680 | N60: -20947 | O60: -11463.257 | P60: -7644.732 | Q60: -8704 | R60: 6608 | S60: -20476 | T60: -19860 | U60: -61422 | V60: -12202 | W60: -7319 | X60: -9793 | Y60: 7428 | Z60: 53437 | AA60: -15956 | AB60: 42820
A61: 1 | C61: =IF(SUBTOTAL(109,A62)=A62,"Basic EPS","Basic EPS") -> Basic EPS | D61: =IF(COUNT(M61:AB61)>0,MEDIAN(M61:AB61),"") -> #VALUE! | E61: =IF(COUNT(M61:AB61)>0,AVERAGE(M61:AB61),"") -> #VALUE! | F61: =IF(COUNT(M61:AB61)>0,MIN(M61:AB61),"") -> #VALUE! | G61: =IF(COUNT(M61:AB61)>0,MAX(M61:AB61),"") -> #VALUE! | H61: =IF(COUNT(M61:AB61)>0,QUARTILE(M61:AB61,1),"") -> #VALUE! | I61: =IF(COUNT(M61:AB61)>0,QUARTILE(M61:AB61,3),"") -> #VALUE! | J61: =IF(COUNT(M61:AB61)>1,STDEV(M61:AB61),"") | K61: =IF(COUNT(M61:AB61)>1,STDEV(M61:AB61)/AVERAGE(M61:AB61),"") | M61: =IF(SUBTOTAL(109,#REF!)=#REF!,"",-5.23) -> #VALUE! | N61: =IF(SUBTOTAL(109,#REF!)=#REF!,"",-7.33) -> #VALUE! | O61: =IF(SUBTOTAL(109,#REF!)=#REF!,"",-4.04) -> #VALUE! | P61: =IF(SUBTOTAL(109,#REF!)=#REF!,"",-2.63) -> #VALUE! | Q61: =IF(SUBTOTAL(109,#REF!)=#REF!,"",-2.89) -> #VALUE! | R61: =IF(SUBTOTAL(109,#REF!)=#REF!,"",0.36) -> #VALUE! | S61: =IF(SUBTOTAL(109,#REF!)=#REF!,"",-0.86) -> #VALUE! | T61: =IF(SUBTOTAL(109,#REF!)=#REF!,"",-0.82) -> #VALUE! | U61: =IF(SUBTOTAL(109,B62)=B62,"",-2.51) | V61: =IF(SUBTOTAL(109,D62)=D62,"",-0.49) | W61: =IF(SUBTOTAL(109,F62)=F62,"",-0.29) | X61: =IF(SUBTOTAL(109,H62)=H62,"",-0.37) | Y61: =IF(SUBTOTAL(109,J62)=J62,"",0.27) | Z61: =IF(SUBTOTAL(109,L62)=L62,"",1.91) -> 1.91 | AA61: =IF(SUBTOTAL(109,N62)=N62,"",-0.53) | AB61: =IF(SUBTOTAL(109,P62)=P62,"",1.31)
A62: 1 | C62: =" Basic EPS from Continuing Operations" -> Basic EPS from Continuing Operations | D62: =IF(COUNT(M62:AB62)>0,MEDIAN(M62:AB62),"") -> -0.675 | E62: =IF(COUNT(M62:AB62)>0,AVERAGE(M62:AB62),"") -> -1.50875 | F62: =IF(COUNT(M62:AB62)>0,MIN(M62:AB62),"") -> -7.33 | G62: =IF(COUNT(M62:AB62)>0,MAX(M62:AB62),"") -> 1.91 | H62: =IF(COUNT(M62:AB62)>0,QUARTILE(M62:AB62,1),"") -> -2.695 | I62: =IF(COUNT(M62:AB62)>0,QUARTILE(M62:AB62,3),"") -> -0.15 | J62: =IF(COUNT(M62:AB62)>1,STDEV(M62:AB62),"") -> 2.4531881 | K62: =IF(COUNT(M62:AB62)>1,STDEV(M62:AB62)/AVERAGE(M62:AB62),"") -> -1.6259739 | M62: -5.23 | N62: -7.33 | O62: -4.04 | P62: -2.63 | Q62: -2.89 | R62: 0.36 | S62: -0.86 | T62: -0.82 | U62: -2.51 | V62: -0.49 | W62: -0.29 | X62: -0.37 | Y62: 0.27 | Z62: 1.91 | AA62: -0.53 | AB62: 1.31
A63: 1 | C63: =" Basic EPS from Discontinued Operations" -> Basic EPS from Discontinued Operations | D63: =IF(COUNT(M63:AB63)>0,MEDIAN(M63:AB63),"") -> 0 | E63: =IF(COUNT(M63:AB63)>0,AVERAGE(M63:AB63),"") -> 0 | F63: =IF(COUNT(M63:AB63)>0,MIN(M63:AB63),"") -> 0 | G63: =IF(COUNT(M63:AB63)>0,MAX(M63:AB63),"") -> 0 | H63: =IF(COUNT(M63:AB63)>0,QUARTILE(M63:AB63,1),"") -> 0 | I63: =IF(COUNT(M63:AB63)>0,QUARTILE(M63:AB63,3),"") -> 0 | J63: =IF(COUNT(M63:AB63)>1,STDEV(M63:AB63),"") -> 0 | K63: =IF(COUNT(M63:AB63)>1,STDEV(M63:AB63)/AVERAGE(M63:AB63),"") -> #DIV/0! | M63: 0 | N63: 0 | O63: 0 | P63: 0 | Q63: 0 | R63: 0 | S63: 0 | T63: 0 | U63: 0 | V63: 0 | W63: 0 | X63: 0 | Y63: 0 | Z63: 0 | AA63: 0
A64: 1 | C64: =" Total Basic EPS" -> Total Basic EPS | D64: =IF(COUNT(M64:AB64)>0,MEDIAN(M64:AB64),"") -> -0.675 | E64: =IF(COUNT(M64:AB64)>0,AVERAGE(M64:AB64),"") -> -1.50875 | F64: =IF(COUNT(M64:AB64)>0,MIN(M64:AB64),"") -> -7.33 | G64: =IF(COUNT(M64:AB64)>0,MAX(M64:AB64),"") -> 1.91 | H64: =IF(COUNT(M64:AB64)>0,QUARTILE(M64:AB64,1),"") -> -2.695 | I64: =IF(COUNT(M64:AB64)>0,QUARTILE(M64:AB64,3),"") -> -0.15 | J64: =IF(COUNT(M64:AB64)>1,STDEV(M64:AB64),"") -> 2.4531881 | K64: =IF(COUNT(M64:AB64)>1,STDEV(M64:AB64)/AVERAGE(M64:AB64),"") -> -1.6259739 | M64: -5.23 | N64: -7.33 | O64: -4.04 | P64: -2.63 | Q64: -2.89 | R64: 0.36 | S64: -0.86 | T64: -0.82 | U64: -2.51 | V64: -0.49 | W64: -0.29 | X64: -0.37 | Y64: 0.27 | Z64: 1.91 | AA64: -0.53 | AB64: 1.31
A65: 1 | C65: =IF(SUBTOTAL(109,A66)=A66,"Diluted EPS","Diluted EPS") -> Diluted EPS | D65: =IF(COUNT(M65:AB65)>0,MEDIAN(M65:AB65),"") -> #VALUE! | E65: =IF(COUNT(M65:AB65)>0,AVERAGE(M65:AB65),"") -> #VALUE! | F65: =IF(COUNT(M65:AB65)>0,MIN(M65:AB65),"") -> #VALUE! | G65: =IF(COUNT(M65:AB65)>0,MAX(M65:AB65),"") -> #VALUE! | H65: =IF(COUNT(M65:AB65)>0,QUARTILE(M65:AB65,1),"") -> #VALUE! | I65: =IF(COUNT(M65:AB65)>0,QUARTILE(M65:AB65,3),"") -> #VALUE! | J65: =IF(COUNT(M65:AB65)>1,STDEV(M65:AB65),"") | K65: =IF(COUNT(M65:AB65)>1,STDEV(M65:AB65)/AVERAGE(M65:AB65),"") | M65: =IF(SUBTOTAL(109,#REF!)=#REF!,"",-5.233027) -> #VALUE! | N65: =IF(SUBTOTAL(109,#REF!)=#REF!,"",-7.334199) -> #VALUE! | O65: =IF(SUBTOTAL(109,#REF!)=#REF!,"",-4.04) -> #VALUE! | P65: =IF(SUBTOTAL(109,#REF!)=#REF!,"",-2.63) -> #VALUE! | Q65: =IF(SUBTOTAL(109,#REF!)=#REF!,"",-2.89) -> #VALUE! | R65: =IF(SUBTOTAL(109,#REF!)=#REF!,"",0.29) -> #VALUE! | S65: =IF(SUBTOTAL(109,#REF!)=#REF!,"",-0.86) -> #VALUE! | T65: =IF(SUBTOTAL(109,#REF!)=#REF!,"",-0.82) -> #VALUE! | U65: =IF(SUBTOTAL(109,B66)=B66,"",-2.51) | V65: =IF(SUBTOTAL(109,D66)=D66,"",-0.49) | W65: =IF(SUBTOTAL(109,F66)=F66,"",-0.29) | X65: =IF(SUBTOTAL(109,H66)=H66,"",-0.37) | Y65: =IF(SUBTOTAL(109,J66)=J66,"",0.26) | Z65: =IF(SUBTOTAL(109,L66)=L66,"",1.75) -> 1.75 | AA65: =IF(SUBTOTAL(109,N66)=N66,"",-0.53) | AB65: =IF(SUBTOTAL(109,P66)=P66,"",1.2)
A66: 1 | C66: =" Diluted EPS from Continuing Operations" -> Diluted EPS from Continuing Operations | D66: =IF(COUNT(M66:AB66)>0,MEDIAN(M66:AB66),"") -> -0.675 | E66: =IF(COUNT(M66:AB66)>0,AVERAGE(M66:AB66),"") -> -1.5310766 | F66: =IF(COUNT(M66:AB66)>0,MIN(M66:AB66),"") -> -7.334199 | G66: =IF(COUNT(M66:AB66)>0,MAX(M66:AB66),"") -> 1.75 | H66: =IF(COUNT(M66:AB66)>0,QUARTILE(M66:AB66,1),"") -> -2.695 | I66: =IF(COUNT(M66:AB66)>0,QUARTILE(M66:AB66,3),"") -> -0.1525 | J66: =IF(COUNT(M66:AB66)>1,STDEV(M66:AB66),"") -> 2.4271632 | K66: =IF(COUNT(M66:AB66)>1,STDEV(M66:AB66)/AVERAGE(M66:AB66),"") -> -1.5852656 | M66: -5.233027 | N66: -7.334199 | O66: -4.04 | P66: -2.63 | Q66: -2.89 | R66: 0.29 | S66: -0.86 | T66: -0.82 | U66: -2.51 | V66: -0.49 | W66: -0.29 | X66: -0.37 | Y66: 0.26 | Z66: 1.75 | AA66: -0.53 | AB66: 1.2
A67: 1 | C67: =" Diluted EPS from Discontinued Operations" -> Diluted EPS from Discontinued Operations | D67: =IF(COUNT(M67:AB67)>0,MEDIAN(M67:AB67),"") -> 0 | E67: =IF(COUNT(M67:AB67)>0,AVERAGE(M67:AB67),"") -> 0 | F67: =IF(COUNT(M67:AB67)>0,MIN(M67:AB67),"") -> 0 | G67: =IF(COUNT(M67:AB67)>0,MAX(M67:AB67),"") -> 0 | H67: =IF(COUNT(M67:AB67)>0,QUARTILE(M67:AB67,1),"") -> 0 | I67: =IF(COUNT(M67:AB67)>0,QUARTILE(M67:AB67,3),"") -> 0 | J67: =IF(COUNT(M67:AB67)>1,STDEV(M67:AB67),"") -> 0 | K67: =IF(COUNT(M67:AB67)>1,STDEV(M67:AB67)/AVERAGE(M67:AB67),"") -> #DIV/0! | M67: 0 | N67: 0 | O67: 0 | P67: 0 | Q67: 0 | R67: 0 | S67: 0 | T67: 0 | U67: 0 | V67: 0 | W67: 0 | X67: 0 | Y67: 0 | Z67: 0 | AA67: 0
A68: 1 | C68: =" Total Diluted EPS" -> Total Diluted EPS | D68: =IF(COUNT(M68:AB68)>0,MEDIAN(M68:AB68),"") -> -0.675 | E68: =IF(COUNT(M68:AB68)>0,AVERAGE(M68:AB68),"") -> -1.5310766 | F68: =IF(COUNT(M68:AB68)>0,MIN(M68:AB68),"") -> -7.334199 | G68: =IF(COUNT(M68:AB68)>0,MAX(M68:AB68),"") -> 1.75 | H68: =IF(COUNT(M68:AB68)>0,QUARTILE(M68:AB68,1),"") -> -2.695 | I68: =IF(COUNT(M68:AB68)>0,QUARTILE(M68:AB68,3),"") -> -0.1525 | J68: =IF(COUNT(M68:AB68)>1,STDEV(M68:AB68),"") -> 2.4271632 | K68: =IF(COUNT(M68:AB68)>1,STDEV(M68:AB68)/AVERAGE(M68:AB68),"") -> -1.5852656 | M68: -5.233027 | N68: -7.334199 | O68: -4.04 | P68: -2.63 | Q68: -2.89 | R68: 0.29 | S68: -0.86 | T68: -0.82 | U68: -2.51 | V68: -0.49 | W68: -0.29 | X68: -0.37 | Y68: 0.26 | Z68: 1.75 | AA68: -0.53 | AB68: 1.2
A69: 1 | C69: ="Basic Weighted Average Shares Outstanding" -> Basic Weighted Average Shares Outstanding | D69: =IF(COUNT(M69:AB69)>0,MEDIAN(M69:AB69),"") -> 24267202 | E69: =IF(COUNT(M69:AB69)>0,AVERAGE(M69:AB69),"") -> 18734017 | F69: =IF(COUNT(M69:AB69)>0,MIN(M69:AB69),"") -> 2423072 | G69: =IF(COUNT(M69:AB69)>0,MAX(M69:AB69),"") -> 32709000 | H69: =IF(COUNT(M69:AB69)>0,QUARTILE(M69:AB69,1),"") -> 2985864.2 | I69: =IF(COUNT(M69:AB69)>0,QUARTILE(M69:AB69,3),"") -> 26612470 | J69: =IF(COUNT(M69:AB69)>1,STDEV(M69:AB69),"") -> 11504387 | K69: =IF(COUNT(M69:AB69)>1,STDEV(M69:AB69)/AVERAGE(M69:AB69),"") -> 0.6140908 | M69: 2423072 | N69: 2856072 | O69: 2837772 | P69: 2908360 | Q69: 3011699 | R69: 18348594 | S69: 23771368 | T69: 24109085 | U69: 24425318 | V69: 24933656 | W69: 25543646 | X69: 26444626 | Y69: 27116000 | Z69: 27920000 | AA69: 30386000 | AB69: 32709000
A70: 1 | C70: ="Diluted Weighted Average Shares Outstanding" -> Diluted Weighted Average Shares Outstanding | D70: =IF(COUNT(M70:AB70)>0,MEDIAN(M70:AB70),"") -> 24267202 | E70: =IF(COUNT(M70:AB70)>0,AVERAGE(M70:AB70),"") -> 19479405 | F70: =IF(COUNT(M70:AB70)>0,MIN(M70:AB70),"") -> 2423072 | G70: =IF(COUNT(M70:AB70)>0,MAX(M70:AB70),"") -> 35783000 | H70: =IF(COUNT(M70:AB70)>0,QUARTILE(M70:AB70,1),"") -> 2985864.2 | I70: =IF(COUNT(M70:AB70)>0,QUARTILE(M70:AB70,3),"") -> 27105720 | J70: =IF(COUNT(M70:AB70)>1,STDEV(M70:AB70),"") -> 12049240 | K70: =IF(COUNT(M70:AB70)>1,STDEV(M70:AB70)/AVERAGE(M70:AB70),"") -> 0.61856303 | M70: 2423072 | N70: 2856072 | O70: 2837772 | P70: 2908360 | Q70: 3011699 | R70: 22658813 | S70: 23771368 | T70: 24109085 | U70: 24425318 | V70: 24933656 | W70: 25543646 | X70: 26444626 | Y70: 29089000 | Z70: 30489000 | AA70: 30386000 | AB70: 35783000
A71: 1 | C71: ="Income Statement Supplemental Section" -> Income Statement Supplemental Section
A72: 1 | C72: =" Reported Normalized and Operating Income/Expense Supplemental Section" -> Reported Normalized and Operating Income/Expense Supplemental Section
A73: 1 | C73: =" Reported Total Revenue" -> Reported Total Revenue | D73: =IF(COUNT(M73:AB73)>0,MEDIAN(M73:AB73),"") -> 120189 | E73: =IF(COUNT(M73:AB73)>0,AVERAGE(M73:AB73),"") -> 134293.35 | F73: =IF(COUNT(M73:AB73)>0,MIN(M73:AB73),"") -> 7923 | G73: =IF(COUNT(M73:AB73)>0,MAX(M73:AB73),"") -> 399472 | H73: =IF(COUNT(M73:AB73)>0,QUARTILE(M73:AB73,1),"") -> 63224.7 | I73: =IF(COUNT(M73:AB73)>0,QUARTILE(M73:AB73,3),"") -> 169561.75 | J73: =IF(COUNT(M73:AB73)>1,STDEV(M73:AB73),"") -> 102080.37 | K73: =IF(COUNT(M73:AB73)>1,STDEV(M73:AB73)/AVERAGE(M73:AB73),"") -> 0.76012978 | M73: 7923 | N73: 22231 | O73: 30937.728 | P73: 33922.801 | Q73: 72992 | R73: 120454 | S73: 140621 | T73: 119924 | U73: 119022 | V73: 111494 | W73: 129501 | X73: 166578 | Y73: 178513 | Z73: 208332 | AA73: 286776 | AB73: 399472
A74: 1 | C74: =" Reported Operating Expense" -> Reported Operating Expense | D74: =IF(COUNT(M74:AB74)>0,MEDIAN(M74:AB74),"") -> -92124 | E74: =IF(COUNT(M74:AB74)>0,AVERAGE(M74:AB74),"") -> -91078.115 | F74: =IF(COUNT(M74:AB74)>0,MIN(M74:AB74),"") -> -200672 | G74: =IF(COUNT(M74:AB74)>0,MAX(M74:AB74),"") -> -14985 | H74: =IF(COUNT(M74:AB74)>0,QUARTILE(M74:AB74,1),"") -> -112010 | I74: =IF(COUNT(M74:AB74)>0,QUARTILE(M74:AB74,3),"") -> -59037 | J74: =IF(COUNT(M74:AB74)>1,STDEV(M74:AB74),"") -> 52350.384 | K74: =IF(COUNT(M74:AB74)>1,STDEV(M74:AB74)/AVERAGE(M74:AB74),"") -> -0.57478554 | M74: -14985 | N74: -25359 | P74: -25709.719 | Q74: -47224 | R74: -70850 | S74: -112582 | T74: -92124 | U74: -131268 | V74: -79060 | W74: -85951 | X74: -97777 | Y74: -97039 | Z74: -111438 | AA74: -174133 | AB74: -200672
A75: 1 | C75: =" Reported Total Operating Profit/Loss" -> Reported Total Operating Profit/Loss | D75: =IF(COUNT(M75:AB75)>0,MEDIAN(M75:AB75),"") -> -4487.916 | E75: =IF(COUNT(M75:AB75)>0,AVERAGE(M75:AB75),"") -> -5187.6611 | F75: =IF(COUNT(M75:AB75)>0,MIN(M75:AB75),"") -> -61322 | G75: =IF(COUNT(M75:AB75)>0,MAX(M75:AB75),"") -> 49814 | H75: =IF(COUNT(M75:AB75)>0,QUARTILE(M75:AB75,1),"") -> -16425.5 | I75: =IF(COUNT(M75:AB75)>0,QUARTILE(M75:AB75,3),"") -> 4880 | J75: =IF(COUNT(M75:AB75)>1,STDEV(M75:AB75),"") -> 23888.998 | K75: =IF(COUNT(M75:AB75)>1,STDEV(M75:AB75)/AVERAGE(M75:AB75),"") -> -4.6049651 | M75: -12726 | N75: -20099 | P75: -4487.916 | Q75: 242 | R75: 9691 | S75: -20649 | T75: -19692 | U75: -61322 | V75: -13159 | W75: -6881 | X75: -4313 | Y75: 9518 | Z75: 18012 | AA75: -1763 | AB75: 49814
A76: 1 | C76: =" Reported Normalized Income" -> Reported Normalized Income | D76: =IF(COUNT(M76:AB76)>0,MEDIAN(M76:AB76),"") -> 2688 | E76: =IF(COUNT(M76:AB76)>0,AVERAGE(M76:AB76),"") -> 8687.5714 | F76: =IF(COUNT(M76:AB76)>0,MIN(M76:AB76),"") -> -7895 | G76: =IF(COUNT(M76:AB76)>0,MAX(M76:AB76),"") -> 32077 | H76: =IF(COUNT(M76:AB76)>0,QUARTILE(M76:AB76,1),"") -> -2683.5 | I76: =IF(COUNT(M76:AB76)>0,QUARTILE(M76:AB76,3),"") -> 19655 | J76: =IF(COUNT(M76:AB76)>1,STDEV(M76:AB76),"") -> 15649.941 | K76: =IF(COUNT(M76:AB76)>1,STDEV(M76:AB76)/AVERAGE(M76:AB76),"") -> 1.8014173 | U76: -7895 | V76: -6945 | W76: 1578 | X76: 2688 | Y76: 13491 | Z76: 25819 | AA76: 32077
A77: 1 | C77: =" Reported Effective Tax Rate" -> Reported Effective Tax Rate | D77: =IF(COUNT(M77:AB77)>0,MEDIAN(M77:AB77),"") -> -0.0134 | E77: =IF(COUNT(M77:AB77)>0,AVERAGE(M77:AB77),"") -> -0.32148889 | F77: =IF(COUNT(M77:AB77)>0,MIN(M77:AB77),"") -> -2.389 | G77: =IF(COUNT(M77:AB77)>0,MAX(M77:AB77),"") -> 0.191 | H77: =IF(COUNT(M77:AB77)>0,QUARTILE(M77:AB77,1),"") -> -0.059 | I77: =IF(COUNT(M77:AB77)>0,QUARTILE(M77:AB77,3),"") -> -0.004 | J77: =IF(COUNT(M77:AB77)>1,STDEV(M77:AB77),"") -> 0.80964696 | K77: =IF(COUNT(M77:AB77)>1,STDEV(M77:AB77)/AVERAGE(M77:AB77),"") -> -2.5184291 | T77: -0.0134 | U77: -0.004 | V77: 0.069 | W77: -0.03 | X77: 0.191 | Y77: -0.059 | Z77: -2.389 | AA77: -0.649 | AB77: -0.009
A78: 1 | C78: =" Reported Normalized Operating Profit" -> Reported Normalized Operating Profit | D78: =IF(COUNT(M78:AB78)>0,MEDIAN(M78:AB78),"") -> 3895 | E78: =IF(COUNT(M78:AB78)>0,AVERAGE(M78:AB78),"") -> 10279.143 | F78: =IF(COUNT(M78:AB78)>0,MIN(M78:AB78),"") -> -7795 | G78: =IF(COUNT(M78:AB78)>0,MAX(M78:AB78),"") -> 37188 | H78: =IF(COUNT(M78:AB78)>0,QUARTILE(M78:AB78,1),"") -> -2431.5 | I78: =IF(COUNT(M78:AB78)>0,QUARTILE(M78:AB78,3),"") -> 21764.5 | J78: =IF(COUNT(M78:AB78)>1,STDEV(M78:AB78),"") -> 17294.017 | K78: =IF(COUNT(M78:AB78)>1,STDEV(M78:AB78)/AVERAGE(M78:AB78),"") -> 1.6824376 | U78: -7795 | V78: -6879 | W78: 2016 | X78: 3895 | Y78: 15581 | Z78: 27948 | AA78: 37188
A79: 1 | C79: =" Reported Normalized EBITDA" -> Reported Normalized EBITDA | D79: =IF(COUNT(M79:AB79)>0,MEDIAN(M79:AB79),"") -> 20482 | E79: =IF(COUNT(M79:AB79)>0,AVERAGE(M79:AB79),"") -> 27452.143 | F79: =IF(COUNT(M79:AB79)>0,MIN(M79:AB79),"") -> 3637 | G79: =IF(COUNT(M79:AB79)>0,MAX(M79:AB79),"") -> 65253 | H79: =IF(COUNT(M79:AB79)>0,QUARTILE(M79:AB79,1),"") -> 11175 | I79: =IF(COUNT(M79:AB79)>0,QUARTILE(M79:AB79,3),"") -> 40221.5 | J79: =IF(COUNT(M79:AB79)>1,STDEV(M79:AB79),"") -> 22622.806 | K79: =IF(COUNT(M79:AB79)>1,STDEV(M79:AB79)/AVERAGE(M79:AB79),"") -> 0.82408161 | U79: 3637 | V79: 5413 | W79: 16937 | X79: 20482 | Y79: 33021 | Z79: 47422 | AA79: 65253
A80: 1 | C80: ="Profitability Metrics" -> Profitability Metrics
A81: 1 | C81: =" Earnings Before Interest, Tax, Depreciation, & Amortization (EBITDA)" -> Earnings Before Interest, Tax, Depreciation, & Amortization (EBITDA) | D81: =IF(COUNT(M81:AB81)>0,MEDIAN(M81:AB81),"") -> 6837 | E81: =IF(COUNT(M81:AB81)>0,AVERAGE(M81:AB81),"") -> 11224.25 | F81: =IF(COUNT(M81:AB81)>0,MIN(M81:AB81),"") -> -49046 | G81: =IF(COUNT(M81:AB81)>0,MAX(M81:AB81),"") -> 91101 | H81: =IF(COUNT(M81:AB81)>0,QUARTILE(M81:AB81,1),"") -> -4702 | I81: =IF(COUNT(M81:AB81)>0,QUARTILE(M81:AB81,3),"") -> 22204 | J81: =IF(COUNT(M81:AB81)>1,STDEV(M81:AB81),"") -> 32815.776 | K81: =IF(COUNT(M81:AB81)>1,STDEV(M81:AB81)/AVERAGE(M81:AB81),"") -> 2.9236498 | Q81: 4791 | R81: 18384 | S81: -9712 | T81: -7621 | U81: -49046 | V81: -3729 | W81: 5437 | X81: 8237 | Y81: 21918 | Z81: 31869 | AA81: 23062 | AB81: 91101
A82: 1 | C82: =" Normalized EBITDA" -> Normalized EBITDA | D82: =IF(COUNT(M82:AB82)>0,MEDIAN(M82:AB82),"") -> 6938.5 | E82: =IF(COUNT(M82:AB82)>0,AVERAGE(M82:AB82),"") -> 22490.167 | F82: =IF(COUNT(M82:AB82)>0,MIN(M82:AB82),"") -> -3729 | G82: =IF(COUNT(M82:AB82)>0,MAX(M82:AB82),"") -> 113569 | H82: =IF(COUNT(M82:AB82)>0,QUARTILE(M82:AB82,1),"") -> 3124.75 | I82: =IF(COUNT(M82:AB82)>0,QUARTILE(M82:AB82,3),"") -> 28287 | J82: =IF(COUNT(M82:AB82)>1,STDEV(M82:AB82),"") -> 33526.936 | K82: =IF(COUNT(M82:AB82)>1,STDEV(M82:AB82)/AVERAGE(M82:AB82),"") -> 1.4907375 | Q82: 4841 | R82: 23687 | S82: 3677 | T82: -2160 | U82: 1468 | V82: -3729 | W82: 5437 | X82: 8440 | Y82: 21918 | Z82: 42087 | AA82: 50647 | AB82: 113569
A83: 1 | C83: =" Earnings Before Interest, Tax and Amortization (EBITA)" -> Earnings Before Interest, Tax and Amortization (EBITA) | D83: =IF(COUNT(M83:AB83)>0,MEDIAN(M83:AB83),"") -> 0 | E83: =IF(COUNT(M83:AB83)>0,AVERAGE(M83:AB83),"") -> 178.9375 | F83: =IF(COUNT(M83:AB83)>0,MIN(M83:AB83),"") -> -59959 | G83: =IF(COUNT(M83:AB83)>0,MAX(M83:AB83),"") -> 68138 | H83: =IF(COUNT(M83:AB83)>0,QUARTILE(M83:AB83,1),"") -> -6347.25 | I83: =IF(COUNT(M83:AB83)>0,QUARTILE(M83:AB83,3),"") -> 6212.5 | J83: =IF(COUNT(M83:AB83)>1,STDEV(M83:AB83),"") -> 25716.151 | K83: =IF(COUNT(M83:AB83)>1,STDEV(M83:AB83)/AVERAGE(M83:AB83),"") -> 143.71583 | M83: 0 | N83: 0 | O83: 0 | P83: 0 | Q83: 1041 | R83: 10675 | S83: -19765 | T83: -19317 | U83: -59959 | V83: -11766 | W83: -4541 | X83: -621 | Y83: 12931 | Z83: 21322 | AA83: 4725 | AB83: 68138
A84: 1 | C84: =" Earnings Before Interest and Tax (EBIT)" -> Earnings Before Interest and Tax (EBIT) | D84: =IF(COUNT(M84:AB84)>0,MEDIAN(M84:AB84),"") -> -4906 | E84: =IF(COUNT(M84:AB84)>0,AVERAGE(M84:AB84),"") -> -3618.5833 | F84: =IF(COUNT(M84:AB84)>0,MIN(M84:AB84),"") -> -61178 | G84: =IF(COUNT(M84:AB84)>0,MAX(M84:AB84),"") -> 50933 | H84: =IF(COUNT(M84:AB84)>0,QUARTILE(M84:AB84,1),"") -> -14753.25 | I84: =IF(COUNT(M84:AB84)>0,QUARTILE(M84:AB84,3),"") -> 9495.25 | J84: =IF(COUNT(M84:AB84)>1,STDEV(M84:AB84),"") -> 26551.127 | K84: =IF(COUNT(M84:AB84)>1,STDEV(M84:AB84)/AVERAGE(M84:AB84),"") -> -7.337437 | Q84: 242 | R84: 9691 | S84: -20649 | T84: -19692 | U84: -61178 | V84: -13107 | W84: -6881 | X84: -4313 | Y84: 9430 | Z84: 17600 | AA84: -5499 | AB84: 50933
A85: 1 | C85: =" Normalized EBIT" -> Normalized EBIT | D85: =IF(COUNT(M85:AB85)>0,MEDIAN(M85:AB85),"") -> -1909 | E85: =IF(COUNT(M85:AB85)>0,AVERAGE(M85:AB85),"") -> 7647.3333 | F85: =IF(COUNT(M85:AB85)>0,MIN(M85:AB85),"") -> -14231 | G85: =IF(COUNT(M85:AB85)>0,MAX(M85:AB85),"") -> 73401 | H85: =IF(COUNT(M85:AB85)>0,QUARTILE(M85:AB85,1),"") -> -8111 | I85: =IF(COUNT(M85:AB85)>0,QUARTILE(M85:AB85,3),"") -> 16767 | J85: =IF(COUNT(M85:AB85)>1,STDEV(M85:AB85),"") -> 24984.309 | K85: =IF(COUNT(M85:AB85)>1,STDEV(M85:AB85)/AVERAGE(M85:AB85),"") -> 3.2670616 | Q85: 292 | R85: 14994 | S85: -7260 | T85: -14231 | U85: -10664 | V85: -13107 | W85: -6881 | X85: -4110 | Y85: 9430 | Z85: 27818 | AA85: 22086 | AB85: 73401
A86: 1 | C86: =" Earnings Before Interest, Tax, Depreciation, Amortization and Rent Expenses (EBITDAR)" -> Earnings Before Interest, Tax, Depreciation, Amortization and Rent Expenses (EBITDAR) | D86: =IF(COUNT(M86:AB86)>0,MEDIAN(M86:AB86),"") -> 6837 | E86: =IF(COUNT(M86:AB86)>0,AVERAGE(M86:AB86),"") -> 11224.25 | F86: =IF(COUNT(M86:AB86)>0,MIN(M86:AB86),"") -> -49046 | G86: =IF(COUNT(M86:AB86)>0,MAX(M86:AB86),"") -> 91101 | H86: =IF(COUNT(M86:AB86)>0,QUARTILE(M86:AB86,1),"") -> -4702 | I86: =IF(COUNT(M86:AB86)>0,QUARTILE(M86:AB86,3),"") -> 22204 | J86: =IF(COUNT(M86:AB86)>1,STDEV(M86:AB86),"") -> 32815.776 | K86: =IF(COUNT(M86:AB86)>1,STDEV(M86:AB86)/AVERAGE(M86:AB86),"") -> 2.9236498 | Q86: 4791 | R86: 18384 | S86: -9712 | T86: -7621 | U86: -49046 | V86: -3729 | W86: 5437 | X86: 8237 | Y86: 21918 | Z86: 31869 | AA86: 23062 | AB86: 91101
A87: 1 | C87: =" Normalized EBITDAR" -> Normalized EBITDAR | D87: =IF(COUNT(M87:AB87)>0,MEDIAN(M87:AB87),"") -> 6938.5 | E87: =IF(COUNT(M87:AB87)>0,AVERAGE(M87:AB87),"") -> 22490.167 | F87: =IF(COUNT(M87:AB87)>0,MIN(M87:AB87),"") -> -3729 | G87: =IF(COUNT(M87:AB87)>0,MAX(M87:AB87),"") -> 113569 | H87: =IF(COUNT(M87:AB87)>0,QUARTILE(M87:AB87,1),"") -> 3124.75 | I87: =IF(COUNT(M87:AB87)>0,QUARTILE(M87:AB87,3),"") -> 28287 | J87: =IF(COUNT(M87:AB87)>1,STDEV(M87:AB87),"") -> 33526.936 | K87: =IF(COUNT(M87:AB87)>1,STDEV(M87:AB87)/AVERAGE(M87:AB87),"") -> 1.4907375 | Q87: 4841 | R87: 23687 | S87: 3677 | T87: -2160 | U87: 1468 | V87: -3729 | W87: 5437 | X87: 8440 | Y87: 21918 | Z87: 42087 | AA87: 50647 | AB87: 113569
A88: 1 | C88: =" Interest and Dividend Income" -> Interest and Dividend Income | D88: =IF(COUNT(M88:AB88)>0,MEDIAN(M88:AB88),"") -> 678.5 | E88: =IF(COUNT(M88:AB88)>0,AVERAGE(M88:AB88),"") -> 768.75 | F88: =IF(COUNT(M88:AB88)>0,MIN(M88:AB88),"") -> 97 | G88: =IF(COUNT(M88:AB88)>0,MAX(M88:AB88),"") -> 1621 | H88: =IF(COUNT(M88:AB88)>0,QUARTILE(M88:AB88,1),"") -> 166.75 | I88: =IF(COUNT(M88:AB88)>0,QUARTILE(M88:AB88,3),"") -> 1280.5 | J88: =IF(COUNT(M88:AB88)>1,STDEV(M88:AB88),"") -> 746.35397 | K88: =IF(COUNT(M88:AB88)>1,STDEV(M88:AB88)/AVERAGE(M88:AB88),"") -> 0.97086695 | Q88: 1621 | R88: 1167 | S88: 190 | T88: 97
A89: 1 | C89: =" Normalized Basic EPS" -> Normalized Basic EPS | D89: =IF(COUNT(M89:AB89)>0,MEDIAN(M89:AB89),"") -> -0.4919468 | E89: =IF(COUNT(M89:AB89)>0,AVERAGE(M89:AB89),"") -> -1.2965596 | F89: =IF(COUNT(M89:AB89)>0,MIN(M89:AB89),"") -> -7.33 | G89: =IF(COUNT(M89:AB89)>0,MAX(M89:AB89),"") -> 2.1295845 | H89: =IF(COUNT(M89:AB89)>0,QUARTILE(M89:AB89,1),"") -> -2.6908495 | I89: =IF(COUNT(M89:AB89)>0,QUARTILE(M89:AB89,3),"") -> 0.078518726 | J89: =IF(COUNT(M89:AB89)>1,STDEV(M89:AB89),"") -> 2.5357709 | K89: =IF(COUNT(M89:AB89)>1,STDEV(M89:AB89)/AVERAGE(M89:AB89),"") -> -1.9557689 | M89: -5.23 | N89: -7.33 | O89: -4.04 | P89: -2.63 | Q89: -2.8733981 | R89: 0.6089122 | S89: -0.4938936 | T89: -0.67276712 | U89: -1.165735 | V89: -0.49 | W89: -0.29 | X89: -0.36378978 | Y89: 0.27 | Z89: 2.1295845 | AA89: 0.014691634 | AB89: 1.8114412
A90: 1 | C90: =" Recommended Normalized Basic EPS" -> Recommended Normalized Basic EPS | D90: =IF(COUNT(M90:AB90)>0,MEDIAN(M90:AB90),"") -> -0.4919468 | E90: =IF(COUNT(M90:AB90)>0,AVERAGE(M90:AB90),"") -> -1.2965596 | F90: =IF(COUNT(M90:AB90)>0,MIN(M90:AB90),"") -> -7.33 | G90: =IF(COUNT(M90:AB90)>0,MAX(M90:AB90),"") -> 2.1295845 | H90: =IF(COUNT(M90:AB90)>0,QUARTILE(M90:AB90,1),"") -> -2.6908495 | I90: =IF(COUNT(M90:AB90)>0,QUARTILE(M90:AB90,3),"") -> 0.078518726 | J90: =IF(COUNT(M90:AB90)>1,STDEV(M90:AB90),"") -> 2.5357709 | K90: =IF(COUNT(M90:AB90)>1,STDEV(M90:AB90)/AVERAGE(M90:AB90),"") -> -1.9557689 | M90: -5.23 | N90: -7.33 | O90: -4.04 | P90: -2.63 | Q90: -2.8733981 | R90: 0.6089122 | S90: -0.4938936 | T90: -0.67276712 | U90: -1.165735 | V90: -0.49 | W90: -0.29 | X90: -0.36378978 | Y90: 0.27 | Z90: 2.1295845 | AA90: 0.014691634 | AB90: 1.8114412
A91: 1 | C91: =" Normalized Diluted EPS" -> Normalized Diluted EPS | D91: =IF(COUNT(M91:AB91)>0,MEDIAN(M91:AB91),"") -> -0.4919468 | E91: =IF(COUNT(M91:AB91)>0,AVERAGE(M91:AB91),"") -> -1.3256943 | F91: =IF(COUNT(M91:AB91)>0,MIN(M91:AB91),"") -> -7.334199 | G91: =IF(COUNT(M91:AB91)>0,MAX(M91:AB91),"") -> 1.9510824 | H91: =IF(COUNT(M91:AB91)>0,QUARTILE(M91:AB91,1),"") -> -2.6908495 | I91: =IF(COUNT(M91:AB91)>0,QUARTILE(M91:AB91,3),"") -> 0.076018726 | J91: =IF(COUNT(M91:AB91)>1,STDEV(M91:AB91),"") -> 2.5023841 | K91: =IF(COUNT(M91:AB91)>1,STDEV(M91:AB91)/AVERAGE(M91:AB91),"") -> -1.8876027 | M91: -5.233027 | N91: -7.334199 | O91: -4.04 | P91: -2.63 | Q91: -2.8733981 | R91: 0.49156347 | S91: -0.4938936 | T91: -0.67276712 | U91: -1.165735 | V91: -0.49 | W91: -0.29 | X91: -0.36378978 | Y91: 0.26 | Z91: 1.9510824 | AA91: 0.014691634 | AB91: 1.658364
A92: 1 | C92: =" Recommended Normalized Diluted EPS" -> Recommended Normalized Diluted EPS | D92: =IF(COUNT(M92:AB92)>0,MEDIAN(M92:AB92),"") -> -0.4919468 | E92: =IF(COUNT(M92:AB92)>0,AVERAGE(M92:AB92),"") -> -1.3256943 | F92: =IF(COUNT(M92:AB92)>0,MIN(M92:AB92),"") -> -7.334199 | G92: =IF(COUNT(M92:AB92)>0,MAX(M92:AB92),"") -> 1.9510824 | H92: =IF(COUNT(M92:AB92)>0,QUARTILE(M92:AB92,1),"") -> -2.6908495 | I92: =IF(COUNT(M92:AB92)>0,QUARTILE(M92:AB92,3),"") -> 0.076018726 | J92: =IF(COUNT(M92:AB92)>1,STDEV(M92:AB92),"") -> 2.5023841 | K92: =IF(COUNT(M92:AB92)>1,STDEV(M92:AB92)/AVERAGE(M92:AB92),"") -> -1.8876027 | M92: -5.233027 | N92: -7.334199 | O92: -4.04 | P92: -2.63 | Q92: -2.8733981 | R92: 0.49156347 | S92: -0.4938936 | T92: -0.67276712 | U92: -1.165735 | V92: -0.49 | W92: -0.29 | X92: -0.36378978 | Y92: 0.26 | Z92: 1.9510824 | AA92: 0.014691634 | AB92: 1.658364
A93: 1 | C93: =" Normalized Income" -> Normalized Income | D93: =IF(COUNT(M93:AB93)>0,MEDIAN(M93:AB93),"") -> -8636.7525 | E93: =IF(COUNT(M93:AB93)>0,AVERAGE(M93:AB93),"") -> -25.783319 | F93: =IF(COUNT(M93:AB93)>0,MIN(M93:AB93),"") -> -28587.9 | G93: =IF(COUNT(M93:AB93)>0,MAX(M93:AB93),"") -> 59567.8 | H93: =IF(COUNT(M93:AB93)>0,QUARTILE(M93:AB93,1),"") -> -12321.5 | I93: =IF(COUNT(M93:AB93)>0,QUARTILE(M93:AB93,3),"") -> 1626 | J93: =IF(COUNT(M93:AB93)>1,STDEV(M93:AB93),"") -> 25160.996 | K93: =IF(COUNT(M93:AB93)>1,STDEV(M93:AB93)/AVERAGE(M93:AB93),"") -> -975.86337 | M93: -12680 | N93: -20947 | O93: -11463.257 | P93: -7644.732 | Q93: -308 | R93: 13772.189 | S93: -11773.15 | T93: -16310.35 | U93: -28587.9 | V93: -12202 | W93: -7319 | X93: -9628.773 | Y93: 7428 | Z93: 59567.8 | AA93: -592 | AB93: 58275.64
A94: 1 | C94: =" Tax Effect of Unusual Items" -> Tax Effect of Unusual Items | D94: =IF(COUNT(M94:AB94)>0,MEDIAN(M94:AB94),"") -> 2999.275 | E94: =IF(COUNT(M94:AB94)>0,AVERAGE(M94:AB94),"") -> 4623.9544 | F94: =IF(COUNT(M94:AB94)>0,MIN(M94:AB94),"") -> 0 | G94: =IF(COUNT(M94:AB94)>0,MAX(M94:AB94),"") -> 17679.9 | H94: =IF(COUNT(M94:AB94)>0,QUARTILE(M94:AB94,1),"") -> 213.03252 | I94: =IF(COUNT(M94:AB94)>0,QUARTILE(M94:AB94,3),"") -> 5721.3075 | J94: =IF(COUNT(M94:AB94)>1,STDEV(M94:AB94),"") -> 5775.2401 | K94: =IF(COUNT(M94:AB94)>1,STDEV(M94:AB94)/AVERAGE(M94:AB94),"") -> 1.2489829 | Q94: 0 | R94: 735.8111 | S94: 4686.15 | T94: 1911.35 | U94: 17679.9 | V94: 0 | X94: 38.773 | Z94: 4087.2 | AA94: 11034 | AB94: 6066.36
A95: 1 | C95: =" Total Unusual Items" -> Total Unusual Items | D95: =IF(COUNT(M95:AB95)>0,MEDIAN(M95:AB95),"") -> 7839.5 | E95: =IF(COUNT(M95:AB95)>0,AVERAGE(M95:AB95),"") -> 13519.1 | F95: =IF(COUNT(M95:AB95)>0,MIN(M95:AB95),"") -> 0 | G95: =IF(COUNT(M95:AB95)>0,MAX(M95:AB95),"") -> 50514 | H95: =IF(COUNT(M95:AB95)>0,QUARTILE(M95:AB95,1),"") -> 1478 | I95: =IF(COUNT(M95:AB95)>0,QUARTILE(M95:AB95,3),"") -> 20198.25 | J95: =IF(COUNT(M95:AB95)>1,STDEV(M95:AB95),"") -> 16094.884 | K95: =IF(COUNT(M95:AB95)>1,STDEV(M95:AB95)/AVERAGE(M95:AB95),"") -> 1.1905293 | Q95: 50 | R95: 5303 | S95: 13389 | T95: 5461 | U95: 50514 | V95: 0 | X95: 203 | Z95: 10218 | AA95: 27585 | AB95: 22468
A96: 1 | C96: =" Total Unusual Items Excluding Goodwill" -> Total Unusual Items Excluding Goodwill | D96: =IF(COUNT(M96:AB96)>0,MEDIAN(M96:AB96),"") -> 7839.5 | E96: =IF(COUNT(M96:AB96)>0,AVERAGE(M96:AB96),"") -> 13519.1 | F96: =IF(COUNT(M96:AB96)>0,MIN(M96:AB96),"") -> 0 | G96: =IF(COUNT(M96:AB96)>0,MAX(M96:AB96),"") -> 50514 | H96: =IF(COUNT(M96:AB96)>0,QUARTILE(M96:AB96,1),"") -> 1478 | I96: =IF(COUNT(M96:AB96)>0,QUARTILE(M96:AB96,3),"") -> 20198.25 | J96: =IF(COUNT(M96:AB96)>1,STDEV(M96:AB96),"") -> 16094.884 | K96: =IF(COUNT(M96:AB96)>1,STDEV(M96:AB96)/AVERAGE(M96:AB96),"") -> 1.1905293 | Q96: 50 | R96: 5303 | S96: 13389 | T96: 5461 | U96: 50514 | V96: 0 | X96: 203 | Z96: 10218 | AA96: 27585 | AB96: 22468
A97: 1 | C97: =" Cost of Revenue and Operating Expense" -> Cost of Revenue and Operating Expense | D97: =IF(COUNT(M97:AB97)>0,MEDIAN(M97:AB97),"") -> 134962 | E97: =IF(COUNT(M97:AB97)>0,AVERAGE(M97:AB97),"") -> 138046.85 | F97: =IF(COUNT(M97:AB97)>0,MIN(M97:AB97),"") -> 20649 | G97: =IF(COUNT(M97:AB97)>0,MAX(M97:AB97),"") -> 327436 | H97: =IF(COUNT(M97:AB97)>0,QUARTILE(M97:AB97,1),"") -> 89316.5 | I97: =IF(COUNT(M97:AB97)>0,QUARTILE(M97:AB97,3),"") -> 166911.5 | J97: =IF(COUNT(M97:AB97)>1,STDEV(M97:AB97),"") -> 83119.687 | K97: =IF(COUNT(M97:AB97)>1,STDEV(M97:AB97)/AVERAGE(M97:AB97),"") -> 0.60211217 | M97: 20649 | N97: 42330 | P97: 38410.717 | Q97: 72750 | R97: 105883 | S97: 148289 | T97: 134962 | U97: 129686 | V97: 124465 | W97: 136382 | X97: 170891 | Y97: 162932 | Z97: 180389 | AA97: 275248 | AB97: 327436
A98: 1 | C98: =" Net Operating Profit After Tax (NOPAT)" -> Net Operating Profit After Tax (NOPAT) | D98: =IF(COUNT(M98:AB98)>0,MEDIAN(M98:AB98),"") -> -9553.9945 | E98: =IF(COUNT(M98:AB98)>0,AVERAGE(M98:AB98),"") -> -4436.7197 | F98: =IF(COUNT(M98:AB98)>0,MIN(M98:AB98),"") -> -61422 | G98: =IF(COUNT(M98:AB98)>0,MAX(M98:AB98),"") -> 54535 | H98: =IF(COUNT(M98:AB98)>0,QUARTILE(M98:AB98,1),"") -> -15633.875 | I98: =IF(COUNT(M98:AB98)>0,QUARTILE(M98:AB98,3),"") -> 2268.0844 | J98: =IF(COUNT(M98:AB98)>1,STDEV(M98:AB98),"") -> 27058.001 | K98: =IF(COUNT(M98:AB98)>1,STDEV(M98:AB98)/AVERAGE(M98:AB98),"") -> -6.0986501 | M98: -12680 | N98: -20947 | O98: -11463.257 | P98: -7644.732 | Q98: 242 | R98: 8346.3375 | S98: -20591.7 | T98: -19921.1 | U98: -61422 | V98: -12202 | W98: -7174.05 | X98: -3488.463 | Y98: 8871.079 | Z98: 54535 | AA98: -14204.8 | AB98: 48757.17
A99: 1 | C99: ="Data Origination" -> Data Origination
A100: 1 | C100: =" Preliminary" -> Preliminary | M100: No | N100: No | O100: No | P100: No | Q100: No | R100: No | S100: No | T100: No | U100: No | V100: No | W100: No | X100: No | Y100: No | Z100: No | AA100: No | AB100: No
A101: 1 | C101: =" Original" -> Original | M101: No | N101: No | O101: No | P101: No | Q101: No | R101: No | S101: No | T101: No | U101: No | V101: No | W101: No | X101: No | Y101: No | Z101: No | AA101: No | AB101: No
A102: 1 | C102: =" Restated" -> Restated | M102: No | N102: No | O102: No | P102: No | Q102: No | R102: No | S102: No | T102: No | U102: No | V102: No | W102: No | X102: No | Y102: No | Z102: No | AA102: No | AB102: No
A103: 1 | C103: =" Calculated" -> Calculated | M103: No | N103: No | O103: No | P103: No | Q103: No | R103: No | S103: No | T103: No | U103: No | V103: No | W103: No | X103: No | Y103: No | Z103: No | AA103: No | AB103: No
...

Sheet inogen P&L
C3: Income Statement (Fiscal Year)
C4: Downloaded On: 10-Mar-2019 | D4: Summary Stats
C5: Company: Inogen (NAS: INGN) | D5: Median | E5: Mean | F5: Min | G5: Max | H5: 25th pctile | I5: 75th pctile | J5: Std. Dev | K5: Coefficient of Variation | M5: =HYPERLINK("https://my.pitchbook.com?c=52707-34", "FY 2011") -> FY 2011 | N5: =HYPERLINK("https://my.pitchbook.com?c=52707-34", "FY 2012") -> FY 2012 | O5: =HYPERLINK("https://my.pitchbook.com?c=52707-34", "FY 2013") -> FY 2013 | P5: =HYPERLINK("https://my.pitchbook.com?c=52707-34", "FY 2014") -> FY 2014 | Q5: =HYPERLINK("https://my.pitchbook.com?c=52707-34", "FY 2015") -> FY 2015 | R5: =HYPERLINK("https://my.pitchbook.com?c=52707-34", "FY 2016") -> FY 2016 | S5: =HYPERLINK("https://my.pitchbook.com?c=52707-34", "FY 2017") -> FY 2017 | T5: =HYPERLINK("https://my.pitchbook.com?c=52707-34", "FY 2018") -> FY 2018
C6: Amounts in Thousands, USD (except Ratios, Multiples & per share items)
M8: Filed: 31-Dec-2011 | N8: Filed: 31-Dec-2012 | O8: Filed: 14-Mar-2016 | P8: Filed: 28-Feb-2017 | Q8: Filed: 27-Feb-2018 | R8: Filed: 26-Feb-2019 | S8: Filed: 26-Feb-2019 | T8: Filed: 26-Feb-2019
M9: =HYPERLINK("https://my.pitchbook.com/profile/52707-34/company/financials?reportId=28838697953&financialGroup=INCOME_STATEMENT&period=ANN&exchangeId=NAS&exchangeSymbol=INGN", "View 10-K") -> View 10-K | N9: =HYPERLINK("https://my.pitchbook.com/profile/52707-34/company/financials?reportId=28838698017&financialGroup=INCOME_STATEMENT&period=ANN&exchangeId=NAS&exchangeSymbol=INGN", "View IPO-A") -> View IPO-A | O9: =HYPERLINK("https://my.pitchbook.com/profile/52707-34/company/financials?reportId=28838698081&financialGroup=INCOME_STATEMENT&period=ANN&exchangeId=NAS&exchangeSymbol=INGN", "View 10-K") -> View 10-K | P9: =HYPERLINK("https://my.pitchbook.com/profile/52707-34/company/financials?reportId=28838698145&financialGroup=INCOME_STATEMENT&period=ANN&exchangeId=NAS&exchangeSymbol=INGN", "View 10-K") -> View 10-K | Q9: =HYPERLINK("https://my.pitchbook.com/profile/52707-34/company/financials?reportId=28838698209&financialGroup=INCOME_STATEMENT&period=ANN&exchangeId=NAS&exchangeSymbol=INGN", "View 10-K") -> View 10-K | R9: =HYPERLINK("https://my.pitchbook.com/profile/52707-34/company/financials?reportId=28838698273&financialGroup=INCOME_STATEMENT&period=ANN&exchangeId=NAS&exchangeSymbol=INGN", "View 10-K") -> View 10-K | S9: =HYPERLINK("https://my.pitchbook.com/profile/52707-34/company/financials?reportId=28838698337&financialGroup=INCOME_STATEMENT&period=ANN&exchangeId=NAS&exchangeSymbol=INGN", "View 10-K") -> View 10-K | T9: =HYPERLINK("https://my.pitchbook.com/profile/52707-34/company/financials?reportId=28838698401&financialGroup=INCOME_STATEMENT&period=ANN&exchangeId=NAS&exchangeSymbol=INGN", "View 10-K") -> View 10-K
A10: 1 | M10: 2011 | N10: 2012 | O10: 2013 | P10: 2014 | Q10: 2015 | R10: 2016 | S10: 2017 | T10: 2018
A11: 1 | C11: =IF(SUBTOTAL(109,A12)=A12," Revenue"," Total Revenue") -> Revenue | D11: =IF(COUNT(M11:T11)>0,MEDIAN(M11:T11),"") | E11: =IF(COUNT(M11:T11)>0,AVERAGE(M11:T11),"") | F11: =IF(COUNT(M11:T11)>0,MIN(M11:T11),"") | G11: =IF(COUNT(M11:T11)>0,MAX(M11:T11),"") | H11: =IF(COUNT(M11:T11)>0,QUARTILE(M11:T11,1),"") | I11: =IF(COUNT(M11:T11)>0,QUARTILE(M11:T11,3),"") | J11: =IF(COUNT(M11:T11)>1,STDEV(M11:T11),"") | K11: =IF(COUNT(M11:T11)>1,STDEV(M11:T11)/AVERAGE(M11:T11),"") | M11: =IF(SUBTOTAL(109,#REF!)=#REF!,"",30634) -> #VALUE! | N11: =IF(SUBTOTAL(109,#REF!)=#REF!,"",48576) -> #VALUE! | O11: =IF(SUBTOTAL(109,#REF!)=#REF!,"",75443) -> #VALUE! | P11: =IF(SUBTOTAL(109,#REF!)=#REF!,"",112537) -> #VALUE! | Q11: =IF(SUBTOTAL(109,B12)=B12,"",159005) | R11: =IF(SUBTOTAL(109,D12)=D12,"",202829) | S11: =IF(SUBTOTAL(109,F12)=F12,"",249438) | T11: =IF(SUBTOTAL(109,H12)=H12,"",358111)
A12: 1 | C12: =" Business Revenue" -> Business Revenue | D12: =IF(COUNT(M12:T12)>0,MEDIAN(M12:T12),"") -> 135771 | E12: =IF(COUNT(M12:T12)>0,AVERAGE(M12:T12),"") -> 154504.75 | F12: =IF(COUNT(M12:T12)>0,MIN(M12:T12),"") -> 30099 | G12: =IF(COUNT(M12:T12)>0,MAX(M12:T12),"") -> 358111 | H12: =IF(COUNT(M12:T12)>0,QUARTILE(M12:T12,1),"") -> 68726.25 | I12: =IF(COUNT(M12:T12)>0,QUARTILE(M12:T12,3),"") -> 214481.25 | J12: =IF(COUNT(M12:T12)>1,STDEV(M12:T12),"") -> 111824.52 | K12: =IF(COUNT(M12:T12)>1,STDEV(M12:T12)/AVERAGE(M12:T12),"") -> 0.72376102 | M12: 30099 | N12: 48576 | O12: 75443 | P12: 112537 | Q12: 159005 | R12: 202829 | S12: 249438 | T12: 358111
A13: 1 | C13: =" Other Revenue" -> Other Revenue | D13: =IF(COUNT(M13:T13)>0,MEDIAN(M13:T13),"") -> 535 | E13: =IF(COUNT(M13:T13)>0,AVERAGE(M13:T13),"") -> 535 | F13: =IF(COUNT(M13:T13)>0,MIN(M13:T13),"") -> 535 | G13: =IF(COUNT(M13:T13)>0,MAX(M13:T13),"") -> 535 | H13: =IF(COUNT(M13:T13)>0,QUARTILE(M13:T13,1),"") -> 535 | I13: =IF(COUNT(M13:T13)>0,QUARTILE(M13:T13,3),"") -> 535 | J13: =IF(COUNT(M13:T13)>1,STDEV(M13:T13),"") | K13: =IF(COUNT(M13:T13)>1,STDEV(M13:T13)/AVERAGE(M13:T13),"") | M13: 535
A14: 1 | C14: =" Total Revenue" -> Total Revenue | D14: =IF(COUNT(M14:T14)>0,MEDIAN(M14:T14),"") -> 135771 | E14: =IF(COUNT(M14:T14)>0,AVERAGE(M14:T14),"") -> 154571.62 | F14: =IF(COUNT(M14:T14)>0,MIN(M14:T14),"") -> 30634 | G14: =IF(COUNT(M14:T14)>0,MAX(M14:T14),"") -> 358111 | H14: =IF(COUNT(M14:T14)>0,QUARTILE(M14:T14,1),"") -> 68726.25 | I14: =IF(COUNT(M14:T14)>0,QUARTILE(M14:T14,3),"") -> 214481.25 | J14: =IF(COUNT(M14:T14)>1,STDEV(M14:T14),"") -> 111739.62 | K14: =IF(COUNT(M14:T14)>1,STDEV(M14:T14)/AVERAGE(M14:T14),"") -> 0.72289863 | M14: 30634 | N14: 48576 | O14: 75443 | P14: 112537 | Q14: 159005 | R14: 202829 | S14: 249438 | T14: 358111
A15: 1 | C15: =IF(SUBTOTAL(109,A16)=A16," Cost of Revenue"," Cost of Revenue") -> Cost of Revenue | D15: =IF(COUNT(M15:T15)>0,MEDIAN(M15:T15),"") | E15: =IF(COUNT(M15:T15)>0,AVERAGE(M15:T15),"") | F15: =IF(COUNT(M15:T15)>0,MIN(M15:T15),"") | G15: =IF(COUNT(M15:T15)>0,MAX(M15:T15),"") | H15: =IF(COUNT(M15:T15)>0,QUARTILE(M15:T15,1),"") | I15: =IF(COUNT(M15:T15)>0,QUARTILE(M15:T15,3),"") | J15: =IF(COUNT(M15:T15)>1,STDEV(M15:T15),"") | K15: =IF(COUNT(M15:T15)>1,STDEV(M15:T15)/AVERAGE(M15:T15),"") | M15: =IF(SUBTOTAL(109,#REF!)=#REF!,"",15930) -> #VALUE! | N15: =IF(SUBTOTAL(109,#REF!)=#REF!,"",24627) -> #VALUE! | O15: =IF(SUBTOTAL(109,#REF!)=#REF!,"",36452) -> #VALUE! | P15: =IF(SUBTOTAL(109,#REF!)=#REF!,"",57020) -> #VALUE! | Q15: =IF(SUBTOTAL(109,B16)=B16,"",82747) | R15: =IF(SUBTOTAL(109,D16)=D16,"",105519) | S15: =IF(SUBTOTAL(109,F16)=F16,"",128201) | T15: =IF(SUBTOTAL(109,H16)=H16,"",179531)
A16: 1 | C16: =" Cost of Goods and Services" -> Cost of Goods and Services | D16: =IF(COUNT(M16:T16)>0,MEDIAN(M16:T16),"") -> 64714 | E16: =IF(COUNT(M16:T16)>0,AVERAGE(M16:T16),"") -> 75760.25 | F16: =IF(COUNT(M16:T16)>0,MIN(M16:T16),"") -> 13512 | G16: =IF(COUNT(M16:T16)>0,MAX(M16:T16),"") -> 179531 | H16: =IF(COUNT(M16:T16)>0,QUARTILE(M16:T16,1),"") -> 27132.75 | I16: =IF(COUNT(M16:T16)>0,QUARTILE(M16:T16,3),"") -> 111189.5 | J16: =IF(COUNT(M16:T16)>1,STDEV(M16:T16),"") -> 59010.648 | K16: =IF(COUNT(M16:T16)>1,STDEV(M16:T16)/AVERAGE(M16:T16),"") -> 0.77891306 | M16: 13512 | N16: 20571 | O16: 29320 | P16: 46681 | Q16: 82747 | R16: 105519 | S16: 128201 | T16: 179531
A17: 1 | C17: =" Depreciation & Amortization, Cost of Revenue" -> Depreciation & Amortization, Cost of Revenue | D17: =IF(COUNT(M17:T17)>0,MEDIAN(M17:T17),"") -> 5594 | E17: =IF(COUNT(M17:T17)>0,AVERAGE(M17:T17),"") -> 5986.25 | F17: =IF(COUNT(M17:T17)>0,MIN(M17:T17),"") -> 2418 | G17: =IF(COUNT(M17:T17)>0,MAX(M17:T17),"") -> 10339 | H17: =IF(COUNT(M17:T17)>0,QUARTILE(M17:T17,1),"") -> 3646.5 | I17: =IF(COUNT(M17:T17)>0,QUARTILE(M17:T17,3),"") -> 7933.75 | J17: =IF(COUNT(M17:T17)>1,STDEV(M17:T17),"") -> 3498.4496 | K17: =IF(COUNT(M17:T17)>1,STDEV(M17:T17)/AVERAGE(M17:T17),"") -> 0.58441422 | M17: 2418 | N17: 4056 | O17: 7132 | P17: 10339
A18: 1 | C18: =" Total Cost of Revenue" -> Total Cost of Revenue | D18: =IF(COUNT(M18:T18)>0,MEDIAN(M18:T18),"") -> 69883.5 | E18: =IF(COUNT(M18:T18)>0,AVERAGE(M18:T18),"") -> 78753.375 | F18: =IF(COUNT(M18:T18)>0,MIN(M18:T18),"") -> 15930 | G18: =IF(COUNT(M18:T18)>0,MAX(M18:T18),"") -> 179531 | H18: =IF(COUNT(M18:T18)>0,QUARTILE(M18:T18,1),"") -> 33495.75 | I18: =IF(COUNT(M18:T18)>0,QUARTILE(M18:T18,3),"") -> 111189.5 | J18: =IF(COUNT(M18:T18)>1,STDEV(M18:T18),"") -> 56659.045 | K18: =IF(COUNT(M18:T18)>1,STDEV(M18:T18)/AVERAGE(M18:T18),"") -> 0.71944911 | M18: 15930 | N18: 24627 | O18: 36452 | P18: 57020 | Q18: 82747 | R18: 105519 | S18: 128201 | T18: 179531
A19: 1 | C19: =" Total Gross Profit" -> Total Gross Profit | D19: =IF(COUNT(M19:T19)>0,MEDIAN(M19:T19),"") -> 65887.5 | E19: =IF(COUNT(M19:T19)>0,AVERAGE(M19:T19),"") -> 75818.25 | F19: =IF(COUNT(M19:T19)>0,MIN(M19:T19),"") -> 14704 | G19: =IF(COUNT(M19:T19)>0,MAX(M19:T19),"") -> 178580 | H19: =IF(COUNT(M19:T19)>0,QUARTILE(M19:T19,1),"") -> 35230.5 | I19: =IF(COUNT(M19:T19)>0,QUARTILE(M19:T19,3),"") -> 103291.75 | J19: =IF(COUNT(M19:T19)>1,STDEV(M19:T19),"") -> 55134.493 | K19: =IF(COUNT(M19:T19)>1,STDEV(M19:T19)/AVERAGE(M19:T19),"") -> 0.7271929 | M19: 14704 | N19: 23949 | O19: 38991 | P19: 55517 | Q19: 76258 | R19: 97310 | S19: 121237 | T19: 178580
A20: 1 | C20: =IF(SUBTOTAL(109,A21)=A21,"Operating (Income)/Expenses","Operating (Income)/Expenses") -> Operating (Income)/Expenses | D20: =IF(COUNT(M20:T20)>0,MEDIAN(M20:T20),"") -> #VALUE! | E20: =IF(COUNT(M20:T20)>0,AVERAGE(M20:T20),"") -> #VALUE! | F20: =IF(COUNT(M20:T20)>0,MIN(M20:T20),"") -> #VALUE! | G20: =IF(COUNT(M20:T20)>0,MAX(M20:T20),"") -> #VALUE! | H20: =IF(COUNT(M20:T20)>0,QUARTILE(M20:T20,1),"") -> #VALUE! | I20: =IF(COUNT(M20:T20)>0,QUARTILE(M20:T20,3),"") -> #VALUE! | J20: =IF(COUNT(M20:T20)>1,STDEV(M20:T20),"") -> #VALUE! | K20: =IF(COUNT(M20:T20)>1,STDEV(M20:T20)/AVERAGE(M20:T20),"") -> #VALUE! | M20: =IF(SUBTOTAL(109,#REF!)=#REF!,"",16426) -> #VALUE! | N20: =IF(SUBTOTAL(109,#REF!)=#REF!,"",23120) -> #VALUE! | O20: =IF(SUBTOTAL(109,#REF!)=#REF!,"",34527) -> #VALUE! | P20: =IF(SUBTOTAL(109,#REF!)=#REF!,"",45006) -> #VALUE! | Q20: =IF(SUBTOTAL(109,B21)=B21,"",61207) | R20: =IF(SUBTOTAL(109,D21)=D21,"",74446) -> 74446 | S20: =IF(SUBTOTAL(109,F21)=F21,"",93647) -> 93647 | T20: =IF(SUBTOTAL(109,H21)=H21,"",140688) -> 140688
A21: 1 | C21: =IF(SUBTOTAL(109,A22)=A22," Selling, General and Administrative Expenses"," Selling, General and Administrative Expenses") -> Selling, General and Administrative Expenses | D21: =IF(COUNT(M21:T21)>0,MEDIAN(M21:T21),"") | E21: =IF(COUNT(M21:T21)>0,AVERAGE(M21:T21),"") | F21: =IF(COUNT(M21:T21)>0,MIN(M21:T21),"") | G21: =IF(COUNT(M21:T21)>0,MAX(M21:T21),"") | H21: =IF(COUNT(M21:T21)>0,QUARTILE(M21:T21,1),"") | I21: =IF(COUNT(M21:T21)>0,QUARTILE(M21:T21,3),"") | J21: =IF(COUNT(M21:T21)>1,STDEV(M21:T21),"") | K21: =IF(COUNT(M21:T21)>1,STDEV(M21:T21)/AVERAGE(M21:T21),"") | M21: =IF(SUBTOTAL(109,#REF!)=#REF!,"",14637) -> #VALUE! | N21: =IF(SUBTOTAL(109,#REF!)=#REF!,"",20858) -> #VALUE! | O21: =IF(SUBTOTAL(109,#REF!)=#REF!,"",32129) -> #VALUE! | P21: =IF(SUBTOTAL(109,#REF!)=#REF!,"",42029) -> #VALUE! | Q21: =IF(SUBTOTAL(109,B22)=B22,"",57027) | R21: =IF(SUBTOTAL(109,D22)=D22,"",69333) | S21: =IF(SUBTOTAL(109,F22)=F22,"",88334) | T21: =IF(SUBTOTAL(109,H22)=H22,"",133659)
A22: 1 | C22: =" General and Administrative Expenses" -> General and Administrative Expenses | D22: =IF(COUNT(M22:T22)>0,MEDIAN(M22:T22),"") -> 21800 | E22: =IF(COUNT(M22:T22)>0,AVERAGE(M22:T22),"") -> 22331.625 | F22: =IF(COUNT(M22:T22)>0,MIN(M22:T22),"") -> 5623 | G22: =IF(COUNT(M22:T22)>0,MAX(M22:T22),"") -> 38018 | H22: =IF(COUNT(M22:T22)>0,QUARTILE(M22:T22,1),"") -> 12387.75 | I22: =IF(COUNT(M22:T22)>0,QUARTILE(M22:T22,3),"") -> 33238.75 | J22: =IF(COUNT(M22:T22)>1,STDEV(M22:T22),"") -> 12807.663 | K22: =IF(COUNT(M22:T22)>1,STDEV(M22:T22)/AVERAGE(M22:T22),"") -> 0.57352132 | M22: 5623 | N22: 8289 | O22: 13754 | P22: 17942 | Q22: 25658 | R22: 31793 | S22: 37576 | T22: 38018
A23: 1 | C23: =" Selling and Marketing Expenses" -> Selling and Marketing Expenses | D23: =IF(COUNT(M23:T23)>0,MEDIAN(M23:T23),"") -> 27728 | E23: =IF(COUNT(M23:T23)>0,AVERAGE(M23:T23),"") -> 34919.125 | F23: =IF(COUNT(M23:T23)>0,MIN(M23:T23),"") -> 9014 | G23: =IF(COUNT(M23:T23)>0,MAX(M23:T23),"") -> 95641 | H23: =IF(COUNT(M23:T23)>0,QUARTILE(M23:T23,1),"") -> 16923.5 | I23: =IF(COUNT(M23:T23)>0,QUARTILE(M23:T23,3),"") -> 40844.5 | J23: =IF(COUNT(M23:T23)>1,STDEV(M23:T23),"") -> 28079.314 | K23: =IF(COUNT(M23:T23)>1,STDEV(M23:T23)/AVERAGE(M23:T23),"") -> 0.80412421 | M23: 9014 | N23: 12569 | O23: 18375 | P23: 24087 | Q23: 31369 | R23: 37540 | S23: 50758 | T23: 95641
A24: 1 | C24: =" Total Selling, General and Administrative Expenses" -> Total Selling, General and Administrative Expenses | D24: =IF(COUNT(M24:T24)>0,MEDIAN(M24:T24),"") -> 49528 | E24: =IF(COUNT(M24:T24)>0,AVERAGE(M24:T24),"") -> 57250.75 | F24: =IF(COUNT(M24:T24)>0,MIN(M24:T24),"") -> 14637 | G24: =IF(COUNT(M24:T24)>0,MAX(M24:T24),"") -> 133659 | H24: =IF(COUNT(M24:T24)>0,QUARTILE(M24:T24,1),"") -> 29311.25 | I24: =IF(COUNT(M24:T24)>0,QUARTILE(M24:T24,3),"") -> 74083.25 | J24: =IF(COUNT(M24:T24)>1,STDEV(M24:T24),"") -> 39557.531 | K24: =IF(COUNT(M24:T24)>1,STDEV(M24:T24)/AVERAGE(M24:T24),"") -> 0.69095219 | M24: 14637 | N24: 20858 | O24: 32129 | P24: 42029 | Q24: 57027 | R24: 69333 | S24: 88334 | T24: 133659
A25: 1 | C25: =" Research and Development Expenses" -> Research and Development Expenses | D25: =IF(COUNT(M25:T25)>0,MEDIAN(M25:T25),"") -> 3578.5 | E25: =IF(COUNT(M25:T25)>0,AVERAGE(M25:T25),"") -> 3882.625 | F25: =IF(COUNT(M25:T25)>0,MIN(M25:T25),"") -> 1789 | G25: =IF(COUNT(M25:T25)>0,MAX(M25:T25),"") -> 7029 | H25: =IF(COUNT(M25:T25)>0,QUARTILE(M25:T25,1),"") -> 2364 | I25: =IF(COUNT(M25:T25)>0,QUARTILE(M25:T25,3),"") -> 5163 | J25: =IF(COUNT(M25:T25)>1,STDEV(M25:T25),"") -> 1835.4393 | K25: =IF(COUNT(M25:T25)>1,STDEV(M25:T25)/AVERAGE(M25:T25),"") -> 0.47273154 | M25: 1789 | N25: 2262 | O25: 2398 | P25: 2977 | Q25: 4180 | R25: 5113 | S25: 5313 | T25: 7029
A26: 1 | C26: =" Total Operating (Income)/Expenses" -> Total Operating (Income)/Expenses | D26: =IF(COUNT(M26:T26)>0,MEDIAN(M26:T26),"") -> 53106.5 | E26: =IF(COUNT(M26:T26)>0,AVERAGE(M26:T26),"") -> 61133.375 | F26: =IF(COUNT(M26:T26)>0,MIN(M26:T26),"") -> 16426 | G26: =IF(COUNT(M26:T26)>0,MAX(M26:T26),"") -> 140688 | H26: =IF(COUNT(M26:T26)>0,QUARTILE(M26:T26,1),"") -> 31675.25 | I26: =IF(COUNT(M26:T26)>0,QUARTILE(M26:T26,3),"") -> 79246.25 | J26: =IF(COUNT(M26:T26)>1,STDEV(M26:T26),"") -> 41360.891 | K26: =IF(COUNT(M26:T26)>1,STDEV(M26:T26)/AVERAGE(M26:T26),"") -> 0.67656809 | M26: 16426 | N26: 23120 | O26: 34527 | P26: 45006 | Q26: 61207 | R26: 74446 | S26: 93647 | T26: 140688
A27: 1 | C27: ="Total Operating Profit/(Loss)" -> Total Operating Profit/(Loss) | D27: =IF(COUNT(M27:T27)>0,MEDIAN(M27:T27),"") -> 12781 | E27: =IF(COUNT(M27:T27)>0,AVERAGE(M27:T27),"") -> 14684.875 | F27: =IF(COUNT(M27:T27)>0,MIN(M27:T27),"") -> -1722 | G27: =IF(COUNT(M27:T27)>0,MAX(M27:T27),"") -> 37892 | H27: =IF(COUNT(M27:T27)>0,QUARTILE(M27:T27,1),"") -> 3555.25 | I27: =IF(COUNT(M27:T27)>0,QUARTILE(M27:T27,3),"") -> 24045.5 | J27: =IF(COUNT(M27:T27)>1,STDEV(M27:T27),"") -> 13914.039 | K27: =IF(COUNT(M27:T27)>1,STDEV(M27:T27)/AVERAGE(M27:T27),"") -> 0.94750817 | M27: -1722 | N27: 829 | O27: 4464 | P27: 10511 | Q27: 15051 | R27: 22864 | S27: 27590 | T27: 37892
A28: 1 | C28: =IF(SUBTOTAL(109,A29)=A29,"Non-Operating Income/(Expenses)","Non-Operating Income/(Expenses), Total") -> Non-Operating Income/(Expenses), Total | D28: =IF(COUNT(M28:T28)>0,MEDIAN(M28:T28),"") | E28: =IF(COUNT(M28:T28)>0,AVERAGE(M28:T28),"") | F28: =IF(COUNT(M28:T28)>0,MIN(M28:T28),"") | G28: =IF(COUNT(M28:T28)>0,MAX(M28:T28),"") | H28: =IF(COUNT(M28:T28)>0,QUARTILE(M28:T28,1),"") | I28: =IF(COUNT(M28:T28)>0,QUARTILE(M28:T28,3),"") | J28: =IF(COUNT(M28:T28)>1,STDEV(M28:T28),"") | K28: =IF(COUNT(M28:T28)>1,STDEV(M28:T28)/AVERAGE(M28:T28),"") | M28: =IF(SUBTOTAL(109,#REF!)=#REF!,"",-267) -> #VALUE! | N28: =IF(SUBTOTAL(109,#REF!)=#REF!,"",-247) -> #VALUE! | O28: =IF(SUBTOTAL(109,#REF!)=#REF!,"",-616) -> #VALUE! | P28: =IF(SUBTOTAL(109,#REF!)=#REF!,"",-459) -> #VALUE! | Q28: =IF(SUBTOTAL(109,B29)=B29,"",-324) | R28: =IF(SUBTOTAL(109,D29)=D29,"",-139) -> #VALUE! | S28: =IF(SUBTOTAL(109,F29)=F29,"",2066) -> #VALUE! | T28: =IF(SUBTOTAL(109,H29)=H29,"",2563) -> #VALUE!
A29: 1 | C29: =IF(SUBTOTAL(109,A30)=A30," Net Finance (Income)/Expense"," Total Net Finance (Income)/Expense") -> Total Net Finance (Income)/Expense | D29: =IF(COUNT(M29:T29)>0,MEDIAN(M29:T29),"") -> #VALUE! | E29: =IF(COUNT(M29:T29)>0,AVERAGE(M29:T29),"") -> #VALUE! | F29: =IF(COUNT(M29:T29)>0,MIN(M29:T29),"") -> #VALUE! | G29: =IF(COUNT(M29:T29)>0,MAX(M29:T29),"") -> #VALUE! | H29: =IF(COUNT(M29:T29)>0,QUARTILE(M29:T29,1),"") -> #VALUE! | I29: =IF(COUNT(M29:T29)>0,QUARTILE(M29:T29,3),"") -> #VALUE! | J29: =IF(COUNT(M29:T29)>1,STDEV(M29:T29),"") -> #VALUE! | K29: =IF(COUNT(M29:T29)>1,STDEV(M29:T29)/AVERAGE(M29:T29),"") -> #VALUE! | M29: =IF(SUBTOTAL(109,#REF!)=#REF!,"",148) -> #VALUE! | N29: =IF(SUBTOTAL(109,#REF!)=#REF!,"",405) -> #VALUE! | O29: =IF(SUBTOTAL(109,#REF!)=#REF!,"",550) -> #VALUE! | P29: =IF(SUBTOTAL(109,#REF!)=#REF!,"",407) -> #VALUE! | Q29: =IF(SUBTOTAL(109,B30)=B30,"",-80) | R29: =IF(SUBTOTAL(109,D30)=D30,"",-190) -> -190 | S29: =IF(SUBTOTAL(109,F30)=F30,"",-765) -> -765 | T29: =IF(SUBTOTAL(109,H30)=H30,"",-3259) -> -3259
A30: 1 | C30: =IF(SUBTOTAL(109,A31)=A31," Net Interest (Income)/Expense"," Net Interest (Income)/Expense") -> Net Interest (Income)/Expense | D30: =IF(COUNT(M30:T30)>0,MEDIAN(M30:T30),"") | E30: =IF(COUNT(M30:T30)>0,AVERAGE(M30:T30),"") | F30: =IF(COUNT(M30:T30)>0,MIN(M30:T30),"") | G30: =IF(COUNT(M30:T30)>0,MAX(M30:T30),"") | H30: =IF(COUNT(M30:T30)>0,QUARTILE(M30:T30,1),"") | I30: =IF(COUNT(M30:T30)>0,QUARTILE(M30:T30,3),"") | J30: =IF(COUNT(M30:T30)>1,STDEV(M30:T30),"") | K30: =IF(COUNT(M30:T30)>1,STDEV(M30:T30)/AVERAGE(M30:T30),"") | M30: =IF(SUBTOTAL(109,#REF!)=#REF!,"",148) -> #VALUE! | N30: =IF(SUBTOTAL(109,#REF!)=#REF!,"",405) -> #VALUE! | O30: =IF(SUBTOTAL(109,#REF!)=#REF!,"",550) -> #VALUE! | P30: =IF(SUBTOTAL(109,#REF!)=#REF!,"",407) -> #VALUE! | Q30: =IF(SUBTOTAL(109,B31)=B31,"",-80) | R30: =IF(SUBTOTAL(109,D31)=D31,"",-190) -> #VALUE! | S30: =IF(SUBTOTAL(109,F31)=F31,"",-765) -> #VALUE! | T30: =IF(SUBTOTAL(109,H31)=H31,"",-3259) -> #VALUE!
