Workbook

Sheet Executive AI Model
A1: AI Startup Executive Cost Model
A2: Simple front sheet for CFO and technical executives. Edit blue-font inputs only. Green-font cells are formula-driven.
A4: 1. Core Inputs | D4: Executive Snapshot | H4: Hidden model logic keeps the interface lean: 1. Revenue grows monthly in Year 1 from the starting ARR. 2. Net hires ramp evenly through the first 12 months. 3. Years 2-10 revenue growth fades linearly to terminal growth. 4. Post-Year-1 headcount scales at 40% of revenue growth. 5. Cash taxes apply only when operating profit is positive.
A5: Starting cash ($) | B5: 7500000 | D5: Year 1 Revenue | F5: =Q24
A6: Starting ARR ($) | B6: 6000000 | D6: Year 1 Cash Burn | F6: =Q35
A7: Year 1 ARR growth | B7: 0.6 | D7: Year 1 Operating Profit | F7: =Q31
A8: Gross margin | B8: 0.72 | D8: Ending Cash After 12 Months | F8: =O35
A9: Starting headcount | B9: 28 | D9: DCF Enterprise Value | F9: =IF($B$14<=$B$17,"n/a",SUM(Q38:Z38)+((Z34*(1+$B$17))/($B$14-$B$17))*Z37)
A10: Planned net new hires in next 12 months | B10: 12 | D10: Year 10 Revenue | F10: =Z24
A11: Annual fully loaded cost per FTE ($) | B11: 210000
A12: AI infra + tooling as % of revenue | B12: 0.14
A13: Other operating costs as % of revenue | B13: 0.18
A14: Discount rate | B14: 0.18
A16: 2. Built-in Defaults
A17: Terminal growth | B17: 0.03
A18: Cash tax rate | B18: 0.25
A19: Capex as % of revenue | B19: 0.03
A20: Headcount growth factor vs. revenue growth | B20: 0.4
A21: Annual payroll inflation | B21: 0.03
A22: 3. Monthly Cash Burn: Next 12 Months | Q22: 4. Annual View: Years 1-10
D23: =$B$22 | E23: =EDATE($B$22,1) | F23: =EDATE($B$22,2) | G23: =EDATE($B$22,3) | H23: =EDATE($B$22,4) | I23: =EDATE($B$22,5) | J23: =EDATE($B$22,6) | K23: =EDATE($B$22,7) | L23: =EDATE($B$22,8) | M23: =EDATE($B$22,9) | N23: =EDATE($B$22,10) | O23: =EDATE($B$22,11) | Q23: Year 1 | R23: Year 2 | S23: Year 3 | T23: Year 4 | U23: Year 5 | V23: Year 6 | W23: Year 7 | X23: Year 8 | Y23: Year 9 | Z23: Year 10
A24: Revenue | D24: =$B$6/12 | E24: =D24*(1+(1+$B$7)^(1/12)-1) | F24: =E24*(1+(1+$B$7)^(1/12)-1) | G24: =F24*(1+(1+$B$7)^(1/12)-1) | H24: =G24*(1+(1+$B$7)^(1/12)-1) | I24: =H24*(1+(1+$B$7)^(1/12)-1) | J24: =I24*(1+(1+$B$7)^(1/12)-1) | K24: =J24*(1+(1+$B$7)^(1/12)-1) | L24: =K24*(1+(1+$B$7)^(1/12)-1) | ... O24: =N24*(1+(1+$B$7)^(1/12)-1) | P24: Revenue | Q24: =SUM(D24:O24) | R24: =Q24*(1+R25) | S24: =R24*(1+S25) | T24: =S24*(1+T25) | U24: =T24*(1+U25) | V24: =U24*(1+V25) | W24: =V24*(1+W25) | X24: =W24*(1+X25) | Y24: =X24*(1+Y25) | Z24: =Y24*(1+Z25)
A25: Gross Profit | D25: =D24*$B$8 | E25: =E24*$B$8 | F25: =F24*$B$8 | G25: =G24*$B$8 | H25: =H24*$B$8 | I25: =I24*$B$8 | J25: =J24*$B$8 | K25: =K24*$B$8 | ... O25: =O24*$B$8 | P25: Revenue Growth | Q25: =$B$7 | R25: =$B$7+(($B$17-$B$7)*1/9) | S25: =$B$7+(($B$17-$B$7)*2/9) | T25: =$B$7+(($B$17-$B$7)*3/9) | U25: =$B$7+(($B$17-$B$7)*4/9) | V25: =$B$7+(($B$17-$B$7)*5/9) | W25: =$B$7+(($B$17-$B$7)*6/9) | X25: =$B$7+(($B$17-$B$7)*7/9) | Y25: =$B$7+(($B$17-$B$7)*8/9) | Z25: =$B$7+(($B$17-$B$7)*9/9)
A26: Ending Headcount | D26: =$B$9+(1*$B$10/12) | E26: =$B$9+(2*$B$10/12) | F26: =$B$9+(3*$B$10/12) | G26: =$B$9+(4*$B$10/12) | H26: =$B$9+(5*$B$10/12) | I26: =$B$9+(6*$B$10/12) | J26: =$B$9+(7*$B$10/12) | K26: =$B$9+(8*$B$10/12) | L26: =$B$9+(9*$B$10/12) | M26: =$B$9+(10*$B$10/12) | N26: =$B$9+(11*$B$10/12) | O26: =$B$9+(12*$B$10/12) | P26: Gross Profit | Q26: =Q24*$B$8 | R26: =R24*$B$8 | S26: =S24*$B$8 | T26: =T24*$B$8 | U26: =U24*$B$8 | V26: =V24*$B$8 | W26: =W24*$B$8 | X26: =X24*$B$8 | ... Z26: =Z24*$B$8
A27: Payroll | D27: =D26*$B$11/12 | E27: =E26*$B$11/12 | F27: =F26*$B$11/12 | G27: =G26*$B$11/12 | H27: =H26*$B$11/12 | I27: =I26*$B$11/12 | J27: =J26*$B$11/12 | K27: =K26*$B$11/12 | ... O27: =O26*$B$11/12 | P27: Ending Headcount | Q27: =O26 | R27: =Q27*(1+MAX(R25*$B$20,0)) | S27: =R27*(1+MAX(S25*$B$20,0)) | T27: =S27*(1+MAX(T25*$B$20,0)) | U27: =T27*(1+MAX(U25*$B$20,0)) | V27: =U27*(1+MAX(V25*$B$20,0)) | W27: =V27*(1+MAX(W25*$B$20,0)) | X27: =W27*(1+MAX(X25*$B$20,0)) | Y27: =X27*(1+MAX(Y25*$B$20,0)) | Z27: =Y27*(1+MAX(Z25*$B$20,0))
A28: AI Infra + Tooling | D28: =D24*$B$12 | E28: =E24*$B$12 | F28: =F24*$B$12 | G28: =G24*$B$12 | H28: =H24*$B$12 | I28: =I24*$B$12 | J28: =J24*$B$12 | K28: =K24*$B$12 | ... O28: =O24*$B$12 | P28: Payroll | Q28: =SUM(D27:O27) | R28: =R27*$B$11*(1+$B$21)^1 | S28: =S27*$B$11*(1+$B$21)^2 | T28: =T27*$B$11*(1+$B$21)^3 | U28: =U27*$B$11*(1+$B$21)^4 | V28: =V27*$B$11*(1+$B$21)^5 | W28: =W27*$B$11*(1+$B$21)^6 | X28: =X27*$B$11*(1+$B$21)^7 | Y28: =Y27*$B$11*(1+$B$21)^8 | Z28: =Z27*$B$11*(1+$B$21)^9
A29: Other Operating Costs | D29: =D24*$B$13 | E29: =E24*$B$13 | F29: =F24*$B$13 | G29: =G24*$B$13 | H29: =H24*$B$13 | I29: =I24*$B$13 | J29: =J24*$B$13 | K29: =K24*$B$13 | ... O29: =O24*$B$13 | P29: AI Infra + Tooling | Q29: =Q24*$B$12 | R29: =R24*$B$12 | S29: =S24*$B$12 | T29: =T24*$B$12 | U29: =U24*$B$12 | V29: =V24*$B$12 | W29: =W24*$B$12 | X29: =X24*$B$12 | ... Z29: =Z24*$B$12
A30: Operating Profit | D30: =D25-D27-D28-D29 | E30: =E25-E27-E28-E29 | F30: =F25-F27-F28-F29 | G30: =G25-G27-G28-G29 | H30: =H25-H27-H28-H29 | I30: =I25-I27-I28-I29 | J30: =J25-J27-J28-J29 | K30: =K25-K27-K28-K29 | ... O30: =O25-O27-O28-O29 | P30: Other Operating Costs | Q30: =Q24*$B$13 | R30: =R24*$B$13 | S30: =S24*$B$13 | T30: =T24*$B$13 | U30: =U24*$B$13 | V30: =V24*$B$13 | W30: =W24*$B$13 | X30: =X24*$B$13 | ... Z30: =Z24*$B$13
A31: Cash Taxes | D31: =MAX(D30,0)*$B$18 | E31: =MAX(E30,0)*$B$18 | F31: =MAX(F30,0)*$B$18 | G31: =MAX(G30,0)*$B$18 | H31: =MAX(H30,0)*$B$18 | I31: =MAX(I30,0)*$B$18 | J31: =MAX(J30,0)*$B$18 | K31: =MAX(K30,0)*$B$18 | ... O31: =MAX(O30,0)*$B$18 | P31: Operating Profit | Q31: =Q26-Q28-Q29-Q30 | R31: =R26-R28-R29-R30 | S31: =S26-S28-S29-S30 | T31: =T26-T28-T29-T30 | U31: =U26-U28-U29-U30 | V31: =V26-V28-V29-V30 | W31: =W26-W28-W29-W30 | X31: =X26-X28-X29-X30 | ... Z31: =Z26-Z28-Z29-Z30
A32: Capex | D32: =D24*$B$19 | E32: =E24*$B$19 | F32: =F24*$B$19 | G32: =G24*$B$19 | H32: =H24*$B$19 | I32: =I24*$B$19 | J32: =J24*$B$19 | K32: =K24*$B$19 | ... O32: =O24*$B$19 | P32: Cash Taxes | Q32: =MAX(Q31,0)*$B$18 | R32: =MAX(R31,0)*$B$18 | S32: =MAX(S31,0)*$B$18 | T32: =MAX(T31,0)*$B$18 | U32: =MAX(U31,0)*$B$18 | V32: =MAX(V31,0)*$B$18 | W32: =MAX(W31,0)*$B$18 | X32: =MAX(X31,0)*$B$18 | ... Z32: =MAX(Z31,0)*$B$18
A33: Free Cash Flow | D33: =D30-D31-D32 | E33: =E30-E31-E32 | F33: =F30-F31-F32 | G33: =G30-G31-G32 | H33: =H30-H31-H32 | I33: =I30-I31-I32 | J33: =J30-J31-J32 | K33: =K30-K31-K32 | ... O33: =O30-O31-O32 | P33: Capex | Q33: =Q24*$B$19 | R33: =R24*$B$19 | S33: =S24*$B$19 | T33: =T24*$B$19 | U33: =U24*$B$19 | V33: =V24*$B$19 | W33: =W24*$B$19 | X33: =X24*$B$19 | ... Z33: =Z24*$B$19
A34: Cash Burn | D34: =MAX(-D33,0) | E34: =MAX(-E33,0) | F34: =MAX(-F33,0) | G34: =MAX(-G33,0) | H34: =MAX(-H33,0) | I34: =MAX(-I33,0) | J34: =MAX(-J33,0) | K34: =MAX(-K33,0) | ... O34: =MAX(-O33,0) | P34: Free Cash Flow | Q34: =Q31-Q32-Q33 | R34: =R31-R32-R33 | S34: =S31-S32-S33 | T34: =T31-T32-T33 | U34: =U31-U32-U33 | V34: =V31-V32-V33 | W34: =W31-W32-W33 | X34: =X31-X32-X33 | ... Z34: =Z31-Z32-Z33
A35: Ending Cash | D35: =$B$5+D33 | E35: =D35+E33 | F35: =E35+F33 | G35: =F35+G33 | H35: =G35+H33 | I35: =H35+I33 | J35: =I35+J33 | K35: =J35+K33 | L35: =K35+L33 | ... O35: =N35+O33 | P35: Cash Burn | Q35: =MAX(-Q34,0) | R35: =MAX(-R34,0) | S35: =MAX(-S34,0) | T35: =MAX(-T34,0) | U35: =MAX(-U34,0) | V35: =MAX(-V34,0) | W35: =MAX(-W34,0) | X35: =MAX(-X34,0) | ... Z35: =MAX(-Z34,0)
P36: Ending Cash | Q36: =O35 | R36: =Q36+R34 | S36: =R36+S34 | T36: =S36+T34 | U36: =T36+U34 | V36: =U36+V34 | W36: =V36+W34 | X36: =W36+X34 | Y36: =X36+Y34 | Z36: =Y36+Z34
P37: Discount Factor | Q37: =1/(1+$B$14)^1 | R37: =1/(1+$B$14)^2 | S37: =1/(1+$B$14)^3 | T37: =1/(1+$B$14)^4 | U37: =1/(1+$B$14)^5 | V37: =1/(1+$B$14)^6 | W37: =1/(1+$B$14)^7 | X37: =1/(1+$B$14)^8 | Y37: =1/(1+$B$14)^9 | Z37: =1/(1+$B$14)^10
A38: 5. Visuals | P38: PV of Free Cash Flow | Q38: =Q34*Q37 | R38: =R34*R37 | S38: =S34*S37 | T38: =T34*T37 | U38: =U34*U37 | V38: =V34*V37 | W38: =W34*W37 | X38: =X34*X37 | ... Z38: =Z34*Z37
A55: Interpretation guide: Cash burn is shown as a positive number only when free cash flow is negative. Operating profit is shown before financing. DCF is based on Years 1-10 free cash flow plus a terminal value using the built-in terminal growth assumption.

Sheet Ats Slide
A1: DELTA COST CENTRE MODEL - DRAFT&CONFIDENTIAL | Y1: STATUS | AI1: 1000000
B2: - Expect cash usage of $3m-$3.5m upon signing | Y2: Will Audrey be on the call later? | Z2: CHANGE TO MILLIONS
B3: - Delta is expected to add approx $3.8m to opex run - rate ($2.8m of which are headcount costs)
B4: - Includes 14 existing heads and 14 new hires (13 engineers plus 1 product designer)
B5: - cost centre will roll into Jon Oakes
B6: - 1-time integration/deal costs of $900k, additional costs of $452k expected to be negotiated as part of purchase price/working capital negotiation
B7: - Founder earnout of $2.25 is not included in the p&l
E9: 2019E | H9: 2020E | M9: 2021 | R9: 2022 | W9: TOTAL COSTS
C10: Provided by | E10: Q319 | F10: Q419 | G10: 2H19 | H10: 1Q20 | I10: 2Q20 | J10: 3Q20 | K10: 4Q20 | L10: FY2020 | M10: Q1 | N10: Q2 | O10: Q3 | P10: Q4 | Q10: FY | R10: Q1 | S10: Q2 | T10: Q3 | U10: Q4 | V10: FY | W10: FY 2019 - 2022
B11: Headcount (HC):
B12: Delta Employees | F12: =[1]Sheet1!$A$28 | G12: =F12 | H12: =G12 | I12: =H12 | J12: =I12 | K12: =J12 | L12: =K12 | M12: =L12 | N12: =M12 | ... W12: =V12
B13: New Asia Hires | F13: 6 | G13: =F13 | H13: 12 | I13: 12 | J13: 14 | K13: 14 | L13: =K13 | M13: 14 | N13: 14 | O13: 14 | P13: 14 | Q13: =P13 | R13: =P13 | S13: =R13 | T13: =S13 | U13: =T13 | V13: =U13 | W13: =V13 | Y13: 1.5m founder holdback, 25%, 25% and 50% - 375k in q4 2020 - new category
B14: Total Ending HC | F14: =F12+F13 | G14: =G12+G13 | H14: =H12+H13 | I14: =I12+I13 | J14: =J12+J13 | K14: =K12+K13 | L14: =L12+L13 | M14: =M12+M13 | ... V14: =V12+V13 | W14: =V14
B16: Run Rate Costs:
B17: =B12 | F17: =F43 | G17: =G43 | H17: =H43 | I17: =I43 | J17: =J43 | K17: =K43 | L17: =L43 | M17: =M43 | ... W17: =W43
B18: =B13 | F18: =F69 | G18: =G69 | H18: =H69 | I18: =I69 | J18: =J69 | K18: =K69 | L18: =L69 | M18: =M69 | ... W18: =W69 | Z18: More engineers | AA18: =(L18-L17)/L17
B19: Total HC Costs | F19: =F43+F69 | G19: =G43+G69 | H19: =H43+H69 | I19: =I43+I69 | J19: =J43+J69 | K19: =K43+K69 | L19: =L43+L69 | M19: =M43+M69 | ... W19: =W43+W69 | Z19: =L17+L18
B20: T&E | F20: =F85 | G20: =G85 | H20: =H85 | I20: =I85 | J20: =J85 | K20: =K85 | L20: =L85 | M20: =#REF!+M3 | N20: =#REF!+N3 | O20: =#REF!+O3 | P20: =#REF!+P3 | Q20: =SUM(M20:P20) | R20: =#REF!+R3 | S20: =#REF!+S3 | T20: =#REF!+T3 | U20: =#REF!+U3 | V20: =SUM(R20:U20) | W20: =G20+L20+Q20+V20
B21: Facility and Office Exp | F21: =F86 | G21: =G86 | H21: =H86 | I21: =I86 | J21: =J86 | K21: =K86 | L21: =L86 | M21: =#REF!+M4 | N21: =#REF!+N4 | O21: =#REF!+O4 | P21: =#REF!+P4 | Q21: =SUM(M21:P21) | R21: =#REF!+R4 | S21: =#REF!+S4 | T21: =#REF!+T4 | U21: =#REF!+U4 | V21: =SUM(R21:U21) | W21: =G21+L21+Q21+V21
B22: IT Costs - wi fi&special software | C22: Bill Bragg | F22: =F90 | G22: =G90 | H22: =H90 | I22: =I90 | J22: =J90 | K22: =K90 | L22: =L90 | M22: =K22 | N22: =M22 | O22: =N22 | P22: =M22 | Q22: =SUM(M22:P22) | R22: =M22 | S22: =R22 | T22: =S22 | U22: =S22 | V22: =SUM(R22:U22) | W22: =G22+L22+Q22+V22
B23: Engineering non h/c | C23: Paul Quinn | F23: =F93 | G23: =G93 | H23: =H93 | I23: =I93 | J23: =J93 | K23: =K93 | L23: =L93 | M23: =#REF! | N23: =#REF! | O23: =#REF! | P23: =#REF! | Q23: =SUM(M23:P23) | R23: =#REF! | S23: =#REF! | T23: =#REF! | U23: =#REF! | V23: =SUM(R23:U23) | W23: =#REF!
B24: Tax | C24: Anu/Harvey | F24: =F95 | G24: =G95 | H24: =H95 | I24: =I95 | J24: =J95 | K24: =K95 | L24: =L95 | M24: =#REF! | N24: =#REF! | O24: =#REF! | P24: =#REF! | Q24: =SUM(M24:P24) | R24: =#REF! | S24: =#REF! | T24: =#REF! | U24: =#REF! | V24: =SUM(R24:U24) | W24: =#REF! | Y24: Stamp duty cost - 2% of shares of company - would it go to p&l?
B25: Other | C25: Nish/Tom | F25: =F96 | G25: =G96 | H25: =H96 | I25: =I96 | J25: =J96 | K25: =K96 | L25: =L96 | M25: =#REF! | N25: =#REF! | O25: =#REF! | P25: =#REF! | Q25: =SUM(M25:P25) | R25: =#REF! | S25: =#REF! | T25: =#REF! | U25: =#REF! | V25: =SUM(R25:U25) | W25: =#REF!
B26: Non-HC Costs | F26: =F98-F19-F112 | G26: =G98-G19-G112 | H26: =H98-H19-H112 | I26: =I98-I19-I112 | J26: =J98-J19-J112 | K26: 231390.5 | L26: =SUM(H26:K26) | M26: =M98-M19-M112 | N26: =N98-N19-N112 | O26: =O98-O19-O112 | P26: =P98-P19-P112 | Q26: =Q98-Q19-Q112 | R26: =R98-R19-R112 | S26: =S98-S19-S112 | T26: =T98-T19-T112 | ... W26: =W98-W19-W112 | Z26: =SUM(H26:K26)
B27: Total Run Rate Costs | F27: =F19+F26 | G27: =G19+G26 | H27: =H19+H26 | I27: =I19+I26 | J27: =J19+J26 | K27: =K19+K26 | L27: =L19+L26 | M27: =M19+M26 | ... W27: =W19+W26
B29: Cost of goods sold
B30: Inventory write off - DokiPal units that we will not sell | C30: Audrey | F30: =100000 | G30: =SUM(E30:F30) | W30: =G30+L30+Q30+V30
B31: Inventory write off - Buy back of DokiPal units | F31: ='Recoverable units'!F20 | G31: =SUM(E31:F31) | W31: =G31+L31+Q31+V31
B33: Operating costs:
B35: Gross wages - yoy inc | H35: 0 | M35: 0.05 | R35: =M35
B36: Gross Wages | C36: HR | F36: =[1]Sheet1!$G$30/4 | G36: =SUM(E36:F36) | H36: =F36*(1+H35) | I36: =H36 | J36: =I36 | K36: =J36 | L36: =SUM(H36:K36) | M36: =H36*(1+M35) | N36: =M36 | O36: =N36 | P36: =O36 | Q36: =SUM(M36:P36) | R36: =M36*(1+R35) | S36: =R36 | T36: =S36 | U36: =T36 | V36: =SUM(R36:U36) | W36: =G36+L36+Q36+V36
B37: Bonus - yoy inc | H37: 0 | M37: 0.05 | R37: =M37 | W37: =G37+L37+Q37+V37
B38: Bonus | C38: HR | F38: =[1]Sheet1!$K$32/4 | G38: =SUM(E38:F38) | H38: =F38*(1+H37) | I38: =H38 | J38: =I38 | K38: =J38 | L38: =SUM(H38:K38) | M38: =H38*(1+M37) | N38: =M38 | O38: =N38 | P38: =O38 | Q38: =SUM(M38:P38) | R38: =M38*(1+R37) | S38: =R38 | T38: =S38 | U38: =T38 | V38: =SUM(R38:U38) | W38: =G38+L38+Q38+V38
B39: Fringe assumption | F39: 0.15 | G39: =F39 | H39: =G39 | I39: =H39 | J39: =I39 | K39: =J39 | L39: =K39 | M39: =L39 | N39: =M39 | ... V39: =U39 | W39: =G39+L39+Q39+V39
B40: Fringe | C40: HR | F40: =SUM(F36:F38)*$F$39 | G40: =SUM(E40:F40) | H40: =SUM(H36:H38)*$F$39 | I40: =SUM(I36:I38)*$F$39 | J40: =SUM(J36:J38)*$F$39 | K40: =SUM(K36:K38)*$F$39 | L40: =SUM(H40:K40) | M40: =SUM(M36:M38)*$F$39 | N40: =M40 | O40: =N40 | P40: =O40 | Q40: =SUM(M40:P40) | R40: =SUM(R36:R38)*$F$39 | S40: =SUM(S36:S38)*$F$39 | T40: =SUM(T36:T38)*$F$39 | U40: =SUM(U36:U38)*$F$39 | V40: =SUM(R40:U40) | W40: =G40+L40+Q40+V40
B41: Retention | C41: HR | F41: =((85000/18)*3)+(85000/36)*3 | G41: =SUM(E41:F41) | H41: =F41 | I41: =H41 | J41: =I41 | K41: =J41 | L41: =SUM(H41:K41) | M41: =K41 | N41: =(85000/36)*3 | O41: =N41 | P41: =O41 | Q41: =SUM(M41:P41) | R41: =N41 | S41: =R41 | T41: =S41 | V41: =SUM(R41:U41) | W41: =G41+L41+Q41+V41
B42: Severance | C42: HR | F42: 0 | G42: =SUM(E42:F42) | H42: 0 | I42: 0 | J42: 0 | K42: 0 | L42: =SUM(H42:K42) | M42: 0 | N42: =M42 | O42: =N42 | P42: =O42 | Q42: =SUM(M42:P42) | R42: 0 | S42: 0 | T42: 0 | U42: 0 | V42: =SUM(R42:U42) | W42: =G42+L42+Q42+V42
B43: HC Related costs | C43: HR | F43: =SUM(F36:F42) | G43: =SUM(E43:F43) | H43: =SUM(H36:H42) | I43: =SUM(I36:I42) | J43: =SUM(J36:J42) | K43: =SUM(K36:K42) | L43: =SUM(L36:L42) | M43: =SUM(M36:M42) | N43: =SUM(N36:N42) | O43: =SUM(O36:O42) | ... V43: =SUM(V36:V42) | W43: =G43+L43+Q43+V43 | AI43: HC Costs Copy of Delta Comp v2- 9.27.19 - Sent to Casper.xlsx
B44: T&E - per person p.a | F44: =5000/4 | G44: =SUM(E44:F44) | H44: =F44 | I44: =H44 | J44: =I44 | K44: =J44 | L44: =SUM(H44:K44) | M44: =H44 | N44: =I44 | O44: =J44 | P44: =K44 | Q44: =SUM(M44:P44) | R44: =M44 | S44: =N44 | T44: =O44 | U44: =P44 | V44: =SUM(R44:U44) | W44: =G44+L44+Q44+V44
B45: T&E | C45: FP&A | F45: =F12*$F44 | G45: =SUM(E45:F45) | H45: =H12*$F44 | I45: =I12*$F44 | J45: =J12*$F44 | K45: =K12*$F44 | L45: =SUM(H45:K45) | M45: =M12*$F44 | N45: =N12*$F44 | O45: =O12*$F44 | P45: =P12*$F44 | Q45: =SUM(M45:P45) | R45: =R12*$F44 | S45: =S12*$F44 | T45: =T12*$F44 | U45: =U12*$F44 | V45: =SUM(R45:U45) | W45: =G45+L45+Q45+V45
B46: Facility and Office Exp | C46: Peter | F46: ='8) Facilities'!I41 | G46: =SUM(E46:F46) | H46: ='8) Facilities'!J41/H14*H12 | I46: ='8) Facilities'!K41/I14*I12 | J46: ='8) Facilities'!L41/J14*J12 | K46: ='8) Facilities'!M41/K14*K12 | L46: =SUM(H46:K46) | M46: =K46 | N46: =M46 | O46: =M46 | P46: =N46 | Q46: =SUM(M46:P46) | R46: =P46 | S46: =R46 | T46: =R46 | U46: =S46 | V46: =SUM(R46:U46) | W46: =G46+L46+Q46+V46
B47: Founder holdback | C47: Jonathan W | G47: =SUM(E47:F47) | K47: 375000 | L47: =SUM(H47:K47) | M47: =J47 | N47: =M47 | O47: =N47 | P47: =K47 | Q47: =SUM(M47:P47) | R47: =M47 | S47: =R47 | T47: =S47 | U47: 750000 | V47: =SUM(R47:U47) | W47: =G47+L47+Q47+V47
B48: IT Costs - security Blackduck | C48: Jonathan W | E48: ='13) IT- Security'!$H$41 | G48: =SUM(E48:F48) | L48: =SUM(H48:K48) | M48: =J48 | N48: =M48 | O48: =N48 | P48: =M48 | Q48: =SUM(M48:P48) | R48: =M48 | S48: =R48 | T48: =S48 | U48: =S48 | V48: =SUM(R48:U48) | W48: =G48+L48+Q48+V48
B49: IT Costs - laptops etc | C49: Bill Bragg | F49: ='11) IT-Infrastructure'!$I$41-F50 | G49: =SUM(E49:F49) | L49: =SUM(H49:K49) | M49: =J49 | N49: =M49 | O49: =N49 | P49: =M49 | Q49: =SUM(M49:P49) | R49: =M49 | S49: =R49 | T49: =S49 | U49: =S49 | V49: =SUM(R49:U49) | W49: =G49+L49+Q49+V49
B50: IT Costs - wi fi&special software | C50: Bill Bragg | F50: ='11) IT-Infrastructure'!$I$31+'11) IT-Infrastructure'!I34 | G50: =SUM(E50:F50) | H50: ='11) IT-Infrastructure'!$I$31+'11) IT-Infrastructure'!K34 | I50: ='11) IT-Infrastructure'!$I$31+'11) IT-Infrastructure'!L34 | J50: ='11) IT-Infrastructure'!$I$31+'11) IT-Infrastructure'!M34 | K50: ='11) IT-Infrastructure'!$I$31+'11) IT-Infrastructure'!N34 | L50: =SUM(H50:K50) | M50: =K50 | N50: =M50 | O50: =N50 | P50: =M50 | Q50: =SUM(M50:P50) | R50: =M50 | S50: =R50 | T50: =S50 | U50: =S50 | V50: =SUM(R50:U50) | W50: =G50+L50+Q50+V50
B51: Valuation reviews - BVA+External cost | C51: Heather | F51: =15000+30000 | G51: =SUM(E51:F51) | L51: =SUM(H51:K51) | Q51: =SUM(M51:P51) | V51: =SUM(R51:U51) | W51: =G51+L51+Q51+V51
B52: Legal expenses - external counsel | C52: Nisha | F52: 425000 | G52: =SUM(E52:F52) | L52: =SUM(H52:K52) | Q52: =SUM(M52:P52) | V52: =SUM(R52:U52) | W52: =G52+L52+Q52+V52
B53: Engineering - Agora + other aps | C53: Paul Quinn | F53: ='2) SW Eng'!$I$41 | G53: =SUM(E53:F53) | H53: ='2) SW Eng'!J41 | I53: ='2) SW Eng'!K41 | J53: ='2) SW Eng'!L41 | K53: ='2) SW Eng'!M41 | L53: =SUM(H53:K53) | M53: ='2) SW Eng'!N41 | N53: ='2) SW Eng'!O41 | O53: ='2) SW Eng'!P41 | P53: ='2) SW Eng'!Q41 | Q53: =SUM(M53:P53) | R53: ='2) SW Eng'!P41 | S53: ='2) SW Eng'!Q41 | T53: ='2) SW Eng'!R41 | U53: ='2) SW Eng'!S41 | V53: =SUM(R53:U53) | W53: =G53+L53+Q53+V53
B54: Operations | C54: Bobinder | E54: ='14) Operations'!$H$41 | F54: =E54 | G54: =SUM(E54:F54) | H54: =E54 | I54: =H54 | L54: =SUM(H54:K54) | Q54: =SUM(M54:P54) | V54: =SUM(R54:U54) | W54: =G54+L54+Q54+V54
B55: Tax - compliance costs | C55: Anu/Harvey | G55: =SUM(E55:F55) | I55: 12000 | L55: =SUM(H55:K55) | N55: =I55 | Q55: =SUM(M55:P55) | S55: =I55 | V55: =SUM(R55:U55) | W55: =G55+L55+Q55+V55
B56: Tax - stamp duty | C56: Legal | F56: =7500000*50%*0.2% | G56: =SUM(E56:F56) | L56: =SUM(H56:K56) | N56: =I56 | Q56: =SUM(M56:P56) | S56: =I56 | V56: =SUM(R56:U56) | W56: =G56+L56+Q56+V56
B57: Other | F57: 25000 | G57: =SUM(E57:F57) | H57: =F57 | I57: =G57 | J57: =H57 | K57: =I57 | L57: =SUM(H57:K57) | M57: =H57 | N57: =I57 | O57: =J57 | P57: =K57 | Q57: =SUM(M57:P57) | R57: =M57 | S57: =N57 | T57: =O57 | U57: =P57 | V57: =SUM(R57:U57) | W57: =G57+L57+Q57+V57
B58: Total Operating costs | F58: =F43+F45+SUM(F46:F57) | G58: =G43+G45+SUM(G46:G57) | H58: =H43+H45+SUM(H46:H57) | I58: =I43+I45+SUM(I46:I57) | J58: =J43+J45+SUM(J46:J57) | K58: =K43+K45+SUM(K46:K57) | L58: =L43+L45+SUM(L46:L57) | M58: =M43+M45+SUM(M46:M57) | ... V58: =V43+V45+SUM(V46:V57) | W58: =G58+L58+Q58+V58
B59: Total Costs associated with current employees | E59: =E36+E38+E40+E41+E42+E45+E46+E50+E51+E55+E53+E52+E57+E49+E54+E48+E30+E31+E47 | F59: =F36+F38+F40+F41+F42+F45+F46+F50+F51+F55+F53+F52+F57+F49+F54+F48+F30+F31+F47 | G59: =G36+G38+G40+G41+G42+G45+G46+G50+G51+G55+G53+G52+G57+G49+G54+G48+G30+G31 | H59: =H36+H38+H40+H41+H42+H45+H46+H50+H51+H55+H53+H52+H57+H49+H54+H48+H30+H31+H47 | I59: =I36+I38+I40+I41+I42+I45+I46+I50+I51+I55+I53+I52+I57+I49+I54+I48+I30+I31+I47 | J59: =J36+J38+J40+J41+J42+J45+J46+J50+J51+J55+J53+J52+J57+J49+J54+J48+J30+J31+J47 | K59: =K36+K38+K40+K41+K42+K45+K46+K50+K51+K55+K53+K52+K57+K49+K54+K48+K30+K31+K47 | L59: =L36+L38+L40+L41+L42+L45+L46+L50+L51+L55+L53+L52+L57+L49+L54+L48+L30+L31+L47 | M59: =M36+M38+M40+M41+M42+M45+M46+M50+M51+M55+M53+M52+M57+M49+M54+M48+M30+M31 | N59: =N36+N38+N40+N41+N42+N45+N46+N50+N51+N55+N53+N52+N57+N49+N54+N48+N30+N31 | O59: =O36+O38+O40+O41+O42+O45+O46+O50+O51+O55+O53+O52+O57+O49+O54+O48+O30+O31 | P59: =P36+P38+P40+P41+P42+P45+P46+P50+P51+P55+P53+P52+P57+P49+P54+P48+P30+P31 | Q59: =Q36+Q38+Q40+Q41+Q42+Q45+Q46+Q50+Q51+Q55+Q53+Q52+Q57+Q49+Q54+Q48+Q30+Q31 | R59: =R36+R38+R40+R41+R42+R45+R46+R50+R51+R55+R53+R52+R57+R49+R54+R48+R30+R31 | S59: =S36+S38+S40+S41+S42+S45+S46+S50+S51+S55+S53+S52+S57+S49+S54+S48+S30+S31 | T59: =T36+T38+T40+T41+T42+T45+T46+T50+T51+T55+T53+T52+T57+T49+T54+T48+T30+T31 | ... W59: =W36+W38+W40+W41+W42+W45+W46+W50+W51+W55+W53+W52+W57+W49+W54+W48+W30+W31
B60: Check | G60: =G59 | L60: =L59 | Q60: =Q59 | V60: =V59 | W60: =(G60+L60+Q60+V60)-W59
M62: 0.05 | R62: 0.05
B63: Gross Wages | F63: =((650000*0.12755)*F13)/4 | G63: =SUM(E63:F63) | H63: =((650000*0.12755)*H13)/4 | I63: =((650000*0.12755)*I13)/4 | J63: =((650000*0.12755)*J13)/4 | K63: =((650000*0.12755)*K13)/4 | L63: =SUM(H63:K63) | M63: =K63*(1+M62) | N63: =M63 | O63: =N63 | P63: =O63 | Q63: =SUM(M63:P63) | R63: =P63*(1+R62) | S63: =R63 | T63: =S63 | U63: =T63 | V63: =SUM(R63:U63) | W63: =G63+L63+Q63+V63 | Z63: =(L63-L36)/L36
B64: Bonus % assumption | F64: 0.1 | H64: =F64 | I64: =H64 | J64: =I64 | K64: =J64 | M64: =K64 | N64: =M64 | O64: =N64 | P64: =O64 | R64: =M64 | S64: =R64 | T64: =S64 | U64: =T64
B65: Bonus | F65: =F63*F64 | G65: =SUM(E65:F65) | H65: =H63*H64 | I65: =I63*I64 | J65: =J63*J64 | K65: =K63*K64 | L65: =SUM(H65:K65) | M65: =M63*M64 | N65: =N63*N64 | O65: =O63*O64 | P65: =P63*P64 | Q65: =SUM(M65:P65) | R65: =R63*R64 | S65: =S63*S64 | T65: =T63*T64 | U65: =U63*U64 | V65: =SUM(R65:U65) | W65: =G65+L65+Q65+V65
B66: Fringe assumption | F66: 0.15 | G66: =F66 | H66: =G66 | I66: =H66 | J66: =I66 | K66: =J66 | L66: =K66 | M66: =L66 | N66: =M66 | ... V66: =U66 | W66: =G66+L66+Q66+V66
B67: Fringe | F67: =SUM(F63:F65)*$F$66 | G67: =SUM(E67:F67) | H67: =SUM(H63:H65)*$F$66 | I67: =SUM(I63:I65)*$F$66 | J67: =SUM(J63:J65)*$F$66 | K67: =SUM(K63:K65)*$F$66 | L67: =SUM(H67:K67) | M67: =SUM(M63:M65)*$F$66 | N67: =SUM(N63:N65)*$F$66 | O67: =SUM(O63:O65)*$F$66 | P67: =SUM(P63:P65)*$F$66 | Q67: =SUM(M67:P67) | R67: =SUM(R63:R65)*$F$66 | S67: =SUM(S63:S65)*$F$66 | T67: =SUM(T63:T65)*$F$66 | U67: =SUM(U63:U65)*$F$66 | V67: =SUM(R67:U67) | W67: =G67+L67+Q67+V67
B68: Recruiting cost | F68: =((F63/F13)/3*2)*6 | G68: =SUM(E68:F68) | H68: =((H63/12)/3*2)*6 | J68: =((J63/14)/3*2)*2 | L68: =SUM(H68:K68) | Q68: =SUM(M68:P68) | V68: =SUM(R68:U68) | W68: =G68+L68+Q68+V68
B69: HC Related costs | E69: =SUM(E63:E68) | F69: =SUM(F63:F68) | G69: =SUM(G63:G68) | H69: =SUM(H63:H68) | I69: =SUM(I63:I68) | J69: =SUM(J63:J68) | K69: =SUM(K63:K68) | L69: =SUM(L63:L68) | ... W69: =SUM(W63:W68) | Y69: Still haven't got levelling/hr inputs
B70: T&E | G70: =SUM(E70:F70) | H70: =H13*$F$44 | I70: =I13*$F$44 | J70: =J13*$F$44 | K70: =K13*$F$44 | L70: =SUM(H70:K70) | M70: =M13*$F$44 | N70: =N13*$F$44 | O70: =O13*$F$44 | P70: =P13*$F$44 | Q70: =SUM(M70:P70) | R70: =R13*$F$44 | S70: =S13*$F$44 | T70: =T13*$F$44 | U70: =U13*$F$44 | V70: =SUM(R70:U70) | W70: =G70+L70+Q70+V70
B71: Facility and Office Exp | G71: =SUM(E71:F71) | H71: ='8) Facilities'!J41-H46 | I71: ='8) Facilities'!K41-I46 | J71: ='8) Facilities'!L41-J46 | K71: ='8) Facilities'!M41-K46 | L71: =SUM(H71:K71) | M71: =K71 | N71: =M71 | O71: =M71 | P71: =N71 | Q71: =SUM(M71:P71) | R71: =M71 | S71: =N71 | T71: =O71 | U71: =P71 | V71: =SUM(R71:U71) | W71: =G71+L71+Q71+V71
B72: Costs related to New Employees in HK | E72: =E69+E70+E71 | F72: =F69+F70+F71 | G72: =G69+G70+G71 | H72: =H69+H70+H71 | I72: =I69+I70+I71 | J72: =J69+J70+J71 | K72: =K69+K70+K71 | L72: =L69+L70+L71 | ... V72: =V69+V70+V71 | W72: =G72+L72+Q72+V72
W73: =G73+L73+Q73+V73
B74: Inventory E&O + write off | C74: Audrey | F74: =F30 | G74: =SUM(E74:F74) | W74: =G74+L74+Q74+V74
B75: Inventory write off - Buy back of DokiPal units | F75: =F31 | G75: =SUM(E75:F75) | W75: =G75+L75+Q75+V75
B77: Operating costs:
B78: Gross Wages | E78: =E36+E63 | F78: =F36+F63 | G78: =G36+G63 | H78: =H36+H63 | I78: =I36+I63 | J78: =J36+J63 | K78: =K36+K63 | L78: =L36+L63 | ... W78: =W36+W63
B79: Bonus | E79: =E38+E65 | F79: =F38+F65 | G79: =G38+G65 | H79: =H38+H65 | I79: =I38+I65 | J79: =J38+J65 | K79: =K38+K65 | L79: =L38+L65 | ... W79: =W38+W65
B80: Fringe | E80: =E40+E67 | F80: =F40+F67 | G80: =G40+G67 | H80: =H40+H67 | I80: =I40+I67 | J80: =J40+J67 | K80: =K40+K67 | L80: =L40+L67 | ... W80: =W40+W67
B81: Retention | E81: =E41+E68 | F81: =F41+F68 | G81: =G41+G68 | H81: =H41+H68 | I81: =I41+I68 | J81: =J41+J68 | K81: =K41+K68 | L81: =L41+L68 | ... W81: =W41+W68
B82: Severance | E82: =E42+E69 | F82: =F42+F69 | G82: =G42+G69 | H82: =H42+H69 | I82: =I42+I69 | J82: =J42+J69 | K82: =K42+K69 | L82: =L42+L69 | ... W82: =W42+W69
B83: Recruiting cost | E83: =E68 | F83: =F68 | G83: =SUM(E83:F83) | H83: =H68 | I83: =I68 | J83: =J68 | K83: =K68 | L83: =SUM(H83:K83) | M83: =M68 | N83: =N68 | O83: =O68 | P83: =P68 | Q83: =SUM(M83:P83) | R83: =R68 | S83: =S68 | T83: =T68 | U83: =U68 | V83: =SUM(R83:U83) | W83: =G83+L83+Q83+V83 | Y83: Per Ryan Krenms, add 2mths of average salary for this
B84: HC Related costs | E84: =E43+E69 | F84: =F43+F69 | G84: =SUM(E84:F84) | H84: =H43+H69 | I84: =I43+I69 | J84: =J43+J69 | K84: =K43+K69 | L84: =SUM(H84:K84) | M84: =M43+M69 | N84: =N43+N69 | O84: =O43+O69 | P84: =P43+P69 | Q84: =SUM(M84:P84) | R84: =R43+R69 | S84: =S43+S69 | T84: =T43+T69 | U84: =U43+U69 | V84: =SUM(R84:U84) | W84: =G84+L84+Q84+V84
B85: T&E | E85: =E45+E70 | F85: =F45+F70 | G85: =SUM(E85:F85) | H85: =H45+H70 | I85: =I45+I70 | J85: =J45+J70 | K85: =K45+K70 | L85: =SUM(H85:K85) | M85: =M45+M70 | N85: =N45+N70 | O85: =O45+O70 | P85: =P45+P70 | Q85: =SUM(M85:P85) | R85: =R45+R70 | S85: =S45+S70 | T85: =T45+T70 | U85: =U45+U70 | V85: =SUM(R85:U85) | W85: =G85+L85+Q85+V85
B86: Facility and Office Exp | E86: =E46+E71 | F86: =F46+F71 | G86: =SUM(E86:F86) | H86: =H46+H71 | I86: =I46+I71 | J86: =J46+J71 | K86: =K46+K71 | L86: =SUM(H86:K86) | M86: =M46+M71 | N86: =N46+N71 | O86: =O46+O71 | P86: =P46+P71 | Q86: =SUM(M86:P86) | R86: =R46+R71 | S86: =S46+S71 | T86: =T46+T71 | U86: =U46+U71 | V86: =SUM(R86:U86) | W86: =G86+L86+Q86+V86
B87: Founder holdback | E87: =E47 | F87: =F47 | G87: =G47 | H87: =H47 | I87: =I47 | J87: =J47 | K87: =K47 | L87: =L47 | ... W87: =W47
B88: IT Costs - security | E88: =E48 | F88: =F48 | G88: =G48 | H88: =H48 | I88: =I48 | J88: =J48 | K88: =K48 | L88: =L48 | ... W88: =W48
B89: IT Costs - integration | E89: =E49 | F89: =F49 | G89: =G49 | H89: =H49 | I89: =I49 | J89: =J49 | K89: =K49 | L89: =SUM(H89:K89) | M89: =M49 | N89: =N49 | O89: =O49 | P89: =P49 | Q89: =SUM(M89:P89) | R89: =R49 | S89: =S49 | T89: =T49 | U89: =U49 | V89: =SUM(R89:U89) | W89: =W49
B90: IT Costs - ongoing | C90: IT team | E90: =E50 | F90: =F50 | G90: =G50 | H90: =H50 | I90: =I50 | J90: =J50 | K90: =K50 | L90: =SUM(H90:K90) | M90: =M50 | N90: =N50 | O90: =O50 | P90: =P50 | Q90: =SUM(M90:P90) | R90: =R50 | S90: =S50 | T90: =T50 | U90: =U50 | V90: =SUM(R90:U90) | W90: =W50
B91: Valuation reviews | C91: Heather | E91: =E51 | F91: =F51 | G91: =G51 | H91: =H51 | I91: =I51 | J91: =J51 | K91: =K51 | L91: =SUM(H91:K91) | M91: =M51 | N91: =N51 | O91: =O51 | P91: =P51 | Q91: =SUM(M91:P91) | R91: =R51 | S91: =S51 | T91: =T51 | U91: =U51 | V91: =SUM(R91:U91) | W91: =W51
B92: Legal/Deal Expenses | C92: Nisha | E92: =E52 | F92: =F52 | G92: =G52 | H92: =H52 | I92: =I52 | J92: =J52 | K92: =K52 | L92: =SUM(H92:K92) | M92: =M52 | N92: =N52 | O92: =O52 | P92: =P52 | Q92: =SUM(M92:P92) | R92: =R52 | S92: =S52 | T92: =T52 | U92: =U52 | V92: =SUM(R92:U92) | W92: =W52
B93: Engineering non h/c | C93: Paul Quinn | E93: =E53 | F93: =F53 | G93: =G53 | H93: =H53 | I93: =I53 | J93: =J53 | K93: =K53 | L93: =SUM(H93:K93) | M93: =M53 | N93: =N53 | O93: =O53 | P93: =P53 | Q93: =SUM(M93:P93) | R93: =R53 | S93: =S53 | T93: =T53 | U93: =U53 | V93: =SUM(R93:U93) | W93: =W53
B94: Operations | E94: =E54 | F94: =F54 | G94: =G54 | H94: =H54 | I94: =I54 | J94: =J54 | K94: =K54 | L94: =L54 | ... W94: =W54
B95: Tax | C95: Anu/Harvey | E95: =E55 | F95: =F55 | G95: =G55 | H95: =H55 | I95: =I55 | J95: =J55 | K95: =K55 | L95: =SUM(H95:K95) | M95: =M55 | N95: =N55 | O95: =O55 | P95: =P55 | Q95: =SUM(M95:P95) | R95: =R55 | S95: =S55 | T95: =T55 | U95: =U55 | V95: =SUM(R95:U95) | W95: =W55 | Y95: Stamp duty cost - 2% of shares of company - would it go to p&l?
B96: Other | C96: Nish/Tom | E96: =E57 | F96: =F57 | G96: =G57 | H96: =H57 | I96: =I57 | J96: =J57 | K96: =K57 | L96: =SUM(H96:K96) | M96: =M57 | N96: =N57 | O96: =O57 | P96: =P57 | Q96: =SUM(M96:P96) | R96: =R57 | S96: =S57 | T96: =T57 | U96: =U57 | V96: =SUM(R96:U96) | W96: =W57
B97: Total Operating costs | E97: =SUM(E84:E96) | F97: =SUM(F84:F96) | G97: =SUM(G84:G96) | H97: =SUM(H84:H96) | I97: =SUM(I84:I96) | J97: =SUM(J84:J96) | K97: =SUM(K84:K96) | L97: =SUM(H97:K97) | M97: =SUM(M84:M96) | N97: =SUM(N84:N96) | O97: =SUM(O84:O96) | P97: =SUM(P84:P96) | Q97: =SUM(M97:P97) | R97: =SUM(R84:R96) | S97: =SUM(S84:S96) | T97: =SUM(T84:T96) | U97: =SUM(U84:U96) | V97: =SUM(R97:U97) | W97: =SUM(W84:W96)
B98: Total costs (including one off costs) | E98: =+E59+E72 | F98: =+F59+F72 | G98: =+G59+G72 | H98: =+H59+H72 | I98: =+I59+I72 | J98: =+J59+J72 | K98: =+K59+K72 | L98: =+L59+L72 | ... W98: =+W59+W72
B100: Non GAAP run rate costs | E100: =(E36+E38+E40+E45+E46+E50+E57+E70+E71+E54+E55+E53+E63+E65+E67+E41+E68) | F100: =(F36+F38+F40+F45+F46+F50+F57+F70+F71+F54+F55+F53+F63+F65+F67+F41+F68) | G100: =(G36+G38+G40+G45+G46+G50+G57+G70+G71+G54+G55+G53+G63+G65+G67+G41+G68) | H100: =(H36+H38+H40+H45+H46+H50+H57+H70+H71+H54+H55+H53+H63+H65+H67+H41+H68) | I100: =(I36+I38+I40+I45+I46+I50+I57+I70+I71+I54+I55+I53+I63+I65+I67+I41+I68) | J100: =(J36+J38+J40+J45+J46+J50+J57+J70+J71+J54+J55+J53+J63+J65+J67+J41+J68) | K100: =(K36+K38+K40+K45+K46+K50+K57+K70+K71+K54+K55+K53+K63+K65+K67+K41+K68) | L100: =(L36+L38+L40+L45+L46+L50+L57+L70+L71+L54+L55+L53+L63+L65+L67+L41+L68) | ... W100: =(W36+W38+W40+W45+W46+W50+W57+W70+W71+W54+W55+W53+W63+W65+W67+W41+W68)
W101: =G101+L101+Q101+V101
B102: One Time Costs:
B103: Founder Holdback | E103: =E87 | F103: =F87 | H103: =H87 | I103: =I87 | J103: =J87 | K103: =K87 | L103: =L87
B104: Legal/Deal Expenses | C104: Nisha | F104: =F52 | G104: =SUM(E104:F104) | L104: =SUM(H104:K104) | Q104: =SUM(M104:P104) | V104: =SUM(R104:U104) | W104: =G104+L104+Q104+V104
B105: Security Blackduck | C105: Jonathan W | E105: =E48 | F105: 0 | G105: =SUM(E105:F105) | W105: =G105+L105+Q105+V105 | Z105: HAVE MOVED THIS TO FOOTNOTE
B106: Deal Costs | E106: =SUM(E103:E105) | F106: =SUM(F103:F105) | G106: =SUM(G103:G105) | H106: =SUM(H103:H105) | I106: =SUM(I103:I105) | J106: =SUM(J103:J105) | K106: =SUM(K103:K105) | L106: =SUM(H106:K106) | M106: =SUM(M104:M105) | N106: =SUM(N104:N105) | O106: =SUM(O104:O105) | P106: =SUM(P104:P105) | Q106: =SUM(Q104:Q105) | R106: =SUM(R104:R105) | S106: =SUM(S104:S105) | T106: =SUM(T104:T105) | ... W106: =SUM(W104:W105) | Z106: HAVE PUT FOUNDER EARN OUT COSTS IN AS A FOOTNOTE
B107: Inventory write off - units that we will not sell | C107: Audrey | F107: =F30 | G107: =SUM(E107:F107) | W107: =G107+L107+Q107+V107 | Y107: Given it results from the transaction and our decision to discontinue selling their product (one time event), there is rationale for it to be GAAP expense only however it is not material enough to consider as GAAP only
B108: Inventory write off - Buy back of DokiPal units | E108: =E31 | F108: =F31 | G108: =G31 | H108: =H31 | I108: =I31 | J108: =J31 | K108: =K31 | L108: =L31 | ... W108: =W31
...

Sheet Financial model
A1: DELTA COST CENTRE MODEL - DRAFT&CONFIDENTIAL | Y1: STATUS
B2: - Expect cash usage of $3m-$3.5m upon signing | Y2: Will Audrey be on the call later?
B3: - Delta is expected to add approx $3.8m to opex run - rate ($2.8m of which are headcount costs)
B4: - Includes 14 existing heads and 14 new hires (13 engineers plus 1 product designer)
B5: - cost centre will roll into Jon Oakes
B6: - 1-time integration/deal costs of $900k, additional costs of $452k expected to be negotiated as part of purchase price/working capital negotiation
B7: - Founder earnout of $2.25 is not included in the p&l
E9: 2019 | H9: 2020 | M9: 2021 | R9: 2022 | W9: TOTAL COSTS
C10: Provided by | E10: Q3 | F10: Q4 | G10: FY | H10: Q1 | I10: Q2 | J10: Q3 | K10: Q4 | L10: FY | M10: Q1 | N10: Q2 | O10: Q3 | P10: Q4 | Q10: FY | R10: Q1 | S10: Q2 | T10: Q3 | U10: Q4 | V10: FY | W10: FY 2019 - 2022
B11: Delta Employees | F11: =[1]Sheet1!$A$28 | G11: =F11 | H11: =G11 | I11: =H11 | J11: =I11 | K11: =J11 | L11: =K11 | M11: =L11 | N11: =M11 | ... W11: =V11
B12: New Employees in HK | F12: 6 | G12: =F12 | H12: 12 | I12: 12 | J12: 14 | K12: 14 | L12: =K12 | M12: 14 | N12: 14 | O12: 14 | P12: 14 | Q12: =P12 | R12: =P12 | S12: =R12 | T12: =S12 | U12: =T12 | V12: =U12 | W12: =V12
B13: TOTAL DELTA HC | F13: =F11+F12 | G13: =G11+G12 | H13: =H11+H12 | I13: =I11+I12 | J13: =J11+J12 | K13: =K11+K12 | L13: =L11+L12 | M13: =M11+M12 | ... V13: =V11+V12 | W13: =V13
B15: Cost of goods sold
B16: Inventory write off - DokiPal units that we will not sell | C16: Audrey | F16: =100000 | G16: =SUM(E16:F16) | W16: =G16+L16+Q16+V16
B17: Inventory write off - Buy back of DokiPal units | F17: ='Recoverable units'!F20 | G17: =SUM(E17:F17) | W17: =G17+L17+Q17+V17
B19: Operating costs:
B21: Gross wages - yoy inc | H21: 0 | M21: 0.05 | R21: =M21
B22: Gross Wages | C22: HR | F22: =[1]Sheet1!$G$30/4 | G22: =SUM(E22:F22) | H22: =F22*(1+H21) | I22: =H22 | J22: =I22 | K22: =J22 | L22: =SUM(H22:K22) | M22: =H22*(1+M21) | N22: =M22 | O22: =N22 | P22: =O22 | Q22: =SUM(M22:P22) | R22: =M22*(1+R21) | S22: =R22 | T22: =S22 | U22: =T22 | V22: =SUM(R22:U22) | W22: =G22+L22+Q22+V22
B23: Bonus - yoy inc | H23: 0 | M23: 0.05 | R23: =M23 | W23: =G23+L23+Q23+V23
B24: Bonus | C24: HR | F24: =[1]Sheet1!$K$32/4 | G24: =SUM(E24:F24) | H24: =F24*(1+H23) | I24: =H24 | J24: =I24 | K24: =J24 | L24: =SUM(H24:K24) | M24: =H24*(1+M23) | N24: =M24 | O24: =N24 | P24: =O24 | Q24: =SUM(M24:P24) | R24: =M24*(1+R23) | S24: =R24 | T24: =S24 | U24: =T24 | V24: =SUM(R24:U24) | W24: =G24+L24+Q24+V24
B25: Fringe assumption | F25: 0.15 | G25: =F25 | H25: =G25 | I25: =H25 | J25: =I25 | K25: =J25 | L25: =K25 | M25: =L25 | N25: =M25 | ... V25: =U25 | W25: =G25+L25+Q25+V25
B26: Fringe | C26: HR | F26: =SUM(F22:F24)*$F$25 | G26: =SUM(E26:F26) | H26: =SUM(H22:H24)*$F$25 | I26: =SUM(I22:I24)*$F$25 | J26: =SUM(J22:J24)*$F$25 | K26: =SUM(K22:K24)*$F$25 | L26: =SUM(H26:K26) | M26: =SUM(M22:M24)*$F$25 | N26: =M26 | O26: =N26 | P26: =O26 | Q26: =SUM(M26:P26) | R26: =SUM(R22:R24)*$F$25 | S26: =SUM(S22:S24)*$F$25 | T26: =SUM(T22:T24)*$F$25 | U26: =SUM(U22:U24)*$F$25 | V26: =SUM(R26:U26) | W26: =G26+L26+Q26+V26
B27: Retention | C27: HR | F27: =((85000/18)*3)+(85000/36)*3 | G27: =SUM(E27:F27) | H27: =F27 | I27: =H27 | J27: =I27 | K27: =J27 | L27: =SUM(H27:K27) | M27: =K27 | N27: =(85000/36)*3 | O27: =N27 | P27: =O27 | Q27: =SUM(M27:P27) | R27: =N27 | S27: =R27 | T27: =S27 | V27: =SUM(R27:U27) | W27: =G27+L27+Q27+V27
B28: Severance | C28: HR | F28: 0 | G28: =SUM(E28:F28) | H28: 0 | I28: 0 | J28: 0 | K28: 0 | L28: =SUM(H28:K28) | M28: 0 | N28: =M28 | O28: =N28 | P28: =O28 | Q28: =SUM(M28:P28) | R28: 0 | S28: 0 | T28: 0 | U28: 0 | V28: =SUM(R28:U28) | W28: =G28+L28+Q28+V28
B29: HC Related costs | C29: HR | F29: =SUM(F22:F28) | G29: =SUM(E29:F29) | H29: =SUM(H22:H28) | I29: =SUM(I22:I28) | J29: =SUM(J22:J28) | K29: =SUM(K22:K28) | L29: =SUM(L22:L28) | M29: =SUM(M22:M28) | N29: =SUM(N22:N28) | O29: =SUM(O22:O28) | ... V29: =SUM(V22:V28) | W29: =G29+L29+Q29+V29 | AI29: HC Costs Copy of Delta Comp v2- 9.27.19 - Sent to Casper.xlsx
B30: T&E - per person p.a | F30: =5000/4 | G30: =SUM(E30:F30) | H30: =F30 | I30: =H30 | J30: =I30 | K30: =J30 | L30: =SUM(H30:K30) | M30: =H30 | N30: =I30 | O30: =J30 | P30: =K30 | Q30: =SUM(M30:P30) | R30: =M30 | S30: =N30 | T30: =O30 | U30: =P30 | V30: =SUM(R30:U30) | W30: =G30+L30+Q30+V30
B31: T&E | C31: FP&A | F31: =F11*$F30 | G31: =SUM(E31:F31) | H31: =H11*$F30 | I31: =I11*$F30 | J31: =J11*$F30 | K31: =K11*$F30 | L31: =SUM(H31:K31) | M31: =M11*$F30 | N31: =N11*$F30 | O31: =O11*$F30 | P31: =P11*$F30 | Q31: =SUM(M31:P31) | R31: =R11*$F30 | S31: =S11*$F30 | T31: =T11*$F30 | U31: =U11*$F30 | V31: =SUM(R31:U31) | W31: =G31+L31+Q31+V31
B32: Facility and Office Exp | C32: Peter | F32: ='8) Facilities'!I41 | G32: =SUM(E32:F32) | H32: ='8) Facilities'!J41/H13*H11 | I32: ='8) Facilities'!K41/I13*I11 | J32: ='8) Facilities'!L41/J13*J11 | K32: ='8) Facilities'!M41/K13*K11 | L32: =SUM(H32:K32) | M32: =K32 | N32: =M32 | O32: =M32 | P32: =N32 | Q32: =SUM(M32:P32) | R32: =P32 | S32: =R32 | T32: =R32 | U32: =S32 | V32: =SUM(R32:U32) | W32: =G32+L32+Q32+V32
B33: IT Costs - security Blackduck | C33: Jonathan W | E33: ='13) IT- Security'!$H$41 | G33: =SUM(E33:F33) | L33: =SUM(H33:K33) | M33: =J33 | N33: =M33 | O33: =N33 | P33: =M33 | Q33: =SUM(M33:P33) | R33: =M33 | S33: =R33 | T33: =S33 | U33: =S33 | V33: =SUM(R33:U33) | W33: =G33+L33+Q33+V33
B34: IT Costs - laptops etc | C34: Bill Bragg | F34: ='11) IT-Infrastructure'!$I$41-F35 | G34: =SUM(E34:F34) | L34: =SUM(H34:K34) | M34: =J34 | N34: =M34 | O34: =N34 | P34: =M34 | Q34: =SUM(M34:P34) | R34: =M34 | S34: =R34 | T34: =S34 | U34: =S34 | V34: =SUM(R34:U34) | W34: =G34+L34+Q34+V34
B35: IT Costs - wi fi&special software | C35: Bill Bragg | F35: ='11) IT-Infrastructure'!$I$31+'11) IT-Infrastructure'!I34 | G35: =SUM(E35:F35) | H35: ='11) IT-Infrastructure'!$I$31+'11) IT-Infrastructure'!K34 | I35: ='11) IT-Infrastructure'!$I$31+'11) IT-Infrastructure'!L34 | J35: ='11) IT-Infrastructure'!$I$31+'11) IT-Infrastructure'!M34 | K35: ='11) IT-Infrastructure'!$I$31+'11) IT-Infrastructure'!N34 | L35: =SUM(H35:K35) | M35: =K35 | N35: =M35 | O35: =N35 | P35: =M35 | Q35: =SUM(M35:P35) | R35: =M35 | S35: =R35 | T35: =S35 | U35: =S35 | V35: =SUM(R35:U35) | W35: =G35+L35+Q35+V35
B36: Valuation reviews - BVA+External cost | C36: Heather | F36: =15000+30000 | G36: =SUM(E36:F36) | L36: =SUM(H36:K36) | Q36: =SUM(M36:P36) | V36: =SUM(R36:U36) | W36: =G36+L36+Q36+V36
B37: Legal expenses - external counsel | C37: Nisha | F37: 425000 | G37: =SUM(E37:F37) | L37: =SUM(H37:K37) | Q37: =SUM(M37:P37) | V37: =SUM(R37:U37) | W37: =G37+L37+Q37+V37
B38: Engineering - Agora + other aps | C38: Paul Quinn | F38: ='2) SW Eng'!$I$41 | G38: =SUM(E38:F38) | H38: ='2) SW Eng'!J41 | I38: ='2) SW Eng'!K41 | J38: ='2) SW Eng'!L41 | K38: ='2) SW Eng'!M41 | L38: =SUM(H38:K38) | M38: ='2) SW Eng'!N41 | N38: ='2) SW Eng'!O41 | O38: ='2) SW Eng'!P41 | P38: ='2) SW Eng'!Q41 | Q38: =SUM(M38:P38) | R38: ='2) SW Eng'!P41 | S38: ='2) SW Eng'!Q41 | T38: ='2) SW Eng'!R41 | U38: ='2) SW Eng'!S41 | V38: =SUM(R38:U38) | W38: =G38+L38+Q38+V38
B39: Operations | C39: Bobinder | E39: ='14) Operations'!$H$41 | F39: =E39 | G39: =SUM(E39:F39) | H39: =E39 | I39: =H39 | L39: =SUM(H39:K39) | Q39: =SUM(M39:P39) | V39: =SUM(R39:U39) | W39: =G39+L39+Q39+V39
B40: Tax - compliance costs | C40: Anu/Harvey | G40: =SUM(E40:F40) | I40: 12000 | L40: =SUM(H40:K40) | N40: =I40 | Q40: =SUM(M40:P40) | S40: =I40 | V40: =SUM(R40:U40) | W40: =G40+L40+Q40+V40
B41: Tax - stamp duty | C41: Legal | F41: =7500000*50%*0.2% | G41: =SUM(E41:F41) | L41: =SUM(H41:K41) | N41: =I41 | Q41: =SUM(M41:P41) | S41: =I41 | V41: =SUM(R41:U41) | W41: =G41+L41+Q41+V41
B42: Other | F42: 25000 | G42: =SUM(E42:F42) | H42: =F42 | I42: =G42 | J42: =H42 | K42: =I42 | L42: =SUM(H42:K42) | M42: =H42 | N42: =I42 | O42: =J42 | P42: =K42 | Q42: =SUM(M42:P42) | R42: =M42 | S42: =N42 | T42: =O42 | U42: =P42 | V42: =SUM(R42:U42) | W42: =G42+L42+Q42+V42
B43: Total Operating costs | F43: =F29+F31+SUM(F32:F42) | G43: =G29+G31+SUM(G32:G42) | H43: =H29+H31+SUM(H32:H42) | I43: =I29+I31+SUM(I32:I42) | J43: =J29+J31+SUM(J32:J42) | K43: =K29+K31+SUM(K32:K42) | L43: =L29+L31+SUM(L32:L42) | M43: =M29+M31+SUM(M32:M42) | ... V43: =V29+V31+SUM(V32:V42) | W43: =G43+L43+Q43+V43
B44: Total Costs associated with current employees | E44: =E22+E24+E26+E27+E28+E31+E32+E35+E36+E40+E38+E37+E42+E34+E39+E33+E16+E17 | F44: =F22+F24+F26+F27+F28+F31+F32+F35+F36+F40+F38+F37+F42+F34+F39+F33+F16+F17 | G44: =G22+G24+G26+G27+G28+G31+G32+G35+G36+G40+G38+G37+G42+G34+G39+G33+G16+G17 | H44: =H22+H24+H26+H27+H28+H31+H32+H35+H36+H40+H38+H37+H42+H34+H39+H33+H16+H17 | I44: =I22+I24+I26+I27+I28+I31+I32+I35+I36+I40+I38+I37+I42+I34+I39+I33+I16+I17 | J44: =J22+J24+J26+J27+J28+J31+J32+J35+J36+J40+J38+J37+J42+J34+J39+J33+J16+J17 | K44: =K22+K24+K26+K27+K28+K31+K32+K35+K36+K40+K38+K37+K42+K34+K39+K33+K16+K17 | L44: =L22+L24+L26+L27+L28+L31+L32+L35+L36+L40+L38+L37+L42+L34+L39+L33+L16+L17 | ... W44: =W22+W24+W26+W27+W28+W31+W32+W35+W36+W40+W38+W37+W42+W34+W39+W33+W16+W17
B45: Check | G45: =G44 | L45: =L44 | Q45: =Q44 | V45: =V44 | W45: =(G45+L45+Q45+V45)-W44
M47: 0.05 | R47: 0.05
B48: Gross Wages | F48: =((650000*0.12755)*F12)/4 | G48: =SUM(E48:F48) | H48: =((650000*0.12755)*H12)/4 | I48: =((650000*0.12755)*I12)/4 | J48: =((650000*0.12755)*J12)/4 | K48: =((650000*0.12755)*K12)/4 | L48: =SUM(H48:K48) | M48: =K48*(1+M47) | N48: =M48 | O48: =N48 | P48: =O48 | Q48: =SUM(M48:P48) | R48: =P48*(1+R47) | S48: =R48 | T48: =S48 | U48: =T48 | V48: =SUM(R48:U48) | W48: =G48+L48+Q48+V48 | Z48: =(L48-L22)/L22
B49: Bonus % assumption | F49: 0.1 | H49: =F49 | I49: =H49 | J49: =I49 | K49: =J49 | M49: =K49 | N49: =M49 | O49: =N49 | P49: =O49 | R49: =M49 | S49: =R49 | T49: =S49 | U49: =T49
B50: Bonus | F50: =F48*F49 | G50: =SUM(E50:F50) | H50: =H48*H49 | I50: =I48*I49 | J50: =J48*J49 | K50: =K48*K49 | L50: =SUM(H50:K50) | M50: =M48*M49 | N50: =N48*N49 | O50: =O48*O49 | P50: =P48*P49 | Q50: =SUM(M50:P50) | R50: =R48*R49 | S50: =S48*S49 | T50: =T48*T49 | U50: =U48*U49 | V50: =SUM(R50:U50) | W50: =G50+L50+Q50+V50
B51: Fringe assumption | F51: 0.15 | G51: =F51 | H51: =G51 | I51: =H51 | J51: =I51 | K51: =J51 | L51: =K51 | M51: =L51 | N51: =M51 | ... V51: =U51 | W51: =G51+L51+Q51+V51
B52: Fringe | F52: =SUM(F48:F50)*$F$51 | G52: =SUM(E52:F52) | H52: =SUM(H48:H50)*$F$51 | I52: =SUM(I48:I50)*$F$51 | J52: =SUM(J48:J50)*$F$51 | K52: =SUM(K48:K50)*$F$51 | L52: =SUM(H52:K52) | M52: =SUM(M48:M50)*$F$51 | N52: =SUM(N48:N50)*$F$51 | O52: =SUM(O48:O50)*$F$51 | P52: =SUM(P48:P50)*$F$51 | Q52: =SUM(M52:P52) | R52: =SUM(R48:R50)*$F$51 | S52: =SUM(S48:S50)*$F$51 | T52: =SUM(T48:T50)*$F$51 | U52: =SUM(U48:U50)*$F$51 | V52: =SUM(R52:U52) | W52: =G52+L52+Q52+V52
B53: Recruiting cost | F53: =((F48/F12)/3*2)*6 | G53: =SUM(E53:F53) | H53: =((H48/12)/3*2)*6 | J53: =((J48/14)/3*2)*2 | L53: =SUM(H53:K53) | Q53: =SUM(M53:P53) | V53: =SUM(R53:U53) | W53: =G53+L53+Q53+V53
B54: HC Related costs | E54: =SUM(E48:E53) | F54: =SUM(F48:F53) | G54: =SUM(G48:G53) | H54: =SUM(H48:H53) | I54: =SUM(I48:I53) | J54: =SUM(J48:J53) | K54: =SUM(K48:K53) | L54: =SUM(L48:L53) | ... W54: =SUM(W48:W53) | Y54: Still haven't got levelling/hr inputs
B55: T&E | G55: =SUM(E55:F55) | H55: =H12*$F$30 | I55: =I12*$F$30 | J55: =J12*$F$30 | K55: =K12*$F$30 | L55: =SUM(H55:K55) | M55: =M12*$F$30 | N55: =N12*$F$30 | O55: =O12*$F$30 | P55: =P12*$F$30 | Q55: =SUM(M55:P55) | R55: =R12*$F$30 | S55: =S12*$F$30 | T55: =T12*$F$30 | U55: =U12*$F$30 | V55: =SUM(R55:U55) | W55: =G55+L55+Q55+V55
B56: Facility and Office Exp | G56: =SUM(E56:F56) | H56: ='8) Facilities'!J41-H32 | I56: ='8) Facilities'!K41-I32 | J56: ='8) Facilities'!L41-J32 | K56: ='8) Facilities'!M41-K32 | L56: =SUM(H56:K56) | M56: =K56 | N56: =M56 | O56: =M56 | P56: =N56 | Q56: =SUM(M56:P56) | R56: =M56 | S56: =N56 | T56: =O56 | U56: =P56 | V56: =SUM(R56:U56) | W56: =G56+L56+Q56+V56
B57: Costs related to New Employees in HK | E57: =E54+E55+E56 | F57: =F54+F55+F56 | G57: =G54+G55+G56 | H57: =H54+H55+H56 | I57: =I54+I55+I56 | J57: =J54+J55+J56 | K57: =K54+K55+K56 | L57: =L54+L55+L56 | ... V57: =V54+V55+V56 | W57: =G57+L57+Q57+V57
W58: =G58+L58+Q58+V58
B59: Inventory E&O + write off | C59: Audrey | F59: =F16 | G59: =SUM(E59:F59) | W59: =G59+L59+Q59+V59
B60: Inventory write off - Buy back of DokiPal units | F60: =F17 | G60: =SUM(E60:F60) | W60: =G60+L60+Q60+V60
B62: Operating costs:
B63: Gross Wages | E63: =E22+E48 | F63: =F22+F48 | G63: =G22+G48 | H63: =H22+H48 | I63: =I22+I48 | J63: =J22+J48 | K63: =K22+K48 | L63: =L22+L48 | ... W63: =W22+W48
B64: Bonus | E64: =E24+E50 | F64: =F24+F50 | G64: =G24+G50 | H64: =H24+H50 | I64: =I24+I50 | J64: =J24+J50 | K64: =K24+K50 | L64: =L24+L50 | ... W64: =W24+W50
B65: Fringe | E65: =E26+E52 | F65: =F26+F52 | G65: =G26+G52 | H65: =H26+H52 | I65: =I26+I52 | J65: =J26+J52 | K65: =K26+K52 | L65: =L26+L52 | ... W65: =W26+W52
B66: Retention | E66: =E27+E53 | F66: =F27+F53 | G66: =G27+G53 | H66: =H27+H53 | I66: =I27+I53 | J66: =J27+J53 | K66: =K27+K53 | L66: =L27+L53 | ... W66: =W27+W53
B67: Severance | E67: =E28+E54 | F67: =F28+F54 | G67: =G28+G54 | H67: =H28+H54 | I67: =I28+I54 | J67: =J28+J54 | K67: =K28+K54 | L67: =L28+L54 | ... W67: =W28+W54
B68: Recruiting cost | E68: =E53 | F68: =F53 | G68: =SUM(E68:F68) | H68: =H53 | I68: =I53 | J68: =J53 | K68: =K53 | L68: =SUM(H68:K68) | M68: =M53 | N68: =N53 | O68: =O53 | P68: =P53 | Q68: =SUM(M68:P68) | R68: =R53 | S68: =S53 | T68: =T53 | U68: =U53 | V68: =SUM(R68:U68) | W68: =G68+L68+Q68+V68 | Y68: Per Ryan Krenms, add 2mths of average salary for this
B69: HC Related costs | E69: =E29+E54 | F69: =F29+F54 | G69: =SUM(E69:F69) | H69: =H29+H54 | I69: =I29+I54 | J69: =J29+J54 | K69: =K29+K54 | L69: =SUM(H69:K69) | M69: =M29+M54 | N69: =N29+N54 | O69: =O29+O54 | P69: =P29+P54 | Q69: =SUM(M69:P69) | R69: =R29+R54 | S69: =S29+S54 | T69: =T29+T54 | U69: =U29+U54 | V69: =SUM(R69:U69) | W69: =G69+L69+Q69+V69
B70: T&E | E70: =E31+E55 | F70: =F31+F55 | G70: =SUM(E70:F70) | H70: =H31+H55 | I70: =I31+I55 | J70: =J31+J55 | K70: =K31+K55 | L70: =SUM(H70:K70) | M70: =M31+M55 | N70: =N31+N55 | O70: =O31+O55 | P70: =P31+P55 | Q70: =SUM(M70:P70) | R70: =R31+R55 | S70: =S31+S55 | T70: =T31+T55 | U70: =U31+U55 | V70: =SUM(R70:U70) | W70: =G70+L70+Q70+V70
B71: Facility and Office Exp | E71: =E32+E56 | F71: =F32+F56 | G71: =SUM(E71:F71) | H71: =H32+H56 | I71: =I32+I56 | J71: =J32+J56 | K71: =K32+K56 | L71: =SUM(H71:K71) | M71: =M32+M56 | N71: =N32+N56 | O71: =O32+O56 | P71: =P32+P56 | Q71: =SUM(M71:P71) | R71: =R32+R56 | S71: =S32+S56 | T71: =T32+T56 | U71: =U32+U56 | V71: =SUM(R71:U71) | W71: =G71+L71+Q71+V71
B72: IT Costs - security | E72: =E33 | F72: =F33 | G72: =G33 | H72: =H33 | I72: =I33 | J72: =J33 | K72: =K33 | L72: =L33 | ... W72: =W33
B73: IT Costs - integration | E73: =E34 | F73: =F34 | G73: =G34 | H73: =H34 | I73: =I34 | J73: =J34 | K73: =K34 | L73: =SUM(H73:K73) | M73: =M34 | N73: =N34 | O73: =O34 | P73: =P34 | Q73: =SUM(M73:P73) | R73: =R34 | S73: =S34 | T73: =T34 | U73: =U34 | V73: =SUM(R73:U73) | W73: =W34
B74: IT Costs - ongoing | C74: IT team | E74: =E35 | F74: =F35 | G74: =G35 | H74: =H35 | I74: =I35 | J74: =J35 | K74: =K35 | L74: =SUM(H74:K74) | M74: =M35 | N74: =N35 | O74: =O35 | P74: =P35 | Q74: =SUM(M74:P74) | R74: =R35 | S74: =S35 | T74: =T35 | U74: =U35 | V74: =SUM(R74:U74) | W74: =W35
B75: Valuation reviews | C75: Heather | E75: =E36 | F75: =F36 | G75: =G36 | H75: =H36 | I75: =I36 | J75: =J36 | K75: =K36 | L75: =SUM(H75:K75) | M75: =M36 | N75: =N36 | O75: =O36 | P75: =P36 | Q75: =SUM(M75:P75) | R75: =R36 | S75: =S36 | T75: =T36 | U75: =U36 | V75: =SUM(R75:U75) | W75: =W36
B76: Legal/Deal Expenses | C76: Nisha | E76: =E37 | F76: =F37 | G76: =G37 | H76: =H37 | I76: =I37 | J76: =J37 | K76: =K37 | L76: =SUM(H76:K76) | M76: =M37 | N76: =N37 | O76: =O37 | P76: =P37 | Q76: =SUM(M76:P76) | R76: =R37 | S76: =S37 | T76: =T37 | U76: =U37 | V76: =SUM(R76:U76) | W76: =W37
B77: Engineering non h/c | C77: Paul Quinn | E77: =E38 | F77: =F38 | G77: =G38 | H77: =H38 | I77: =I38 | J77: =J38 | K77: =K38 | L77: =SUM(H77:K77) | M77: =M38 | N77: =N38 | O77: =O38 | P77: =P38 | Q77: =SUM(M77:P77) | R77: =R38 | S77: =S38 | T77: =T38 | U77: =U38 | V77: =SUM(R77:U77) | W77: =W38
B78: Operations | E78: =E39 | F78: =F39 | G78: =G39 | H78: =H39 | I78: =I39 | J78: =J39 | K78: =K39 | L78: =L39 | ... W78: =W39
B79: Tax | C79: Anu/Harvey | E79: =E40 | F79: =F40 | G79: =G40 | H79: =H40 | I79: =I40 | J79: =J40 | K79: =K40 | L79: =SUM(H79:K79) | M79: =M40 | N79: =N40 | O79: =O40 | P79: =P40 | Q79: =SUM(M79:P79) | R79: =R40 | S79: =S40 | T79: =T40 | U79: =U40 | V79: =SUM(R79:U79) | W79: =W40 | Y79: Stamp duty cost - 2% of shares of company - would it go to p&l?
B80: Other | C80: Nish/Tom | E80: =E42 | F80: =F42 | G80: =G42 | H80: =H42 | I80: =I42 | J80: =J42 | K80: =K42 | L80: =SUM(H80:K80) | M80: =M42 | N80: =N42 | O80: =O42 | P80: =P42 | Q80: =SUM(M80:P80) | R80: =R42 | S80: =S42 | T80: =T42 | U80: =U42 | V80: =SUM(R80:U80) | W80: =W42
B81: Total Operating costs | E81: =SUM(E69:E80) | F81: =SUM(F69:F80) | G81: =SUM(G69:G80) | H81: =SUM(H69:H80) | I81: =SUM(I69:I80) | J81: =SUM(J69:J80) | K81: =SUM(K69:K80) | L81: =SUM(H81:K81) | M81: =SUM(M69:M80) | N81: =SUM(N69:N80) | O81: =SUM(O69:O80) | P81: =SUM(P69:P80) | Q81: =SUM(M81:P81) | R81: =SUM(R69:R80) | S81: =SUM(S69:S80) | T81: =SUM(T69:T80) | U81: =SUM(U69:U80) | V81: =SUM(R81:U81) | W81: =SUM(W69:W80)
B82: Total costs (including one off costs) | E82: =+E44+E57 | F82: =+F44+F57 | G82: =+G44+G57 | H82: =+H44+H57 | I82: =+I44+I57 | J82: =+J44+J57 | K82: =+K44+K57 | L82: =+L44+L57 | ... W82: =+W44+W57
B83: Check | E83: =E82-SUM(E69:E80)-E59-E60 | F83: =F82-SUM(F69:F80)-F59-F60 | G83: =G82-SUM(G69:G80)-G59-G60 | H83: =H82-SUM(H69:H80)-H59-H60 | I83: =I82-SUM(I69:I80)-I59-I60 | J83: =J82-SUM(J69:J80)-J59-J60 | K83: =K82-SUM(K69:K80)-K59-K60 | L83: =L82-SUM(L69:L80)-L59-L60 | ... W83: =W82-SUM(W69:W80)-W59-W60
B84: Non GAAP run rate costs | E84: =(E22+E24+E26+E31+E32+E35+E42+E55+E56+E39+E40+E38+E48+E50+E52+E27+E53) | F84: =(F22+F24+F26+F31+F32+F35+F42+F55+F56+F39+F40+F38+F48+F50+F52+F27+F53) | G84: =(G22+G24+G26+G31+G32+G35+G42+G55+G56+G39+G40+G38+G48+G50+G52+G27+G53) | H84: =(H22+H24+H26+H31+H32+H35+H42+H55+H56+H39+H40+H38+H48+H50+H52+H27+H53) | I84: =(I22+I24+I26+I31+I32+I35+I42+I55+I56+I39+I40+I38+I48+I50+I52+I27+I53) | J84: =(J22+J24+J26+J31+J32+J35+J42+J55+J56+J39+J40+J38+J48+J50+J52+J27+J53) | K84: =(K22+K24+K26+K31+K32+K35+K42+K55+K56+K39+K40+K38+K48+K50+K52+K27+K53) | L84: =(L22+L24+L26+L31+L32+L35+L42+L55+L56+L39+L40+L38+L48+L50+L52+L27+L53) | ... W84: =(W22+W24+W26+W31+W32+W35+W42+W55+W56+W39+W40+W38+W48+W50+W52+W27+W53)
W85: =G85+L85+Q85+V85
B86: One time costs:
B87: Legal/Deal Expenses | C87: Nisha | F87: =F37 | G87: =SUM(E87:F87) | L87: =SUM(H87:K87) | Q87: =SUM(M87:P87) | V87: =SUM(R87:U87) | W87: =G87+L87+Q87+V87
B88: IT Costs - security/Blackduck costs | C88: Jonathan W | E88: =E33 | G88: =SUM(E88:F88) | W88: =G88+L88+Q88+V88
B89: Deal costs | E89: =SUM(E87:E88) | F89: =SUM(F87:F88) | G89: =SUM(G87:G88) | H89: =SUM(H87:H88) | I89: =SUM(I87:I88) | J89: =SUM(J87:J88) | K89: =SUM(K87:K88) | L89: =SUM(L87:L88) | ... W89: =SUM(W87:W88)
B90: Inventory write off - units that we will not sell | C90: Audrey | F90: =F16 | G90: =SUM(E90:F90) | W90: =G90+L90+Q90+V90 | Y90: Given it results from the transaction and our decision to discontinue selling their product (one time event), there is rationale for it to be GAAP expense only however it is not material enough to consider as GAAP only
B91: Inventory write off - Buy back of DokiPal units | E91: =E17 | F91: =F17 | G91: =G17 | H91: =H17 | I91: =I17 | J91: =J17 | K91: =K17 | L91: =L17 | ... W91: =W17
B92: IT Costs - integration | C92: Bill B | E92: =E34 | F92: =F34 | G92: =G34 | H92: =H34 | I92: =I34 | J92: =J34 | K92: =K34 | L92: =L34 | ... V92: =V34 | W92: =G92+L92+Q92+V92
B93: Valuation reviews | C93: Heather | F93: =F36 | G93: =SUM(E93:F93) | L93: =SUM(H93:K93) | Q93: =SUM(M93:P93) | V93: =SUM(R93:U93) | W93: =G93+L93+Q93+V93
B94: Integration costs | E94: =SUM(E90:E93) | F94: =SUM(F90:F93) | G94: =SUM(G90:G93) | H94: =SUM(H90:H93) | I94: =SUM(I90:I93) | J94: =SUM(J90:J93) | K94: =SUM(K90:K93) | L94: =SUM(L90:L93) | ... W94: =SUM(W90:W93)
B95: Total one off costs | E95: =E94+E89 | F95: =F94+F89 | G95: =G94+G89 | H95: =H94+H89 | I95: =I94+I89 | J95: =J94+J89 | K95: =K94+K89 | L95: =L94+L89 | ... W95: =W94+W89
B96: Check | E96: =E95-E37-E36-E33-E34-E16-E17 | F96: =F95-F37-F36-F33-F34-F16-F17 | G96: =G95-G37-G36-G33-G34-G16-G17 | H96: =H95-H37-H36-H33-H34-H16-H17 | I96: =I95-I37-I36-I33-I34-I16-I17 | J96: =J95-J37-J36-J33-J34-J16-J17 | K96: =K95-K37-K36-K33-K34-K16-K17 | L96: =L95-L37-L36-L33-L34-L16-L17 | ... W96: =W95-W37-W36-W33-W34-W16-W17
B97: Check | E97: =E82-E95-E84 | F97: =F82-F95-F84 | G97: =G82-G95-G84 | H97: =H82-H95-H84 | I97: =I82-I95-I84 | J97: =J82-J95-J84 | K97: =K82-K95-K84 | L97: =L82-L95-L84 | ... W97: =W82-W95-W84
B99: HC Costs | E99: =E29+E54 | F99: =F29+F54 | G99: =G29+G54 | H99: =H29+H54 | I99: =I29+I54 | J99: =J29+J54 | K99: =K29+K54 | L99: =L29+L54 | ... W99: =W29+W54
B100: - curent headcount | E100: =E29 | F100: =F29 | G100: =G29 | H100: =H29 | I100: =I29 | J100: =J29 | K100: =K29 | L100: =L29 | ... W100: =W29
B101: - new headcount | E101: =E54 | F101: =F54 | G101: =G54 | H101: =H54 | I101: =I54 | J101: =J54 | K101: =K54 | L101: =L54 | ... W101: =W54 | Z101: More engineers | AA101: =(L101-L100)/L100
B102: Non HC Costs | E102: =E82-E99-E95 | F102: =F82-F99-F95 | G102: =G82-G99-G95 | H102: =H82-H99-H95 | I102: =I82-I99-I95 | J102: =J82-J99-J95 | K102: =K82-K99-K95 | L102: =L82-L99-L95 | ... W102: =W82-W99-W95
B103: Non GAAP run rate costs | E103: =E99+E102 | F103: =F99+F102 | G103: =G99+G102 | H103: =H99+H102 | I103: =I99+I102 | J103: =J99+J102 | K103: =K99+K102 | L103: =L99+L102 | ... W103: =W99+W102
W104: =W82-W95-W103
B106: RSUs | F106: =[1]Sheet1!$N$37/4 | G106: =F106 | H106: =G106 | I106: =H106 | J106: =I106 | K106: =J106 | L106: =SUM(H106:K106) | M106: =H106 | N106: =M106 | O106: =N106 | P106: =O106 | Q106: =SUM(M106:P106) | R106: =H106 | S106: =R106 | T106: =S106 | V106: =SUM(R106:U106) | W106: =G106+L106+Q106+V106
B107: Non GAAP Costs
B109: Working capital costs - purchase price negotiation or posted against Goodwill | Y109: These are net working capital costs which are not already included in the books at the point of acquisition (whereas the inventory and facilities current lease costs above are our decision once we have already integrated)
...

Sheet Recoverable units
A3: DokiPal Units as of September 1, 2019
B5: # in inventory at Doki | C5: # w/ channel Partners | D5: # sold into Market | E5: Sub-total Units | F5: # activated | G5: # active (last 30 days) | H5: # active (last 6 Months) (i.e., pinged server at least once in last 6 months) | I5: Warranty Period Length | J5: # units defective / warranty claim | K5: Cost of Replacements | L5: # Still Under warranty
B6: 3018 | C6: ? | D6: 4982 | E6: 8000 | F6: 2221 | G6: 2221 | H6: 2221 | I6: 12 months | J6: 55 | K6: $65/ unit | L6: All
C8: We don't have visibility on the # of units our distributors/ retailers have in stock | D8: This is the total # of units we sold through wholesale and online channels
E12: =D6-F6
B14: Added by LB:
B15: Invoice price disti would have paid | E15: =180*60% | M15: Q for Audrey - why multiply by 40% for returns?
A16: 0.1 | B16: 10% mark up to incentivise partners to return stock | E16: =E15*(1+A16)
B18: % of units able to repurchase | E18: 0.4 | F18: 0.5 | G18: 0.6 | H18: 0.7 | I18: 0.8 | J18: 0.9 | K18: 1 | M18: This is a q for Bobinder?
E20: =($E$12*E18)*$E$16 | F20: =($E$12*F18)*$E$16 | G20: =($E$12*G18)*$E$16 | H20: =($E$12*H18)*$E$16 | I20: =($E$12*I18)*$E$16 | J20: =($E$12*J18)*$E$16 | K20: =($E$12*K18)*$E$16 | M20: Will we write these off/keep them for returns/warranty (in which case a double hit to the p&l is showing)?

Sheet Stamp duty
B2: We wanted also to get back to the group on the stamp duty. The current rate of stamp duty is an aggregate of 0.2 percent (0.1 percent payable by each of Seller and Buyer) of the higher of (i) the purchase price or (ii) the value of the stock, which is typically the net asset value of the target as shown in its latest audited accounts. The determination of the purchase price (assuming it exceeds NAV) would (1) take into account any purchase price adjustments e.g. working capital adjustment and (2) include the maximum amount of the earnout. Fyi, there is an opportunity to apply for a refund of excessive stamp duty paid if turns out the actual earnout is less than the maximum, but the period to do so is limited to 2 years.

Sheet 2) SW Eng
A1: Delta Incremental Costs
A3: Headcount | H3: 2019 | J3: 2020 | N3: 2021 | R3: 2022
H4: 43647 | I4: 43739 | J4: 43831 | K4: 43922 | L4: 44013 | M4: 44105 | N4: 44197 | O4: 44287 | P4: 44378 | Q4: 44470 | R4: 44562 | S4: 44652
A5: Submitted by | B5: Department | C5: TBH Title | D5: Description | E5: Hire Date | F5: Location | G5: Base Salary Estimate USD | H5: Q3 | I5: Q4 | J5: Q1 | K5: Q2 | L5: Q3 | M5: Q4 | N5: Q1 | O5: Q2 | P5: Q3 | Q5: Q4 | R5: Q1 | S5: Q2
H6: =IF($E6<I$4,($G6*1.3)/4,0) | I6: =IF($E6<J$4,($G6*1.3)/4,0) | J6: =IF($E6<K$4,($G6*1.3)/4,0) | K6: =IF($E6<L$4,($G6*1.3)/4,0) | L6: =IF($E6<M$4,($G6*1.3)/4,0) | M6: =IF($E6<N$4,($G6*1.3)/4,0) | N6: =IF($E6<O$4,($G6*1.3)/4,0) | O6: =IF($E6<P$4,($G6*1.3)/4,0) | ... R6: =IF($E6<S$4,($G6*1.3)/4,0) | S6: =IF($E6<S$4,($G6*1.3)/4,0)
H7: =IF($E7<I$4,($G7*1.3)/4,0) | I7: =IF($E7<J$4,($G7*1.3)/4,0) | J7: =IF($E7<K$4,($G7*1.3)/4,0) | K7: =IF($E7<L$4,($G7*1.3)/4,0) | L7: =IF($E7<M$4,($G7*1.3)/4,0) | M7: =IF($E7<N$4,($G7*1.3)/4,0) | N7: =IF($E7<O$4,($G7*1.3)/4,0) | O7: =IF($E7<P$4,($G7*1.3)/4,0) | ... R7: =IF($E7<S$4,($G7*1.3)/4,0) | S7: =IF($E7<S$4,($G7*1.3)/4,0)
H8: =IF($E8<I$4,($G8*1.3)/4,0) | I8: =IF($E8<J$4,($G8*1.3)/4,0) | J8: =IF($E8<K$4,($G8*1.3)/4,0) | K8: =IF($E8<L$4,($G8*1.3)/4,0) | L8: =IF($E8<M$4,($G8*1.3)/4,0) | M8: =IF($E8<N$4,($G8*1.3)/4,0) | N8: =IF($E8<O$4,($G8*1.3)/4,0) | O8: =IF($E8<P$4,($G8*1.3)/4,0) | ... R8: =IF($E8<S$4,($G8*1.3)/4,0) | S8: =IF($E8<S$4,($G8*1.3)/4,0)
H9: =IF($E9<I$4,($G9*1.3)/4,0) | I9: =IF($E9<J$4,($G9*1.3)/4,0) | J9: =IF($E9<K$4,($G9*1.3)/4,0) | K9: =IF($E9<L$4,($G9*1.3)/4,0) | L9: =IF($E9<M$4,($G9*1.3)/4,0) | M9: =IF($E9<N$4,($G9*1.3)/4,0) | N9: =IF($E9<O$4,($G9*1.3)/4,0) | O9: =IF($E9<P$4,($G9*1.3)/4,0) | ... R9: =IF($E9<S$4,($G9*1.3)/4,0) | S9: =IF($E9<S$4,($G9*1.3)/4,0)
H10: =IF($E10<I$4,($G10*1.3)/4,0) | I10: =IF($E10<J$4,($G10*1.3)/4,0) | J10: =IF($E10<K$4,($G10*1.3)/4,0) | K10: =IF($E10<L$4,($G10*1.3)/4,0) | L10: =IF($E10<M$4,($G10*1.3)/4,0) | M10: =IF($E10<N$4,($G10*1.3)/4,0) | N10: =IF($E10<O$4,($G10*1.3)/4,0) | O10: =IF($E10<P$4,($G10*1.3)/4,0) | ... R10: =IF($E10<S$4,($G10*1.3)/4,0) | S10: =IF($E10<S$4,($G10*1.3)/4,0)
H11: =IF($E11<I$4,($G11*1.3)/4,0) | I11: =IF($E11<J$4,($G11*1.3)/4,0) | J11: =IF($E11<K$4,($G11*1.3)/4,0) | K11: =IF($E11<L$4,($G11*1.3)/4,0) | L11: =IF($E11<M$4,($G11*1.3)/4,0) | M11: =IF($E11<N$4,($G11*1.3)/4,0) | N11: =IF($E11<O$4,($G11*1.3)/4,0) | O11: =IF($E11<P$4,($G11*1.3)/4,0) | ... R11: =IF($E11<S$4,($G11*1.3)/4,0) | S11: =IF($E11<S$4,($G11*1.3)/4,0)
H12: =IF($E12<I$4,($G12*1.3)/4,0) | I12: =IF($E12<J$4,($G12*1.3)/4,0) | J12: =IF($E12<K$4,($G12*1.3)/4,0) | K12: =IF($E12<L$4,($G12*1.3)/4,0) | L12: =IF($E12<M$4,($G12*1.3)/4,0) | M12: =IF($E12<N$4,($G12*1.3)/4,0) | N12: =IF($E12<O$4,($G12*1.3)/4,0) | O12: =IF($E12<P$4,($G12*1.3)/4,0) | ... R12: =IF($E12<S$4,($G12*1.3)/4,0) | S12: =IF($E12<S$4,($G12*1.3)/4,0)
H13: =IF($E13<I$4,($G13*1.3)/4,0) | I13: =IF($E13<J$4,($G13*1.3)/4,0) | J13: =IF($E13<K$4,($G13*1.3)/4,0) | K13: =IF($E13<L$4,($G13*1.3)/4,0) | L13: =IF($E13<M$4,($G13*1.3)/4,0) | M13: =IF($E13<N$4,($G13*1.3)/4,0) | N13: =IF($E13<O$4,($G13*1.3)/4,0) | O13: =IF($E13<P$4,($G13*1.3)/4,0) | ... R13: =IF($E13<S$4,($G13*1.3)/4,0) | S13: =IF($E13<S$4,($G13*1.3)/4,0)
H14: =IF($E14<I$4,($G14*1.3)/4,0) | I14: =IF($E14<J$4,($G14*1.3)/4,0) | J14: =IF($E14<K$4,($G14*1.3)/4,0) | K14: =IF($E14<L$4,($G14*1.3)/4,0) | L14: =IF($E14<M$4,($G14*1.3)/4,0) | M14: =IF($E14<N$4,($G14*1.3)/4,0) | N14: =IF($E14<O$4,($G14*1.3)/4,0) | O14: =IF($E14<P$4,($G14*1.3)/4,0) | ... R14: =IF($E14<S$4,($G14*1.3)/4,0) | S14: =IF($E14<S$4,($G14*1.3)/4,0)
H15: =IF($E15<I$4,($G15*1.3)/4,0) | I15: =IF($E15<J$4,($G15*1.3)/4,0) | J15: =IF($E15<K$4,($G15*1.3)/4,0) | K15: =IF($E15<L$4,($G15*1.3)/4,0) | L15: =IF($E15<M$4,($G15*1.3)/4,0) | M15: =IF($E15<N$4,($G15*1.3)/4,0) | N15: =IF($E15<O$4,($G15*1.3)/4,0) | O15: =IF($E15<P$4,($G15*1.3)/4,0) | ... R15: =IF($E15<S$4,($G15*1.3)/4,0) | S15: =IF($E15<S$4,($G15*1.3)/4,0)
H16: =IF($E16<I$4,($G16*1.3)/4,0) | I16: =IF($E16<J$4,($G16*1.3)/4,0) | J16: =IF($E16<K$4,($G16*1.3)/4,0) | K16: =IF($E16<L$4,($G16*1.3)/4,0) | L16: =IF($E16<M$4,($G16*1.3)/4,0) | M16: =IF($E16<N$4,($G16*1.3)/4,0) | N16: =IF($E16<O$4,($G16*1.3)/4,0) | O16: =IF($E16<P$4,($G16*1.3)/4,0) | ... R16: =IF($E16<S$4,($G16*1.3)/4,0) | S16: =IF($E16<S$4,($G16*1.3)/4,0)
H17: =IF($E17<I$4,($G17*1.3)/4,0) | I17: =IF($E17<J$4,($G17*1.3)/4,0) | J17: =IF($E17<K$4,($G17*1.3)/4,0) | K17: =IF($E17<L$4,($G17*1.3)/4,0) | L17: =IF($E17<M$4,($G17*1.3)/4,0) | M17: =IF($E17<N$4,($G17*1.3)/4,0) | N17: =IF($E17<O$4,($G17*1.3)/4,0) | O17: =IF($E17<P$4,($G17*1.3)/4,0) | ... R17: =IF($E17<S$4,($G17*1.3)/4,0) | S17: =IF($E17<S$4,($G17*1.3)/4,0)
... H24: =IF($E24<I$4,($G24*1.3)/4,0) | I24: =IF($E24<J$4,($G24*1.3)/4,0) | J24: =IF($E24<K$4,($G24*1.3)/4,0) | K24: =IF($E24<L$4,($G24*1.3)/4,0) | L24: =IF($E24<M$4,($G24*1.3)/4,0) | M24: =IF($E24<N$4,($G24*1.3)/4,0) | N24: =IF($E24<O$4,($G24*1.3)/4,0) | O24: =IF($E24<P$4,($G24*1.3)/4,0) | ... R24: =IF($E24<S$4,($G24*1.3)/4,0) | S24: =IF($E24<S$4,($G24*1.3)/4,0)
H25: =SUM(H6:H24) | I25: =SUM(I6:I24) | J25: =SUM(J6:J24) | K25: =SUM(K6:K24) | L25: =SUM(L6:L24) | M25: =SUM(M6:M24) | N25: =SUM(N6:N24) | O25: =SUM(O6:O24) | ... S25: =SUM(S6:S24)
A27: Non Headcount | H27: 2019 | J27: 2020 | N27: 2021 | R27: 2022
A28: Submitted by | B28: Department | C28: Description of Spend | D28: Justification | G28: Total Cost Estimate | H28: Q3 | I28: Q4 | J28: Q1 | K28: Q2 | L28: Q3 | M28: Q4 | N28: Q1 | O28: Q2 | P28: Q3 | Q28: Q4 | R28: Q1 | S28: Q2
A29: LB (Based on email from Paul Quinn) | B29: Agora | C29: Set up a new Fitbit owned Agora account - 10k to 50k | D29: Shares video calling API use with another company. This may incur unforeseen costs as we support their existing in-market devices for a yea | I29: =50000/4 | J29: =I29 | K29: =J29 | L29: =K29
A31: Engineering | B31: licensing for devt tools - current employees | C31: Licensing for development tools | G31: $500 per engineering employee per year listed above (new hire) - for above people in Hong Kong office | I31: ='I. TECH'!J26*(500/4) | J31: ='I. TECH'!K26*(500/4) | K31: ='I. TECH'!L26*(500/4) | L31: ='I. TECH'!M26*(500/4) | M31: ='I. TECH'!N26*(500/4) | N31: ='I. TECH'!O26*(500/4) | O31: ='I. TECH'!P26*(500/4) | P31: ='I. TECH'!Q26*(500/4) | ... S31: ='I. TECH'!T26*(500/4)
B32: licensing for devt tools - new employees | G32: $500 per engineering employee per year listed above (existing ) - for above people in Hong Kong office | I32: =14*(500/4) | J32: =14*(500/4) | K32: =14*(500/4) | L32: =14*(500/4) | M32: =14*(500/4) | N32: =14*(500/4) | O32: =14*(500/4) | P32: =14*(500/4) | ... S32: =14*(500/4)
A33: Ryan Krems | B33: Product | C33: Recruiting Budget | D33: Need to get new-hires on-board - 2 months of average salary per new hire
A35: adde by LB based on email from Ryan | B35: For 4Q2019 only as we will want to support the PRC mode for a limited time only. | D35: alibaba cloud | I35: 1000
A36: adde by LB based on email from Ryan | B36: Github - Yes - Through 4Q2020 (small amount, want to make sure it isn't effecting their work flow for existing users) | I36: =344/8*3 | J36: =I36 | K36: =J36 | L36: =K36 | M36: =L36
A37: adde by LB based on email from Ryan | B37: Mailchimp - Yes - Through 4Q2020 (would expect this to be a much smaller amount that they were having before) | I37: =1600/8*3 | J37: =I37 | K37: =J37 | L37: =K37 | M37: =L37
A38: adde by LB based on email from Ryan | B38: Linode - Yes - Through 4Q2020 (not sure what they are using for, but a really small amount) | I38: =80/8*3 | J38: =I38 | K38: =J38 | L38: =K38 | M38: =L38
A39: adde by LB based on email from Ryan | B39: AWS - Yes - Through 4Q2020 (this is to support their current user base) | I39: =7081/8*3 | J39: =I39 | K39: =J39 | L39: =K39 | M39: =L39
A40: adde by LB based on email from Ryan | B40: Google Cloud - Yes - Through 4Q2019 (expect these to all be rolled over to Fitbit infra by EOY) | I40: =16400/8*3
G41: =SUM(G29:G40) | H41: =SUM(H29:H34) | I41: =SUM(I29:I40) | J41: =SUM(J29:J40) | K41: =SUM(K29:K40) | L41: =SUM(L29:L40) | M41: =SUM(M29:M40) | N41: =SUM(N29:N40) | O41: =SUM(O29:O40) | P41: =SUM(P29:P40) | ... S41: =SUM(S29:S40)

Sheet 4) Accounting
A1: Delta Incremental Costs
A3: Headcount | H3: 2019 | J3: 2020 | N3: 2021 | R3: 2022
H4: 43647 | I4: 43739 | J4: 43831 | K4: 43922 | L4: 44013 | M4: 44105 | N4: 44197 | O4: 44287 | P4: 44378 | Q4: 44470 | R4: 44562 | S4: 44652
A5: Submitted by | B5: Department | C5: TBH Title | D5: Description | E5: Hire Date | F5: Location | G5: Base Salary Estimate USD | H5: Q3 | I5: Q4 | J5: Q1 | K5: Q2 | L5: Q3 | M5: Q4 | N5: Q1 | O5: Q2 | P5: Q3 | Q5: Q4 | R5: Q1 | S5: Q2
H6: =IF($E6<I$4,($G6*1.3)/4,0) | I6: =IF($E6<J$4,($G6*1.3)/4,0) | J6: =IF($E6<K$4,($G6*1.3)/4,0) | K6: =IF($E6<L$4,($G6*1.3)/4,0) | L6: =IF($E6<M$4,($G6*1.3)/4,0) | M6: =IF($E6<N$4,($G6*1.3)/4,0) | N6: =IF($E6<O$4,($G6*1.3)/4,0) | O6: =IF($E6<P$4,($G6*1.3)/4,0) | ... R6: =IF($E6<S$4,($G6*1.3)/4,0) | S6: =IF($E6<S$4,($G6*1.3)/4,0)
H7: =IF($E7<I$4,($G7*1.3)/4,0) | I7: =IF($E7<J$4,($G7*1.3)/4,0) | J7: =IF($E7<K$4,($G7*1.3)/4,0) | K7: =IF($E7<L$4,($G7*1.3)/4,0) | L7: =IF($E7<M$4,($G7*1.3)/4,0) | M7: =IF($E7<N$4,($G7*1.3)/4,0) | N7: =IF($E7<O$4,($G7*1.3)/4,0) | O7: =IF($E7<P$4,($G7*1.3)/4,0) | ... R7: =IF($E7<S$4,($G7*1.3)/4,0) | S7: =IF($E7<S$4,($G7*1.3)/4,0)
H8: =IF($E8<I$4,($G8*1.3)/4,0) | I8: =IF($E8<J$4,($G8*1.3)/4,0) | J8: =IF($E8<K$4,($G8*1.3)/4,0) | K8: =IF($E8<L$4,($G8*1.3)/4,0) | L8: =IF($E8<M$4,($G8*1.3)/4,0) | M8: =IF($E8<N$4,($G8*1.3)/4,0) | N8: =IF($E8<O$4,($G8*1.3)/4,0) | O8: =IF($E8<P$4,($G8*1.3)/4,0) | ... R8: =IF($E8<S$4,($G8*1.3)/4,0) | S8: =IF($E8<S$4,($G8*1.3)/4,0)
H9: =IF($E9<I$4,($G9*1.3)/4,0) | I9: =IF($E9<J$4,($G9*1.3)/4,0) | J9: =IF($E9<K$4,($G9*1.3)/4,0) | K9: =IF($E9<L$4,($G9*1.3)/4,0) | L9: =IF($E9<M$4,($G9*1.3)/4,0) | M9: =IF($E9<N$4,($G9*1.3)/4,0) | N9: =IF($E9<O$4,($G9*1.3)/4,0) | O9: =IF($E9<P$4,($G9*1.3)/4,0) | ... R9: =IF($E9<S$4,($G9*1.3)/4,0) | S9: =IF($E9<S$4,($G9*1.3)/4,0)
H10: =IF($E10<I$4,($G10*1.3)/4,0) | I10: =IF($E10<J$4,($G10*1.3)/4,0) | J10: =IF($E10<K$4,($G10*1.3)/4,0) | K10: =IF($E10<L$4,($G10*1.3)/4,0) | L10: =IF($E10<M$4,($G10*1.3)/4,0) | M10: =IF($E10<N$4,($G10*1.3)/4,0) | N10: =IF($E10<O$4,($G10*1.3)/4,0) | O10: =IF($E10<P$4,($G10*1.3)/4,0) | ... R10: =IF($E10<S$4,($G10*1.3)/4,0) | S10: =IF($E10<S$4,($G10*1.3)/4,0)
H11: =IF($E11<I$4,($G11*1.3)/4,0) | I11: =IF($E11<J$4,($G11*1.3)/4,0) | J11: =IF($E11<K$4,($G11*1.3)/4,0) | K11: =IF($E11<L$4,($G11*1.3)/4,0) | L11: =IF($E11<M$4,($G11*1.3)/4,0) | M11: =IF($E11<N$4,($G11*1.3)/4,0) | N11: =IF($E11<O$4,($G11*1.3)/4,0) | O11: =IF($E11<P$4,($G11*1.3)/4,0) | ... R11: =IF($E11<S$4,($G11*1.3)/4,0) | S11: =IF($E11<S$4,($G11*1.3)/4,0)
H12: =IF($E12<I$4,($G12*1.3)/4,0) | I12: =IF($E12<J$4,($G12*1.3)/4,0) | J12: =IF($E12<K$4,($G12*1.3)/4,0) | K12: =IF($E12<L$4,($G12*1.3)/4,0) | L12: =IF($E12<M$4,($G12*1.3)/4,0) | M12: =IF($E12<N$4,($G12*1.3)/4,0) | N12: =IF($E12<O$4,($G12*1.3)/4,0) | O12: =IF($E12<P$4,($G12*1.3)/4,0) | ... R12: =IF($E12<S$4,($G12*1.3)/4,0) | S12: =IF($E12<S$4,($G12*1.3)/4,0)
H13: =IF($E13<I$4,($G13*1.3)/4,0) | I13: =IF($E13<J$4,($G13*1.3)/4,0) | J13: =IF($E13<K$4,($G13*1.3)/4,0) | K13: =IF($E13<L$4,($G13*1.3)/4,0) | L13: =IF($E13<M$4,($G13*1.3)/4,0) | M13: =IF($E13<N$4,($G13*1.3)/4,0) | N13: =IF($E13<O$4,($G13*1.3)/4,0) | O13: =IF($E13<P$4,($G13*1.3)/4,0) | ... R13: =IF($E13<S$4,($G13*1.3)/4,0) | S13: =IF($E13<S$4,($G13*1.3)/4,0)
H14: =IF($E14<I$4,($G14*1.3)/4,0) | I14: =IF($E14<J$4,($G14*1.3)/4,0) | J14: =IF($E14<K$4,($G14*1.3)/4,0) | K14: =IF($E14<L$4,($G14*1.3)/4,0) | L14: =IF($E14<M$4,($G14*1.3)/4,0) | M14: =IF($E14<N$4,($G14*1.3)/4,0) | N14: =IF($E14<O$4,($G14*1.3)/4,0) | O14: =IF($E14<P$4,($G14*1.3)/4,0) | ... R14: =IF($E14<S$4,($G14*1.3)/4,0) | S14: =IF($E14<S$4,($G14*1.3)/4,0)
H15: =IF($E15<I$4,($G15*1.3)/4,0) | I15: =IF($E15<J$4,($G15*1.3)/4,0) | J15: =IF($E15<K$4,($G15*1.3)/4,0) | K15: =IF($E15<L$4,($G15*1.3)/4,0) | L15: =IF($E15<M$4,($G15*1.3)/4,0) | M15: =IF($E15<N$4,($G15*1.3)/4,0) | N15: =IF($E15<O$4,($G15*1.3)/4,0) | O15: =IF($E15<P$4,($G15*1.3)/4,0) | ... R15: =IF($E15<S$4,($G15*1.3)/4,0) | S15: =IF($E15<S$4,($G15*1.3)/4,0)
H16: =IF($E16<I$4,($G16*1.3)/4,0) | I16: =IF($E16<J$4,($G16*1.3)/4,0) | J16: =IF($E16<K$4,($G16*1.3)/4,0) | K16: =IF($E16<L$4,($G16*1.3)/4,0) | L16: =IF($E16<M$4,($G16*1.3)/4,0) | M16: =IF($E16<N$4,($G16*1.3)/4,0) | N16: =IF($E16<O$4,($G16*1.3)/4,0) | O16: =IF($E16<P$4,($G16*1.3)/4,0) | ... R16: =IF($E16<S$4,($G16*1.3)/4,0) | S16: =IF($E16<S$4,($G16*1.3)/4,0)
H17: =IF($E17<I$4,($G17*1.3)/4,0) | I17: =IF($E17<J$4,($G17*1.3)/4,0) | J17: =IF($E17<K$4,($G17*1.3)/4,0) | K17: =IF($E17<L$4,($G17*1.3)/4,0) | L17: =IF($E17<M$4,($G17*1.3)/4,0) | M17: =IF($E17<N$4,($G17*1.3)/4,0) | N17: =IF($E17<O$4,($G17*1.3)/4,0) | O17: =IF($E17<P$4,($G17*1.3)/4,0) | ... R17: =IF($E17<S$4,($G17*1.3)/4,0) | S17: =IF($E17<S$4,($G17*1.3)/4,0)
... H24: =IF($E24<I$4,($G24*1.3)/4,0) | I24: =IF($E24<J$4,($G24*1.3)/4,0) | J24: =IF($E24<K$4,($G24*1.3)/4,0) | K24: =IF($E24<L$4,($G24*1.3)/4,0) | L24: =IF($E24<M$4,($G24*1.3)/4,0) | M24: =IF($E24<N$4,($G24*1.3)/4,0) | N24: =IF($E24<O$4,($G24*1.3)/4,0) | O24: =IF($E24<P$4,($G24*1.3)/4,0) | ... R24: =IF($E24<S$4,($G24*1.3)/4,0) | S24: =IF($E24<S$4,($G24*1.3)/4,0)
H25: =SUM(H6:H24) | I25: =SUM(I6:I24) | J25: =SUM(J6:J24) | K25: =SUM(K6:K24) | L25: =SUM(L6:L24) | M25: =SUM(M6:M24) | N25: =SUM(N6:N24) | O25: =SUM(O6:O24) | ... S25: =SUM(S6:S24)
A27: Non Headcount | H27: 2019 | J27: 2020 | N27: 2021 | R27: 2022
A28: Submitted by | B28: Department | C28: Description of Spend | D28: Justification | G28: Total Cost Estimate | H28: Q3 | I28: Q4 | J28: Q1 | K28: Q2 | L28: Q3 | M28: Q4 | N28: Q1 | O28: Q2 | P28: Q3 | Q28: Q4 | R28: Q1 | S28: Q2
A29: Heather | B29: Accounting | C29: Valuation PPA | D29: Valuation of Intangibles & Goodwill | G29: =I29 | I29: 15000
A30: Heather | B30: Accounting | C30: GT PPA Review | D30: External Audit Review of Valuation | G30: =I30 | I30: 30000
G41: =SUM(G29:G40) | H41: =SUM(H29:H34) | I41: =SUM(I29:I34) | J41: =SUM(J29:J34) | K41: =SUM(K29:K34) | L41: =SUM(L29:L34) | M41: =SUM(M29:M34) | N41: =SUM(N29:N34) | O41: =SUM(O29:O34) | ... S41: =SUM(S29:S34)

Sheet 8) Facilities
A1: Delta Incremental Costs
A3: Headcount | H3: 2019 | J3: 2020 | N3: 2021 | R3: 2022
H4: 43647 | I4: 43739 | J4: 43831 | K4: 43922 | L4: 44013 | M4: 44105 | N4: 44197 | O4: 44287 | P4: 44378 | Q4: 44470 | R4: 44562 | S4: 44652
A5: Submitted by | B5: Department | C5: TBH Title | D5: Description | E5: Hire Date | F5: Location | G5: Base Salary Estimate USD | H5: Q3 | I5: Q4 | J5: Q1 | K5: Q2 | L5: Q3 | M5: Q4 | N5: Q1 | O5: Q2 | P5: Q3 | Q5: Q4 | R5: Q1 | S5: Q2
H6: =IF($E6<I$4,($G6*1.3)/4,0) | I6: =IF($E6<J$4,($G6*1.3)/4,0) | J6: =IF($E6<K$4,($G6*1.3)/4,0) | K6: =IF($E6<L$4,($G6*1.3)/4,0) | L6: =IF($E6<M$4,($G6*1.3)/4,0) | M6: =IF($E6<N$4,($G6*1.3)/4,0) | N6: =IF($E6<O$4,($G6*1.3)/4,0) | O6: =IF($E6<P$4,($G6*1.3)/4,0) | ... R6: =IF($E6<S$4,($G6*1.3)/4,0) | S6: =IF($E6<S$4,($G6*1.3)/4,0)
H7: =IF($E7<I$4,($G7*1.3)/4,0) | I7: =IF($E7<J$4,($G7*1.3)/4,0) | J7: =IF($E7<K$4,($G7*1.3)/4,0) | K7: =IF($E7<L$4,($G7*1.3)/4,0) | L7: =IF($E7<M$4,($G7*1.3)/4,0) | M7: =IF($E7<N$4,($G7*1.3)/4,0) | N7: =IF($E7<O$4,($G7*1.3)/4,0) | O7: =IF($E7<P$4,($G7*1.3)/4,0) | ... R7: =IF($E7<S$4,($G7*1.3)/4,0) | S7: =IF($E7<S$4,($G7*1.3)/4,0)
H8: =IF($E8<I$4,($G8*1.3)/4,0) | I8: =IF($E8<J$4,($G8*1.3)/4,0) | J8: =IF($E8<K$4,($G8*1.3)/4,0) | K8: =IF($E8<L$4,($G8*1.3)/4,0) | L8: =IF($E8<M$4,($G8*1.3)/4,0) | M8: =IF($E8<N$4,($G8*1.3)/4,0) | N8: =IF($E8<O$4,($G8*1.3)/4,0) | O8: =IF($E8<P$4,($G8*1.3)/4,0) | ... R8: =IF($E8<S$4,($G8*1.3)/4,0) | S8: =IF($E8<S$4,($G8*1.3)/4,0)
H9: =IF($E9<I$4,($G9*1.3)/4,0) | I9: =IF($E9<J$4,($G9*1.3)/4,0) | J9: =IF($E9<K$4,($G9*1.3)/4,0) | K9: =IF($E9<L$4,($G9*1.3)/4,0) | L9: =IF($E9<M$4,($G9*1.3)/4,0) | M9: =IF($E9<N$4,($G9*1.3)/4,0) | N9: =IF($E9<O$4,($G9*1.3)/4,0) | O9: =IF($E9<P$4,($G9*1.3)/4,0) | ... R9: =IF($E9<S$4,($G9*1.3)/4,0) | S9: =IF($E9<S$4,($G9*1.3)/4,0)
H10: =IF($E10<I$4,($G10*1.3)/4,0) | I10: =IF($E10<J$4,($G10*1.3)/4,0) | J10: =IF($E10<K$4,($G10*1.3)/4,0) | K10: =IF($E10<L$4,($G10*1.3)/4,0) | L10: =IF($E10<M$4,($G10*1.3)/4,0) | M10: =IF($E10<N$4,($G10*1.3)/4,0) | N10: =IF($E10<O$4,($G10*1.3)/4,0) | O10: =IF($E10<P$4,($G10*1.3)/4,0) | ... R10: =IF($E10<S$4,($G10*1.3)/4,0) | S10: =IF($E10<S$4,($G10*1.3)/4,0)
H11: =IF($E11<I$4,($G11*1.3)/4,0) | I11: =IF($E11<J$4,($G11*1.3)/4,0) | J11: =IF($E11<K$4,($G11*1.3)/4,0) | K11: =IF($E11<L$4,($G11*1.3)/4,0) | L11: =IF($E11<M$4,($G11*1.3)/4,0) | M11: =IF($E11<N$4,($G11*1.3)/4,0) | N11: =IF($E11<O$4,($G11*1.3)/4,0) | O11: =IF($E11<P$4,($G11*1.3)/4,0) | ... R11: =IF($E11<S$4,($G11*1.3)/4,0) | S11: =IF($E11<S$4,($G11*1.3)/4,0)
H12: =IF($E12<I$4,($G12*1.3)/4,0) | I12: =IF($E12<J$4,($G12*1.3)/4,0) | J12: =IF($E12<K$4,($G12*1.3)/4,0) | K12: =IF($E12<L$4,($G12*1.3)/4,0) | L12: =IF($E12<M$4,($G12*1.3)/4,0) | M12: =IF($E12<N$4,($G12*1.3)/4,0) | N12: =IF($E12<O$4,($G12*1.3)/4,0) | O12: =IF($E12<P$4,($G12*1.3)/4,0) | ... R12: =IF($E12<S$4,($G12*1.3)/4,0) | S12: =IF($E12<S$4,($G12*1.3)/4,0)
H13: =IF($E13<I$4,($G13*1.3)/4,0) | I13: =IF($E13<J$4,($G13*1.3)/4,0) | J13: =IF($E13<K$4,($G13*1.3)/4,0) | K13: =IF($E13<L$4,($G13*1.3)/4,0) | L13: =IF($E13<M$4,($G13*1.3)/4,0) | M13: =IF($E13<N$4,($G13*1.3)/4,0) | N13: =IF($E13<O$4,($G13*1.3)/4,0) | O13: =IF($E13<P$4,($G13*1.3)/4,0) | ... R13: =IF($E13<S$4,($G13*1.3)/4,0) | S13: =IF($E13<S$4,($G13*1.3)/4,0)
H14: =IF($E14<I$4,($G14*1.3)/4,0) | I14: =IF($E14<J$4,($G14*1.3)/4,0) | J14: =IF($E14<K$4,($G14*1.3)/4,0) | K14: =IF($E14<L$4,($G14*1.3)/4,0) | L14: =IF($E14<M$4,($G14*1.3)/4,0) | M14: =IF($E14<N$4,($G14*1.3)/4,0) | N14: =IF($E14<O$4,($G14*1.3)/4,0) | O14: =IF($E14<P$4,($G14*1.3)/4,0) | ... R14: =IF($E14<S$4,($G14*1.3)/4,0) | S14: =IF($E14<S$4,($G14*1.3)/4,0)
H15: =IF($E15<I$4,($G15*1.3)/4,0) | I15: =IF($E15<J$4,($G15*1.3)/4,0) | J15: =IF($E15<K$4,($G15*1.3)/4,0) | K15: =IF($E15<L$4,($G15*1.3)/4,0) | L15: =IF($E15<M$4,($G15*1.3)/4,0) | M15: =IF($E15<N$4,($G15*1.3)/4,0) | N15: =IF($E15<O$4,($G15*1.3)/4,0) | O15: =IF($E15<P$4,($G15*1.3)/4,0) | ... R15: =IF($E15<S$4,($G15*1.3)/4,0) | S15: =IF($E15<S$4,($G15*1.3)/4,0)
H16: =IF($E16<I$4,($G16*1.3)/4,0) | I16: =IF($E16<J$4,($G16*1.3)/4,0) | J16: =IF($E16<K$4,($G16*1.3)/4,0) | K16: =IF($E16<L$4,($G16*1.3)/4,0) | L16: =IF($E16<M$4,($G16*1.3)/4,0) | M16: =IF($E16<N$4,($G16*1.3)/4,0) | N16: =IF($E16<O$4,($G16*1.3)/4,0) | O16: =IF($E16<P$4,($G16*1.3)/4,0) | ... R16: =IF($E16<S$4,($G16*1.3)/4,0) | S16: =IF($E16<S$4,($G16*1.3)/4,0)
H17: =IF($E17<I$4,($G17*1.3)/4,0) | I17: =IF($E17<J$4,($G17*1.3)/4,0) | J17: =IF($E17<K$4,($G17*1.3)/4,0) | K17: =IF($E17<L$4,($G17*1.3)/4,0) | L17: =IF($E17<M$4,($G17*1.3)/4,0) | M17: =IF($E17<N$4,($G17*1.3)/4,0) | N17: =IF($E17<O$4,($G17*1.3)/4,0) | O17: =IF($E17<P$4,($G17*1.3)/4,0) | ... R17: =IF($E17<S$4,($G17*1.3)/4,0) | S17: =IF($E17<S$4,($G17*1.3)/4,0)
... H24: =IF($E24<I$4,($G24*1.3)/4,0) | I24: =IF($E24<J$4,($G24*1.3)/4,0) | J24: =IF($E24<K$4,($G24*1.3)/4,0) | K24: =IF($E24<L$4,($G24*1.3)/4,0) | L24: =IF($E24<M$4,($G24*1.3)/4,0) | M24: =IF($E24<N$4,($G24*1.3)/4,0) | N24: =IF($E24<O$4,($G24*1.3)/4,0) | O24: =IF($E24<P$4,($G24*1.3)/4,0) | ... R24: =IF($E24<S$4,($G24*1.3)/4,0) | S24: =IF($E24<S$4,($G24*1.3)/4,0)
H25: =SUM(H6:H24) | I25: =SUM(I6:I24) | J25: =SUM(J6:J24) | K25: =SUM(K6:K24) | L25: =SUM(L6:L24) | M25: =SUM(M6:M24) | N25: =SUM(N6:N24) | O25: =SUM(O6:O24) | ... S25: =SUM(S6:S24)
A27: Non Headcount | H27: 2019 | J27: 2020 | N27: 2021 | R27: 2022
A28: Submitted by | B28: Department | C28: Description of Spend | D28: Justification | G28: Total Cost Estimate | H28: Q3 | I28: Q4 | J28: Q1 | K28: Q2 | L28: Q3 | M28: Q4 | N28: Q1 | O28: Q2 | P28: Q3 | Q28: Q4 | R28: Q1 | S28: Q2
A29: Peter Schaffer | B29: Delta | C29: Rent-Current premises | D29: Office Space -lease obligation through 6/31/2020 | G29: =SUM(I29:M29) | I29: 22963 | J29: 22963 | K29: 22963
A30: Nish,Peter&LB Email | B30: Workplace | C30: "Base" Rent for WeWork | D30: Assumes 26 heads Q1 - 28 heads Q3 - flat at 28 forward - numbers reflect cost to secure the space in Q1 | G30: =SUM(I30:O30) | J30: =(28*1839)*3 | K30: =(28*1839)*3 | L30: =(28*1839)*3 | M30: =(28*1839)*3
G41: =SUM(G29:G40) | H41: =SUM(H29:H34) | I41: =SUM(I29:I34) | J41: =SUM(J29:J34) | K41: =SUM(K29:K34) | L41: =SUM(L29:L34) | M41: =SUM(M29:M34) | N41: =SUM(N29:N34) | O41: =SUM(O29:O34) | ... S41: =SUM(S29:S34)

Sheet 11) IT-Infrastructure
A1: Delta Incremental Costs
A3: Headcount | H3: 2019 | J3: 2020 | N3: 2021 | R3: 2022
H4: 43647 | I4: 43739 | J4: 43831 | K4: 43922 | L4: 44013 | M4: 44105 | N4: 44197 | O4: 44287 | P4: 44378 | Q4: 44470 | R4: 44562 | S4: 44652
A5: Submitted by | B5: Department | C5: TBH Title | D5: Description | E5: Hire Date | F5: Location | G5: Base Salary Estimate USD | H5: Q3 | I5: Q4 | J5: Q1 | K5: Q2 | L5: Q3 | M5: Q4 | N5: Q1 | O5: Q2 | P5: Q3 | Q5: Q4 | R5: Q1 | S5: Q2
A6: n/a - utilize existing MSP/ HC IT support strategy for region | G6: 0 | H6: =IF($E6<I$4,($G6*1.3)/4,0) | I6: =IF($E6<J$4,($G6*1.3)/4,0) | J6: =IF($E6<K$4,($G6*1.3)/4,0) | K6: =IF($E6<L$4,($G6*1.3)/4,0) | L6: =IF($E6<M$4,($G6*1.3)/4,0) | M6: =IF($E6<N$4,($G6*1.3)/4,0) | N6: =IF($E6<O$4,($G6*1.3)/4,0) | O6: =IF($E6<P$4,($G6*1.3)/4,0) | ... R6: =IF($E6<S$4,($G6*1.3)/4,0) | S6: =IF($E6<S$4,($G6*1.3)/4,0)
H7: =IF($E7<I$4,($G7*1.3)/4,0) | I7: =IF($E7<J$4,($G7*1.3)/4,0) | J7: =IF($E7<K$4,($G7*1.3)/4,0) | K7: =IF($E7<L$4,($G7*1.3)/4,0) | L7: =IF($E7<M$4,($G7*1.3)/4,0) | M7: =IF($E7<N$4,($G7*1.3)/4,0) | N7: =IF($E7<O$4,($G7*1.3)/4,0) | O7: =IF($E7<P$4,($G7*1.3)/4,0) | ... R7: =IF($E7<S$4,($G7*1.3)/4,0) | S7: =IF($E7<S$4,($G7*1.3)/4,0)
H8: =IF($E8<I$4,($G8*1.3)/4,0) | I8: =IF($E8<J$4,($G8*1.3)/4,0) | J8: =IF($E8<K$4,($G8*1.3)/4,0) | K8: =IF($E8<L$4,($G8*1.3)/4,0) | L8: =IF($E8<M$4,($G8*1.3)/4,0) | M8: =IF($E8<N$4,($G8*1.3)/4,0) | N8: =IF($E8<O$4,($G8*1.3)/4,0) | O8: =IF($E8<P$4,($G8*1.3)/4,0) | ... R8: =IF($E8<S$4,($G8*1.3)/4,0) | S8: =IF($E8<S$4,($G8*1.3)/4,0)
H9: =IF($E9<I$4,($G9*1.3)/4,0) | I9: =IF($E9<J$4,($G9*1.3)/4,0) | J9: =IF($E9<K$4,($G9*1.3)/4,0) | K9: =IF($E9<L$4,($G9*1.3)/4,0) | L9: =IF($E9<M$4,($G9*1.3)/4,0) | M9: =IF($E9<N$4,($G9*1.3)/4,0) | N9: =IF($E9<O$4,($G9*1.3)/4,0) | O9: =IF($E9<P$4,($G9*1.3)/4,0) | ... R9: =IF($E9<S$4,($G9*1.3)/4,0) | S9: =IF($E9<S$4,($G9*1.3)/4,0)
H10: =IF($E10<I$4,($G10*1.3)/4,0) | I10: =IF($E10<J$4,($G10*1.3)/4,0) | J10: =IF($E10<K$4,($G10*1.3)/4,0) | K10: =IF($E10<L$4,($G10*1.3)/4,0) | L10: =IF($E10<M$4,($G10*1.3)/4,0) | M10: =IF($E10<N$4,($G10*1.3)/4,0) | N10: =IF($E10<O$4,($G10*1.3)/4,0) | O10: =IF($E10<P$4,($G10*1.3)/4,0) | ... R10: =IF($E10<S$4,($G10*1.3)/4,0) | S10: =IF($E10<S$4,($G10*1.3)/4,0)
H11: =IF($E11<I$4,($G11*1.3)/4,0) | I11: =IF($E11<J$4,($G11*1.3)/4,0) | J11: =IF($E11<K$4,($G11*1.3)/4,0) | K11: =IF($E11<L$4,($G11*1.3)/4,0) | L11: =IF($E11<M$4,($G11*1.3)/4,0) | M11: =IF($E11<N$4,($G11*1.3)/4,0) | N11: =IF($E11<O$4,($G11*1.3)/4,0) | O11: =IF($E11<P$4,($G11*1.3)/4,0) | ... R11: =IF($E11<S$4,($G11*1.3)/4,0) | S11: =IF($E11<S$4,($G11*1.3)/4,0)
H12: =IF($E12<I$4,($G12*1.3)/4,0) | I12: =IF($E12<J$4,($G12*1.3)/4,0) | J12: =IF($E12<K$4,($G12*1.3)/4,0) | K12: =IF($E12<L$4,($G12*1.3)/4,0) | L12: =IF($E12<M$4,($G12*1.3)/4,0) | M12: =IF($E12<N$4,($G12*1.3)/4,0) | N12: =IF($E12<O$4,($G12*1.3)/4,0) | O12: =IF($E12<P$4,($G12*1.3)/4,0) | ... R12: =IF($E12<S$4,($G12*1.3)/4,0) | S12: =IF($E12<S$4,($G12*1.3)/4,0)
H13: =IF($E13<I$4,($G13*1.3)/4,0) | I13: =IF($E13<J$4,($G13*1.3)/4,0) | J13: =IF($E13<K$4,($G13*1.3)/4,0) | K13: =IF($E13<L$4,($G13*1.3)/4,0) | L13: =IF($E13<M$4,($G13*1.3)/4,0) | M13: =IF($E13<N$4,($G13*1.3)/4,0) | N13: =IF($E13<O$4,($G13*1.3)/4,0) | O13: =IF($E13<P$4,($G13*1.3)/4,0) | ... R13: =IF($E13<S$4,($G13*1.3)/4,0) | S13: =IF($E13<S$4,($G13*1.3)/4,0)
H14: =IF($E14<I$4,($G14*1.3)/4,0) | I14: =IF($E14<J$4,($G14*1.3)/4,0) | J14: =IF($E14<K$4,($G14*1.3)/4,0) | K14: =IF($E14<L$4,($G14*1.3)/4,0) | L14: =IF($E14<M$4,($G14*1.3)/4,0) | M14: =IF($E14<N$4,($G14*1.3)/4,0) | N14: =IF($E14<O$4,($G14*1.3)/4,0) | O14: =IF($E14<P$4,($G14*1.3)/4,0) | ... R14: =IF($E14<S$4,($G14*1.3)/4,0) | S14: =IF($E14<S$4,($G14*1.3)/4,0)
H15: =IF($E15<I$4,($G15*1.3)/4,0) | I15: =IF($E15<J$4,($G15*1.3)/4,0) | J15: =IF($E15<K$4,($G15*1.3)/4,0) | K15: =IF($E15<L$4,($G15*1.3)/4,0) | L15: =IF($E15<M$4,($G15*1.3)/4,0) | M15: =IF($E15<N$4,($G15*1.3)/4,0) | N15: =IF($E15<O$4,($G15*1.3)/4,0) | O15: =IF($E15<P$4,($G15*1.3)/4,0) | ... R15: =IF($E15<S$4,($G15*1.3)/4,0) | S15: =IF($E15<S$4,($G15*1.3)/4,0)
H16: =IF($E16<I$4,($G16*1.3)/4,0) | I16: =IF($E16<J$4,($G16*1.3)/4,0) | J16: =IF($E16<K$4,($G16*1.3)/4,0) | K16: =IF($E16<L$4,($G16*1.3)/4,0) | L16: =IF($E16<M$4,($G16*1.3)/4,0) | M16: =IF($E16<N$4,($G16*1.3)/4,0) | N16: =IF($E16<O$4,($G16*1.3)/4,0) | O16: =IF($E16<P$4,($G16*1.3)/4,0) | ... R16: =IF($E16<S$4,($G16*1.3)/4,0) | S16: =IF($E16<S$4,($G16*1.3)/4,0)
H17: =IF($E17<I$4,($G17*1.3)/4,0) | I17: =IF($E17<J$4,($G17*1.3)/4,0) | J17: =IF($E17<K$4,($G17*1.3)/4,0) | K17: =IF($E17<L$4,($G17*1.3)/4,0) | L17: =IF($E17<M$4,($G17*1.3)/4,0) | M17: =IF($E17<N$4,($G17*1.3)/4,0) | N17: =IF($E17<O$4,($G17*1.3)/4,0) | O17: =IF($E17<P$4,($G17*1.3)/4,0) | ... R17: =IF($E17<S$4,($G17*1.3)/4,0) | S17: =IF($E17<S$4,($G17*1.3)/4,0)
H18: =IF($E18<I$4,($G18*1.3)/4,0) | I18: =IF($E18<J$4,($G18*1.3)/4,0) | J18: =IF($E18<K$4,($G18*1.3)/4,0) | K18: =IF($E18<L$4,($G18*1.3)/4,0) | L18: =IF($E18<M$4,($G18*1.3)/4,0) | M18: =IF($E18<N$4,($G18*1.3)/4,0) | N18: =IF($E18<O$4,($G18*1.3)/4,0) | O18: =IF($E18<P$4,($G18*1.3)/4,0) | ... R18: =IF($E18<S$4,($G18*1.3)/4,0) | S18: =IF($E18<S$4,($G18*1.3)/4,0)
... H24: =IF($E24<I$4,($G24*1.3)/4,0) | I24: =IF($E24<J$4,($G24*1.3)/4,0) | J24: =IF($E24<K$4,($G24*1.3)/4,0) | K24: =IF($E24<L$4,($G24*1.3)/4,0) | L24: =IF($E24<M$4,($G24*1.3)/4,0) | M24: =IF($E24<N$4,($G24*1.3)/4,0) | N24: =IF($E24<O$4,($G24*1.3)/4,0) | O24: =IF($E24<P$4,($G24*1.3)/4,0) | ... R24: =IF($E24<S$4,($G24*1.3)/4,0) | S24: =IF($E24<S$4,($G24*1.3)/4,0)
H25: =SUM(H6:H24) | I25: =SUM(I6:I24) | J25: =SUM(J6:J24) | K25: =SUM(K6:K24) | L25: =SUM(L6:L24) | M25: =SUM(M6:M24) | N25: =SUM(N6:N24) | O25: =SUM(O6:O24) | ... S25: =SUM(S6:S24)
A27: Non Headcount | H27: 2019 | J27: 2020 | N27: 2021 | R27: 2022
A28: Submitted by | B28: Department | C28: Description of Spend | D28: Justification | G28: Total Cost Estimate | H28: Q3 | I28: Q4 | J28: Q1 | K28: Q2 | L28: Q3 | M28: Q4 | N28: Q1 | O28: Q2 | P28: Q3 | Q28: Q4 | R28: Q1 | S28: Q2
A29: BBragg | B29: 8010 | C29: Laptops/ Monitors / Docs | D29: Hitrust compliance and employee productivity standard, Apac expensed in Qtr | G29: =SUM(H29:M29) | I29: =18*5000
A30: BBragg | B30: 8010 | C30: Zoom Equipment | D30: Presumes conference needs at location met by facility and laptops | G30: n/a
A31: BBragg | B31: 8010 | C31: Fitbit-Corp Wifi | D31: Presumes co-working location (e.g. WeWork?) and procuring as a service from the facility. | G31: =SUM(H31:M31) | I31: 10000 | J31: 10000 | K31: 10000 | L31: 10000 | M31: 10000
A32: BBragg | B32: 8010 | C32: Printers | D32: Presume co-working location provided and usage billed to local CC | G32: n/a
A33: BBragg | B33: 8010 | C33: Google/ Slack /Zoom /O365 | D33: Sufficient existing terms | G33: n/a
A34: BBragg | B34: Likely Jonah Org as current model | C34: Special software : Adobe, Zepplin, Sketch | D34: Existing design tools and similar to FB standards used by ID | G34: =SUM(H34:M34) | I34: 10000 | M34: 10000
A35: BBragg | B35: 8010 | C35: Outside Services | D35: Temp IT Systems Engineer in APAC to support, transition and decom existing internal systems | G35: =SUM(H35:M35) | I35: 30000
G41: =SUM(G29:G40) | H41: =SUM(H29:H34) | I41: =SUM(I29:I34) | J41: =SUM(J29:J34) | K41: =SUM(K29:K34) | L41: =SUM(L29:L34) | M41: =SUM(M29:M34) | N41: =SUM(N29:N34) | O41: =SUM(O29:O34) | ... S41: =SUM(S29:S34)

Sheet 13) IT- Security
A1: Delta Incremental Costs
A3: Headcount | H3: 2019 | J3: 2020 | N3: 2021 | R3: 2022
H4: 43647 | I4: 43739 | J4: 43831 | K4: 43922 | L4: 44013 | M4: 44105 | N4: 44197 | O4: 44287 | P4: 44378 | Q4: 44470 | R4: 44562 | S4: 44652
A5: Submitted by | B5: Department | C5: TBH Title | D5: Description | E5: Hire Date | F5: Location | G5: Base Salary Estimate USD | H5: Q3 | I5: Q4 | J5: Q1 | K5: Q2 | L5: Q3 | M5: Q4 | N5: Q1 | O5: Q2 | P5: Q3 | Q5: Q4 | R5: Q1 | S5: Q2
H6: =IF($E6<I$4,($G6*1.3)/4,0) | I6: =IF($E6<J$4,($G6*1.3)/4,0) | J6: =IF($E6<K$4,($G6*1.3)/4,0) | K6: =IF($E6<L$4,($G6*1.3)/4,0) | L6: =IF($E6<M$4,($G6*1.3)/4,0) | M6: =IF($E6<N$4,($G6*1.3)/4,0) | N6: =IF($E6<O$4,($G6*1.3)/4,0) | O6: =IF($E6<P$4,($G6*1.3)/4,0) | ... R6: =IF($E6<S$4,($G6*1.3)/4,0) | S6: =IF($E6<S$4,($G6*1.3)/4,0)
H7: =IF($E7<I$4,($G7*1.3)/4,0) | I7: =IF($E7<J$4,($G7*1.3)/4,0) | J7: =IF($E7<K$4,($G7*1.3)/4,0) | K7: =IF($E7<L$4,($G7*1.3)/4,0) | L7: =IF($E7<M$4,($G7*1.3)/4,0) | M7: =IF($E7<N$4,($G7*1.3)/4,0) | N7: =IF($E7<O$4,($G7*1.3)/4,0) | O7: =IF($E7<P$4,($G7*1.3)/4,0) | ... R7: =IF($E7<S$4,($G7*1.3)/4,0) | S7: =IF($E7<S$4,($G7*1.3)/4,0)
H8: =IF($E8<I$4,($G8*1.3)/4,0) | I8: =IF($E8<J$4,($G8*1.3)/4,0) | J8: =IF($E8<K$4,($G8*1.3)/4,0) | K8: =IF($E8<L$4,($G8*1.3)/4,0) | L8: =IF($E8<M$4,($G8*1.3)/4,0) | M8: =IF($E8<N$4,($G8*1.3)/4,0) | N8: =IF($E8<O$4,($G8*1.3)/4,0) | O8: =IF($E8<P$4,($G8*1.3)/4,0) | ... R8: =IF($E8<S$4,($G8*1.3)/4,0) | S8: =IF($E8<S$4,($G8*1.3)/4,0)
H9: =IF($E9<I$4,($G9*1.3)/4,0) | I9: =IF($E9<J$4,($G9*1.3)/4,0) | J9: =IF($E9<K$4,($G9*1.3)/4,0) | K9: =IF($E9<L$4,($G9*1.3)/4,0) | L9: =IF($E9<M$4,($G9*1.3)/4,0) | M9: =IF($E9<N$4,($G9*1.3)/4,0) | N9: =IF($E9<O$4,($G9*1.3)/4,0) | O9: =IF($E9<P$4,($G9*1.3)/4,0) | ... R9: =IF($E9<S$4,($G9*1.3)/4,0) | S9: =IF($E9<S$4,($G9*1.3)/4,0)
H10: =IF($E10<I$4,($G10*1.3)/4,0) | I10: =IF($E10<J$4,($G10*1.3)/4,0) | J10: =IF($E10<K$4,($G10*1.3)/4,0) | K10: =IF($E10<L$4,($G10*1.3)/4,0) | L10: =IF($E10<M$4,($G10*1.3)/4,0) | M10: =IF($E10<N$4,($G10*1.3)/4,0) | N10: =IF($E10<O$4,($G10*1.3)/4,0) | O10: =IF($E10<P$4,($G10*1.3)/4,0) | ... R10: =IF($E10<S$4,($G10*1.3)/4,0) | S10: =IF($E10<S$4,($G10*1.3)/4,0)
H11: =IF($E11<I$4,($G11*1.3)/4,0) | I11: =IF($E11<J$4,($G11*1.3)/4,0) | J11: =IF($E11<K$4,($G11*1.3)/4,0) | K11: =IF($E11<L$4,($G11*1.3)/4,0) | L11: =IF($E11<M$4,($G11*1.3)/4,0) | M11: =IF($E11<N$4,($G11*1.3)/4,0) | N11: =IF($E11<O$4,($G11*1.3)/4,0) | O11: =IF($E11<P$4,($G11*1.3)/4,0) | ... R11: =IF($E11<S$4,($G11*1.3)/4,0) | S11: =IF($E11<S$4,($G11*1.3)/4,0)
H12: =IF($E12<I$4,($G12*1.3)/4,0) | I12: =IF($E12<J$4,($G12*1.3)/4,0) | J12: =IF($E12<K$4,($G12*1.3)/4,0) | K12: =IF($E12<L$4,($G12*1.3)/4,0) | L12: =IF($E12<M$4,($G12*1.3)/4,0) | M12: =IF($E12<N$4,($G12*1.3)/4,0) | N12: =IF($E12<O$4,($G12*1.3)/4,0) | O12: =IF($E12<P$4,($G12*1.3)/4,0) | ... R12: =IF($E12<S$4,($G12*1.3)/4,0) | S12: =IF($E12<S$4,($G12*1.3)/4,0)
H13: =IF($E13<I$4,($G13*1.3)/4,0) | I13: =IF($E13<J$4,($G13*1.3)/4,0) | J13: =IF($E13<K$4,($G13*1.3)/4,0) | K13: =IF($E13<L$4,($G13*1.3)/4,0) | L13: =IF($E13<M$4,($G13*1.3)/4,0) | M13: =IF($E13<N$4,($G13*1.3)/4,0) | N13: =IF($E13<O$4,($G13*1.3)/4,0) | O13: =IF($E13<P$4,($G13*1.3)/4,0) | ... R13: =IF($E13<S$4,($G13*1.3)/4,0) | S13: =IF($E13<S$4,($G13*1.3)/4,0)
H14: =IF($E14<I$4,($G14*1.3)/4,0) | I14: =IF($E14<J$4,($G14*1.3)/4,0) | J14: =IF($E14<K$4,($G14*1.3)/4,0) | K14: =IF($E14<L$4,($G14*1.3)/4,0) | L14: =IF($E14<M$4,($G14*1.3)/4,0) | M14: =IF($E14<N$4,($G14*1.3)/4,0) | N14: =IF($E14<O$4,($G14*1.3)/4,0) | O14: =IF($E14<P$4,($G14*1.3)/4,0) | ... R14: =IF($E14<S$4,($G14*1.3)/4,0) | S14: =IF($E14<S$4,($G14*1.3)/4,0)
H15: =IF($E15<I$4,($G15*1.3)/4,0) | I15: =IF($E15<J$4,($G15*1.3)/4,0) | J15: =IF($E15<K$4,($G15*1.3)/4,0) | K15: =IF($E15<L$4,($G15*1.3)/4,0) | L15: =IF($E15<M$4,($G15*1.3)/4,0) | M15: =IF($E15<N$4,($G15*1.3)/4,0) | N15: =IF($E15<O$4,($G15*1.3)/4,0) | O15: =IF($E15<P$4,($G15*1.3)/4,0) | ... R15: =IF($E15<S$4,($G15*1.3)/4,0) | S15: =IF($E15<S$4,($G15*1.3)/4,0)
H16: =IF($E16<I$4,($G16*1.3)/4,0) | I16: =IF($E16<J$4,($G16*1.3)/4,0) | J16: =IF($E16<K$4,($G16*1.3)/4,0) | K16: =IF($E16<L$4,($G16*1.3)/4,0) | L16: =IF($E16<M$4,($G16*1.3)/4,0) | M16: =IF($E16<N$4,($G16*1.3)/4,0) | N16: =IF($E16<O$4,($G16*1.3)/4,0) | O16: =IF($E16<P$4,($G16*1.3)/4,0) | ... R16: =IF($E16<S$4,($G16*1.3)/4,0) | S16: =IF($E16<S$4,($G16*1.3)/4,0)
H17: =IF($E17<I$4,($G17*1.3)/4,0) | I17: =IF($E17<J$4,($G17*1.3)/4,0) | J17: =IF($E17<K$4,($G17*1.3)/4,0) | K17: =IF($E17<L$4,($G17*1.3)/4,0) | L17: =IF($E17<M$4,($G17*1.3)/4,0) | M17: =IF($E17<N$4,($G17*1.3)/4,0) | N17: =IF($E17<O$4,($G17*1.3)/4,0) | O17: =IF($E17<P$4,($G17*1.3)/4,0) | ... R17: =IF($E17<S$4,($G17*1.3)/4,0) | S17: =IF($E17<S$4,($G17*1.3)/4,0)
... H24: =IF($E24<I$4,($G24*1.3)/4,0) | I24: =IF($E24<J$4,($G24*1.3)/4,0) | J24: =IF($E24<K$4,($G24*1.3)/4,0) | K24: =IF($E24<L$4,($G24*1.3)/4,0) | L24: =IF($E24<M$4,($G24*1.3)/4,0) | M24: =IF($E24<N$4,($G24*1.3)/4,0) | N24: =IF($E24<O$4,($G24*1.3)/4,0) | O24: =IF($E24<P$4,($G24*1.3)/4,0) | ... R24: =IF($E24<S$4,($G24*1.3)/4,0) | S24: =IF($E24<S$4,($G24*1.3)/4,0)
H25: =SUM(H6:H24) | I25: =SUM(I6:I24) | J25: =SUM(J6:J24) | K25: =SUM(K6:K24) | L25: =SUM(L6:L24) | M25: =SUM(M6:M24) | N25: =SUM(N6:N24) | O25: =SUM(O6:O24) | ... S25: =SUM(S6:S24)
A27: Non Headcount | H27: 2019 | J27: 2020 | N27: 2021 | R27: 2022
A28: Submitted by | B28: Department | C28: Description of Spend | D28: Justification | G28: Total Cost Estimate | H28: Q3 | I28: Q4 | J28: Q1 | K28: Q2 | L28: Q3 | M28: Q4 | N28: Q1 | O28: Q2 | P28: Q3 | Q28: Q4 | R28: Q1 | S28: Q2
A29: jwerrett | B29: 3620 | C29: Open Source and Third-Party Code Audit | D29: Identify the source and license of third-party software in Delta code bases | G29: 23000 | H29: 23000
A30: jwerrett | B30: 3620 | C30: Open Source Risk Assessment | D30: Identify known vulnerbailities and security deficiencies in Delta code bases | G30: 5750 | H30: 5750
A31: jwerrett | B31: 3620 | C31: Penetration Test | D31: Assess Delta backend services and infrastructure for security vulnerabilities and misconfigurations | G31: 15000 | H31: 15000
G41: =SUM(G29:G40) | H41: =SUM(H29:H34) | I41: =SUM(I29:I34) | J41: =SUM(J29:J34) | K41: =SUM(K29:K34) | L41: =SUM(L29:L34) | M41: =SUM(M29:M34) | N41: =SUM(N29:N34) | O41: =SUM(O29:O34) | ... S41: =SUM(S29:S34)

Sheet 12) IT- Apps
A1: Delta Incremental Costs
A3: Headcount | H3: 2019 | J3: 2020 | N3: 2021 | R3: 2022
H4: 43647 | I4: 43739 | J4: 43831 | K4: 43922 | L4: 44013 | M4: 44105 | N4: 44197 | O4: 44287 | P4: 44378 | Q4: 44470 | R4: 44562 | S4: 44652
A5: Submitted by | B5: Department | C5: TBH Title | D5: Description | E5: Hire Date | F5: Location | G5: Base Salary Estimate USD | H5: Q3 | I5: Q4 | J5: Q1 | K5: Q2 | L5: Q3 | M5: Q4 | N5: Q1 | O5: Q2 | P5: Q3 | Q5: Q4 | R5: Q1 | S5: Q2
A6: Existing headcount and external resources will suffice | H6: =IF($E6<I$4,($G6*1.3)/4,0) | I6: =IF($E6<J$4,($G6*1.3)/4,0) | J6: =IF($E6<K$4,($G6*1.3)/4,0) | K6: =IF($E6<L$4,($G6*1.3)/4,0) | L6: =IF($E6<M$4,($G6*1.3)/4,0) | M6: =IF($E6<N$4,($G6*1.3)/4,0) | N6: =IF($E6<O$4,($G6*1.3)/4,0) | O6: =IF($E6<P$4,($G6*1.3)/4,0) | ... R6: =IF($E6<S$4,($G6*1.3)/4,0) | S6: =IF($E6<S$4,($G6*1.3)/4,0)
H7: =IF($E7<I$4,($G7*1.3)/4,0) | I7: =IF($E7<J$4,($G7*1.3)/4,0) | J7: =IF($E7<K$4,($G7*1.3)/4,0) | K7: =IF($E7<L$4,($G7*1.3)/4,0) | L7: =IF($E7<M$4,($G7*1.3)/4,0) | M7: =IF($E7<N$4,($G7*1.3)/4,0) | N7: =IF($E7<O$4,($G7*1.3)/4,0) | O7: =IF($E7<P$4,($G7*1.3)/4,0) | ... R7: =IF($E7<S$4,($G7*1.3)/4,0) | S7: =IF($E7<S$4,($G7*1.3)/4,0)
H8: =IF($E8<I$4,($G8*1.3)/4,0) | I8: =IF($E8<J$4,($G8*1.3)/4,0) | J8: =IF($E8<K$4,($G8*1.3)/4,0) | K8: =IF($E8<L$4,($G8*1.3)/4,0) | L8: =IF($E8<M$4,($G8*1.3)/4,0) | M8: =IF($E8<N$4,($G8*1.3)/4,0) | N8: =IF($E8<O$4,($G8*1.3)/4,0) | O8: =IF($E8<P$4,($G8*1.3)/4,0) | ... R8: =IF($E8<S$4,($G8*1.3)/4,0) | S8: =IF($E8<S$4,($G8*1.3)/4,0)
H9: =IF($E9<I$4,($G9*1.3)/4,0) | I9: =IF($E9<J$4,($G9*1.3)/4,0) | J9: =IF($E9<K$4,($G9*1.3)/4,0) | K9: =IF($E9<L$4,($G9*1.3)/4,0) | L9: =IF($E9<M$4,($G9*1.3)/4,0) | M9: =IF($E9<N$4,($G9*1.3)/4,0) | N9: =IF($E9<O$4,($G9*1.3)/4,0) | O9: =IF($E9<P$4,($G9*1.3)/4,0) | ... R9: =IF($E9<S$4,($G9*1.3)/4,0) | S9: =IF($E9<S$4,($G9*1.3)/4,0)
H10: =IF($E10<I$4,($G10*1.3)/4,0) | I10: =IF($E10<J$4,($G10*1.3)/4,0) | J10: =IF($E10<K$4,($G10*1.3)/4,0) | K10: =IF($E10<L$4,($G10*1.3)/4,0) | L10: =IF($E10<M$4,($G10*1.3)/4,0) | M10: =IF($E10<N$4,($G10*1.3)/4,0) | N10: =IF($E10<O$4,($G10*1.3)/4,0) | O10: =IF($E10<P$4,($G10*1.3)/4,0) | ... R10: =IF($E10<S$4,($G10*1.3)/4,0) | S10: =IF($E10<S$4,($G10*1.3)/4,0)
H11: =IF($E11<I$4,($G11*1.3)/4,0) | I11: =IF($E11<J$4,($G11*1.3)/4,0) | J11: =IF($E11<K$4,($G11*1.3)/4,0) | K11: =IF($E11<L$4,($G11*1.3)/4,0) | L11: =IF($E11<M$4,($G11*1.3)/4,0) | M11: =IF($E11<N$4,($G11*1.3)/4,0) | N11: =IF($E11<O$4,($G11*1.3)/4,0) | O11: =IF($E11<P$4,($G11*1.3)/4,0) | ... R11: =IF($E11<S$4,($G11*1.3)/4,0) | S11: =IF($E11<S$4,($G11*1.3)/4,0)
H12: =IF($E12<I$4,($G12*1.3)/4,0) | I12: =IF($E12<J$4,($G12*1.3)/4,0) | J12: =IF($E12<K$4,($G12*1.3)/4,0) | K12: =IF($E12<L$4,($G12*1.3)/4,0) | L12: =IF($E12<M$4,($G12*1.3)/4,0) | M12: =IF($E12<N$4,($G12*1.3)/4,0) | N12: =IF($E12<O$4,($G12*1.3)/4,0) | O12: =IF($E12<P$4,($G12*1.3)/4,0) | ... R12: =IF($E12<S$4,($G12*1.3)/4,0) | S12: =IF($E12<S$4,($G12*1.3)/4,0)
H13: =IF($E13<I$4,($G13*1.3)/4,0) | I13: =IF($E13<J$4,($G13*1.3)/4,0) | J13: =IF($E13<K$4,($G13*1.3)/4,0) | K13: =IF($E13<L$4,($G13*1.3)/4,0) | L13: =IF($E13<M$4,($G13*1.3)/4,0) | M13: =IF($E13<N$4,($G13*1.3)/4,0) | N13: =IF($E13<O$4,($G13*1.3)/4,0) | O13: =IF($E13<P$4,($G13*1.3)/4,0) | ... R13: =IF($E13<S$4,($G13*1.3)/4,0) | S13: =IF($E13<S$4,($G13*1.3)/4,0)
H14: =IF($E14<I$4,($G14*1.3)/4,0) | I14: =IF($E14<J$4,($G14*1.3)/4,0) | J14: =IF($E14<K$4,($G14*1.3)/4,0) | K14: =IF($E14<L$4,($G14*1.3)/4,0) | L14: =IF($E14<M$4,($G14*1.3)/4,0) | M14: =IF($E14<N$4,($G14*1.3)/4,0) | N14: =IF($E14<O$4,($G14*1.3)/4,0) | O14: =IF($E14<P$4,($G14*1.3)/4,0) | ... R14: =IF($E14<S$4,($G14*1.3)/4,0) | S14: =IF($E14<S$4,($G14*1.3)/4,0)
H15: =IF($E15<I$4,($G15*1.3)/4,0) | I15: =IF($E15<J$4,($G15*1.3)/4,0) | J15: =IF($E15<K$4,($G15*1.3)/4,0) | K15: =IF($E15<L$4,($G15*1.3)/4,0) | L15: =IF($E15<M$4,($G15*1.3)/4,0) | M15: =IF($E15<N$4,($G15*1.3)/4,0) | N15: =IF($E15<O$4,($G15*1.3)/4,0) | O15: =IF($E15<P$4,($G15*1.3)/4,0) | ... R15: =IF($E15<S$4,($G15*1.3)/4,0) | S15: =IF($E15<S$4,($G15*1.3)/4,0)
H16: =IF($E16<I$4,($G16*1.3)/4,0) | I16: =IF($E16<J$4,($G16*1.3)/4,0) | J16: =IF($E16<K$4,($G16*1.3)/4,0) | K16: =IF($E16<L$4,($G16*1.3)/4,0) | L16: =IF($E16<M$4,($G16*1.3)/4,0) | M16: =IF($E16<N$4,($G16*1.3)/4,0) | N16: =IF($E16<O$4,($G16*1.3)/4,0) | O16: =IF($E16<P$4,($G16*1.3)/4,0) | ... R16: =IF($E16<S$4,($G16*1.3)/4,0) | S16: =IF($E16<S$4,($G16*1.3)/4,0)
H17: =IF($E17<I$4,($G17*1.3)/4,0) | I17: =IF($E17<J$4,($G17*1.3)/4,0) | J17: =IF($E17<K$4,($G17*1.3)/4,0) | K17: =IF($E17<L$4,($G17*1.3)/4,0) | L17: =IF($E17<M$4,($G17*1.3)/4,0) | M17: =IF($E17<N$4,($G17*1.3)/4,0) | N17: =IF($E17<O$4,($G17*1.3)/4,0) | O17: =IF($E17<P$4,($G17*1.3)/4,0) | ... R17: =IF($E17<S$4,($G17*1.3)/4,0) | S17: =IF($E17<S$4,($G17*1.3)/4,0)
H18: =IF($E18<I$4,($G18*1.3)/4,0) | I18: =IF($E18<J$4,($G18*1.3)/4,0) | J18: =IF($E18<K$4,($G18*1.3)/4,0) | K18: =IF($E18<L$4,($G18*1.3)/4,0) | L18: =IF($E18<M$4,($G18*1.3)/4,0) | M18: =IF($E18<N$4,($G18*1.3)/4,0) | N18: =IF($E18<O$4,($G18*1.3)/4,0) | O18: =IF($E18<P$4,($G18*1.3)/4,0) | ... R18: =IF($E18<S$4,($G18*1.3)/4,0) | S18: =IF($E18<S$4,($G18*1.3)/4,0)
... H24: =IF($E24<I$4,($G24*1.3)/4,0) | I24: =IF($E24<J$4,($G24*1.3)/4,0) | J24: =IF($E24<K$4,($G24*1.3)/4,0) | K24: =IF($E24<L$4,($G24*1.3)/4,0) | L24: =IF($E24<M$4,($G24*1.3)/4,0) | M24: =IF($E24<N$4,($G24*1.3)/4,0) | N24: =IF($E24<O$4,($G24*1.3)/4,0) | O24: =IF($E24<P$4,($G24*1.3)/4,0) | ... R24: =IF($E24<S$4,($G24*1.3)/4,0) | S24: =IF($E24<S$4,($G24*1.3)/4,0)
H25: =SUM(H6:H24) | I25: =SUM(I6:I24) | J25: =SUM(J6:J24) | K25: =SUM(K6:K24) | L25: =SUM(L6:L24) | M25: =SUM(M6:M24) | N25: =SUM(N6:N24) | O25: =SUM(O6:O24) | ... S25: =SUM(S6:S24)
A27: Non Headcount | H27: 2019 | J27: 2020 | N27: 2021 | R27: 2022
A28: Submitted by | B28: Department | C28: Description of Spend | D28: Justification | G28: Total Cost Estimate | H28: Q3 | I28: Q4 | J28: Q1 | K28: Q2 | L28: Q3 | M28: Q4 | N28: Q1 | O28: Q2 | P28: Q3 | Q28: Q4 | R28: Q1 | S28: Q2
A29: ( Existing migration tools will suffice for performing the tasks. Do not fore see any additional costs)
G41: =SUM(G29:G40) | H41: =SUM(H29:H34) | I41: =SUM(I29:I34) | J41: =SUM(J29:J34) | K41: =SUM(K29:K34) | L41: =SUM(L29:L34) | M41: =SUM(M29:M34) | N41: =SUM(N29:N34) | O41: =SUM(O29:O34) | ... S41: =SUM(S29:S34)

Sheet 14) Operations
A1: Delta Incremental Costs
A3: Headcount | H3: 2019 | J3: 2020 | N3: 2021 | R3: 2022
H4: 43647 | I4: 43739 | J4: 43831 | K4: 43922 | L4: 44013 | M4: 44105 | N4: 44197 | O4: 44287 | P4: 44378 | Q4: 44470 | R4: 44562 | S4: 44652
A5: Submitted by | B5: Department | C5: TBH Title | D5: Description | E5: Hire Date | F5: Location | G5: Base Salary Estimate USD | H5: Q3 | I5: Q4 | J5: Q1 | K5: Q2 | L5: Q3 | M5: Q4 | N5: Q1 | O5: Q2 | P5: Q3 | Q5: Q4 | R5: Q1 | S5: Q2
H6: =IF($E6<I$4,($G6*1.3)/4,0) | I6: =IF($E6<J$4,($G6*1.3)/4,0) | J6: =IF($E6<K$4,($G6*1.3)/4,0) | K6: =IF($E6<L$4,($G6*1.3)/4,0) | L6: =IF($E6<M$4,($G6*1.3)/4,0) | M6: =IF($E6<N$4,($G6*1.3)/4,0) | N6: =IF($E6<O$4,($G6*1.3)/4,0) | O6: =IF($E6<P$4,($G6*1.3)/4,0) | ... R6: =IF($E6<S$4,($G6*1.3)/4,0) | S6: =IF($E6<S$4,($G6*1.3)/4,0)
H7: =IF($E7<I$4,($G7*1.3)/4,0) | I7: =IF($E7<J$4,($G7*1.3)/4,0) | J7: =IF($E7<K$4,($G7*1.3)/4,0) | K7: =IF($E7<L$4,($G7*1.3)/4,0) | L7: =IF($E7<M$4,($G7*1.3)/4,0) | M7: =IF($E7<N$4,($G7*1.3)/4,0) | N7: =IF($E7<O$4,($G7*1.3)/4,0) | O7: =IF($E7<P$4,($G7*1.3)/4,0) | ... R7: =IF($E7<S$4,($G7*1.3)/4,0) | S7: =IF($E7<S$4,($G7*1.3)/4,0)
H8: =IF($E8<I$4,($G8*1.3)/4,0) | I8: =IF($E8<J$4,($G8*1.3)/4,0) | J8: =IF($E8<K$4,($G8*1.3)/4,0) | K8: =IF($E8<L$4,($G8*1.3)/4,0) | L8: =IF($E8<M$4,($G8*1.3)/4,0) | M8: =IF($E8<N$4,($G8*1.3)/4,0) | N8: =IF($E8<O$4,($G8*1.3)/4,0) | O8: =IF($E8<P$4,($G8*1.3)/4,0) | ... R8: =IF($E8<S$4,($G8*1.3)/4,0) | S8: =IF($E8<S$4,($G8*1.3)/4,0)
H9: =IF($E9<I$4,($G9*1.3)/4,0) | I9: =IF($E9<J$4,($G9*1.3)/4,0) | J9: =IF($E9<K$4,($G9*1.3)/4,0) | K9: =IF($E9<L$4,($G9*1.3)/4,0) | L9: =IF($E9<M$4,($G9*1.3)/4,0) | M9: =IF($E9<N$4,($G9*1.3)/4,0) | N9: =IF($E9<O$4,($G9*1.3)/4,0) | O9: =IF($E9<P$4,($G9*1.3)/4,0) | ... R9: =IF($E9<S$4,($G9*1.3)/4,0) | S9: =IF($E9<S$4,($G9*1.3)/4,0)
H10: =IF($E10<I$4,($G10*1.3)/4,0) | I10: =IF($E10<J$4,($G10*1.3)/4,0) | J10: =IF($E10<K$4,($G10*1.3)/4,0) | K10: =IF($E10<L$4,($G10*1.3)/4,0) | L10: =IF($E10<M$4,($G10*1.3)/4,0) | M10: =IF($E10<N$4,($G10*1.3)/4,0) | N10: =IF($E10<O$4,($G10*1.3)/4,0) | O10: =IF($E10<P$4,($G10*1.3)/4,0) | ... R10: =IF($E10<S$4,($G10*1.3)/4,0) | S10: =IF($E10<S$4,($G10*1.3)/4,0)
H11: =IF($E11<I$4,($G11*1.3)/4,0) | I11: =IF($E11<J$4,($G11*1.3)/4,0) | J11: =IF($E11<K$4,($G11*1.3)/4,0) | K11: =IF($E11<L$4,($G11*1.3)/4,0) | L11: =IF($E11<M$4,($G11*1.3)/4,0) | M11: =IF($E11<N$4,($G11*1.3)/4,0) | N11: =IF($E11<O$4,($G11*1.3)/4,0) | O11: =IF($E11<P$4,($G11*1.3)/4,0) | ... R11: =IF($E11<S$4,($G11*1.3)/4,0) | S11: =IF($E11<S$4,($G11*1.3)/4,0)
H12: =IF($E12<I$4,($G12*1.3)/4,0) | I12: =IF($E12<J$4,($G12*1.3)/4,0) | J12: =IF($E12<K$4,($G12*1.3)/4,0) | K12: =IF($E12<L$4,($G12*1.3)/4,0) | L12: =IF($E12<M$4,($G12*1.3)/4,0) | M12: =IF($E12<N$4,($G12*1.3)/4,0) | N12: =IF($E12<O$4,($G12*1.3)/4,0) | O12: =IF($E12<P$4,($G12*1.3)/4,0) | ... R12: =IF($E12<S$4,($G12*1.3)/4,0) | S12: =IF($E12<S$4,($G12*1.3)/4,0)
H13: =IF($E13<I$4,($G13*1.3)/4,0) | I13: =IF($E13<J$4,($G13*1.3)/4,0) | J13: =IF($E13<K$4,($G13*1.3)/4,0) | K13: =IF($E13<L$4,($G13*1.3)/4,0) | L13: =IF($E13<M$4,($G13*1.3)/4,0) | M13: =IF($E13<N$4,($G13*1.3)/4,0) | N13: =IF($E13<O$4,($G13*1.3)/4,0) | O13: =IF($E13<P$4,($G13*1.3)/4,0) | ... R13: =IF($E13<S$4,($G13*1.3)/4,0) | S13: =IF($E13<S$4,($G13*1.3)/4,0)
H14: =IF($E14<I$4,($G14*1.3)/4,0) | I14: =IF($E14<J$4,($G14*1.3)/4,0) | J14: =IF($E14<K$4,($G14*1.3)/4,0) | K14: =IF($E14<L$4,($G14*1.3)/4,0) | L14: =IF($E14<M$4,($G14*1.3)/4,0) | M14: =IF($E14<N$4,($G14*1.3)/4,0) | N14: =IF($E14<O$4,($G14*1.3)/4,0) | O14: =IF($E14<P$4,($G14*1.3)/4,0) | ... R14: =IF($E14<S$4,($G14*1.3)/4,0) | S14: =IF($E14<S$4,($G14*1.3)/4,0)
H15: =IF($E15<I$4,($G15*1.3)/4,0) | I15: =IF($E15<J$4,($G15*1.3)/4,0) | J15: =IF($E15<K$4,($G15*1.3)/4,0) | K15: =IF($E15<L$4,($G15*1.3)/4,0) | L15: =IF($E15<M$4,($G15*1.3)/4,0) | M15: =IF($E15<N$4,($G15*1.3)/4,0) | N15: =IF($E15<O$4,($G15*1.3)/4,0) | O15: =IF($E15<P$4,($G15*1.3)/4,0) | ... R15: =IF($E15<S$4,($G15*1.3)/4,0) | S15: =IF($E15<S$4,($G15*1.3)/4,0)
H16: =IF($E16<I$4,($G16*1.3)/4,0) | I16: =IF($E16<J$4,($G16*1.3)/4,0) | J16: =IF($E16<K$4,($G16*1.3)/4,0) | K16: =IF($E16<L$4,($G16*1.3)/4,0) | L16: =IF($E16<M$4,($G16*1.3)/4,0) | M16: =IF($E16<N$4,($G16*1.3)/4,0) | N16: =IF($E16<O$4,($G16*1.3)/4,0) | O16: =IF($E16<P$4,($G16*1.3)/4,0) | ... R16: =IF($E16<S$4,($G16*1.3)/4,0) | S16: =IF($E16<S$4,($G16*1.3)/4,0)
H17: =IF($E17<I$4,($G17*1.3)/4,0) | I17: =IF($E17<J$4,($G17*1.3)/4,0) | J17: =IF($E17<K$4,($G17*1.3)/4,0) | K17: =IF($E17<L$4,($G17*1.3)/4,0) | L17: =IF($E17<M$4,($G17*1.3)/4,0) | M17: =IF($E17<N$4,($G17*1.3)/4,0) | N17: =IF($E17<O$4,($G17*1.3)/4,0) | O17: =IF($E17<P$4,($G17*1.3)/4,0) | ... R17: =IF($E17<S$4,($G17*1.3)/4,0) | S17: =IF($E17<S$4,($G17*1.3)/4,0)
... H24: =IF($E24<I$4,($G24*1.3)/4,0) | I24: =IF($E24<J$4,($G24*1.3)/4,0) | J24: =IF($E24<K$4,($G24*1.3)/4,0) | K24: =IF($E24<L$4,($G24*1.3)/4,0) | L24: =IF($E24<M$4,($G24*1.3)/4,0) | M24: =IF($E24<N$4,($G24*1.3)/4,0) | N24: =IF($E24<O$4,($G24*1.3)/4,0) | O24: =IF($E24<P$4,($G24*1.3)/4,0) | ... R24: =IF($E24<S$4,($G24*1.3)/4,0) | S24: =IF($E24<S$4,($G24*1.3)/4,0)
H25: =SUM(H6:H24) | I25: =SUM(I6:I24) | J25: =SUM(J6:J24) | K25: =SUM(K6:K24) | L25: =SUM(L6:L24) | M25: =SUM(M6:M24) | N25: =SUM(N6:N24) | O25: =SUM(O6:O24) | ... S25: =SUM(S6:S24)
A27: Non Headcount | H27: 2019 | J27: 2020 | N27: 2021 | R27: 2022
A28: Submitted by | B28: Department | C28: Description of Spend | D28: Justification | G28: Total Cost Estimate | H28: Q3 | I28: Q4 | J28: Q1 | K28: Q2 | L28: Q3 | M28: Q4 | N28: Q1 | O28: Q2 | P28: Q3 | Q28: Q4 | R28: Q1 | S28: Q2
A29: Bobinder | B29: Ops | C29: CS Costs | D29: Logistics costs of shipping out Doki replacement units | G29: 40000 | I29: 10000 | J29: 10000 | K29: 10000 | L29: 10000
A30: Bobinder | B30: Ops | C30: Field Issue Invesgiation | D30: Need to add budget to Bobinders Ops team | G30: 20000 | I30: 5000 | J30: 5000 | K30: 5000 | L30: 5000
A31: Dale (in email) | D31: Zendesk subscription | G31: =SUM(H31:K31) | I31: =500*3 | J31: =500*3 | K31: =500*3 | L31: =500*3
G41: =SUM(G29:G40) | H41: =SUM(H29:H34) | I41: =SUM(I29:I34) | J41: =SUM(J29:J34) | K41: =SUM(K29:K34) | L41: =SUM(L29:L34) | M41: =SUM(M29:M34) | N41: =SUM(N29:N34) | O41: =SUM(O29:O34) | ... S41: =SUM(S29:S34)

Sheet Summary cost inputs
A1: DELTA INCREMENTAL COSTS
A2: SUMMARY
F4: 2019 | H4: 2020 | L4: 2021 | P4: 2022
A5: Headcount Related (if needed) | C5: Owner | D5: Key Need: | E5: Status | F5: Q3 | G5: Q4 | H5: Q1 | I5: Q2 | J5: Q3 | K5: Q4 | L5: Q1 | M5: Q2 | N5: Q3 | O5: Q4 | P5: Q1 | Q5: Q2
B6: I TECH | C6: Ryan Krems | E6: Complete | F6: ='I. TECH'!I26 | G6: ='I. TECH'!J26 | H6: ='I. TECH'!K26 | I6: ='I. TECH'!L26 | J6: ='I. TECH'!M26 | K6: ='I. TECH'!N26 | L6: ='I. TECH'!O26 | M6: ='I. TECH'!P26 | ... Q6: ='I. TECH'!T26
B7: II NON TECH | C7: Ryan Krems | E7: Complete
A8: 1 | B8: Product | C8: Jon Oakes, Ryan K | D8: New Hires to expedite Viking development
A9: 2 | B9: SW Engineering | C9: Jon Oakes, Ryan K | D9: New Hires to expedite Viking development
A10: 3 | B10: HW Engineering | C10: Mark M | E10: Work In Progress | F10: ='3) HW Eng'!H25 | G10: ='3) HW Eng'!I25 | H10: ='3) HW Eng'!J25 | I10: ='3) HW Eng'!K25 | J10: ='3) HW Eng'!L25 | K10: ='3) HW Eng'!M25 | L10: ='3) HW Eng'!N25 | M10: ='3) HW Eng'!O25 | ... Q10: ='3) HW Eng'!S25
A11: 4 | B11: Accounting | C11: Audrey Zhang | D11: Integration costs, inventory write off costs | E11: Work In Progress | F11: ='4) Accounting'!H25 | G11: ='4) Accounting'!I25 | H11: ='4) Accounting'!J25 | I11: ='4) Accounting'!K25 | J11: ='4) Accounting'!L25 | K11: ='4) Accounting'!M25 | L11: ='4) Accounting'!N25 | M11: ='4) Accounting'!O25 | ... Q11: ='4) Accounting'!S25
A12: 5 | B12: Tax & Treasury | C12: Harvey, Anu | D12: Tax costs | E12: Complete | F12: ='5) Tax & Treasury'!H25 | G12: ='5) Tax & Treasury'!I25 | H12: ='5) Tax & Treasury'!J25 | I12: ='5) Tax & Treasury'!K25 | J12: ='5) Tax & Treasury'!L25 | K12: ='5) Tax & Treasury'!M25 | L12: ='5) Tax & Treasury'!N25 | M12: ='5) Tax & Treasury'!O25 | ... Q12: ='5) Tax & Treasury'!S25
A13: 6 | B13: Legal | C13: Nisha | D13: Legal closing costs | E13: Work In Progress | F13: ='6) Legal'!H25 | G13: ='6) Legal'!I25 | H13: ='6) Legal'!J25 | I13: ='6) Legal'!K25 | J13: ='6) Legal'!L25 | K13: ='6) Legal'!M25 | L13: ='6) Legal'!N25 | M13: ='6) Legal'!O25 | ... Q13: ='6) Legal'!S25
A14: 7 | B14: HR | C14: Bob, Sheryl | D14: Employee related (separate file) | E14: N/A | F14: ='7) HR'!H25 | G14: ='7) HR'!I25 | H14: ='7) HR'!J25 | I14: ='7) HR'!K25 | J14: ='7) HR'!L25 | K14: ='7) HR'!M25 | L14: ='7) HR'!N25 | M14: ='7) HR'!O25 | ... Q14: ='7) HR'!S25 | R14: Separate file
A15: 8 | B15: Facilities | C15: Peter Schaffer | D15: New facility costs in HK | E15: Work In Progress | F15: ='8) Facilities'!H25 | G15: ='8) Facilities'!I25 | H15: ='8) Facilities'!J25 | I15: ='8) Facilities'!K25 | J15: ='8) Facilities'!L25 | K15: ='8) Facilities'!M25 | L15: ='8) Facilities'!N25 | M15: ='8) Facilities'!O25 | ... Q15: ='8) Facilities'!S25
A16: 9 | B16: Marketing | C16: Lisa Swift | E16: Complete | F16: ='9) Marketing'!H25 | G16: ='9) Marketing'!I25 | H16: ='9) Marketing'!J25 | I16: ='9) Marketing'!K25 | J16: ='9) Marketing'!L25 | K16: ='9) Marketing'!M25 | L16: ='9) Marketing'!N25 | M16: ='9) Marketing'!O25 | ... Q16: ='9) Marketing'!S25
A17: 10 | B17: Int'l S&M | C17: Des Power | E17: Complete | F17: ='10) Int''l S&M'!H25 | G17: ='10) Int''l S&M'!I25 | H17: ='10) Int''l S&M'!J25 | I17: ='10) Int''l S&M'!K25 | J17: ='10) Int''l S&M'!L25 | K17: ='10) Int''l S&M'!M25 | L17: ='10) Int''l S&M'!N25 | M17: ='10) Int''l S&M'!O25 | ... Q17: ='10) Int''l S&M'!S25
A18: 11 | B18: IT - Infrastructure | C18: Bill Bragg | D18: Costs for new employees | E18: Work In Progress | F18: ='11) IT-Infrastructure'!H25 | G18: ='11) IT-Infrastructure'!I25 | H18: ='11) IT-Infrastructure'!J25 | I18: ='11) IT-Infrastructure'!K25 | J18: ='11) IT-Infrastructure'!L25 | K18: ='11) IT-Infrastructure'!M25 | L18: ='11) IT-Infrastructure'!N25 | M18: ='11) IT-Infrastructure'!O25 | ... Q18: ='11) IT-Infrastructure'!S25
A19: 12 | B19: IT - Apps | C19: Vijay | D19: Costs for new employees | E19: Work In Progress | G19: ='12) IT- Apps'!I25 | H19: ='12) IT- Apps'!J25 | I19: ='12) IT- Apps'!K25 | J19: ='12) IT- Apps'!L25 | K19: ='12) IT- Apps'!M25 | L19: ='12) IT- Apps'!N25 | M19: ='12) IT- Apps'!O25 | N19: ='12) IT- Apps'!P25 | ... Q19: ='12) IT- Apps'!S25
A20: 13 | B20: IT - Security | C20: Jonathan Werrett | D20: Black duck code review | E20: Complete | F20: ='13) IT- Security'!H25 | G20: ='13) IT- Security'!I25 | H20: ='13) IT- Security'!J25 | I20: ='13) IT- Security'!K25 | J20: ='13) IT- Security'!L25 | K20: ='13) IT- Security'!M25 | L20: ='13) IT- Security'!N25 | M20: ='13) IT- Security'!O25 | ... Q20: ='13) IT- Security'!S25
A21: 14 | B21: Operations | C21: Bobinder | E21: Work In Progress | F21: ='14) Operations'!H25 | G21: ='14) Operations'!I25 | H21: ='14) Operations'!J25 | I21: ='14) Operations'!K25 | J21: ='14) Operations'!L25 | K21: ='14) Operations'!M25 | L21: ='14) Operations'!N25 | M21: ='14) Operations'!O25 | ... Q21: ='14) Operations'!S25
F22: =SUM(F6:F21) | G22: =SUM(G6:G21) | H22: =SUM(H6:H21) | I22: =SUM(I6:I21) | J22: =SUM(J6:J21) | K22: =SUM(K6:K21) | L22: =SUM(L6:L21) | M22: =SUM(M6:M21) | ... Q22: =SUM(Q6:Q21)
F25: 2019 | H25: 2020 | L25: 2021 | P25: 2022
A26: Non Headcount | C26: Owner | D26: Key Need: | E26: Status | F26: Q3 | G26: Q4 | H26: Q1 | I26: Q2 | J26: Q3 | K26: Q4 | L26: Q1 | M26: Q2 | N26: Q3 | O26: Q4 | P26: Q1 | Q26: Q2
A27: 1 | B27: Product | C27: Jon Oakes, Ryan K | E27: Complete | F27: ='1) ProductUX'!H41 | G27: ='1) ProductUX'!I41 | H27: ='1) ProductUX'!J41 | I27: ='1) ProductUX'!K41 | J27: ='1) ProductUX'!L41 | K27: ='1) ProductUX'!M41 | L27: ='1) ProductUX'!N41 | M27: ='1) ProductUX'!O41 | ... Q27: ='1) ProductUX'!S41
A28: 2 | B28: SW Engineering | C28: James W, Dawn | D28: Additional headcount | E28: Complete | F28: ='2) SW Eng'!H41 | G28: ='2) SW Eng'!I41 | H28: ='2) SW Eng'!J41 | I28: ='2) SW Eng'!K41 | J28: ='2) SW Eng'!L41 | K28: ='2) SW Eng'!M41 | L28: ='2) SW Eng'!N41 | M28: ='2) SW Eng'!O41 | ... Q28: ='2) SW Eng'!S41
A29: 3 | B29: HW Engineering | C29: Mark M | E29: Complete | F29: ='3) HW Eng'!H41 | G29: ='3) HW Eng'!I41 | H29: ='3) HW Eng'!J41 | I29: ='3) HW Eng'!K41 | J29: ='3) HW Eng'!L41 | K29: ='3) HW Eng'!M41 | L29: ='3) HW Eng'!N41 | M29: ='3) HW Eng'!O41 | ... Q29: ='3) HW Eng'!S41
A30: 4 | B30: Accounting | C30: Audrey Zhang | D30: Integration costs, inventory write off costs | E30: Complete | F30: ='4) Accounting'!H41 | G30: ='4) Accounting'!I41 | H30: ='4) Accounting'!J41 | I30: ='4) Accounting'!K41 | J30: ='4) Accounting'!L41 | K30: ='4) Accounting'!M41 | L30: ='4) Accounting'!N41 | M30: ='4) Accounting'!O41 | ... Q30: ='4) Accounting'!S41
A31: 5 | B31: Tax & Treasury* | C31: Harvey, Anu | D31: Tax costs | E31: Complete | F31: ='5) Tax & Treasury'!H41 | G31: ='5) Tax & Treasury'!I41 | H31: ='5) Tax & Treasury'!J41 | I31: 12000 | J31: ='5) Tax & Treasury'!L41 | K31: ='5) Tax & Treasury'!M41 | L31: ='5) Tax & Treasury'!N41 | M31: 12000 | N31: ='5) Tax & Treasury'!P41 | O31: ='5) Tax & Treasury'!Q41 | P31: ='5) Tax & Treasury'!R41 | Q31: 12000
A32: 6 | B32: Legal | C32: Nisha | D32: Legal closing costs | E32: Complete | F32: ='6) Legal'!H41 | G32: ='6) Legal'!I41 | H32: ='6) Legal'!J41 | I32: ='6) Legal'!K41 | J32: ='6) Legal'!L41 | K32: ='6) Legal'!M41 | L32: ='6) Legal'!N41 | M32: ='6) Legal'!O41 | ... Q32: ='6) Legal'!S41
A33: 7 | B33: HR | C33: Bob, Sheryl | D33: Employee related (separate file) | E33: N/A | F33: ='7) HR'!H41 | G33: ='7) HR'!I41 | H33: ='7) HR'!J41 | I33: ='7) HR'!K41 | J33: ='7) HR'!L41 | K33: ='7) HR'!M41 | L33: ='7) HR'!N41 | M33: ='7) HR'!O41 | ... Q33: ='7) HR'!S41 | R33: Separate file
A34: 8 | B34: Facilities | C34: Peter Schaffer | D34: Current facility costs in HK | E34: Complete | F34: ='8) Facilities'!H41 | G34: ='8) Facilities'!I41 | H34: ='8) Facilities'!J41 | I34: ='8) Facilities'!K41 | J34: ='8) Facilities'!L41 | K34: ='8) Facilities'!M41 | L34: ='8) Facilities'!N41 | M34: ='8) Facilities'!O41 | ... Q34: ='8) Facilities'!S41
A35: 9 | B35: Marketing | C35: Lisa Swift | E35: Complete | F35: ='9) Marketing'!H41 | G35: ='9) Marketing'!I41 | H35: ='9) Marketing'!J41 | I35: ='9) Marketing'!K41 | J35: ='9) Marketing'!L41 | K35: ='9) Marketing'!M41 | L35: ='9) Marketing'!N41 | M35: ='9) Marketing'!O41 | ... Q35: ='9) Marketing'!S41
A36: 10 | B36: Int'l S&M | C36: Des Power | E36: Complete | F36: ='10) Int''l S&M'!H41 | G36: ='10) Int''l S&M'!I41 | H36: ='10) Int''l S&M'!J41 | I36: ='10) Int''l S&M'!K41 | J36: ='10) Int''l S&M'!L41 | K36: ='10) Int''l S&M'!M41 | L36: ='10) Int''l S&M'!N41 | M36: ='10) Int''l S&M'!O41 | ... Q36: ='10) Int''l S&M'!S41
A37: 11 | B37: IT - Infrastructure | C37: Bill Bragg | D37: Costs for new employees, tools & facility wifi | E37: Complete | F37: ='11) IT-Infrastructure'!H41 | G37: ='11) IT-Infrastructure'!I41 | H37: ='11) IT-Infrastructure'!J41 | I37: ='11) IT-Infrastructure'!K41 | J37: ='11) IT-Infrastructure'!L41 | K37: ='11) IT-Infrastructure'!M41 | L37: ='11) IT-Infrastructure'!N41 | M37: ='11) IT-Infrastructure'!O41 | ... Q37: ='11) IT-Infrastructure'!S41
A38: 12 | B38: IT - Apps | C38: Vijay | D38: Costs for new employees | E38: Complete | F38: ='12) IT- Apps'!H41 | G38: ='12) IT- Apps'!I41 | H38: ='12) IT- Apps'!J41 | I38: ='12) IT- Apps'!K41 | J38: ='12) IT- Apps'!L41 | K38: ='12) IT- Apps'!M41 | L38: ='12) IT- Apps'!N41 | M38: ='12) IT- Apps'!O41 | ... Q38: ='12) IT- Apps'!S41
A39: 13 | B39: IT - Security | C39: Jonathan Werrett | D39: Code review & security assessment | E39: Complete | F39: ='13) IT- Security'!H41 | G39: ='13) IT- Security'!I41 | H39: ='13) IT- Security'!J41 | I39: ='13) IT- Security'!K41 | J39: ='13) IT- Security'!L41 | K39: ='13) IT- Security'!M41 | L39: ='13) IT- Security'!N41 | M39: ='13) IT- Security'!O41 | ... Q39: ='13) IT- Security'!S41
A40: 14 | B40: Operations | C40: Bobinder | E40: Complete | F40: ='14) Operations'!H41 | G40: ='14) Operations'!I41 | H40: ='14) Operations'!J41 | I40: ='14) Operations'!K41 | J40: ='14) Operations'!L41 | K40: ='14) Operations'!M41 | L40: ='14) Operations'!N41 | M40: ='14) Operations'!O41 | ... Q40: ='14) Operations'!S41
F41: =SUM(F27:F40) | G41: =SUM(G27:G40) | H41: =SUM(H27:H40) | I41: =SUM(I27:I40) | J41: =SUM(J27:J40) | K41: =SUM(K27:K40) | L41: =SUM(L27:L40) | M41: =SUM(M27:M40) | ... Q41: =SUM(Q27:Q40)
B42: *Ongoing tax compliance costs assuming target entity still exists for any portion of prior year. Assumes target is already compliant with 2018 filings.
B43: TOTAL | F43: =F41+F22 | G43: =G41+G22 | H43: =H41+H22 | I43: =I41+I22 | J43: =J41+J22 | K43: =K41+K22 | L43: =L41+L22 | M43: =M41+M22 | ... Q43: =Q41+Q22

Sheet I. TECH
A1: I. DELTA TECH HC: engineering, product, UX
A3: Headcount | I3: 2019 | K3: 2020 | O3: 2021 | S3: 2022
I4: 43647 | J4: 43739 | K4: 43831 | L4: 43922 | M4: 44013 | N4: 44105 | O4: 44197 | P4: 44287 | Q4: 44378 | R4: 44470 | S4: 44562 | T4: 44652
A5: Submitted by | B5: Department | C5: TBH Title | D5: Description | E5: Hire Date | G5: Location | H5: Base Salary Estimate USD | I5: Q3 | J5: Q4 | K5: Q1 | L5: Q2 | M5: Q3 | N5: Q4 | O5: Q1 | P5: Q2 | Q5: Q3 | R5: Q4 | S5: Q1 | T5: Q2
A6: Ryan Krems | B6: Net New Tech Hires Under New Jon O Org | C6: Staff Engineer (P4) | D6: Android Engineer | E6: Q1 2020 | G6: Hong Kong | H6: Bob to Provide After Leveling mid next week (~Weds, 9/25) | K6: Yes | L6: Yes | M6: Yes | N6: Yes | O6: Yes | P6: Yes | Q6: Yes | R6: Yes | S6: Yes | T6: Yes
A7: Ryan Krems | B7: Net New Tech Hires Under New Jon O Org | C7: Staff Engineer (P4) | D7: iOS Engineer | E7: Q4 2019 | G7: Hong Kong | H7: Bob to Provide After Leveling mid next week (~Weds, 9/25) | J7: Yes | K7: Yes | L7: Yes | M7: Yes | N7: Yes | O7: Yes | P7: Yes | Q7: Yes | R7: Yes | S7: Yes | T7: Yes
A8: Ryan Krems | B8: Net New Tech Hires Under New Jon O Org | C8: Senior Engineer (P3) | D8: iOS Engineer | E8: Q4 2019 | G8: Hong Kong | H8: Bob to Provide After Leveling mid next week (~Weds, 9/25) | J8: Yes | K8: Yes | L8: Yes | M8: Yes | N8: Yes | O8: Yes | P8: Yes | Q8: Yes | R8: Yes | S8: Yes | T8: Yes
A9: Ryan Krems | B9: Net New Tech Hires Under New Jon O Org | C9: Senior Engineer (P3) | D9: iOS Engineer | E9: Q1 2020 | G9: Hong Kong | H9: Bob to Provide After Leveling mid next week (~Weds, 9/25) | K9: Yes | L9: Yes | M9: Yes | N9: Yes | O9: Yes | P9: Yes | Q9: Yes | R9: Yes | S9: Yes | T9: Yes
A10: Ryan Krems | B10: Net New Tech Hires Under New Jon O Org | C10: Senior Engineer (P3) | D10: Backend Engineer | E10: Q1 2020 | G10: Hong Kong | H10: Bob to Provide After Leveling mid next week (~Weds, 9/25) | K10: Yes | L10: Yes | M10: Yes | N10: Yes | O10: Yes | P10: Yes | Q10: Yes | R10: Yes | S10: Yes | T10: Yes
A11: Ryan Krems | B11: Net New Tech Hires Under New Jon O Org | C11: Senior Engineer (P3) | D11: Backend Engineer | E11: Q1 2020 | G11: Hong Kong | H11: Bob to Provide After Leveling mid next week (~Weds, 9/25) | K11: Yes | L11: Yes | M11: Yes | N11: Yes | O11: Yes | P11: Yes | Q11: Yes | R11: Yes | S11: Yes | T11: Yes
A12: Ryan Krems | B12: Net New Tech Hires Under New Jon O Org | C12: Staff Engineer (P4) | D12: Mobile Architect | E12: Q1 2020 | G12: Hong Kong | H12: Bob to Provide After Leveling mid next week (~Weds, 9/25) | K12: Yes | L12: Yes | M12: Yes | N12: Yes | O12: Yes | P12: Yes | Q12: Yes | R12: Yes | S12: Yes | T12: Yes
A13: Ryan Krems | B13: Net New Tech Hires Under New Jon O Org | C13: Senior Engineer (P3) | D13: Software SDET | E13: Q1 2020 | G13: Hong Kong | H13: Bob to Provide After Leveling mid next week (~Weds, 9/25) | K13: Yes | L13: Yes | M13: Yes | N13: Yes | O13: Yes | P13: Yes | Q13: Yes | R13: Yes | S13: Yes | T13: Yes
A14: Ryan Krems | B14: Net New Tech Hires Under New Jon O Org | C14: Staff Engineer (P4) | D14: Senior Software SDET | E14: Q4 2019 | G14: Hong Kong | H14: Bob to Provide After Leveling mid next week (~Weds, 9/25) | J14: Yes | K14: Yes | L14: Yes | M14: Yes | N14: Yes | O14: Yes | P14: Yes | Q14: Yes | R14: Yes | S14: Yes | T14: Yes
A15: Ryan Krems | B15: Net New Tech Hires Under New Jon O Org | C15: Engineer (P2) | D15: Manual QA | E15: Q4 2019 | G15: Hong Kong | H15: Bob to Provide After Leveling mid next week (~Weds, 9/25) | J15: Yes | K15: Yes | L15: Yes | M15: Yes | N15: Yes | O15: Yes | P15: Yes | Q15: Yes | R15: Yes | S15: Yes | T15: Yes
A16: Ryan Krems | B16: Net New Tech Hires Under New Jon O Org | C16: Engineering Manager (M3) | D16: Engineering Manager | E16: Q4 2019 | G16: Hong Kong | H16: Bob to Provide After Leveling mid next week (~Weds, 9/25) | J16: Yes | K16: Yes | L16: Yes | M16: Yes | N16: Yes | O16: Yes | P16: Yes | Q16: Yes | R16: Yes | S16: Yes | T16: Yes
A17: Ryan Krems | B17: Net New Tech Hires Under New Jon O Org | C17: Senior Engineer (P3) | D17: SRE | E17: Q3 2020 | G17: Hong Kong | H17: Bob to Provide After Leveling mid next week (~Weds, 9/25) | M17: Yes | N17: Yes | O17: Yes | P17: Yes | Q17: Yes | R17: Yes | S17: Yes | T17: Yes
A18: Ryan Krems | B18: Net New Tech Hires Under New Jon O Org | C18: Senior Engineer (P3) | D18: SRE | E18: Q3 2020 | G18: Hong Kong | H18: Bob to Provide After Leveling mid next week (~Weds, 9/25) | M18: Yes | N18: Yes | O18: Yes | P18: Yes | Q18: Yes | R18: Yes | S18: Yes | T18: Yes
A19: Ryan Krems | B19: Product | C19: Senior UX Manager (M3) | D19: Manager to build out UX team in the region | G19: Hong Kong | H19: Bob to Provide After Leveling mid next week (~Weds, 9/25) | J19: Yes | K19: Yes | L19: Yes | M19: Yes | N19: Yes | O19: Yes | P19: Yes | Q19: Yes | R19: Yes | S19: Yes | T19: Yes
A20: Ryan Krems | B20: Existing Delta Tech Headcount Under New Jon O Org | C20: Staff Engineer (P4) | D20: Backend - Tech Lead | E20: Clarence - Current | G20: Hong Kong | H20: Bob to Provide After Leveling mid next week (~Weds, 9/25)
A21: Ryan Krems | B21: Existing Delta Tech Headcount Under New Jon O Org | C21: Senior Engineer (P3) | D21: Android Engineer | E21: Kit - Current | G21: Hong Kong | H21: Bob to Provide After Leveling mid next week (~Weds, 9/25)
A22: Ryan Krems | B22: Existing Delta Tech Headcount Under New Jon O Org | C22: Senior Engineer (P3) | D22: Backend Engineer | E22: Keith - Current | G22: Hong Kong | H22: Bob to Provide After Leveling mid next week (~Weds, 9/25)
A23: Ryan Krems | B23: Existing Delta Tech Headcount Under New Jon O Org | C23: Senior Engineer (P3) | D23: Android Engineer | E23: Chung - Current | G23: Hong Kong | H23: Bob to Provide After Leveling mid next week (~Weds, 9/25)
A24: Ryan Krems | B24: Existing Delta Tech Headcount Under New Jon O Org | C24: Engineer (P1) | D24: Associate Android Engineer | E24: Man - Current | G24: Hong Kong | H24: Bob to Provide After Leveling mid next week (~Weds, 9/25)
I26: =COUNTA(I6:I19) | J26: =COUNTA(J6:J19) | K26: =COUNTA(K6:K19) | L26: =COUNTA(L6:L19) | M26: =COUNTA(M6:M19) | N26: =COUNTA(N6:N19) | O26: =COUNTA(O6:O19) | P26: =COUNTA(P6:P19) | ... T26: =COUNTA(T6:T19) | U26: =SUM(U6:U25)
A28: Non Headcount | I28: 2019 | K28: 2020 | O28: 2021 | S28: 2022
A29: Submitted by | B29: Department | C29: Description of Spend | D29: Justification | H29: Total Cost Estimate | I29: Q3 | J29: Q4 | K29: Q1 | L29: Q2 | M29: Q3 | N29: Q4 | O29: Q1 | P29: Q2 | Q29: Q3 | R29: Q4 | S29: Q1 | T29: Q2
A30: Dawn Baker
H43: =SUM(H30:H42) | I43: =SUM(I30:I36) | J43: =SUM(J30:J36) | K43: =SUM(K30:K36) | L43: =SUM(L30:L36) | M43: =SUM(M30:M36) | N43: =SUM(N30:N36) | O43: =SUM(O30:O36) | P43: =SUM(P30:P36) | ... T43: =SUM(T30:T36)

Sheet II NON-TECH
A1: 2. DELTA NON-TECH HC - CS,
A3: Headcount | I3: 2019 | K3: 2020 | O3: 2021 | S3: 2022
I4: 43647 | J4: 43739 | K4: 43831 | L4: 43922 | M4: 44013 | N4: 44105 | O4: 44197 | P4: 44287 | Q4: 44378 | R4: 44470 | S4: 44562 | T4: 44652
A5: Submitted by | B5: Department | C5: TBH Title | D5: Description | E5: Hire Date | G5: Location | H5: Base Salary Estimate USD | I5: Q3 | J5: Q4 | K5: Q1 | L5: Q2 | M5: Q3 | N5: Q4 | O5: Q1 | P5: Q2 | Q5: Q3 | R5: Q4 | S5: Q1 | T5: Q2
B6: DELTA EXISTING NON-TECH HC
B7: Lauren to populate the 9 non-tech existing Delta heads from blue HR dataroom folder: 9. Legal Emp. Docs. Retirement, Handbook, Emp. Contracts/Offer Letters, | H7: Bob to Provide After Leveling mid next week (~Weds, 9/25)
B8: Lauren to populate the 9 non-tech existing Delta heads from blue HR dataroom folder: 9. Legal Emp. Docs. Retirement, Handbook, Emp. Contracts/Offer Letters, | H8: Bob to Provide After Leveling mid next week (~Weds, 9/25)
B9: Lauren to populate the 9 non-tech existing Delta heads from blue HR dataroom folder: 9. Legal Emp. Docs. Retirement, Handbook, Emp. Contracts/Offer Letters, | H9: Bob to Provide After Leveling mid next week (~Weds, 9/25)
B10: Lauren to populate the 9 non-tech existing Delta heads from blue HR dataroom folder: 9. Legal Emp. Docs. Retirement, Handbook, Emp. Contracts/Offer Letters, | H10: Bob to Provide After Leveling mid next week (~Weds, 9/25)
B11: Lauren to populate the 9 non-tech existing Delta heads from blue HR dataroom folder: 9. Legal Emp. Docs. Retirement, Handbook, Emp. Contracts/Offer Letters, | H11: Bob to Provide After Leveling mid next week (~Weds, 9/25)
B12: Lauren to populate the 9 non-tech existing Delta heads from blue HR dataroom folder: 9. Legal Emp. Docs. Retirement, Handbook, Emp. Contracts/Offer Letters,
B13: Lauren to populate the 9 non-tech existing Delta heads from blue HR dataroom folder: 9. Legal Emp. Docs. Retirement, Handbook, Emp. Contracts/Offer Letters, | I13: =SUM(I6:I12) | J13: =SUM(J6:J12) | K13: =SUM(K6:K12) | L13: =SUM(L6:L12) | M13: =SUM(M6:M12) | N13: =SUM(N6:N12) | O13: =SUM(O6:O12) | P13: =SUM(P6:P12) | ... T13: =SUM(T6:T12)
B14: Lauren to populate the 9 non-tech existing Delta heads from blue HR dataroom folder: 9. Legal Emp. Docs. Retirement, Handbook, Emp. Contracts/Offer Letters,
A15: Non Headcount | B15: Lauren to populate the 9 non-tech existing Delta heads from blue HR dataroom folder: 9. Legal Emp. Docs. Retirement, Handbook, Emp. Contracts/Offer Letters, | I15: 2019 | K15: 2020 | O15: 2021 | S15: 2022
A16: Submitted by | B16: Department | C16: Description of Spend | D16: Justification | H16: Total Cost Estimate | I16: Q3 | J16: Q4 | K16: Q1 | L16: Q2 | M16: Q3 | N16: Q4 | O16: Q1 | P16: Q2 | Q16: Q3 | R16: Q4 | S16: Q1 | T16: Q2
A18: Ryan Krems | B18: Product | C18: Recruiting Budget | D18: Need to get new-hires on-board - 2months of average salary to be added once get average salary
H29: =SUM(H17:H28) | I29: =SUM(I17:I22) | J29: =SUM(J17:J22) | K29: =SUM(K17:K22) | L29: =SUM(L17:L22) | M29: =SUM(M17:M22) | N29: =SUM(N17:N22) | O29: =SUM(O17:O22) | P29: =SUM(P17:P22) | ... T29: =SUM(T17:T22)

Sheet 1) ProductUX
A1: Delta Incremental Costs
A3: Headcount | H3: 2019 | J3: 2020 | N3: 2021 | R3: 2022
H4: 43647 | I4: 43739 | J4: 43831 | K4: 43922 | L4: 44013 | M4: 44105 | N4: 44197 | O4: 44287 | P4: 44378 | Q4: 44470 | R4: 44562 | S4: 44652
A5: Submitted by | B5: Department | C5: TBH Title | D5: Description | E5: Hire Date | F5: Location | G5: Base Salary Estimate USD | H5: Q3 | I5: Q4 | J5: Q1 | K5: Q2 | L5: Q3 | M5: Q4 | N5: Q1 | O5: Q2 | P5: Q3 | Q5: Q4 | R5: Q1 | S5: Q2
H7: =IF($E7<I$4,($G7*1.3)/4,0) | I7: =IF($E7<J$4,($G7*1.3)/4,0) | J7: =IF($E7<K$4,($G7*1.3)/4,0) | K7: =IF($E7<L$4,($G7*1.3)/4,0) | L7: =IF($E7<M$4,($G7*1.3)/4,0) | M7: =IF($E7<N$4,($G7*1.3)/4,0) | N7: =IF($E7<O$4,($G7*1.3)/4,0) | O7: =IF($E7<P$4,($G7*1.3)/4,0) | ... R7: =IF($E7<S$4,($G7*1.3)/4,0) | S7: =IF($E7<S$4,($G7*1.3)/4,0)
H8: =IF($E8<I$4,($G8*1.3)/4,0) | I8: =IF($E8<J$4,($G8*1.3)/4,0) | J8: =IF($E8<K$4,($G8*1.3)/4,0) | K8: =IF($E8<L$4,($G8*1.3)/4,0) | L8: =IF($E8<M$4,($G8*1.3)/4,0) | M8: =IF($E8<N$4,($G8*1.3)/4,0) | N8: =IF($E8<O$4,($G8*1.3)/4,0) | O8: =IF($E8<P$4,($G8*1.3)/4,0) | ... R8: =IF($E8<S$4,($G8*1.3)/4,0) | S8: =IF($E8<S$4,($G8*1.3)/4,0)
H9: =IF($E9<I$4,($G9*1.3)/4,0) | I9: =IF($E9<J$4,($G9*1.3)/4,0) | J9: =IF($E9<K$4,($G9*1.3)/4,0) | K9: =IF($E9<L$4,($G9*1.3)/4,0) | L9: =IF($E9<M$4,($G9*1.3)/4,0) | M9: =IF($E9<N$4,($G9*1.3)/4,0) | N9: =IF($E9<O$4,($G9*1.3)/4,0) | O9: =IF($E9<P$4,($G9*1.3)/4,0) | ... R9: =IF($E9<S$4,($G9*1.3)/4,0) | S9: =IF($E9<S$4,($G9*1.3)/4,0)
H10: =IF($E10<I$4,($G10*1.3)/4,0) | I10: =IF($E10<J$4,($G10*1.3)/4,0) | J10: =IF($E10<K$4,($G10*1.3)/4,0) | K10: =IF($E10<L$4,($G10*1.3)/4,0) | L10: =IF($E10<M$4,($G10*1.3)/4,0) | M10: =IF($E10<N$4,($G10*1.3)/4,0) | N10: =IF($E10<O$4,($G10*1.3)/4,0) | O10: =IF($E10<P$4,($G10*1.3)/4,0) | ... R10: =IF($E10<S$4,($G10*1.3)/4,0) | S10: =IF($E10<S$4,($G10*1.3)/4,0)
H11: =IF($E11<I$4,($G11*1.3)/4,0) | I11: =IF($E11<J$4,($G11*1.3)/4,0) | J11: =IF($E11<K$4,($G11*1.3)/4,0) | K11: =IF($E11<L$4,($G11*1.3)/4,0) | L11: =IF($E11<M$4,($G11*1.3)/4,0) | M11: =IF($E11<N$4,($G11*1.3)/4,0) | N11: =IF($E11<O$4,($G11*1.3)/4,0) | O11: =IF($E11<P$4,($G11*1.3)/4,0) | ... R11: =IF($E11<S$4,($G11*1.3)/4,0) | S11: =IF($E11<S$4,($G11*1.3)/4,0)
H12: =IF($E12<I$4,($G12*1.3)/4,0) | I12: =IF($E12<J$4,($G12*1.3)/4,0) | J12: =IF($E12<K$4,($G12*1.3)/4,0) | K12: =IF($E12<L$4,($G12*1.3)/4,0) | L12: =IF($E12<M$4,($G12*1.3)/4,0) | M12: =IF($E12<N$4,($G12*1.3)/4,0) | N12: =IF($E12<O$4,($G12*1.3)/4,0) | O12: =IF($E12<P$4,($G12*1.3)/4,0) | ... R12: =IF($E12<S$4,($G12*1.3)/4,0) | S12: =IF($E12<S$4,($G12*1.3)/4,0)
H13: =IF($E13<I$4,($G13*1.3)/4,0) | I13: =IF($E13<J$4,($G13*1.3)/4,0) | J13: =IF($E13<K$4,($G13*1.3)/4,0) | K13: =IF($E13<L$4,($G13*1.3)/4,0) | L13: =IF($E13<M$4,($G13*1.3)/4,0) | M13: =IF($E13<N$4,($G13*1.3)/4,0) | N13: =IF($E13<O$4,($G13*1.3)/4,0) | O13: =IF($E13<P$4,($G13*1.3)/4,0) | ... R13: =IF($E13<S$4,($G13*1.3)/4,0) | S13: =IF($E13<S$4,($G13*1.3)/4,0)
H14: =IF($E14<I$4,($G14*1.3)/4,0) | I14: =IF($E14<J$4,($G14*1.3)/4,0) | J14: =IF($E14<K$4,($G14*1.3)/4,0) | K14: =IF($E14<L$4,($G14*1.3)/4,0) | L14: =IF($E14<M$4,($G14*1.3)/4,0) | M14: =IF($E14<N$4,($G14*1.3)/4,0) | N14: =IF($E14<O$4,($G14*1.3)/4,0) | O14: =IF($E14<P$4,($G14*1.3)/4,0) | ... R14: =IF($E14<S$4,($G14*1.3)/4,0) | S14: =IF($E14<S$4,($G14*1.3)/4,0)
H15: =IF($E15<I$4,($G15*1.3)/4,0) | I15: =IF($E15<J$4,($G15*1.3)/4,0) | J15: =IF($E15<K$4,($G15*1.3)/4,0) | K15: =IF($E15<L$4,($G15*1.3)/4,0) | L15: =IF($E15<M$4,($G15*1.3)/4,0) | M15: =IF($E15<N$4,($G15*1.3)/4,0) | N15: =IF($E15<O$4,($G15*1.3)/4,0) | O15: =IF($E15<P$4,($G15*1.3)/4,0) | ... R15: =IF($E15<S$4,($G15*1.3)/4,0) | S15: =IF($E15<S$4,($G15*1.3)/4,0)
H16: =IF($E16<I$4,($G16*1.3)/4,0) | I16: =IF($E16<J$4,($G16*1.3)/4,0) | J16: =IF($E16<K$4,($G16*1.3)/4,0) | K16: =IF($E16<L$4,($G16*1.3)/4,0) | L16: =IF($E16<M$4,($G16*1.3)/4,0) | M16: =IF($E16<N$4,($G16*1.3)/4,0) | N16: =IF($E16<O$4,($G16*1.3)/4,0) | O16: =IF($E16<P$4,($G16*1.3)/4,0) | ... R16: =IF($E16<S$4,($G16*1.3)/4,0) | S16: =IF($E16<S$4,($G16*1.3)/4,0)
H17: =IF($E17<I$4,($G17*1.3)/4,0) | I17: =IF($E17<J$4,($G17*1.3)/4,0) | J17: =IF($E17<K$4,($G17*1.3)/4,0) | K17: =IF($E17<L$4,($G17*1.3)/4,0) | L17: =IF($E17<M$4,($G17*1.3)/4,0) | M17: =IF($E17<N$4,($G17*1.3)/4,0) | N17: =IF($E17<O$4,($G17*1.3)/4,0) | O17: =IF($E17<P$4,($G17*1.3)/4,0) | ... R17: =IF($E17<S$4,($G17*1.3)/4,0) | S17: =IF($E17<S$4,($G17*1.3)/4,0)
H18: =IF($E18<I$4,($G18*1.3)/4,0) | I18: =IF($E18<J$4,($G18*1.3)/4,0) | J18: =IF($E18<K$4,($G18*1.3)/4,0) | K18: =IF($E18<L$4,($G18*1.3)/4,0) | L18: =IF($E18<M$4,($G18*1.3)/4,0) | M18: =IF($E18<N$4,($G18*1.3)/4,0) | N18: =IF($E18<O$4,($G18*1.3)/4,0) | O18: =IF($E18<P$4,($G18*1.3)/4,0) | ... R18: =IF($E18<S$4,($G18*1.3)/4,0) | S18: =IF($E18<S$4,($G18*1.3)/4,0)
... H24: =IF($E24<I$4,($G24*1.3)/4,0) | I24: =IF($E24<J$4,($G24*1.3)/4,0) | J24: =IF($E24<K$4,($G24*1.3)/4,0) | K24: =IF($E24<L$4,($G24*1.3)/4,0) | L24: =IF($E24<M$4,($G24*1.3)/4,0) | M24: =IF($E24<N$4,($G24*1.3)/4,0) | N24: =IF($E24<O$4,($G24*1.3)/4,0) | O24: =IF($E24<P$4,($G24*1.3)/4,0) | ... R24: =IF($E24<S$4,($G24*1.3)/4,0) | S24: =IF($E24<S$4,($G24*1.3)/4,0)
H25: =SUM(H6:H24) | I25: =SUM(I6:I24) | J25: =SUM(J6:J24) | K25: =SUM(K6:K24) | L25: =SUM(L6:L24) | M25: =SUM(M6:M24) | N25: =SUM(N6:N24) | O25: =SUM(O6:O24) | ... S25: =SUM(S6:S24)
A27: Non Headcount | H27: 2019 | J27: 2020 | N27: 2021 | R27: 2022
A28: Submitted by | B28: Department | C28: Description of Spend | D28: Justification | G28: Total Cost Estimate | H28: Q3 | I28: Q4 | J28: Q1 | K28: Q2 | L28: Q3 | M28: Q4 | N28: Q1 | O28: Q2 | P28: Q3 | Q28: Q4 | R28: Q1 | S28: Q2
A29: Ryan Krems | B29: Product | C29: Recruiting Budget | D29: Need to get new-hires on-board | G29: 2 months of average salary above
G41: =SUM(G29:G40) | H41: =SUM(H29:H34) | I41: =SUM(I29:I34) | J41: =SUM(J29:J34) | K41: =SUM(K29:K34) | L41: =SUM(L29:L34) | M41: =SUM(M29:M34) | N41: =SUM(N29:N34) | O41: =SUM(O29:O34) | ... S41: =SUM(S29:S34)

Sheet 3) HW Eng
A1: Delta Incremental Costs
A3: Headcount | H3: 2019 | J3: 2020 | N3: 2021 | R3: 2022
H4: 43647 | I4: 43739 | J4: 43831 | K4: 43922 | L4: 44013 | M4: 44105 | N4: 44197 | O4: 44287 | P4: 44378 | Q4: 44470 | R4: 44562 | S4: 44652
A5: Submitted by | B5: Department | C5: TBH Title | D5: Description | E5: Hire Date | F5: Location | G5: Base Salary Estimate USD | H5: Q3 | I5: Q4 | J5: Q1 | K5: Q2 | L5: Q3 | M5: Q4 | N5: Q1 | O5: Q2 | P5: Q3 | Q5: Q4 | R5: Q1 | S5: Q2
H6: =IF($E6<I$4,($G6*1.3)/4,0) | I6: =IF($E6<J$4,($G6*1.3)/4,0) | J6: =IF($E6<K$4,($G6*1.3)/4,0) | K6: =IF($E6<L$4,($G6*1.3)/4,0) | L6: =IF($E6<M$4,($G6*1.3)/4,0) | M6: =IF($E6<N$4,($G6*1.3)/4,0) | N6: =IF($E6<O$4,($G6*1.3)/4,0) | O6: =IF($E6<P$4,($G6*1.3)/4,0) | ... R6: =IF($E6<S$4,($G6*1.3)/4,0) | S6: =IF($E6<S$4,($G6*1.3)/4,0)
H7: =IF($E7<I$4,($G7*1.3)/4,0) | I7: =IF($E7<J$4,($G7*1.3)/4,0) | J7: =IF($E7<K$4,($G7*1.3)/4,0) | K7: =IF($E7<L$4,($G7*1.3)/4,0) | L7: =IF($E7<M$4,($G7*1.3)/4,0) | M7: =IF($E7<N$4,($G7*1.3)/4,0) | N7: =IF($E7<O$4,($G7*1.3)/4,0) | O7: =IF($E7<P$4,($G7*1.3)/4,0) | ... R7: =IF($E7<S$4,($G7*1.3)/4,0) | S7: =IF($E7<S$4,($G7*1.3)/4,0)
B8: Nish Jain: NONE EXPECTED | H8: =IF($E8<I$4,($G8*1.3)/4,0) | I8: =IF($E8<J$4,($G8*1.3)/4,0) | J8: =IF($E8<K$4,($G8*1.3)/4,0) | K8: =IF($E8<L$4,($G8*1.3)/4,0) | L8: =IF($E8<M$4,($G8*1.3)/4,0) | M8: =IF($E8<N$4,($G8*1.3)/4,0) | N8: =IF($E8<O$4,($G8*1.3)/4,0) | O8: =IF($E8<P$4,($G8*1.3)/4,0) | ... R8: =IF($E8<S$4,($G8*1.3)/4,0) | S8: =IF($E8<S$4,($G8*1.3)/4,0)
H9: =IF($E9<I$4,($G9*1.3)/4,0) | I9: =IF($E9<J$4,($G9*1.3)/4,0) | J9: =IF($E9<K$4,($G9*1.3)/4,0) | K9: =IF($E9<L$4,($G9*1.3)/4,0) | L9: =IF($E9<M$4,($G9*1.3)/4,0) | M9: =IF($E9<N$4,($G9*1.3)/4,0) | N9: =IF($E9<O$4,($G9*1.3)/4,0) | O9: =IF($E9<P$4,($G9*1.3)/4,0) | ... R9: =IF($E9<S$4,($G9*1.3)/4,0) | S9: =IF($E9<S$4,($G9*1.3)/4,0)
H10: =IF($E10<I$4,($G10*1.3)/4,0) | I10: =IF($E10<J$4,($G10*1.3)/4,0) | J10: =IF($E10<K$4,($G10*1.3)/4,0) | K10: =IF($E10<L$4,($G10*1.3)/4,0) | L10: =IF($E10<M$4,($G10*1.3)/4,0) | M10: =IF($E10<N$4,($G10*1.3)/4,0) | N10: =IF($E10<O$4,($G10*1.3)/4,0) | O10: =IF($E10<P$4,($G10*1.3)/4,0) | ... R10: =IF($E10<S$4,($G10*1.3)/4,0) | S10: =IF($E10<S$4,($G10*1.3)/4,0)
H11: =IF($E11<I$4,($G11*1.3)/4,0) | I11: =IF($E11<J$4,($G11*1.3)/4,0) | J11: =IF($E11<K$4,($G11*1.3)/4,0) | K11: =IF($E11<L$4,($G11*1.3)/4,0) | L11: =IF($E11<M$4,($G11*1.3)/4,0) | M11: =IF($E11<N$4,($G11*1.3)/4,0) | N11: =IF($E11<O$4,($G11*1.3)/4,0) | O11: =IF($E11<P$4,($G11*1.3)/4,0) | ... R11: =IF($E11<S$4,($G11*1.3)/4,0) | S11: =IF($E11<S$4,($G11*1.3)/4,0)
H12: =IF($E12<I$4,($G12*1.3)/4,0) | I12: =IF($E12<J$4,($G12*1.3)/4,0) | J12: =IF($E12<K$4,($G12*1.3)/4,0) | K12: =IF($E12<L$4,($G12*1.3)/4,0) | L12: =IF($E12<M$4,($G12*1.3)/4,0) | M12: =IF($E12<N$4,($G12*1.3)/4,0) | N12: =IF($E12<O$4,($G12*1.3)/4,0) | O12: =IF($E12<P$4,($G12*1.3)/4,0) | ... R12: =IF($E12<S$4,($G12*1.3)/4,0) | S12: =IF($E12<S$4,($G12*1.3)/4,0)
H13: =IF($E13<I$4,($G13*1.3)/4,0) | I13: =IF($E13<J$4,($G13*1.3)/4,0) | J13: =IF($E13<K$4,($G13*1.3)/4,0) | K13: =IF($E13<L$4,($G13*1.3)/4,0) | L13: =IF($E13<M$4,($G13*1.3)/4,0) | M13: =IF($E13<N$4,($G13*1.3)/4,0) | N13: =IF($E13<O$4,($G13*1.3)/4,0) | O13: =IF($E13<P$4,($G13*1.3)/4,0) | ... R13: =IF($E13<S$4,($G13*1.3)/4,0) | S13: =IF($E13<S$4,($G13*1.3)/4,0)
H14: =IF($E14<I$4,($G14*1.3)/4,0) | I14: =IF($E14<J$4,($G14*1.3)/4,0) | J14: =IF($E14<K$4,($G14*1.3)/4,0) | K14: =IF($E14<L$4,($G14*1.3)/4,0) | L14: =IF($E14<M$4,($G14*1.3)/4,0) | M14: =IF($E14<N$4,($G14*1.3)/4,0) | N14: =IF($E14<O$4,($G14*1.3)/4,0) | O14: =IF($E14<P$4,($G14*1.3)/4,0) | ... R14: =IF($E14<S$4,($G14*1.3)/4,0) | S14: =IF($E14<S$4,($G14*1.3)/4,0)
H15: =IF($E15<I$4,($G15*1.3)/4,0) | I15: =IF($E15<J$4,($G15*1.3)/4,0) | J15: =IF($E15<K$4,($G15*1.3)/4,0) | K15: =IF($E15<L$4,($G15*1.3)/4,0) | L15: =IF($E15<M$4,($G15*1.3)/4,0) | M15: =IF($E15<N$4,($G15*1.3)/4,0) | N15: =IF($E15<O$4,($G15*1.3)/4,0) | O15: =IF($E15<P$4,($G15*1.3)/4,0) | ... R15: =IF($E15<S$4,($G15*1.3)/4,0) | S15: =IF($E15<S$4,($G15*1.3)/4,0)
H16: =IF($E16<I$4,($G16*1.3)/4,0) | I16: =IF($E16<J$4,($G16*1.3)/4,0) | J16: =IF($E16<K$4,($G16*1.3)/4,0) | K16: =IF($E16<L$4,($G16*1.3)/4,0) | L16: =IF($E16<M$4,($G16*1.3)/4,0) | M16: =IF($E16<N$4,($G16*1.3)/4,0) | N16: =IF($E16<O$4,($G16*1.3)/4,0) | O16: =IF($E16<P$4,($G16*1.3)/4,0) | ... R16: =IF($E16<S$4,($G16*1.3)/4,0) | S16: =IF($E16<S$4,($G16*1.3)/4,0)
H17: =IF($E17<I$4,($G17*1.3)/4,0) | I17: =IF($E17<J$4,($G17*1.3)/4,0) | J17: =IF($E17<K$4,($G17*1.3)/4,0) | K17: =IF($E17<L$4,($G17*1.3)/4,0) | L17: =IF($E17<M$4,($G17*1.3)/4,0) | M17: =IF($E17<N$4,($G17*1.3)/4,0) | N17: =IF($E17<O$4,($G17*1.3)/4,0) | O17: =IF($E17<P$4,($G17*1.3)/4,0) | ... R17: =IF($E17<S$4,($G17*1.3)/4,0) | S17: =IF($E17<S$4,($G17*1.3)/4,0)
H18: =IF($E18<I$4,($G18*1.3)/4,0) | I18: =IF($E18<J$4,($G18*1.3)/4,0) | J18: =IF($E18<K$4,($G18*1.3)/4,0) | K18: =IF($E18<L$4,($G18*1.3)/4,0) | L18: =IF($E18<M$4,($G18*1.3)/4,0) | M18: =IF($E18<N$4,($G18*1.3)/4,0) | N18: =IF($E18<O$4,($G18*1.3)/4,0) | O18: =IF($E18<P$4,($G18*1.3)/4,0) | ... R18: =IF($E18<S$4,($G18*1.3)/4,0) | S18: =IF($E18<S$4,($G18*1.3)/4,0)
H19: =IF($E19<I$4,($G19*1.3)/4,0) | I19: =IF($E19<J$4,($G19*1.3)/4,0) | J19: =IF($E19<K$4,($G19*1.3)/4,0) | K19: =IF($E19<L$4,($G19*1.3)/4,0) | L19: =IF($E19<M$4,($G19*1.3)/4,0) | M19: =IF($E19<N$4,($G19*1.3)/4,0) | N19: =IF($E19<O$4,($G19*1.3)/4,0) | O19: =IF($E19<P$4,($G19*1.3)/4,0) | ... R19: =IF($E19<S$4,($G19*1.3)/4,0) | S19: =IF($E19<S$4,($G19*1.3)/4,0)
H20: =IF($E20<I$4,($G20*1.3)/4,0) | I20: =IF($E20<J$4,($G20*1.3)/4,0) | J20: =IF($E20<K$4,($G20*1.3)/4,0) | K20: =IF($E20<L$4,($G20*1.3)/4,0) | L20: =IF($E20<M$4,($G20*1.3)/4,0) | M20: =IF($E20<N$4,($G20*1.3)/4,0) | N20: =IF($E20<O$4,($G20*1.3)/4,0) | O20: =IF($E20<P$4,($G20*1.3)/4,0) | ... R20: =IF($E20<S$4,($G20*1.3)/4,0) | S20: =IF($E20<S$4,($G20*1.3)/4,0)
... H24: =IF($E24<I$4,($G24*1.3)/4,0) | I24: =IF($E24<J$4,($G24*1.3)/4,0) | J24: =IF($E24<K$4,($G24*1.3)/4,0) | K24: =IF($E24<L$4,($G24*1.3)/4,0) | L24: =IF($E24<M$4,($G24*1.3)/4,0) | M24: =IF($E24<N$4,($G24*1.3)/4,0) | N24: =IF($E24<O$4,($G24*1.3)/4,0) | O24: =IF($E24<P$4,($G24*1.3)/4,0) | ... R24: =IF($E24<S$4,($G24*1.3)/4,0) | S24: =IF($E24<S$4,($G24*1.3)/4,0)
H25: =SUM(H6:H24) | I25: =SUM(I6:I24) | J25: =SUM(J6:J24) | K25: =SUM(K6:K24) | L25: =SUM(L6:L24) | M25: =SUM(M6:M24) | N25: =SUM(N6:N24) | O25: =SUM(O6:O24) | ... S25: =SUM(S6:S24)
A27: Non Headcount | H27: 2019 | J27: 2020 | N27: 2021 | R27: 2022
A28: Submitted by | B28: Department | C28: Description of Spend | D28: Justification | G28: Total Cost Estimate | H28: Q3 | I28: Q4 | J28: Q1 | K28: Q2 | L28: Q3 | M28: Q4 | N28: Q1 | O28: Q2 | P28: Q3 | Q28: Q4 | R28: Q1 | S28: Q2
G41: =SUM(G29:G40) | H41: =SUM(H29:H34) | I41: =SUM(I29:I34) | J41: =SUM(J29:J34) | K41: =SUM(K29:K34) | L41: =SUM(L29:L34) | M41: =SUM(M29:M34) | N41: =SUM(N29:N34) | O41: =SUM(O29:O34) | ... S41: =SUM(S29:S34)

Sheet 5) Tax & Treasury
A1: Delta Incremental Costs
A3: Headcount | H3: 2019 | J3: 2020 | N3: 2021 | R3: 2022
H4: 43647 | I4: 43739 | J4: 43831 | K4: 43922 | L4: 44013 | M4: 44105 | N4: 44197 | O4: 44287 | P4: 44378 | Q4: 44470 | R4: 44562 | S4: 44652
A5: Submitted by | B5: Department | C5: TBH Title | D5: Description | E5: Hire Date | F5: Location | G5: Base Salary Estimate USD | H5: Q3 | I5: Q4 | J5: Q1 | K5: Q2 | L5: Q3 | M5: Q4 | N5: Q1 | O5: Q2 | P5: Q3 | Q5: Q4 | R5: Q1 | S5: Q2
H6: =IF($E6<I$4,($G6*1.3)/4,0) | I6: =IF($E6<J$4,($G6*1.3)/4,0) | J6: =IF($E6<K$4,($G6*1.3)/4,0) | K6: =IF($E6<L$4,($G6*1.3)/4,0) | L6: =IF($E6<M$4,($G6*1.3)/4,0) | M6: =IF($E6<N$4,($G6*1.3)/4,0) | N6: =IF($E6<O$4,($G6*1.3)/4,0) | O6: =IF($E6<P$4,($G6*1.3)/4,0) | ... R6: =IF($E6<S$4,($G6*1.3)/4,0) | S6: =IF($E6<S$4,($G6*1.3)/4,0)
H7: =IF($E7<I$4,($G7*1.3)/4,0) | I7: =IF($E7<J$4,($G7*1.3)/4,0) | J7: =IF($E7<K$4,($G7*1.3)/4,0) | K7: =IF($E7<L$4,($G7*1.3)/4,0) | L7: =IF($E7<M$4,($G7*1.3)/4,0) | M7: =IF($E7<N$4,($G7*1.3)/4,0) | N7: =IF($E7<O$4,($G7*1.3)/4,0) | O7: =IF($E7<P$4,($G7*1.3)/4,0) | ... R7: =IF($E7<S$4,($G7*1.3)/4,0) | S7: =IF($E7<S$4,($G7*1.3)/4,0)
H8: =IF($E8<I$4,($G8*1.3)/4,0) | I8: =IF($E8<J$4,($G8*1.3)/4,0) | J8: =IF($E8<K$4,($G8*1.3)/4,0) | K8: =IF($E8<L$4,($G8*1.3)/4,0) | L8: =IF($E8<M$4,($G8*1.3)/4,0) | M8: =IF($E8<N$4,($G8*1.3)/4,0) | N8: =IF($E8<O$4,($G8*1.3)/4,0) | O8: =IF($E8<P$4,($G8*1.3)/4,0) | ... R8: =IF($E8<S$4,($G8*1.3)/4,0) | S8: =IF($E8<S$4,($G8*1.3)/4,0)
H9: =IF($E9<I$4,($G9*1.3)/4,0) | I9: =IF($E9<J$4,($G9*1.3)/4,0) | J9: =IF($E9<K$4,($G9*1.3)/4,0) | K9: =IF($E9<L$4,($G9*1.3)/4,0) | L9: =IF($E9<M$4,($G9*1.3)/4,0) | M9: =IF($E9<N$4,($G9*1.3)/4,0) | N9: =IF($E9<O$4,($G9*1.3)/4,0) | O9: =IF($E9<P$4,($G9*1.3)/4,0) | ... R9: =IF($E9<S$4,($G9*1.3)/4,0) | S9: =IF($E9<S$4,($G9*1.3)/4,0)
H10: =IF($E10<I$4,($G10*1.3)/4,0) | I10: =IF($E10<J$4,($G10*1.3)/4,0) | J10: =IF($E10<K$4,($G10*1.3)/4,0) | K10: =IF($E10<L$4,($G10*1.3)/4,0) | L10: =IF($E10<M$4,($G10*1.3)/4,0) | M10: =IF($E10<N$4,($G10*1.3)/4,0) | N10: =IF($E10<O$4,($G10*1.3)/4,0) | O10: =IF($E10<P$4,($G10*1.3)/4,0) | ... R10: =IF($E10<S$4,($G10*1.3)/4,0) | S10: =IF($E10<S$4,($G10*1.3)/4,0)
H11: =IF($E11<I$4,($G11*1.3)/4,0) | I11: =IF($E11<J$4,($G11*1.3)/4,0) | J11: =IF($E11<K$4,($G11*1.3)/4,0) | K11: =IF($E11<L$4,($G11*1.3)/4,0) | L11: =IF($E11<M$4,($G11*1.3)/4,0) | M11: =IF($E11<N$4,($G11*1.3)/4,0) | N11: =IF($E11<O$4,($G11*1.3)/4,0) | O11: =IF($E11<P$4,($G11*1.3)/4,0) | ... R11: =IF($E11<S$4,($G11*1.3)/4,0) | S11: =IF($E11<S$4,($G11*1.3)/4,0)
H12: =IF($E12<I$4,($G12*1.3)/4,0) | I12: =IF($E12<J$4,($G12*1.3)/4,0) | J12: =IF($E12<K$4,($G12*1.3)/4,0) | K12: =IF($E12<L$4,($G12*1.3)/4,0) | L12: =IF($E12<M$4,($G12*1.3)/4,0) | M12: =IF($E12<N$4,($G12*1.3)/4,0) | N12: =IF($E12<O$4,($G12*1.3)/4,0) | O12: =IF($E12<P$4,($G12*1.3)/4,0) | ... R12: =IF($E12<S$4,($G12*1.3)/4,0) | S12: =IF($E12<S$4,($G12*1.3)/4,0)
H13: =IF($E13<I$4,($G13*1.3)/4,0) | I13: =IF($E13<J$4,($G13*1.3)/4,0) | J13: =IF($E13<K$4,($G13*1.3)/4,0) | K13: =IF($E13<L$4,($G13*1.3)/4,0) | L13: =IF($E13<M$4,($G13*1.3)/4,0) | M13: =IF($E13<N$4,($G13*1.3)/4,0) | N13: =IF($E13<O$4,($G13*1.3)/4,0) | O13: =IF($E13<P$4,($G13*1.3)/4,0) | ... R13: =IF($E13<S$4,($G13*1.3)/4,0) | S13: =IF($E13<S$4,($G13*1.3)/4,0)
H14: =IF($E14<I$4,($G14*1.3)/4,0) | I14: =IF($E14<J$4,($G14*1.3)/4,0) | J14: =IF($E14<K$4,($G14*1.3)/4,0) | K14: =IF($E14<L$4,($G14*1.3)/4,0) | L14: =IF($E14<M$4,($G14*1.3)/4,0) | M14: =IF($E14<N$4,($G14*1.3)/4,0) | N14: =IF($E14<O$4,($G14*1.3)/4,0) | O14: =IF($E14<P$4,($G14*1.3)/4,0) | ... R14: =IF($E14<S$4,($G14*1.3)/4,0) | S14: =IF($E14<S$4,($G14*1.3)/4,0)
H15: =IF($E15<I$4,($G15*1.3)/4,0) | I15: =IF($E15<J$4,($G15*1.3)/4,0) | J15: =IF($E15<K$4,($G15*1.3)/4,0) | K15: =IF($E15<L$4,($G15*1.3)/4,0) | L15: =IF($E15<M$4,($G15*1.3)/4,0) | M15: =IF($E15<N$4,($G15*1.3)/4,0) | N15: =IF($E15<O$4,($G15*1.3)/4,0) | O15: =IF($E15<P$4,($G15*1.3)/4,0) | ... R15: =IF($E15<S$4,($G15*1.3)/4,0) | S15: =IF($E15<S$4,($G15*1.3)/4,0)
H16: =IF($E16<I$4,($G16*1.3)/4,0) | I16: =IF($E16<J$4,($G16*1.3)/4,0) | J16: =IF($E16<K$4,($G16*1.3)/4,0) | K16: =IF($E16<L$4,($G16*1.3)/4,0) | L16: =IF($E16<M$4,($G16*1.3)/4,0) | M16: =IF($E16<N$4,($G16*1.3)/4,0) | N16: =IF($E16<O$4,($G16*1.3)/4,0) | O16: =IF($E16<P$4,($G16*1.3)/4,0) | ... R16: =IF($E16<S$4,($G16*1.3)/4,0) | S16: =IF($E16<S$4,($G16*1.3)/4,0)
H17: =IF($E17<I$4,($G17*1.3)/4,0) | I17: =IF($E17<J$4,($G17*1.3)/4,0) | J17: =IF($E17<K$4,($G17*1.3)/4,0) | K17: =IF($E17<L$4,($G17*1.3)/4,0) | L17: =IF($E17<M$4,($G17*1.3)/4,0) | M17: =IF($E17<N$4,($G17*1.3)/4,0) | N17: =IF($E17<O$4,($G17*1.3)/4,0) | O17: =IF($E17<P$4,($G17*1.3)/4,0) | ... R17: =IF($E17<S$4,($G17*1.3)/4,0) | S17: =IF($E17<S$4,($G17*1.3)/4,0)
... H24: =IF($E24<I$4,($G24*1.3)/4,0) | I24: =IF($E24<J$4,($G24*1.3)/4,0) | J24: =IF($E24<K$4,($G24*1.3)/4,0) | K24: =IF($E24<L$4,($G24*1.3)/4,0) | L24: =IF($E24<M$4,($G24*1.3)/4,0) | M24: =IF($E24<N$4,($G24*1.3)/4,0) | N24: =IF($E24<O$4,($G24*1.3)/4,0) | O24: =IF($E24<P$4,($G24*1.3)/4,0) | ... R24: =IF($E24<S$4,($G24*1.3)/4,0) | S24: =IF($E24<S$4,($G24*1.3)/4,0)
H25: =SUM(H6:H24) | I25: =SUM(I6:I24) | J25: =SUM(J6:J24) | K25: =SUM(K6:K24) | L25: =SUM(L6:L24) | M25: =SUM(M6:M24) | N25: =SUM(N6:N24) | O25: =SUM(O6:O24) | ... S25: =SUM(S6:S24)
A27: Non Headcount | H27: 2019 | J27: 2020 | N27: 2021 | R27: 2022
A28: Submitted by | B28: Department | C28: Description of Spend | D28: Justification | G28: Total Cost Estimate | H28: Q3 | I28: Q4 | J28: Q1 | K28: Q2 | L28: Q3 | M28: Q4 | N28: Q1 | O28: Q2 | P28: Q3 | Q28: Q4 | R28: Q1 | S28: Q2
G41: =SUM(G29:G40) | H41: =SUM(H29:H34) | I41: =SUM(I29:I34) | J41: =SUM(J29:J34) | K41: =SUM(K29:K34) | L41: =SUM(L29:L34) | M41: =SUM(M29:M34) | N41: =SUM(N29:N34) | O41: =SUM(O29:O34) | ... S41: =SUM(S29:S34)

Sheet 6) Legal
A1: Delta Incremental Costs | C1: [Fri (9/20) - Financial model first review (1 of 2)]
A3: Headcount | H3: 2019 | J3: 2020 | N3: 2021 | R3: 2022
H4: 43647 | I4: 43739 | J4: 43831 | K4: 43922 | L4: 44013 | M4: 44105 | N4: 44197 | O4: 44287 | P4: 44378 | Q4: 44470 | R4: 44562 | S4: 44652
A5: Submitted by | B5: Department | C5: TBH Title | D5: Description | E5: Hire Date | F5: Location | G5: Base Salary Estimate USD | H5: Q3 | I5: Q4 | J5: Q1 | K5: Q2 | L5: Q3 | M5: Q4 | N5: Q1 | O5: Q2 | P5: Q3 | Q5: Q4 | R5: Q1 | S5: Q2
H6: =IF($E6<I$4,($G6*1.3)/4,0) | I6: =IF($E6<J$4,($G6*1.3)/4,0) | J6: =IF($E6<K$4,($G6*1.3)/4,0) | K6: =IF($E6<L$4,($G6*1.3)/4,0) | L6: =IF($E6<M$4,($G6*1.3)/4,0) | M6: =IF($E6<N$4,($G6*1.3)/4,0) | N6: =IF($E6<O$4,($G6*1.3)/4,0) | O6: =IF($E6<P$4,($G6*1.3)/4,0) | ... R6: =IF($E6<S$4,($G6*1.3)/4,0) | S6: =IF($E6<S$4,($G6*1.3)/4,0)
H7: =IF($E7<I$4,($G7*1.3)/4,0) | I7: =IF($E7<J$4,($G7*1.3)/4,0) | J7: =IF($E7<K$4,($G7*1.3)/4,0) | K7: =IF($E7<L$4,($G7*1.3)/4,0) | L7: =IF($E7<M$4,($G7*1.3)/4,0) | M7: =IF($E7<N$4,($G7*1.3)/4,0) | N7: =IF($E7<O$4,($G7*1.3)/4,0) | O7: =IF($E7<P$4,($G7*1.3)/4,0) | ... R7: =IF($E7<S$4,($G7*1.3)/4,0) | S7: =IF($E7<S$4,($G7*1.3)/4,0)
H8: =IF($E8<I$4,($G8*1.3)/4,0) | I8: =IF($E8<J$4,($G8*1.3)/4,0) | J8: =IF($E8<K$4,($G8*1.3)/4,0) | K8: =IF($E8<L$4,($G8*1.3)/4,0) | L8: =IF($E8<M$4,($G8*1.3)/4,0) | M8: =IF($E8<N$4,($G8*1.3)/4,0) | N8: =IF($E8<O$4,($G8*1.3)/4,0) | O8: =IF($E8<P$4,($G8*1.3)/4,0) | ... R8: =IF($E8<S$4,($G8*1.3)/4,0) | S8: =IF($E8<S$4,($G8*1.3)/4,0)
H9: =IF($E9<I$4,($G9*1.3)/4,0) | I9: =IF($E9<J$4,($G9*1.3)/4,0) | J9: =IF($E9<K$4,($G9*1.3)/4,0) | K9: =IF($E9<L$4,($G9*1.3)/4,0) | L9: =IF($E9<M$4,($G9*1.3)/4,0) | M9: =IF($E9<N$4,($G9*1.3)/4,0) | N9: =IF($E9<O$4,($G9*1.3)/4,0) | O9: =IF($E9<P$4,($G9*1.3)/4,0) | ... R9: =IF($E9<S$4,($G9*1.3)/4,0) | S9: =IF($E9<S$4,($G9*1.3)/4,0)
H10: =IF($E10<I$4,($G10*1.3)/4,0) | I10: =IF($E10<J$4,($G10*1.3)/4,0) | J10: =IF($E10<K$4,($G10*1.3)/4,0) | K10: =IF($E10<L$4,($G10*1.3)/4,0) | L10: =IF($E10<M$4,($G10*1.3)/4,0) | M10: =IF($E10<N$4,($G10*1.3)/4,0) | N10: =IF($E10<O$4,($G10*1.3)/4,0) | O10: =IF($E10<P$4,($G10*1.3)/4,0) | ... R10: =IF($E10<S$4,($G10*1.3)/4,0) | S10: =IF($E10<S$4,($G10*1.3)/4,0)
H11: =IF($E11<I$4,($G11*1.3)/4,0) | I11: =IF($E11<J$4,($G11*1.3)/4,0) | J11: =IF($E11<K$4,($G11*1.3)/4,0) | K11: =IF($E11<L$4,($G11*1.3)/4,0) | L11: =IF($E11<M$4,($G11*1.3)/4,0) | M11: =IF($E11<N$4,($G11*1.3)/4,0) | N11: =IF($E11<O$4,($G11*1.3)/4,0) | O11: =IF($E11<P$4,($G11*1.3)/4,0) | ... R11: =IF($E11<S$4,($G11*1.3)/4,0) | S11: =IF($E11<S$4,($G11*1.3)/4,0)
H12: =IF($E12<I$4,($G12*1.3)/4,0) | I12: =IF($E12<J$4,($G12*1.3)/4,0) | J12: =IF($E12<K$4,($G12*1.3)/4,0) | K12: =IF($E12<L$4,($G12*1.3)/4,0) | L12: =IF($E12<M$4,($G12*1.3)/4,0) | M12: =IF($E12<N$4,($G12*1.3)/4,0) | N12: =IF($E12<O$4,($G12*1.3)/4,0) | O12: =IF($E12<P$4,($G12*1.3)/4,0) | ... R12: =IF($E12<S$4,($G12*1.3)/4,0) | S12: =IF($E12<S$4,($G12*1.3)/4,0)
H13: =IF($E13<I$4,($G13*1.3)/4,0) | I13: =IF($E13<J$4,($G13*1.3)/4,0) | J13: =IF($E13<K$4,($G13*1.3)/4,0) | K13: =IF($E13<L$4,($G13*1.3)/4,0) | L13: =IF($E13<M$4,($G13*1.3)/4,0) | M13: =IF($E13<N$4,($G13*1.3)/4,0) | N13: =IF($E13<O$4,($G13*1.3)/4,0) | O13: =IF($E13<P$4,($G13*1.3)/4,0) | ... R13: =IF($E13<S$4,($G13*1.3)/4,0) | S13: =IF($E13<S$4,($G13*1.3)/4,0)
H14: =IF($E14<I$4,($G14*1.3)/4,0) | I14: =IF($E14<J$4,($G14*1.3)/4,0) | J14: =IF($E14<K$4,($G14*1.3)/4,0) | K14: =IF($E14<L$4,($G14*1.3)/4,0) | L14: =IF($E14<M$4,($G14*1.3)/4,0) | M14: =IF($E14<N$4,($G14*1.3)/4,0) | N14: =IF($E14<O$4,($G14*1.3)/4,0) | O14: =IF($E14<P$4,($G14*1.3)/4,0) | ... R14: =IF($E14<S$4,($G14*1.3)/4,0) | S14: =IF($E14<S$4,($G14*1.3)/4,0)
H15: =IF($E15<I$4,($G15*1.3)/4,0) | I15: =IF($E15<J$4,($G15*1.3)/4,0) | J15: =IF($E15<K$4,($G15*1.3)/4,0) | K15: =IF($E15<L$4,($G15*1.3)/4,0) | L15: =IF($E15<M$4,($G15*1.3)/4,0) | M15: =IF($E15<N$4,($G15*1.3)/4,0) | N15: =IF($E15<O$4,($G15*1.3)/4,0) | O15: =IF($E15<P$4,($G15*1.3)/4,0) | ... R15: =IF($E15<S$4,($G15*1.3)/4,0) | S15: =IF($E15<S$4,($G15*1.3)/4,0)
H16: =IF($E16<I$4,($G16*1.3)/4,0) | I16: =IF($E16<J$4,($G16*1.3)/4,0) | J16: =IF($E16<K$4,($G16*1.3)/4,0) | K16: =IF($E16<L$4,($G16*1.3)/4,0) | L16: =IF($E16<M$4,($G16*1.3)/4,0) | M16: =IF($E16<N$4,($G16*1.3)/4,0) | N16: =IF($E16<O$4,($G16*1.3)/4,0) | O16: =IF($E16<P$4,($G16*1.3)/4,0) | ... R16: =IF($E16<S$4,($G16*1.3)/4,0) | S16: =IF($E16<S$4,($G16*1.3)/4,0)
H17: =IF($E17<I$4,($G17*1.3)/4,0) | I17: =IF($E17<J$4,($G17*1.3)/4,0) | J17: =IF($E17<K$4,($G17*1.3)/4,0) | K17: =IF($E17<L$4,($G17*1.3)/4,0) | L17: =IF($E17<M$4,($G17*1.3)/4,0) | M17: =IF($E17<N$4,($G17*1.3)/4,0) | N17: =IF($E17<O$4,($G17*1.3)/4,0) | O17: =IF($E17<P$4,($G17*1.3)/4,0) | ... R17: =IF($E17<S$4,($G17*1.3)/4,0) | S17: =IF($E17<S$4,($G17*1.3)/4,0)
... H24: =IF($E24<I$4,($G24*1.3)/4,0) | I24: =IF($E24<J$4,($G24*1.3)/4,0) | J24: =IF($E24<K$4,($G24*1.3)/4,0) | K24: =IF($E24<L$4,($G24*1.3)/4,0) | L24: =IF($E24<M$4,($G24*1.3)/4,0) | M24: =IF($E24<N$4,($G24*1.3)/4,0) | N24: =IF($E24<O$4,($G24*1.3)/4,0) | O24: =IF($E24<P$4,($G24*1.3)/4,0) | ... R24: =IF($E24<S$4,($G24*1.3)/4,0) | S24: =IF($E24<S$4,($G24*1.3)/4,0)
H25: =SUM(H6:H24) | I25: =SUM(I6:I24) | J25: =SUM(J6:J24) | K25: =SUM(K6:K24) | L25: =SUM(L6:L24) | M25: =SUM(M6:M24) | N25: =SUM(N6:N24) | O25: =SUM(O6:O24) | ... S25: =SUM(S6:S24)
A27: Non Headcount | H27: 2019 | J27: 2020 | N27: 2021 | R27: 2022
A28: Submitted by | B28: Department | C28: Description of Spend | D28: Justification | G28: Total Cost Estimate | H28: Q3 | I28: Q4 | J28: Q1 | K28: Q2 | L28: Q3 | M28: Q4 | N28: Q1 | O28: Q2 | P28: Q3 | Q28: Q4 | R28: Q1 | S28: Q2
A29: Legal Counsel (External)
A30: Blackduck Code Scan
G41: =SUM(G29:G40) | H41: =SUM(H29:H34) | I41: =SUM(I29:I34) | J41: =SUM(J29:J34) | K41: =SUM(K29:K34) | L41: =SUM(L29:L34) | M41: =SUM(M29:M34) | N41: =SUM(N29:N34) | O41: =SUM(O29:O34) | ... S41: =SUM(S29:S34)

Sheet 7) HR
A1: Delta Incremental Costs
A3: Headcount | H3: 2019 | J3: 2020 | N3: 2021 | R3: 2022
H4: 43647 | I4: 43739 | J4: 43831 | K4: 43922 | L4: 44013 | M4: 44105 | N4: 44197 | O4: 44287 | P4: 44378 | Q4: 44470 | R4: 44562 | S4: 44652
A5: Submitted by | B5: Department | C5: TBH Title | D5: Description | E5: Hire Date | F5: Location | G5: Base Salary Estimate USD | H5: Q3 | I5: Q4 | J5: Q1 | K5: Q2 | L5: Q3 | M5: Q4 | N5: Q1 | O5: Q2 | P5: Q3 | Q5: Q4 | R5: Q1 | S5: Q2
H6: =IF($E6<I$4,($G6*1.3)/4,0) | I6: =IF($E6<J$4,($G6*1.3)/4,0) | J6: =IF($E6<K$4,($G6*1.3)/4,0) | K6: =IF($E6<L$4,($G6*1.3)/4,0) | L6: =IF($E6<M$4,($G6*1.3)/4,0) | M6: =IF($E6<N$4,($G6*1.3)/4,0) | N6: =IF($E6<O$4,($G6*1.3)/4,0) | O6: =IF($E6<P$4,($G6*1.3)/4,0) | ... R6: =IF($E6<S$4,($G6*1.3)/4,0) | S6: =IF($E6<S$4,($G6*1.3)/4,0)
H7: =IF($E7<I$4,($G7*1.3)/4,0) | I7: =IF($E7<J$4,($G7*1.3)/4,0) | J7: =IF($E7<K$4,($G7*1.3)/4,0) | K7: =IF($E7<L$4,($G7*1.3)/4,0) | L7: =IF($E7<M$4,($G7*1.3)/4,0) | M7: =IF($E7<N$4,($G7*1.3)/4,0) | N7: =IF($E7<O$4,($G7*1.3)/4,0) | O7: =IF($E7<P$4,($G7*1.3)/4,0) | ... R7: =IF($E7<S$4,($G7*1.3)/4,0) | S7: =IF($E7<S$4,($G7*1.3)/4,0)
H8: =IF($E8<I$4,($G8*1.3)/4,0) | I8: =IF($E8<J$4,($G8*1.3)/4,0) | J8: =IF($E8<K$4,($G8*1.3)/4,0) | K8: =IF($E8<L$4,($G8*1.3)/4,0) | L8: =IF($E8<M$4,($G8*1.3)/4,0) | M8: =IF($E8<N$4,($G8*1.3)/4,0) | N8: =IF($E8<O$4,($G8*1.3)/4,0) | O8: =IF($E8<P$4,($G8*1.3)/4,0) | ... R8: =IF($E8<S$4,($G8*1.3)/4,0) | S8: =IF($E8<S$4,($G8*1.3)/4,0)
H9: =IF($E9<I$4,($G9*1.3)/4,0) | I9: =IF($E9<J$4,($G9*1.3)/4,0) | J9: =IF($E9<K$4,($G9*1.3)/4,0) | K9: =IF($E9<L$4,($G9*1.3)/4,0) | L9: =IF($E9<M$4,($G9*1.3)/4,0) | M9: =IF($E9<N$4,($G9*1.3)/4,0) | N9: =IF($E9<O$4,($G9*1.3)/4,0) | O9: =IF($E9<P$4,($G9*1.3)/4,0) | ... R9: =IF($E9<S$4,($G9*1.3)/4,0) | S9: =IF($E9<S$4,($G9*1.3)/4,0)
H10: =IF($E10<I$4,($G10*1.3)/4,0) | I10: =IF($E10<J$4,($G10*1.3)/4,0) | J10: =IF($E10<K$4,($G10*1.3)/4,0) | K10: =IF($E10<L$4,($G10*1.3)/4,0) | L10: =IF($E10<M$4,($G10*1.3)/4,0) | M10: =IF($E10<N$4,($G10*1.3)/4,0) | N10: =IF($E10<O$4,($G10*1.3)/4,0) | O10: =IF($E10<P$4,($G10*1.3)/4,0) | ... R10: =IF($E10<S$4,($G10*1.3)/4,0) | S10: =IF($E10<S$4,($G10*1.3)/4,0)
H11: =IF($E11<I$4,($G11*1.3)/4,0) | I11: =IF($E11<J$4,($G11*1.3)/4,0) | J11: =IF($E11<K$4,($G11*1.3)/4,0) | K11: =IF($E11<L$4,($G11*1.3)/4,0) | L11: =IF($E11<M$4,($G11*1.3)/4,0) | M11: =IF($E11<N$4,($G11*1.3)/4,0) | N11: =IF($E11<O$4,($G11*1.3)/4,0) | O11: =IF($E11<P$4,($G11*1.3)/4,0) | ... R11: =IF($E11<S$4,($G11*1.3)/4,0) | S11: =IF($E11<S$4,($G11*1.3)/4,0)
H12: =IF($E12<I$4,($G12*1.3)/4,0) | I12: =IF($E12<J$4,($G12*1.3)/4,0) | J12: =IF($E12<K$4,($G12*1.3)/4,0) | K12: =IF($E12<L$4,($G12*1.3)/4,0) | L12: =IF($E12<M$4,($G12*1.3)/4,0) | M12: =IF($E12<N$4,($G12*1.3)/4,0) | N12: =IF($E12<O$4,($G12*1.3)/4,0) | O12: =IF($E12<P$4,($G12*1.3)/4,0) | ... R12: =IF($E12<S$4,($G12*1.3)/4,0) | S12: =IF($E12<S$4,($G12*1.3)/4,0)
H13: =IF($E13<I$4,($G13*1.3)/4,0) | I13: =IF($E13<J$4,($G13*1.3)/4,0) | J13: =IF($E13<K$4,($G13*1.3)/4,0) | K13: =IF($E13<L$4,($G13*1.3)/4,0) | L13: =IF($E13<M$4,($G13*1.3)/4,0) | M13: =IF($E13<N$4,($G13*1.3)/4,0) | N13: =IF($E13<O$4,($G13*1.3)/4,0) | O13: =IF($E13<P$4,($G13*1.3)/4,0) | ... R13: =IF($E13<S$4,($G13*1.3)/4,0) | S13: =IF($E13<S$4,($G13*1.3)/4,0)
H14: =IF($E14<I$4,($G14*1.3)/4,0) | I14: =IF($E14<J$4,($G14*1.3)/4,0) | J14: =IF($E14<K$4,($G14*1.3)/4,0) | K14: =IF($E14<L$4,($G14*1.3)/4,0) | L14: =IF($E14<M$4,($G14*1.3)/4,0) | M14: =IF($E14<N$4,($G14*1.3)/4,0) | N14: =IF($E14<O$4,($G14*1.3)/4,0) | O14: =IF($E14<P$4,($G14*1.3)/4,0) | ... R14: =IF($E14<S$4,($G14*1.3)/4,0) | S14: =IF($E14<S$4,($G14*1.3)/4,0)
H15: =IF($E15<I$4,($G15*1.3)/4,0) | I15: =IF($E15<J$4,($G15*1.3)/4,0) | J15: =IF($E15<K$4,($G15*1.3)/4,0) | K15: =IF($E15<L$4,($G15*1.3)/4,0) | L15: =IF($E15<M$4,($G15*1.3)/4,0) | M15: =IF($E15<N$4,($G15*1.3)/4,0) | N15: =IF($E15<O$4,($G15*1.3)/4,0) | O15: =IF($E15<P$4,($G15*1.3)/4,0) | ... R15: =IF($E15<S$4,($G15*1.3)/4,0) | S15: =IF($E15<S$4,($G15*1.3)/4,0)
H16: =IF($E16<I$4,($G16*1.3)/4,0) | I16: =IF($E16<J$4,($G16*1.3)/4,0) | J16: =IF($E16<K$4,($G16*1.3)/4,0) | K16: =IF($E16<L$4,($G16*1.3)/4,0) | L16: =IF($E16<M$4,($G16*1.3)/4,0) | M16: =IF($E16<N$4,($G16*1.3)/4,0) | N16: =IF($E16<O$4,($G16*1.3)/4,0) | O16: =IF($E16<P$4,($G16*1.3)/4,0) | ... R16: =IF($E16<S$4,($G16*1.3)/4,0) | S16: =IF($E16<S$4,($G16*1.3)/4,0)
H17: =IF($E17<I$4,($G17*1.3)/4,0) | I17: =IF($E17<J$4,($G17*1.3)/4,0) | J17: =IF($E17<K$4,($G17*1.3)/4,0) | K17: =IF($E17<L$4,($G17*1.3)/4,0) | L17: =IF($E17<M$4,($G17*1.3)/4,0) | M17: =IF($E17<N$4,($G17*1.3)/4,0) | N17: =IF($E17<O$4,($G17*1.3)/4,0) | O17: =IF($E17<P$4,($G17*1.3)/4,0) | ... R17: =IF($E17<S$4,($G17*1.3)/4,0) | S17: =IF($E17<S$4,($G17*1.3)/4,0)
... H24: =IF($E24<I$4,($G24*1.3)/4,0) | I24: =IF($E24<J$4,($G24*1.3)/4,0) | J24: =IF($E24<K$4,($G24*1.3)/4,0) | K24: =IF($E24<L$4,($G24*1.3)/4,0) | L24: =IF($E24<M$4,($G24*1.3)/4,0) | M24: =IF($E24<N$4,($G24*1.3)/4,0) | N24: =IF($E24<O$4,($G24*1.3)/4,0) | O24: =IF($E24<P$4,($G24*1.3)/4,0) | ... R24: =IF($E24<S$4,($G24*1.3)/4,0) | S24: =IF($E24<S$4,($G24*1.3)/4,0)
H25: =SUM(H6:H24) | I25: =SUM(I6:I24) | J25: =SUM(J6:J24) | K25: =SUM(K6:K24) | L25: =SUM(L6:L24) | M25: =SUM(M6:M24) | N25: =SUM(N6:N24) | O25: =SUM(O6:O24) | ... S25: =SUM(S6:S24)
A27: Non Headcount | H27: 2019 | J27: 2020 | N27: 2021 | R27: 2022
A28: Submitted by | B28: Department | C28: Description of Spend | D28: Justification | G28: Total Cost Estimate | H28: Q3 | I28: Q4 | J28: Q1 | K28: Q2 | L28: Q3 | M28: Q4 | N28: Q1 | O28: Q2 | P28: Q3 | Q28: Q4 | R28: Q1 | S28: Q2
I29: =G29
I30: =G30
I31: =G31
I32: =G32
I33: =G33
I34: =G34
I35: =G35
I36: =G36
I37: =G37
I38: =G38
G41: =SUM(G29:G40) | H41: =SUM(H29:H34) | I41: =SUM(I29:I34) | J41: =SUM(J29:J34) | K41: =SUM(K29:K34) | L41: =SUM(L29:L34) | M41: =SUM(M29:M34) | N41: =SUM(N29:N34) | O41: =SUM(O29:O34) | ... S41: =SUM(S29:S34)

Sheet 9) Marketing
A1: Delta Incremental Costs
A3: Headcount | H3: 2019 | J3: 2020 | N3: 2021 | R3: 2022
H4: 43647 | I4: 43739 | J4: 43831 | K4: 43922 | L4: 44013 | M4: 44105 | N4: 44197 | O4: 44287 | P4: 44378 | Q4: 44470 | R4: 44562 | S4: 44652
A5: Submitted by | B5: Department | C5: TBH Title | D5: Description | E5: Hire Date | F5: Location | G5: Base Salary Estimate USD | H5: Q3 | I5: Q4 | J5: Q1 | K5: Q2 | L5: Q3 | M5: Q4 | N5: Q1 | O5: Q2 | P5: Q3 | Q5: Q4 | R5: Q1 | S5: Q2
H6: =IF($E6<I$4,($G6*1.3)/4,0) | I6: =IF($E6<J$4,($G6*1.3)/4,0) | J6: =IF($E6<K$4,($G6*1.3)/4,0) | K6: =IF($E6<L$4,($G6*1.3)/4,0) | L6: =IF($E6<M$4,($G6*1.3)/4,0) | M6: =IF($E6<N$4,($G6*1.3)/4,0) | N6: =IF($E6<O$4,($G6*1.3)/4,0) | O6: =IF($E6<P$4,($G6*1.3)/4,0) | ... R6: =IF($E6<S$4,($G6*1.3)/4,0) | S6: =IF($E6<S$4,($G6*1.3)/4,0)
B7: Nish Jain: NONE EXPECTED | H7: =IF($E7<I$4,($G7*1.3)/4,0) | I7: =IF($E7<J$4,($G7*1.3)/4,0) | J7: =IF($E7<K$4,($G7*1.3)/4,0) | K7: =IF($E7<L$4,($G7*1.3)/4,0) | L7: =IF($E7<M$4,($G7*1.3)/4,0) | M7: =IF($E7<N$4,($G7*1.3)/4,0) | N7: =IF($E7<O$4,($G7*1.3)/4,0) | O7: =IF($E7<P$4,($G7*1.3)/4,0) | ... R7: =IF($E7<S$4,($G7*1.3)/4,0) | S7: =IF($E7<S$4,($G7*1.3)/4,0)
H8: =IF($E8<I$4,($G8*1.3)/4,0) | I8: =IF($E8<J$4,($G8*1.3)/4,0) | J8: =IF($E8<K$4,($G8*1.3)/4,0) | K8: =IF($E8<L$4,($G8*1.3)/4,0) | L8: =IF($E8<M$4,($G8*1.3)/4,0) | M8: =IF($E8<N$4,($G8*1.3)/4,0) | N8: =IF($E8<O$4,($G8*1.3)/4,0) | O8: =IF($E8<P$4,($G8*1.3)/4,0) | ... R8: =IF($E8<S$4,($G8*1.3)/4,0) | S8: =IF($E8<S$4,($G8*1.3)/4,0)
H9: =IF($E9<I$4,($G9*1.3)/4,0) | I9: =IF($E9<J$4,($G9*1.3)/4,0) | J9: =IF($E9<K$4,($G9*1.3)/4,0) | K9: =IF($E9<L$4,($G9*1.3)/4,0) | L9: =IF($E9<M$4,($G9*1.3)/4,0) | M9: =IF($E9<N$4,($G9*1.3)/4,0) | N9: =IF($E9<O$4,($G9*1.3)/4,0) | O9: =IF($E9<P$4,($G9*1.3)/4,0) | ... R9: =IF($E9<S$4,($G9*1.3)/4,0) | S9: =IF($E9<S$4,($G9*1.3)/4,0)
H10: =IF($E10<I$4,($G10*1.3)/4,0) | I10: =IF($E10<J$4,($G10*1.3)/4,0) | J10: =IF($E10<K$4,($G10*1.3)/4,0) | K10: =IF($E10<L$4,($G10*1.3)/4,0) | L10: =IF($E10<M$4,($G10*1.3)/4,0) | M10: =IF($E10<N$4,($G10*1.3)/4,0) | N10: =IF($E10<O$4,($G10*1.3)/4,0) | O10: =IF($E10<P$4,($G10*1.3)/4,0) | ... R10: =IF($E10<S$4,($G10*1.3)/4,0) | S10: =IF($E10<S$4,($G10*1.3)/4,0)
H11: =IF($E11<I$4,($G11*1.3)/4,0) | I11: =IF($E11<J$4,($G11*1.3)/4,0) | J11: =IF($E11<K$4,($G11*1.3)/4,0) | K11: =IF($E11<L$4,($G11*1.3)/4,0) | L11: =IF($E11<M$4,($G11*1.3)/4,0) | M11: =IF($E11<N$4,($G11*1.3)/4,0) | N11: =IF($E11<O$4,($G11*1.3)/4,0) | O11: =IF($E11<P$4,($G11*1.3)/4,0) | ... R11: =IF($E11<S$4,($G11*1.3)/4,0) | S11: =IF($E11<S$4,($G11*1.3)/4,0)
H12: =IF($E12<I$4,($G12*1.3)/4,0) | I12: =IF($E12<J$4,($G12*1.3)/4,0) | J12: =IF($E12<K$4,($G12*1.3)/4,0) | K12: =IF($E12<L$4,($G12*1.3)/4,0) | L12: =IF($E12<M$4,($G12*1.3)/4,0) | M12: =IF($E12<N$4,($G12*1.3)/4,0) | N12: =IF($E12<O$4,($G12*1.3)/4,0) | O12: =IF($E12<P$4,($G12*1.3)/4,0) | ... R12: =IF($E12<S$4,($G12*1.3)/4,0) | S12: =IF($E12<S$4,($G12*1.3)/4,0)
H13: =IF($E13<I$4,($G13*1.3)/4,0) | I13: =IF($E13<J$4,($G13*1.3)/4,0) | J13: =IF($E13<K$4,($G13*1.3)/4,0) | K13: =IF($E13<L$4,($G13*1.3)/4,0) | L13: =IF($E13<M$4,($G13*1.3)/4,0) | M13: =IF($E13<N$4,($G13*1.3)/4,0) | N13: =IF($E13<O$4,($G13*1.3)/4,0) | O13: =IF($E13<P$4,($G13*1.3)/4,0) | ... R13: =IF($E13<S$4,($G13*1.3)/4,0) | S13: =IF($E13<S$4,($G13*1.3)/4,0)
H14: =IF($E14<I$4,($G14*1.3)/4,0) | I14: =IF($E14<J$4,($G14*1.3)/4,0) | J14: =IF($E14<K$4,($G14*1.3)/4,0) | K14: =IF($E14<L$4,($G14*1.3)/4,0) | L14: =IF($E14<M$4,($G14*1.3)/4,0) | M14: =IF($E14<N$4,($G14*1.3)/4,0) | N14: =IF($E14<O$4,($G14*1.3)/4,0) | O14: =IF($E14<P$4,($G14*1.3)/4,0) | ... R14: =IF($E14<S$4,($G14*1.3)/4,0) | S14: =IF($E14<S$4,($G14*1.3)/4,0)
H15: =IF($E15<I$4,($G15*1.3)/4,0) | I15: =IF($E15<J$4,($G15*1.3)/4,0) | J15: =IF($E15<K$4,($G15*1.3)/4,0) | K15: =IF($E15<L$4,($G15*1.3)/4,0) | L15: =IF($E15<M$4,($G15*1.3)/4,0) | M15: =IF($E15<N$4,($G15*1.3)/4,0) | N15: =IF($E15<O$4,($G15*1.3)/4,0) | O15: =IF($E15<P$4,($G15*1.3)/4,0) | ... R15: =IF($E15<S$4,($G15*1.3)/4,0) | S15: =IF($E15<S$4,($G15*1.3)/4,0)
H16: =IF($E16<I$4,($G16*1.3)/4,0) | I16: =IF($E16<J$4,($G16*1.3)/4,0) | J16: =IF($E16<K$4,($G16*1.3)/4,0) | K16: =IF($E16<L$4,($G16*1.3)/4,0) | L16: =IF($E16<M$4,($G16*1.3)/4,0) | M16: =IF($E16<N$4,($G16*1.3)/4,0) | N16: =IF($E16<O$4,($G16*1.3)/4,0) | O16: =IF($E16<P$4,($G16*1.3)/4,0) | ... R16: =IF($E16<S$4,($G16*1.3)/4,0) | S16: =IF($E16<S$4,($G16*1.3)/4,0)
H17: =IF($E17<I$4,($G17*1.3)/4,0) | I17: =IF($E17<J$4,($G17*1.3)/4,0) | J17: =IF($E17<K$4,($G17*1.3)/4,0) | K17: =IF($E17<L$4,($G17*1.3)/4,0) | L17: =IF($E17<M$4,($G17*1.3)/4,0) | M17: =IF($E17<N$4,($G17*1.3)/4,0) | N17: =IF($E17<O$4,($G17*1.3)/4,0) | O17: =IF($E17<P$4,($G17*1.3)/4,0) | ... R17: =IF($E17<S$4,($G17*1.3)/4,0) | S17: =IF($E17<S$4,($G17*1.3)/4,0)
H18: =IF($E18<I$4,($G18*1.3)/4,0) | I18: =IF($E18<J$4,($G18*1.3)/4,0) | J18: =IF($E18<K$4,($G18*1.3)/4,0) | K18: =IF($E18<L$4,($G18*1.3)/4,0) | L18: =IF($E18<M$4,($G18*1.3)/4,0) | M18: =IF($E18<N$4,($G18*1.3)/4,0) | N18: =IF($E18<O$4,($G18*1.3)/4,0) | O18: =IF($E18<P$4,($G18*1.3)/4,0) | ... R18: =IF($E18<S$4,($G18*1.3)/4,0) | S18: =IF($E18<S$4,($G18*1.3)/4,0)
H19: =IF($E19<I$4,($G19*1.3)/4,0) | I19: =IF($E19<J$4,($G19*1.3)/4,0) | J19: =IF($E19<K$4,($G19*1.3)/4,0) | K19: =IF($E19<L$4,($G19*1.3)/4,0) | L19: =IF($E19<M$4,($G19*1.3)/4,0) | M19: =IF($E19<N$4,($G19*1.3)/4,0) | N19: =IF($E19<O$4,($G19*1.3)/4,0) | O19: =IF($E19<P$4,($G19*1.3)/4,0) | ... R19: =IF($E19<S$4,($G19*1.3)/4,0) | S19: =IF($E19<S$4,($G19*1.3)/4,0)
... H24: =IF($E24<I$4,($G24*1.3)/4,0) | I24: =IF($E24<J$4,($G24*1.3)/4,0) | J24: =IF($E24<K$4,($G24*1.3)/4,0) | K24: =IF($E24<L$4,($G24*1.3)/4,0) | L24: =IF($E24<M$4,($G24*1.3)/4,0) | M24: =IF($E24<N$4,($G24*1.3)/4,0) | N24: =IF($E24<O$4,($G24*1.3)/4,0) | O24: =IF($E24<P$4,($G24*1.3)/4,0) | ... R24: =IF($E24<S$4,($G24*1.3)/4,0) | S24: =IF($E24<S$4,($G24*1.3)/4,0)
H25: =SUM(H6:H24) | I25: =SUM(I6:I24) | J25: =SUM(J6:J24) | K25: =SUM(K6:K24) | L25: =SUM(L6:L24) | M25: =SUM(M6:M24) | N25: =SUM(N6:N24) | O25: =SUM(O6:O24) | ... S25: =SUM(S6:S24)
A27: Non Headcount | H27: 2019 | J27: 2020 | N27: 2021 | R27: 2022
A28: Submitted by | B28: Department | C28: Description of Spend | D28: Justification | G28: Total Cost Estimate | H28: Q3 | I28: Q4 | J28: Q1 | K28: Q2 | L28: Q3 | M28: Q4 | N28: Q1 | O28: Q2 | P28: Q3 | Q28: Q4 | R28: Q1 | S28: Q2
G41: =SUM(G29:G40) | H41: =SUM(H29:H34) | I41: =SUM(I29:I34) | J41: =SUM(J29:J34) | K41: =SUM(K29:K34) | L41: =SUM(L29:L34) | M41: =SUM(M29:M34) | N41: =SUM(N29:N34) | O41: =SUM(O29:O34) | ... S41: =SUM(S29:S34)

Sheet 10) Int'l S&M
A1: Delta Incremental Costs
A3: Headcount | H3: 2019 | J3: 2020 | N3: 2021 | R3: 2022
H4: 43647 | I4: 43739 | J4: 43831 | K4: 43922 | L4: 44013 | M4: 44105 | N4: 44197 | O4: 44287 | P4: 44378 | Q4: 44470 | R4: 44562 | S4: 44652
A5: Submitted by | B5: Department | C5: TBH Title | D5: Description | E5: Hire Date | F5: Location | G5: Base Salary Estimate USD | H5: Q3 | I5: Q4 | J5: Q1 | K5: Q2 | L5: Q3 | M5: Q4 | N5: Q1 | O5: Q2 | P5: Q3 | Q5: Q4 | R5: Q1 | S5: Q2
H6: =IF($E6<I$4,($G6*1.3)/4,0) | I6: =IF($E6<J$4,($G6*1.3)/4,0) | J6: =IF($E6<K$4,($G6*1.3)/4,0) | K6: =IF($E6<L$4,($G6*1.3)/4,0) | L6: =IF($E6<M$4,($G6*1.3)/4,0) | M6: =IF($E6<N$4,($G6*1.3)/4,0) | N6: =IF($E6<O$4,($G6*1.3)/4,0) | O6: =IF($E6<P$4,($G6*1.3)/4,0) | ... R6: =IF($E6<S$4,($G6*1.3)/4,0) | S6: =IF($E6<S$4,($G6*1.3)/4,0)
H7: =IF($E7<I$4,($G7*1.3)/4,0) | I7: =IF($E7<J$4,($G7*1.3)/4,0) | J7: =IF($E7<K$4,($G7*1.3)/4,0) | K7: =IF($E7<L$4,($G7*1.3)/4,0) | L7: =IF($E7<M$4,($G7*1.3)/4,0) | M7: =IF($E7<N$4,($G7*1.3)/4,0) | N7: =IF($E7<O$4,($G7*1.3)/4,0) | O7: =IF($E7<P$4,($G7*1.3)/4,0) | ... R7: =IF($E7<S$4,($G7*1.3)/4,0) | S7: =IF($E7<S$4,($G7*1.3)/4,0)
H8: =IF($E8<I$4,($G8*1.3)/4,0) | I8: =IF($E8<J$4,($G8*1.3)/4,0) | J8: =IF($E8<K$4,($G8*1.3)/4,0) | K8: =IF($E8<L$4,($G8*1.3)/4,0) | L8: =IF($E8<M$4,($G8*1.3)/4,0) | M8: =IF($E8<N$4,($G8*1.3)/4,0) | N8: =IF($E8<O$4,($G8*1.3)/4,0) | O8: =IF($E8<P$4,($G8*1.3)/4,0) | ... R8: =IF($E8<S$4,($G8*1.3)/4,0) | S8: =IF($E8<S$4,($G8*1.3)/4,0)
H9: =IF($E9<I$4,($G9*1.3)/4,0) | I9: =IF($E9<J$4,($G9*1.3)/4,0) | J9: =IF($E9<K$4,($G9*1.3)/4,0) | K9: =IF($E9<L$4,($G9*1.3)/4,0) | L9: =IF($E9<M$4,($G9*1.3)/4,0) | M9: =IF($E9<N$4,($G9*1.3)/4,0) | N9: =IF($E9<O$4,($G9*1.3)/4,0) | O9: =IF($E9<P$4,($G9*1.3)/4,0) | ... R9: =IF($E9<S$4,($G9*1.3)/4,0) | S9: =IF($E9<S$4,($G9*1.3)/4,0)
H10: =IF($E10<I$4,($G10*1.3)/4,0) | I10: =IF($E10<J$4,($G10*1.3)/4,0) | J10: =IF($E10<K$4,($G10*1.3)/4,0) | K10: =IF($E10<L$4,($G10*1.3)/4,0) | L10: =IF($E10<M$4,($G10*1.3)/4,0) | M10: =IF($E10<N$4,($G10*1.3)/4,0) | N10: =IF($E10<O$4,($G10*1.3)/4,0) | O10: =IF($E10<P$4,($G10*1.3)/4,0) | ... R10: =IF($E10<S$4,($G10*1.3)/4,0) | S10: =IF($E10<S$4,($G10*1.3)/4,0)
H11: =IF($E11<I$4,($G11*1.3)/4,0) | I11: =IF($E11<J$4,($G11*1.3)/4,0) | J11: =IF($E11<K$4,($G11*1.3)/4,0) | K11: =IF($E11<L$4,($G11*1.3)/4,0) | L11: =IF($E11<M$4,($G11*1.3)/4,0) | M11: =IF($E11<N$4,($G11*1.3)/4,0) | N11: =IF($E11<O$4,($G11*1.3)/4,0) | O11: =IF($E11<P$4,($G11*1.3)/4,0) | ... R11: =IF($E11<S$4,($G11*1.3)/4,0) | S11: =IF($E11<S$4,($G11*1.3)/4,0)
H12: =IF($E12<I$4,($G12*1.3)/4,0) | I12: =IF($E12<J$4,($G12*1.3)/4,0) | J12: =IF($E12<K$4,($G12*1.3)/4,0) | K12: =IF($E12<L$4,($G12*1.3)/4,0) | L12: =IF($E12<M$4,($G12*1.3)/4,0) | M12: =IF($E12<N$4,($G12*1.3)/4,0) | N12: =IF($E12<O$4,($G12*1.3)/4,0) | O12: =IF($E12<P$4,($G12*1.3)/4,0) | ... R12: =IF($E12<S$4,($G12*1.3)/4,0) | S12: =IF($E12<S$4,($G12*1.3)/4,0)
H13: =IF($E13<I$4,($G13*1.3)/4,0) | I13: =IF($E13<J$4,($G13*1.3)/4,0) | J13: =IF($E13<K$4,($G13*1.3)/4,0) | K13: =IF($E13<L$4,($G13*1.3)/4,0) | L13: =IF($E13<M$4,($G13*1.3)/4,0) | M13: =IF($E13<N$4,($G13*1.3)/4,0) | N13: =IF($E13<O$4,($G13*1.3)/4,0) | O13: =IF($E13<P$4,($G13*1.3)/4,0) | ... R13: =IF($E13<S$4,($G13*1.3)/4,0) | S13: =IF($E13<S$4,($G13*1.3)/4,0)
H14: =IF($E14<I$4,($G14*1.3)/4,0) | I14: =IF($E14<J$4,($G14*1.3)/4,0) | J14: =IF($E14<K$4,($G14*1.3)/4,0) | K14: =IF($E14<L$4,($G14*1.3)/4,0) | L14: =IF($E14<M$4,($G14*1.3)/4,0) | M14: =IF($E14<N$4,($G14*1.3)/4,0) | N14: =IF($E14<O$4,($G14*1.3)/4,0) | O14: =IF($E14<P$4,($G14*1.3)/4,0) | ... R14: =IF($E14<S$4,($G14*1.3)/4,0) | S14: =IF($E14<S$4,($G14*1.3)/4,0)
H15: =IF($E15<I$4,($G15*1.3)/4,0) | I15: =IF($E15<J$4,($G15*1.3)/4,0) | J15: =IF($E15<K$4,($G15*1.3)/4,0) | K15: =IF($E15<L$4,($G15*1.3)/4,0) | L15: =IF($E15<M$4,($G15*1.3)/4,0) | M15: =IF($E15<N$4,($G15*1.3)/4,0) | N15: =IF($E15<O$4,($G15*1.3)/4,0) | O15: =IF($E15<P$4,($G15*1.3)/4,0) | ... R15: =IF($E15<S$4,($G15*1.3)/4,0) | S15: =IF($E15<S$4,($G15*1.3)/4,0)
H16: =IF($E16<I$4,($G16*1.3)/4,0) | I16: =IF($E16<J$4,($G16*1.3)/4,0) | J16: =IF($E16<K$4,($G16*1.3)/4,0) | K16: =IF($E16<L$4,($G16*1.3)/4,0) | L16: =IF($E16<M$4,($G16*1.3)/4,0) | M16: =IF($E16<N$4,($G16*1.3)/4,0) | N16: =IF($E16<O$4,($G16*1.3)/4,0) | O16: =IF($E16<P$4,($G16*1.3)/4,0) | ... R16: =IF($E16<S$4,($G16*1.3)/4,0) | S16: =IF($E16<S$4,($G16*1.3)/4,0)
H17: =IF($E17<I$4,($G17*1.3)/4,0) | I17: =IF($E17<J$4,($G17*1.3)/4,0) | J17: =IF($E17<K$4,($G17*1.3)/4,0) | K17: =IF($E17<L$4,($G17*1.3)/4,0) | L17: =IF($E17<M$4,($G17*1.3)/4,0) | M17: =IF($E17<N$4,($G17*1.3)/4,0) | N17: =IF($E17<O$4,($G17*1.3)/4,0) | O17: =IF($E17<P$4,($G17*1.3)/4,0) | ... R17: =IF($E17<S$4,($G17*1.3)/4,0) | S17: =IF($E17<S$4,($G17*1.3)/4,0)
... H24: =IF($E24<I$4,($G24*1.3)/4,0) | I24: =IF($E24<J$4,($G24*1.3)/4,0) | J24: =IF($E24<K$4,($G24*1.3)/4,0) | K24: =IF($E24<L$4,($G24*1.3)/4,0) | L24: =IF($E24<M$4,($G24*1.3)/4,0) | M24: =IF($E24<N$4,($G24*1.3)/4,0) | N24: =IF($E24<O$4,($G24*1.3)/4,0) | O24: =IF($E24<P$4,($G24*1.3)/4,0) | ... R24: =IF($E24<S$4,($G24*1.3)/4,0) | S24: =IF($E24<S$4,($G24*1.3)/4,0)
H25: =SUM(H6:H24) | I25: =SUM(I6:I24) | J25: =SUM(J6:J24) | K25: =SUM(K6:K24) | L25: =SUM(L6:L24) | M25: =SUM(M6:M24) | N25: =SUM(N6:N24) | O25: =SUM(O6:O24) | ... S25: =SUM(S6:S24)
A27: Non Headcount | H27: 2019 | J27: 2020 | N27: 2021 | R27: 2022
A28: Submitted by | B28: Department | C28: Description of Spend | D28: Justification | G28: Total Cost Estimate | H28: Q3 | I28: Q4 | J28: Q1 | K28: Q2 | L28: Q3 | M28: Q4 | N28: Q1 | O28: Q2 | P28: Q3 | Q28: Q4 | R28: Q1 | S28: Q2
G41: =SUM(G29:G40) | H41: =SUM(H29:H34) | I41: =SUM(I29:I34) | J41: =SUM(J29:J34) | K41: =SUM(K29:K34) | L41: =SUM(L29:L34) | M41: =SUM(M29:M34) | N41: =SUM(N29:N34) | O41: =SUM(O29:O34) | ... S41: =SUM(S29:S34)

Sheet Sheet2
D2: 2019 | E2: 2020 | G2: 2021 | K2: 2019 | L2: 2020 | N2: 2021
C3: Source/Location | D3: 2H | E3: 1H | F3: 2H | G3: 1H | H3: 2H | J3: Source/Location | K3: 2H | L3: 1H | M3: 2H | N3: 1H | O3: 2H
C4: Delta Existing | D4: 14 | E4: 14 | F4: 14 | G4: 14 | H4: 14 | J4: Delta Existing | K4: 14 | L4: 14 | M4: 14 | N4: 14 | O4: 14
C5: Asia New | D5: 6 | E5: 12 | F5: 14 | G5: 14 | H5: 14 | J5: HK New | K5: 6 | L5: 12 | M5: 14 | N5: 14 | O5: 14
C6: Total | D6: =SUM(D4:D5) | E6: =SUM(E4:E5) | F6: =SUM(F4:F5) | G6: =SUM(G4:G5) | H6: =SUM(H4:H5) | J6: Total | K6: =SUM(K4:K5) | L6: =SUM(L4:L5) | M6: =SUM(M4:M5) | N6: =SUM(N4:N5) | O6: =SUM(O4:O5)
